Workbook

Sheet TOC
A1: Take-on schedules as at 31 October 2024, with the E-Banker account mapping to confirm
A2: Dupleix Institute for Tamanda Sitimawina, MAIIC · 7 October 2026 · start with 'Instructions'
A4: Sheet | B4: What it is | C4: Who it is for
A5: =HYPERLINK("#'Instructions'!A1","Instructions") -> Instructions | B5: Read first: what to do and how the sheets are linked | C5: Tamanda
A6: =HYPERLINK("#'Mapping'!A1","Mapping") -> Mapping | B6: One row per facility: the proposed account, five tests, your Y/N | C6: Tamanda, to fill in
A7: =HYPERLINK("#'Not matched'!A1","Not matched") -> Not matched | B7: The four facilities with no proposed account | C7: Tamanda, to fill in
A8: =HYPERLINK("#'Accounts without a block'!A1","Accounts without a block") -> Accounts without a block | B8: E-Banker accounts opened before July 2024 with no facility in the workbook | C8: Tamanda, to fill in
A9: =HYPERLINK("#'Upload summary'!A1","Upload summary") -> Upload summary | B9: The facilities laid out for loading, your terms beside the E-Banker terms | C9: Dupleix
A10: =HYPERLINK("#'Blocks'!A1","Blocks") -> Blocks | B10: One row per amortisation block, linked to its facility and account, with a link into the block | C10: Dupleix
A11: =HYPERLINK("#'E-Banker master'!A1","E-Banker master") -> E-Banker master | B11: The E-Banker values the lookups read (extracted 7 October 2026) | C11: Reference
A12: =HYPERLINK("#'Loan Book'!A1","Loan Book") -> Loan Book | B12: Your sheet, unchanged | C12: Reference
A13: =HYPERLINK("#'Amortisation and Repayments'!A1","Amortisation and Repayments") -> Amortisation and Repayments | B13: Your sheet, unchanged | C13: Reference

Sheet Instructions
A1: What this workbook is
A2: Your take-on workbook of 11 September 2026, exactly as you sent it (the sheets 'Loan Book' and 'Amortisation and Repayments' are untouched), with six sheets added by Dupleix that link each facility and each amortisation block to its E-Banker account number.
A4: Why
A5: The pre-July-2024 history of each loan lives in your workbook; the history from July 2024 lives in E-Banker. To join the two for the effective interest rate, each facility in the workbook needs its E-Banker account number. We have proposed the number for 105 of the 109 facilities. We need you to confirm or correct each one. The fees charged at the start of each loan are the one thing neither your workbook nor E-Banker records against the loan, and the effective interest rate cannot be worked out without them: under IFRS 9 the fee is spread over the life of the loan as part of its yield. That is why the yellow fee columns are asked for.
A7: What to do, in order
A8: 1. Open the sheet 'Mapping'. For each row, look at the proposed account (column J), the E-Banker name beside it (column L) and the five tests (columns S to W). Put Y in column X if the account is right, or N and the correct account number in column Y. Column Z is for any comment.
A9: 2. Open the sheet 'Not matched'. Four facilities have no proposed account: give the account number, or write 'no account' if the facility was never set up in E-Banker (for example an equity holding, or a loan closed before the migration).
A10: 3. Open the sheet 'Accounts without a block'. These E-Banker accounts were opened before July 2024 but match no facility in your workbook. Say which facility each is, or 'none'.
A11: 4. Open the sheet 'Upload summary' and go to the yellow columns at the far right (AO to AT). For every facility, type the arrangement fee and the legal fees charged when the loan was first granted (in kwacha), any other fee that was a condition of the loan (for example a commitment or valuation fee), the date the fees were charged, whether they were deducted from the amount paid out (Y) or paid separately (N), and the reference of the offer letter or receipt you took the figures from. Leave a cell blank if there was no such fee; write 0 only if you know it was nil. Column AU adds them up for you.
A12: 5. Save the file and send it back. Nothing else needs to change.
A13: How the sheets are linked, so that everything can be audited
A14: Every workbook figure shown on the new sheets is a formula pointing at the cell in 'Loan Book' or 'Amortisation and Repayments' it comes from. Click any such cell and the formula bar shows the source. If you correct a figure in your sheets, the new sheets follow.
... A25: Prepared by Dupleix Institute, 7 October 2026. The scripts that built the new sheets are kept in our project folder (Build files) so the work can be re-run.

Sheet Mapping
A1: Loan Book row | B1: Loan Book # | C1: Facility name | D1: Type | E1: Value date | F1: Approved | G1: Disbursed | H1: Principal 31 Oct 2024 | I1: Carrying amount 31 Oct 2024 | J1: Proposed E-Banker account | K1: Confidence | L1: E-Banker name | M1: E-Banker opening date | N1: E-Banker sanction | O1: E-Banker take-on posting 31 Jul 2024 | P1: E-Banker balance 31 Oct 2024 | Q1: E-Banker first disbursement date | R1: E-Banker status | S1: Test 1: principal = take-on posting | T1: Test 2: carrying amount vs balance | U1: Test 3: approved = sanction | V1: Test 4: days, value date to first disbursement | W1: Test 5: name agrees (as scored) | X1: Tamanda: correct? (Y/N) | Y1: If N, correct account number | Z1: Comment
A2: 5 | B2: ='Loan Book'!D5 -> 1 | C2: ='Loan Book'!E5 -> Chikho Hotel Limited | D2: ='Loan Book'!F5 -> Debt | E2: ='Loan Book'!G5 -> 44470 | F2: ='Loan Book'!L5 -> 6.208559e+08 | G2: ='Loan Book'!M5 -> 6.208559e+08 | H2: ='Loan Book'!O5 -> 6.0793125e+08 | I2: ='Loan Book'!R5 -> 1.7285347e-05 | J2: 000104430000001 | K2: High | L2: =IFERROR(INDEX('E-Banker master'!$B$2:$B$186,MATCH($J2,'E-Banker master'!$A$2:$A$186,0)),"") -> CHIKHO HOTEL | M2: =IFERROR(INDEX('E-Banker master'!$H$2:$H$186,MATCH($J2,'E-Banker master'!$A$2:$A$186,0)),"") -> 44652 | N2: =IFERROR(INDEX('E-Banker master'!$I$2:$I$186,MATCH($J2,'E-Banker master'!$A$2:$A$186,0)),"") -> 6.208559e+08 | O2: =IFERROR(INDEX('E-Banker master'!$N$2:$N$186,MATCH($J2,'E-Banker master'!$A$2:$A$186,0)),"") -> 0 | P2: =IFERROR(INDEX('E-Banker master'!$P$2:$P$186,MATCH($J2,'E-Banker master'!$A$2:$A$186,0)),"") -> 0 | Q2: =IFERROR(INDEX('E-Banker master'!$Q$2:$Q$186,MATCH($J2,'E-Banker master'!$A$2:$A$186,0)),"") -> 44470 | R2: =IFERROR(INDEX('E-Banker master'!$E$2:$E$186,MATCH($J2,'E-Banker master'!$A$2:$A$186,0)),"") -> C | S2: =IF($J2="","",IF(O2="","No take-on posting",IF(ABS(H2-O2)<1,"Yes",IF(ABS(H2/O2-1)<0.01,"Within 1%","No")))) -> #DIV/0! | T2: =IF($J2="","",IF(OR(P2="",P2=0),"No balance",IF(ABS(I2-P2)<1,"Yes",IF(ABS(I2/P2-1)<0.02,"Within 2%",IF(ABS(I2/P2-1)<0.05,"Within 5%","No"))))) -> No balance | U2: =IF($J2="","",IF(N2="","",IF(ABS(F2-N2)<1,"Yes",IF(ABS(G2-N2)<1,"Disbursed = sanction","No")))) -> Yes | V2: =IF(OR($J2="",Q2="",E2=""),"",ABS(E2-Q2)) -> 0 | W2: Yes
A3: 6 | B3: ='Loan Book'!D6 -> 2 | C3: ='Loan Book'!E6 -> Edge View Academy Limited | D3: ='Loan Book'!F6 -> Debt | E3: ='Loan Book'!G6 -> 43935 | F3: ='Loan Book'!L6 -> 300000000 | G3: ='Loan Book'!M6 -> 300000000 | H3: ='Loan Book'!O6 -> 3.3139585e+08 | I3: ='Loan Book'!R6 -> 3.7285399e+08 | J3: 000104430000002 | K3: High | L3: =IFERROR(INDEX('E-Banker master'!$B$2:$B$186,MATCH($J3,'E-Banker master'!$A$2:$A$186,0)),"") -> Edge View Academy Limited | M3: =IFERROR(INDEX('E-Banker master'!$H$2:$H$186,MATCH($J3,'E-Banker master'!$A$2:$A$186,0)),"") -> 43894 | N3: =IFERROR(INDEX('E-Banker master'!$I$2:$I$186,MATCH($J3,'E-Banker master'!$A$2:$A$186,0)),"") -> 300000000 | O3: =IFERROR(INDEX('E-Banker master'!$N$2:$N$186,MATCH($J3,'E-Banker master'!$A$2:$A$186,0)),"") -> 3.3139585e+08 | P3: =IFERROR(INDEX('E-Banker master'!$P$2:$P$186,MATCH($J3,'E-Banker master'!$A$2:$A$186,0)),"") -> 3.7864473e+08 | Q3: =IFERROR(INDEX('E-Banker master'!$Q$2:$Q$186,MATCH($J3,'E-Banker master'!$A$2:$A$186,0)),"") -> 43894 | R3: =IFERROR(INDEX('E-Banker master'!$E$2:$E$186,MATCH($J3,'E-Banker master'!$A$2:$A$186,0)),"") -> A | S3: =IF($J3="","",IF(O3="","No take-on posting",IF(ABS(H3-O3)<1,"Yes",IF(ABS(H3/O3-1)<0.01,"Within 1%","No")))) -> Yes | T3: =IF($J3="","",IF(OR(P3="",P3=0),"No balance",IF(ABS(I3-P3)<1,"Yes",IF(ABS(I3/P3-1)<0.02,"Within 2%",IF(ABS(I3/P3-1)<0.05,"Within 5%","No"))))) -> Within 2% | U3: =IF($J3="","",IF(N3="","",IF(ABS(F3-N3)<1,"Yes",IF(ABS(G3-N3)<1,"Disbursed = sanction","No")))) -> Yes | V3: =IF(OR($J3="",Q3="",E3=""),"",ABS(E3-Q3)) -> 41 | W3: Yes
A4: 7 | B4: ='Loan Book'!D7 -> 3 | C4: ='Loan Book'!E7 -> Micholess Creamery | D4: ='Loan Book'!F7 -> Debt | E4: ='Loan Book'!G7 -> 44040 | F4: ='Loan Book'!L7 -> 20000000 | G4: ='Loan Book'!M7 -> 18240000 | H4: ='Loan Book'!O7 -> 18240000 | I4: ='Loan Book'!R7 -> 0 | J4: 000104420000003 | K4: High | L4: =IFERROR(INDEX('E-Banker master'!$B$2:$B$186,MATCH($J4,'E-Banker master'!$A$2:$A$186,0)),"") -> Micholess Creamery | M4: =IFERROR(INDEX('E-Banker master'!$H$2:$H$186,MATCH($J4,'E-Banker master'!$A$2:$A$186,0)),"") -> 44040 | N4: =IFERROR(INDEX('E-Banker master'!$I$2:$I$186,MATCH($J4,'E-Banker master'!$A$2:$A$186,0)),"") -> 20000000 | O4: =IFERROR(INDEX('E-Banker master'!$N$2:$N$186,MATCH($J4,'E-Banker master'!$A$2:$A$186,0)),"") -> 18240000 | P4: =IFERROR(INDEX('E-Banker master'!$P$2:$P$186,MATCH($J4,'E-Banker master'!$A$2:$A$186,0)),"") -> 0 | Q4: =IFERROR(INDEX('E-Banker master'!$Q$2:$Q$186,MATCH($J4,'E-Banker master'!$A$2:$A$186,0)),"") -> 44040 | R4: =IFERROR(INDEX('E-Banker master'!$E$2:$E$186,MATCH($J4,'E-Banker master'!$A$2:$A$186,0)),"") -> A | S4: =IF($J4="","",IF(O4="","No take-on posting",IF(ABS(H4-O4)<1,"Yes",IF(ABS(H4/O4-1)<0.01,"Within 1%","No")))) -> Yes | T4: =IF($J4="","",IF(OR(P4="",P4=0),"No balance",IF(ABS(I4-P4)<1,"Yes",IF(ABS(I4/P4-1)<0.02,"Within 2%",IF(ABS(I4/P4-1)<0.05,"Within 5%","No"))))) -> No balance | U4: =IF($J4="","",IF(N4="","",IF(ABS(F4-N4)<1,"Yes",IF(ABS(G4-N4)<1,"Disbursed = sanction","No")))) -> Yes | V4: =IF(OR($J4="",Q4="",E4=""),"",ABS(E4-Q4)) -> 0 | W4: Yes
A5: 8 | B5: ='Loan Book'!D8 -> 4 | C5: ='Loan Book'!E8 -> COMSIV Limited | D5: ='Loan Book'!F8 -> Debt | E5: ='Loan Book'!G8 -> 44552 | F5: ='Loan Book'!L8 -> 309523514 | G5: ='Loan Book'!M8 -> 309523514 | H5: ='Loan Book'!O8 -> 309523514 | I5: ='Loan Book'!R8 -> 8318966.5 | J5: 000104430000004 | K5: High | L5: =IFERROR(INDEX('E-Banker master'!$B$2:$B$186,MATCH($J5,'E-Banker master'!$A$2:$A$186,0)),"") -> COMSIV Limited | M5: =IFERROR(INDEX('E-Banker master'!$H$2:$H$186,MATCH($J5,'E-Banker master'!$A$2:$A$186,0)),"") -> 44525 | N5: =IFERROR(INDEX('E-Banker master'!$I$2:$I$186,MATCH($J5,'E-Banker master'!$A$2:$A$186,0)),"") -> 309523514 | O5: =IFERROR(INDEX('E-Banker master'!$N$2:$N$186,MATCH($J5,'E-Banker master'!$A$2:$A$186,0)),"") -> 309523514 | P5: =IFERROR(INDEX('E-Banker master'!$P$2:$P$186,MATCH($J5,'E-Banker master'!$A$2:$A$186,0)),"") -> 8318966.5 | Q5: =IFERROR(INDEX('E-Banker master'!$Q$2:$Q$186,MATCH($J5,'E-Banker master'!$A$2:$A$186,0)),"") -> 44525 | R5: =IFERROR(INDEX('E-Banker master'!$E$2:$E$186,MATCH($J5,'E-Banker master'!$A$2:$A$186,0)),"") -> H | S5: =IF($J5="","",IF(O5="","No take-on posting",IF(ABS(H5-O5)<1,"Yes",IF(ABS(H5/O5-1)<0.01,"Within 1%","No")))) -> Yes | T5: =IF($J5="","",IF(OR(P5="",P5=0),"No balance",IF(ABS(I5-P5)<1,"Yes",IF(ABS(I5/P5-1)<0.02,"Within 2%",IF(ABS(I5/P5-1)<0.05,"Within 5%","No"))))) -> Yes | U5: =IF($J5="","",IF(N5="","",IF(ABS(F5-N5)<1,"Yes",IF(ABS(G5-N5)<1,"Disbursed = sanction","No")))) -> Yes | V5: =IF(OR($J5="",Q5="",E5=""),"",ABS(E5-Q5)) -> 27 | W5: Yes
A6: 9 | B6: ='Loan Book'!D9 -> 5 | C6: ='Loan Book'!E9 -> MUSECO | D6: ='Loan Book'!F9 -> Debt | E6: ='Loan Book'!G9 -> 44035 | F6: ='Loan Book'!L9 -> 4.0509799e+08 | G6: ='Loan Book'!M9 -> 4.0509799e+08 | H6: ='Loan Book'!O9 -> 4.0509799e+08 | I6: ='Loan Book'!R9 -> 3.8475303e+08 | J6: 000104420000005 | K6: High | L6: =IFERROR(INDEX('E-Banker master'!$B$2:$B$186,MATCH($J6,'E-Banker master'!$A$2:$A$186,0)),"") -> MUSECO | M6: =IFERROR(INDEX('E-Banker master'!$H$2:$H$186,MATCH($J6,'E-Banker master'!$A$2:$A$186,0)),"") -> 43964 | N6: =IFERROR(INDEX('E-Banker master'!$I$2:$I$186,MATCH($J6,'E-Banker master'!$A$2:$A$186,0)),"") -> 370000000 | O6: =IFERROR(INDEX('E-Banker master'!$N$2:$N$186,MATCH($J6,'E-Banker master'!$A$2:$A$186,0)),"") -> 4.0509799e+08 | P6: =IFERROR(INDEX('E-Banker master'!$P$2:$P$186,MATCH($J6,'E-Banker master'!$A$2:$A$186,0)),"") -> 3.9924351e+08 | Q6: =IFERROR(INDEX('E-Banker master'!$Q$2:$Q$186,MATCH($J6,'E-Banker master'!$A$2:$A$186,0)),"") -> 44035 | R6: =IFERROR(INDEX('E-Banker master'!$E$2:$E$186,MATCH($J6,'E-Banker master'!$A$2:$A$186,0)),"") -> D | S6: =IF($J6="","",IF(O6="","No take-on posting",IF(ABS(H6-O6)<1,"Yes",IF(ABS(H6/O6-1)<0.01,"Within 1%","No")))) -> Yes | T6: =IF($J6="","",IF(OR(P6="",P6=0),"No balance",IF(ABS(I6-P6)<1,"Yes",IF(ABS(I6/P6-1)<0.02,"Within 2%",IF(ABS(I6/P6-1)<0.05,"Within 5%","No"))))) -> Within 5% | U6: =IF($J6="","",IF(N6="","",IF(ABS(F6-N6)<1,"Yes",IF(ABS(G6-N6)<1,"Disbursed = sanction","No")))) -> No | V6: =IF(OR($J6="",Q6="",E6=""),"",ABS(E6-Q6)) -> 0 | W6: Yes
A7: 10 | B7: ='Loan Book'!D10 -> 6 | C7: ='Loan Book'!E10 -> Nsanama Women Cooperatives | D7: ='Loan Book'!F10 -> Debt | E7: ='Loan Book'!G10 -> 44076 | F7: ='Loan Book'!L10 -> 17000000 | G7: ='Loan Book'!M10 -> 12055000 | H7: ='Loan Book'!O10 -> 12055000 | I7: ='Loan Book'!R10 -> 12847907 | J7: 000104420000006 | K7: High | L7: =IFERROR(INDEX('E-Banker master'!$B$2:$B$186,MATCH($J7,'E-Banker master'!$A$2:$A$186,0)),"") -> Nsanama Women Cooperatives | M7: =IFERROR(INDEX('E-Banker master'!$H$2:$H$186,MATCH($J7,'E-Banker master'!$A$2:$A$186,0)),"") -> 44076 | N7: =IFERROR(INDEX('E-Banker master'!$I$2:$I$186,MATCH($J7,'E-Banker master'!$A$2:$A$186,0)),"") -> 17000000 | O7: =IFERROR(INDEX('E-Banker master'!$N$2:$N$186,MATCH($J7,'E-Banker master'!$A$2:$A$186,0)),"") -> 12055000 | P7: =IFERROR(INDEX('E-Banker master'!$P$2:$P$186,MATCH($J7,'E-Banker master'!$A$2:$A$186,0)),"") -> 13568451 | Q7: =IFERROR(INDEX('E-Banker master'!$Q$2:$Q$186,MATCH($J7,'E-Banker master'!$A$2:$A$186,0)),"") -> 44076 | R7: =IFERROR(INDEX('E-Banker master'!$E$2:$E$186,MATCH($J7,'E-Banker master'!$A$2:$A$186,0)),"") -> D | S7: =IF($J7="","",IF(O7="","No take-on posting",IF(ABS(H7-O7)<1,"Yes",IF(ABS(H7/O7-1)<0.01,"Within 1%","No")))) -> Yes | T7: =IF($J7="","",IF(OR(P7="",P7=0),"No balance",IF(ABS(I7-P7)<1,"Yes",IF(ABS(I7/P7-1)<0.02,"Within 2%",IF(ABS(I7/P7-1)<0.05,"Within 5%","No"))))) -> No | U7: =IF($J7="","",IF(N7="","",IF(ABS(F7-N7)<1,"Yes",IF(ABS(G7-N7)<1,"Disbursed = sanction","No")))) -> Yes | V7: =IF(OR($J7="",Q7="",E7=""),"",ABS(E7-Q7)) -> 0 | W7: Yes
A8: 11 | B8: ='Loan Book'!D11 -> 7 | C8: ='Loan Book'!E11 -> LENZIEMILL MILLING LIMITED | D8: ='Loan Book'!F11 -> Debt | E8: ='Loan Book'!G11 -> 44134 | F8: ='Loan Book'!L11 -> 460000000 | G8: ='Loan Book'!M11 -> 297400000 | H8: ='Loan Book'!O11 -> 297400000 | I8: ='Loan Book'!R11 -> 1.670598e+08 | J8: 000104420000007 | K8: High | L8: =IFERROR(INDEX('E-Banker master'!$B$2:$B$186,MATCH($J8,'E-Banker master'!$A$2:$A$186,0)),"") -> LENZIEMILL MILLING LIMITED | M8: =IFERROR(INDEX('E-Banker master'!$H$2:$H$186,MATCH($J8,'E-Banker master'!$A$2:$A$186,0)),"") -> 44075 | N8: =IFERROR(INDEX('E-Banker master'!$I$2:$I$186,MATCH($J8,'E-Banker master'!$A$2:$A$186,0)),"") -> 460000000 | O8: =IFERROR(INDEX('E-Banker master'!$N$2:$N$186,MATCH($J8,'E-Banker master'!$A$2:$A$186,0)),"") -> 297400000 | P8: =IFERROR(INDEX('E-Banker master'!$P$2:$P$186,MATCH($J8,'E-Banker master'!$A$2:$A$186,0)),"") -> 1.6797652e+08 | Q8: =IFERROR(INDEX('E-Banker master'!$Q$2:$Q$186,MATCH($J8,'E-Banker master'!$A$2:$A$186,0)),"") -> 44075 | R8: =IFERROR(INDEX('E-Banker master'!$E$2:$E$186,MATCH($J8,'E-Banker master'!$A$2:$A$186,0)),"") -> H | S8: =IF($J8="","",IF(O8="","No take-on posting",IF(ABS(H8-O8)<1,"Yes",IF(ABS(H8/O8-1)<0.01,"Within 1%","No")))) -> Yes | T8: =IF($J8="","",IF(OR(P8="",P8=0),"No balance",IF(ABS(I8-P8)<1,"Yes",IF(ABS(I8/P8-1)<0.02,"Within 2%",IF(ABS(I8/P8-1)<0.05,"Within 5%","No"))))) -> Within 2% | U8: =IF($J8="","",IF(N8="","",IF(ABS(F8-N8)<1,"Yes",IF(ABS(G8-N8)<1,"Disbursed = sanction","No")))) -> Yes | V8: =IF(OR($J8="",Q8="",E8=""),"",ABS(E8-Q8)) -> 59 | W8: Yes
A9: 12 | B9: ='Loan Book'!D12 -> 8 | C9: ='Loan Book'!E12 -> Corran Farming Limited | D9: ='Loan Book'!F12 -> Debt | E9: ='Loan Book'!G12 -> 44187 | F9: ='Loan Book'!L12 -> 395623962 | G9: ='Loan Book'!M12 -> 395623962 | H9: ='Loan Book'!O12 -> 395623962 | I9: ='Loan Book'!R12 -> 0.00069212914 | J9: 000104430000008 | K9: High | L9: =IFERROR(INDEX('E-Banker master'!$B$2:$B$186,MATCH($J9,'E-Banker master'!$A$2:$A$186,0)),"") -> Corran Farming Limited | M9: =IFERROR(INDEX('E-Banker master'!$H$2:$H$186,MATCH($J9,'E-Banker master'!$A$2:$A$186,0)),"") -> 44501 | N9: =IFERROR(INDEX('E-Banker master'!$I$2:$I$186,MATCH($J9,'E-Banker master'!$A$2:$A$186,0)),"") -> 395623962 | O9: =IFERROR(INDEX('E-Banker master'!$N$2:$N$186,MATCH($J9,'E-Banker master'!$A$2:$A$186,0)),"") -> 0 | P9: =IFERROR(INDEX('E-Banker master'!$P$2:$P$186,MATCH($J9,'E-Banker master'!$A$2:$A$186,0)),"") -> 0 | Q9: =IFERROR(INDEX('E-Banker master'!$Q$2:$Q$186,MATCH($J9,'E-Banker master'!$A$2:$A$186,0)),"") -> 44187 | R9: =IFERROR(INDEX('E-Banker master'!$E$2:$E$186,MATCH($J9,'E-Banker master'!$A$2:$A$186,0)),"") -> C | S9: =IF($J9="","",IF(O9="","No take-on posting",IF(ABS(H9-O9)<1,"Yes",IF(ABS(H9/O9-1)<0.01,"Within 1%","No")))) -> #DIV/0! | T9: =IF($J9="","",IF(OR(P9="",P9=0),"No balance",IF(ABS(I9-P9)<1,"Yes",IF(ABS(I9/P9-1)<0.02,"Within 2%",IF(ABS(I9/P9-1)<0.05,"Within 5%","No"))))) -> No balance | U9: =IF($J9="","",IF(N9="","",IF(ABS(F9-N9)<1,"Yes",IF(ABS(G9-N9)<1,"Disbursed = sanction","No")))) -> Yes | V9: =IF(OR($J9="",Q9="",E9=""),"",ABS(E9-Q9)) -> 0 | W9: Yes
A10: 13 | B10: ='Loan Book'!D13 -> 9 | C10: ='Loan Book'!E13 -> Mach Milk Limited | D10: ='Loan Book'!F13 -> Debt | E10: ='Loan Book'!G13 -> 44242 | F10: ='Loan Book'!L13 -> 81075927 | G10: ='Loan Book'!M13 -> 81075927 | H10: ='Loan Book'!O13 -> 81075927 | I10: ='Loan Book'!R13 -> 1.271618e+08 | J10: 000104420000009 | K10: High | L10: =IFERROR(INDEX('E-Banker master'!$B$2:$B$186,MATCH($J10,'E-Banker master'!$A$2:$A$186,0)),"") -> Mach Milk Limited | M10: =IFERROR(INDEX('E-Banker master'!$H$2:$H$186,MATCH($J10,'E-Banker master'!$A$2:$A$186,0)),"") -> 44117 | N10: =IFERROR(INDEX('E-Banker master'!$I$2:$I$186,MATCH($J10,'E-Banker master'!$A$2:$A$186,0)),"") -> 65023440 | O10: =IFERROR(INDEX('E-Banker master'!$N$2:$N$186,MATCH($J10,'E-Banker master'!$A$2:$A$186,0)),"") -> 81075927 | P10: =IFERROR(INDEX('E-Banker master'!$P$2:$P$186,MATCH($J10,'E-Banker master'!$A$2:$A$186,0)),"") -> 1.3507055e+08 | Q10: =IFERROR(INDEX('E-Banker master'!$Q$2:$Q$186,MATCH($J10,'E-Banker master'!$A$2:$A$186,0)),"") -> 44117 | R10: =IFERROR(INDEX('E-Banker master'!$E$2:$E$186,MATCH($J10,'E-Banker master'!$A$2:$A$186,0)),"") -> D | S10: =IF($J10="","",IF(O10="","No take-on posting",IF(ABS(H10-O10)<1,"Yes",IF(ABS(H10/O10-1)<0.01,"Within 1%","No")))) -> Yes | T10: =IF($J10="","",IF(OR(P10="",P10=0),"No balance",IF(ABS(I10-P10)<1,"Yes",IF(ABS(I10/P10-1)<0.02,"Within 2%",IF(ABS(I10/P10-1)<0.05,"Within 5%","No"))))) -> No | U10: =IF($J10="","",IF(N10="","",IF(ABS(F10-N10)<1,"Yes",IF(ABS(G10-N10)<1,"Disbursed = sanction","No")))) -> No | V10: =IF(OR($J10="",Q10="",E10=""),"",ABS(E10-Q10)) -> 125 | W10: Yes
A11: 14 | B11: ='Loan Book'!D14 -> 10 | C11: ='Loan Book'!E14 -> Nature's Gift Limited | D11: ='Loan Book'!F14 -> Debt | E11: ='Loan Book'!G14 -> 44307 | F11: ='Loan Book'!L14 -> 80000000 | G11: ='Loan Book'!M14 -> 80000000 | H11: ='Loan Book'!O14 -> 80000000 | I11: ='Loan Book'!R14 -> 49987223 | J11: 000104420000010 | K11: High | L11: =IFERROR(INDEX('E-Banker master'!$B$2:$B$186,MATCH($J11,'E-Banker master'!$A$2:$A$186,0)),"") -> Nature's Gift Limited | M11: =IFERROR(INDEX('E-Banker master'!$H$2:$H$186,MATCH($J11,'E-Banker master'!$A$2:$A$186,0)),"") -> 44307 | N11: =IFERROR(INDEX('E-Banker master'!$I$2:$I$186,MATCH($J11,'E-Banker master'!$A$2:$A$186,0)),"") -> 80000000 | O11: =IFERROR(INDEX('E-Banker master'!$N$2:$N$186,MATCH($J11,'E-Banker master'!$A$2:$A$186,0)),"") -> 80000000 | P11: =IFERROR(INDEX('E-Banker master'!$P$2:$P$186,MATCH($J11,'E-Banker master'!$A$2:$A$186,0)),"") -> 50784762 | Q11: =IFERROR(INDEX('E-Banker master'!$Q$2:$Q$186,MATCH($J11,'E-Banker master'!$A$2:$A$186,0)),"") -> 44307 | R11: =IFERROR(INDEX('E-Banker master'!$E$2:$E$186,MATCH($J11,'E-Banker master'!$A$2:$A$186,0)),"") -> A | S11: =IF($J11="","",IF(O11="","No take-on posting",IF(ABS(H11-O11)<1,"Yes",IF(ABS(H11/O11-1)<0.01,"Within 1%","No")))) -> Yes | T11: =IF($J11="","",IF(OR(P11="",P11=0),"No balance",IF(ABS(I11-P11)<1,"Yes",IF(ABS(I11/P11-1)<0.02,"Within 2%",IF(ABS(I11/P11-1)<0.05,"Within 5%","No"))))) -> Within 2% | U11: =IF($J11="","",IF(N11="","",IF(ABS(F11-N11)<1,"Yes",IF(ABS(G11-N11)<1,"Disbursed = sanction","No")))) -> Yes | V11: =IF(OR($J11="",Q11="",E11=""),"",ABS(E11-Q11)) -> 0 | W11: Yes
A12: 15 | B12: ='Loan Book'!D15 -> 11 | C12: ='Loan Book'!E15 -> Nature's Gift Limited | D12: ='Loan Book'!F15 -> Debt | E12: ='Loan Book'!G15 -> 44400 | F12: ='Loan Book'!L15 -> 85000000 | G12: ='Loan Book'!M15 -> 85000000 | H12: ='Loan Book'!O15 -> 85000000 | I12: ='Loan Book'!R15 -> 42379450 | J12: 000104420000012 | K12: High | L12: =IFERROR(INDEX('E-Banker master'!$B$2:$B$186,MATCH($J12,'E-Banker master'!$A$2:$A$186,0)),"") -> Nature's Gift Limited | M12: =IFERROR(INDEX('E-Banker master'!$H$2:$H$186,MATCH($J12,'E-Banker master'!$A$2:$A$186,0)),"") -> 44400 | N12: =IFERROR(INDEX('E-Banker master'!$I$2:$I$186,MATCH($J12,'E-Banker master'!$A$2:$A$186,0)),"") -> 85000000 | O12: =IFERROR(INDEX('E-Banker master'!$N$2:$N$186,MATCH($J12,'E-Banker master'!$A$2:$A$186,0)),"") -> 85000000 | P12: =IFERROR(INDEX('E-Banker master'!$P$2:$P$186,MATCH($J12,'E-Banker master'!$A$2:$A$186,0)),"") -> 42742352 | Q12: =IFERROR(INDEX('E-Banker master'!$Q$2:$Q$186,MATCH($J12,'E-Banker master'!$A$2:$A$186,0)),"") -> 44400 | R12: =IFERROR(INDEX('E-Banker master'!$E$2:$E$186,MATCH($J12,'E-Banker master'!$A$2:$A$186,0)),"") -> A | S12: =IF($J12="","",IF(O12="","No take-on posting",IF(ABS(H12-O12)<1,"Yes",IF(ABS(H12/O12-1)<0.01,"Within 1%","No")))) -> Yes | T12: =IF($J12="","",IF(OR(P12="",P12=0),"No balance",IF(ABS(I12-P12)<1,"Yes",IF(ABS(I12/P12-1)<0.02,"Within 2%",IF(ABS(I12/P12-1)<0.05,"Within 5%","No"))))) -> Within 2% | U12: =IF($J12="","",IF(N12="","",IF(ABS(F12-N12)<1,"Yes",IF(ABS(G12-N12)<1,"Disbursed = sanction","No")))) -> Yes | V12: =IF(OR($J12="",Q12="",E12=""),"",ABS(E12-Q12)) -> 0 | W12: Yes
A13: 16 | B13: ='Loan Book'!D16 -> 12 | C13: ='Loan Book'!E16 -> Kajikhomele Foundation Ltd | D13: ='Loan Book'!F16 -> Debt | E13: ='Loan Book'!G16 -> 44336 | F13: ='Loan Book'!L16 -> 96552500 | G13: ='Loan Book'!M16 -> 96552500 | H13: ='Loan Book'!O16 -> 96552500 | I13: ='Loan Book'!R16 -> 1.5336996e+08 | J13: 000104420000011 | K13: High | L13: =IFERROR(INDEX('E-Banker master'!$B$2:$B$186,MATCH($J13,'E-Banker master'!$A$2:$A$186,0)),"") -> Kajikhomele Foundation Ltd | M13: =IFERROR(INDEX('E-Banker master'!$H$2:$H$186,MATCH($J13,'E-Banker master'!$A$2:$A$186,0)),"") -> 44266 | N13: =IFERROR(INDEX('E-Banker master'!$I$2:$I$186,MATCH($J13,'E-Banker master'!$A$2:$A$186,0)),"") -> 96552500 | O13: =IFERROR(INDEX('E-Banker master'!$N$2:$N$186,MATCH($J13,'E-Banker master'!$A$2:$A$186,0)),"") -> 96552500 | P13: =IFERROR(INDEX('E-Banker master'!$P$2:$P$186,MATCH($J13,'E-Banker master'!$A$2:$A$186,0)),"") -> 1.6208554e+08 | Q13: =IFERROR(INDEX('E-Banker master'!$Q$2:$Q$186,MATCH($J13,'E-Banker master'!$A$2:$A$186,0)),"") -> 44266 | R13: =IFERROR(INDEX('E-Banker master'!$E$2:$E$186,MATCH($J13,'E-Banker master'!$A$2:$A$186,0)),"") -> D | S13: =IF($J13="","",IF(O13="","No take-on posting",IF(ABS(H13-O13)<1,"Yes",IF(ABS(H13/O13-1)<0.01,"Within 1%","No")))) -> Yes | T13: =IF($J13="","",IF(OR(P13="",P13=0),"No balance",IF(ABS(I13-P13)<1,"Yes",IF(ABS(I13/P13-1)<0.02,"Within 2%",IF(ABS(I13/P13-1)<0.05,"Within 5%","No"))))) -> No | U13: =IF($J13="","",IF(N13="","",IF(ABS(F13-N13)<1,"Yes",IF(ABS(G13-N13)<1,"Disbursed = sanction","No")))) -> Yes | V13: =IF(OR($J13="",Q13="",E13=""),"",ABS(E13-Q13)) -> 70 | W13: Yes
... A38: 41 | B38: ='Loan Book'!D41 -> 37 | C38: ='Loan Book'!E41 -> Agribusiness Solutions Ltd | D38: ='Loan Book'!F41 -> Debt | E38: ='Loan Book'!G41 -> 44755 | F38: ='Loan Book'!L41 -> 24000000 | G38: ='Loan Book'!M41 -> 24000000 | H38: ='Loan Book'!O41 -> 24000000 | I38: ='Loan Book'!R41 -> 0 | J38: 000104450000036 | K38: High | L38: =IFERROR(INDEX('E-Banker master'!$B$2:$B$186,MATCH($J38,'E-Banker master'!$A$2:$A$186,0)),"") -> Agribusiness Solutions Limited | M38: =IFERROR(INDEX('E-Banker master'!$H$2:$H$186,MATCH($J38,'E-Banker master'!$A$2:$A$186,0)),"") -> 44753 | N38: =IFERROR(INDEX('E-Banker master'!$I$2:$I$186,MATCH($J38,'E-Banker master'!$A$2:$A$186,0)),"") -> 24000000 | O38: =IFERROR(INDEX('E-Banker master'!$N$2:$N$186,MATCH($J38,'E-Banker master'!$A$2:$A$186,0)),"") -> 0 | P38: =IFERROR(INDEX('E-Banker master'!$P$2:$P$186,MATCH($J38,'E-Banker master'!$A$2:$A$186,0)),"") -> 0 | Q38: =IFERROR(INDEX('E-Banker master'!$Q$2:$Q$186,MATCH($J38,'E-Banker master'!$A$2:$A$186,0)),"") -> 44755 | R38: =IFERROR(INDEX('E-Banker master'!$E$2:$E$186,MATCH($J38,'E-Banker master'!$A$2:$A$186,0)),"") -> C | S38: =IF($J38="","",IF(O38="","No take-on posting",IF(ABS(H38-O38)<1,"Yes",IF(ABS(H38/O38-1)<0.01,"Within 1%","No")))) -> #DIV/0! | T38: =IF($J38="","",IF(OR(P38="",P38=0),"No balance",IF(ABS(I38-P38)<1,"Yes",IF(ABS(I38/P38-1)<0.02,"Within 2%",IF(ABS(I38/P38-1)<0.05,"Within 5%","No"))))) -> No balance | U38: =IF($J38="","",IF(N38="","",IF(ABS(F38-N38)<1,"Yes",IF(ABS(G38-N38)<1,"Disbursed = sanction","No")))) -> Yes | V38: =IF(OR($J38="",Q38="",E38=""),"",ABS(E38-Q38)) -> 0 | W38: Yes
A39: 42 | B39: ='Loan Book'!D42 -> 38 | C39: ='Loan Book'!E42 -> Favoured Farms | D39: ='Loan Book'!F42 -> Debt | E39: ='Loan Book'!G42 -> 44755 | F39: ='Loan Book'!L42 -> 10000000 | G39: ='Loan Book'!M42 -> 10000000 | H39: ='Loan Book'!O42 -> 10000000 | I39: ='Loan Book'!R42 -> 0 | K39: Not matched | L39: =IFERROR(INDEX('E-Banker master'!$B$2:$B$186,MATCH($J39,'E-Banker master'!$A$2:$A$186,0)),"") | M39: =IFERROR(INDEX('E-Banker master'!$H$2:$H$186,MATCH($J39,'E-Banker master'!$A$2:$A$186,0)),"") | N39: =IFERROR(INDEX('E-Banker master'!$I$2:$I$186,MATCH($J39,'E-Banker master'!$A$2:$A$186,0)),"") | O39: =IFERROR(INDEX('E-Banker master'!$N$2:$N$186,MATCH($J39,'E-Banker master'!$A$2:$A$186,0)),"") | P39: =IFERROR(INDEX('E-Banker master'!$P$2:$P$186,MATCH($J39,'E-Banker master'!$A$2:$A$186,0)),"") | Q39: =IFERROR(INDEX('E-Banker master'!$Q$2:$Q$186,MATCH($J39,'E-Banker master'!$A$2:$A$186,0)),"") | R39: =IFERROR(INDEX('E-Banker master'!$E$2:$E$186,MATCH($J39,'E-Banker master'!$A$2:$A$186,0)),"") | S39: =IF($J39="","",IF(O39="","No take-on posting",IF(ABS(H39-O39)<1,"Yes",IF(ABS(H39/O39-1)<0.01,"Within 1%","No")))) | T39: =IF($J39="","",IF(OR(P39="",P39=0),"No balance",IF(ABS(I39-P39)<1,"Yes",IF(ABS(I39/P39-1)<0.02,"Within 2%",IF(ABS(I39/P39-1)<0.05,"Within 5%","No"))))) | U39: =IF($J39="","",IF(N39="","",IF(ABS(F39-N39)<1,"Yes",IF(ABS(G39-N39)<1,"Disbursed = sanction","No")))) | V39: =IF(OR($J39="",Q39="",E39=""),"",ABS(E39-Q39)) | W39: No
A40: 43 | B40: ='Loan Book'!D43 -> 39 | C40: ='Loan Book'!E43 -> Tac-Maz Investment | D40: ='Loan Book'!F43 -> Debt | E40: ='Loan Book'!G43 -> 44755 | F40: ='Loan Book'!L43 -> 10000000 | G40: ='Loan Book'!M43 -> 10000000 | H40: ='Loan Book'!O43 -> 10000000 | I40: ='Loan Book'!R43 -> 5853113.4 | J40: 000104450000038 | K40: High | L40: =IFERROR(INDEX('E-Banker master'!$B$2:$B$186,MATCH($J40,'E-Banker master'!$A$2:$A$186,0)),"") -> Tac-Maz Investment | M40: =IFERROR(INDEX('E-Banker master'!$H$2:$H$186,MATCH($J40,'E-Banker master'!$A$2:$A$186,0)),"") -> 44754 | N40: =IFERROR(INDEX('E-Banker master'!$I$2:$I$186,MATCH($J40,'E-Banker master'!$A$2:$A$186,0)),"") -> 10000000 | O40: =IFERROR(INDEX('E-Banker master'!$N$2:$N$186,MATCH($J40,'E-Banker master'!$A$2:$A$186,0)),"") -> 10000000 | P40: =IFERROR(INDEX('E-Banker master'!$P$2:$P$186,MATCH($J40,'E-Banker master'!$A$2:$A$186,0)),"") -> 5917617.5 | Q40: =IFERROR(INDEX('E-Banker master'!$Q$2:$Q$186,MATCH($J40,'E-Banker master'!$A$2:$A$186,0)),"") -> 44755 | R40: =IFERROR(INDEX('E-Banker master'!$E$2:$E$186,MATCH($J40,'E-Banker master'!$A$2:$A$186,0)),"") -> H | S40: =IF($J40="","",IF(O40="","No take-on posting",IF(ABS(H40-O40)<1,"Yes",IF(ABS(H40/O40-1)<0.01,"Within 1%","No")))) -> Yes | T40: =IF($J40="","",IF(OR(P40="",P40=0),"No balance",IF(ABS(I40-P40)<1,"Yes",IF(ABS(I40/P40-1)<0.02,"Within 2%",IF(ABS(I40/P40-1)<0.05,"Within 5%","No"))))) -> Within 2% | U40: =IF($J40="","",IF(N40="","",IF(ABS(F40-N40)<1,"Yes",IF(ABS(G40-N40)<1,"Disbursed = sanction","No")))) -> Yes | V40: =IF(OR($J40="",Q40="",E40=""),"",ABS(E40-Q40)) -> 0 | W40: Yes
A41: 44 | B41: ='Loan Book'!D44 -> 40 | C41: ='Loan Book'!E44 -> G & S Home Mart & Agrodealer | D41: ='Loan Book'!F44 -> Debt | E41: ='Loan Book'!G44 -> 44755 | F41: ='Loan Book'!L44 -> 10000000 | G41: ='Loan Book'!M44 -> 7000000 | H41: ='Loan Book'!O44 -> 7000000 | I41: ='Loan Book'!R44 -> 0 | J41: 000104450000039 | K41: High | L41: =IFERROR(INDEX('E-Banker master'!$B$2:$B$186,MATCH($J41,'E-Banker master'!$A$2:$A$186,0)),"") -> G&S HomeMart and Agrodealer | M41: =IFERROR(INDEX('E-Banker master'!$H$2:$H$186,MATCH($J41,'E-Banker master'!$A$2:$A$186,0)),"") -> 44754 | N41: =IFERROR(INDEX('E-Banker master'!$I$2:$I$186,MATCH($J41,'E-Banker master'!$A$2:$A$186,0)),"") -> 10000000 | O41: =IFERROR(INDEX('E-Banker master'!$N$2:$N$186,MATCH($J41,'E-Banker master'!$A$2:$A$186,0)),"") -> 0 | P41: =IFERROR(INDEX('E-Banker master'!$P$2:$P$186,MATCH($J41,'E-Banker master'!$A$2:$A$186,0)),"") -> 0 | Q41: =IFERROR(INDEX('E-Banker master'!$Q$2:$Q$186,MATCH($J41,'E-Banker master'!$A$2:$A$186,0)),"") -> 44755 | R41: =IFERROR(INDEX('E-Banker master'!$E$2:$E$186,MATCH($J41,'E-Banker master'!$A$2:$A$186,0)),"") -> C | S41: =IF($J41="","",IF(O41="","No take-on posting",IF(ABS(H41-O41)<1,"Yes",IF(ABS(H41/O41-1)<0.01,"Within 1%","No")))) -> #DIV/0! | T41: =IF($J41="","",IF(OR(P41="",P41=0),"No balance",IF(ABS(I41-P41)<1,"Yes",IF(ABS(I41/P41-1)<0.02,"Within 2%",IF(ABS(I41/P41-1)<0.05,"Within 5%","No"))))) -> No balance | U41: =IF($J41="","",IF(N41="","",IF(ABS(F41-N41)<1,"Yes",IF(ABS(G41-N41)<1,"Disbursed = sanction","No")))) -> Yes | V41: =IF(OR($J41="",Q41="",E41=""),"",ABS(E41-Q41)) -> 0 | W41: Yes
A42: 45 | B42: ='Loan Book'!D45 -> 41 | C42: ='Loan Book'!E45 -> Ziweto Enterprise | D42: ='Loan Book'!F45 -> Debt | E42: ='Loan Book'!G45 -> 44761 | F42: ='Loan Book'!L45 -> 152910000 | G42: ='Loan Book'!M45 -> 152910000 | H42: ='Loan Book'!O45 -> 152910000 | I42: ='Loan Book'!R45 -> 0.00139907 | J42: 000104420000040 | K42: High | L42: =IFERROR(INDEX('E-Banker master'!$B$2:$B$186,MATCH($J42,'E-Banker master'!$A$2:$A$186,0)),"") -> Ziweto Enterprise | M42: =IFERROR(INDEX('E-Banker master'!$H$2:$H$186,MATCH($J42,'E-Banker master'!$A$2:$A$186,0)),"") -> 44761 | N42: =IFERROR(INDEX('E-Banker master'!$I$2:$I$186,MATCH($J42,'E-Banker master'!$A$2:$A$186,0)),"") -> 152910000 | O42: =IFERROR(INDEX('E-Banker master'!$N$2:$N$186,MATCH($J42,'E-Banker master'!$A$2:$A$186,0)),"") -> 0 | P42: =IFERROR(INDEX('E-Banker master'!$P$2:$P$186,MATCH($J42,'E-Banker master'!$A$2:$A$186,0)),"") -> 0 | Q42: =IFERROR(INDEX('E-Banker master'!$Q$2:$Q$186,MATCH($J42,'E-Banker master'!$A$2:$A$186,0)),"") -> 44761 | R42: =IFERROR(INDEX('E-Banker master'!$E$2:$E$186,MATCH($J42,'E-Banker master'!$A$2:$A$186,0)),"") -> C | S42: =IF($J42="","",IF(O42="","No take-on posting",IF(ABS(H42-O42)<1,"Yes",IF(ABS(H42/O42-1)<0.01,"Within 1%","No")))) -> #DIV/0! | T42: =IF($J42="","",IF(OR(P42="",P42=0),"No balance",IF(ABS(I42-P42)<1,"Yes",IF(ABS(I42/P42-1)<0.02,"Within 2%",IF(ABS(I42/P42-1)<0.05,"Within 5%","No"))))) -> No balance | U42: =IF($J42="","",IF(N42="","",IF(ABS(F42-N42)<1,"Yes",IF(ABS(G42-N42)<1,"Disbursed = sanction","No")))) -> Yes | V42: =IF(OR($J42="",Q42="",E42=""),"",ABS(E42-Q42)) -> 0 | W42: Yes
A43: 46 | B43: ='Loan Book'!D46 -> 42 | C43: ='Loan Book'!E46 -> Kadava Investment Limited | D43: ='Loan Book'!F46 -> Debt | E43: ='Loan Book'!G46 -> 44775 | F43: ='Loan Book'!L46 -> 12000000 | G43: ='Loan Book'!M46 -> 12000000 | H43: ='Loan Book'!O46 -> 12000000 | I43: ='Loan Book'!R46 -> 4107865.3 | J43: 000104450000041 | K43: High | L43: =IFERROR(INDEX('E-Banker master'!$B$2:$B$186,MATCH($J43,'E-Banker master'!$A$2:$A$186,0)),"") -> Kadava Investment Limited | M43: =IFERROR(INDEX('E-Banker master'!$H$2:$H$186,MATCH($J43,'E-Banker master'!$A$2:$A$186,0)),"") -> 44785 | N43: =IFERROR(INDEX('E-Banker master'!$I$2:$I$186,MATCH($J43,'E-Banker master'!$A$2:$A$186,0)),"") -> 12000000 | O43: =IFERROR(INDEX('E-Banker master'!$N$2:$N$186,MATCH($J43,'E-Banker master'!$A$2:$A$186,0)),"") -> 12000000 | P43: =IFERROR(INDEX('E-Banker master'!$P$2:$P$186,MATCH($J43,'E-Banker master'!$A$2:$A$186,0)),"") -> 4496798.7 | Q43: =IFERROR(INDEX('E-Banker master'!$Q$2:$Q$186,MATCH($J43,'E-Banker master'!$A$2:$A$186,0)),"") -> 44775 | R43: =IFERROR(INDEX('E-Banker master'!$E$2:$E$186,MATCH($J43,'E-Banker master'!$A$2:$A$186,0)),"") -> H | S43: =IF($J43="","",IF(O43="","No take-on posting",IF(ABS(H43-O43)<1,"Yes",IF(ABS(H43/O43-1)<0.01,"Within 1%","No")))) -> Yes | T43: =IF($J43="","",IF(OR(P43="",P43=0),"No balance",IF(ABS(I43-P43)<1,"Yes",IF(ABS(I43/P43-1)<0.02,"Within 2%",IF(ABS(I43/P43-1)<0.05,"Within 5%","No"))))) -> No | U43: =IF($J43="","",IF(N43="","",IF(ABS(F43-N43)<1,"Yes",IF(ABS(G43-N43)<1,"Disbursed = sanction","No")))) -> Yes | V43: =IF(OR($J43="",Q43="",E43=""),"",ABS(E43-Q43)) -> 0 | W43: Yes
A44: 47 | B44: ='Loan Book'!D47 -> 43 | C44: ='Loan Book'!E47 -> Zikometso Smallholder Farmers Association | D44: ='Loan Book'!F47 -> Debt | E44: ='Loan Book'!G47 -> 44775 | F44: ='Loan Book'!L47 -> 24000000 | G44: ='Loan Book'!M47 -> 11423340 | H44: ='Loan Book'!O47 -> 11423340 | I44: ='Loan Book'!R47 -> -0.0032923882 | J44: 000104450000042 | K44: High | L44: =IFERROR(INDEX('E-Banker master'!$B$2:$B$186,MATCH($J44,'E-Banker master'!$A$2:$A$186,0)),"") -> Zikometso Smallholder Farmers Association | M44: =IFERROR(INDEX('E-Banker master'!$H$2:$H$186,MATCH($J44,'E-Banker master'!$A$2:$A$186,0)),"") -> 44785 | N44: =IFERROR(INDEX('E-Banker master'!$I$2:$I$186,MATCH($J44,'E-Banker master'!$A$2:$A$186,0)),"") -> 24000000 | O44: =IFERROR(INDEX('E-Banker master'!$N$2:$N$186,MATCH($J44,'E-Banker master'!$A$2:$A$186,0)),"") -> 11423340 | P44: =IFERROR(INDEX('E-Banker master'!$P$2:$P$186,MATCH($J44,'E-Banker master'!$A$2:$A$186,0)),"") -> 8338.12 | Q44: =IFERROR(INDEX('E-Banker master'!$Q$2:$Q$186,MATCH($J44,'E-Banker master'!$A$2:$A$186,0)),"") -> 44775 | R44: =IFERROR(INDEX('E-Banker master'!$E$2:$E$186,MATCH($J44,'E-Banker master'!$A$2:$A$186,0)),"") -> H | S44: =IF($J44="","",IF(O44="","No take-on posting",IF(ABS(H44-O44)<1,"Yes",IF(ABS(H44/O44-1)<0.01,"Within 1%","No")))) -> Yes | T44: =IF($J44="","",IF(OR(P44="",P44=0),"No balance",IF(ABS(I44-P44)<1,"Yes",IF(ABS(I44/P44-1)<0.02,"Within 2%",IF(ABS(I44/P44-1)<0.05,"Within 5%","No"))))) -> No | U44: =IF($J44="","",IF(N44="","",IF(ABS(F44-N44)<1,"Yes",IF(ABS(G44-N44)<1,"Disbursed = sanction","No")))) -> Yes | V44: =IF(OR($J44="",Q44="",E44=""),"",ABS(E44-Q44)) -> 0 | W44: Yes
A45: 48 | B45: ='Loan Book'!D48 -> 44 | C45: ='Loan Book'!E48 -> The Food Empire Limited | D45: ='Loan Book'!F48 -> Debt | E45: ='Loan Book'!G48 -> 44785 | F45: ='Loan Book'!L48 -> 154724500 | G45: ='Loan Book'!M48 -> 154724500 | H45: ='Loan Book'!O48 -> 154724500 | I45: ='Loan Book'!R48 -> 1.0087466e+08 | J45: 000104420000043 | K45: High | L45: =IFERROR(INDEX('E-Banker master'!$B$2:$B$186,MATCH($J45,'E-Banker master'!$A$2:$A$186,0)),"") -> The Food Empire Limited | M45: =IFERROR(INDEX('E-Banker master'!$H$2:$H$186,MATCH($J45,'E-Banker master'!$A$2:$A$186,0)),"") -> 44746 | N45: =IFERROR(INDEX('E-Banker master'!$I$2:$I$186,MATCH($J45,'E-Banker master'!$A$2:$A$186,0)),"") -> 154724500 | O45: =IFERROR(INDEX('E-Banker master'!$N$2:$N$186,MATCH($J45,'E-Banker master'!$A$2:$A$186,0)),"") -> 154724500 | P45: =IFERROR(INDEX('E-Banker master'!$P$2:$P$186,MATCH($J45,'E-Banker master'!$A$2:$A$186,0)),"") -> 1.0142784e+08 | Q45: =IFERROR(INDEX('E-Banker master'!$Q$2:$Q$186,MATCH($J45,'E-Banker master'!$A$2:$A$186,0)),"") -> 44746 | R45: =IFERROR(INDEX('E-Banker master'!$E$2:$E$186,MATCH($J45,'E-Banker master'!$A$2:$A$186,0)),"") -> F | S45: =IF($J45="","",IF(O45="","No take-on posting",IF(ABS(H45-O45)<1,"Yes",IF(ABS(H45/O45-1)<0.01,"Within 1%","No")))) -> Yes | T45: =IF($J45="","",IF(OR(P45="",P45=0),"No balance",IF(ABS(I45-P45)<1,"Yes",IF(ABS(I45/P45-1)<0.02,"Within 2%",IF(ABS(I45/P45-1)<0.05,"Within 5%","No"))))) -> Within 2% | U45: =IF($J45="","",IF(N45="","",IF(ABS(F45-N45)<1,"Yes",IF(ABS(G45-N45)<1,"Disbursed = sanction","No")))) -> Yes | V45: =IF(OR($J45="",Q45="",E45=""),"",ABS(E45-Q45)) -> 39 | W45: Yes
A46: 49 | B46: ='Loan Book'!D49 -> 45 | C46: ='Loan Book'!E49 -> Global Seeds Ltd | D46: ='Loan Book'!F49 -> Debt | E46: ='Loan Book'!G49 -> 44803 | F46: ='Loan Book'!L49 -> 103225546 | G46: ='Loan Book'!M49 -> 103225546 | H46: ='Loan Book'!O49 -> 103225546 | I46: ='Loan Book'!R49 -> 0.0030568242 | J46: 000104420000044 | K46: High | L46: =IFERROR(INDEX('E-Banker master'!$B$2:$B$186,MATCH($J46,'E-Banker master'!$A$2:$A$186,0)),"") -> Global Seeds Limited FInES | M46: =IFERROR(INDEX('E-Banker master'!$H$2:$H$186,MATCH($J46,'E-Banker master'!$A$2:$A$186,0)),"") -> 44803 | N46: =IFERROR(INDEX('E-Banker master'!$I$2:$I$186,MATCH($J46,'E-Banker master'!$A$2:$A$186,0)),"") -> 103225546 | O46: =IFERROR(INDEX('E-Banker master'!$N$2:$N$186,MATCH($J46,'E-Banker master'!$A$2:$A$186,0)),"") -> 0 | P46: =IFERROR(INDEX('E-Banker master'!$P$2:$P$186,MATCH($J46,'E-Banker master'!$A$2:$A$186,0)),"") -> 0 | Q46: =IFERROR(INDEX('E-Banker master'!$Q$2:$Q$186,MATCH($J46,'E-Banker master'!$A$2:$A$186,0)),"") -> 44803 | R46: =IFERROR(INDEX('E-Banker master'!$E$2:$E$186,MATCH($J46,'E-Banker master'!$A$2:$A$186,0)),"") -> C | S46: =IF($J46="","",IF(O46="","No take-on posting",IF(ABS(H46-O46)<1,"Yes",IF(ABS(H46/O46-1)<0.01,"Within 1%","No")))) -> #DIV/0! | T46: =IF($J46="","",IF(OR(P46="",P46=0),"No balance",IF(ABS(I46-P46)<1,"Yes",IF(ABS(I46/P46-1)<0.02,"Within 2%",IF(ABS(I46/P46-1)<0.05,"Within 5%","No"))))) -> No balance | U46: =IF($J46="","",IF(N46="","",IF(ABS(F46-N46)<1,"Yes",IF(ABS(G46-N46)<1,"Disbursed = sanction","No")))) -> Yes | V46: =IF(OR($J46="",Q46="",E46=""),"",ABS(E46-Q46)) -> 0 | W46: Yes
A47: 50 | B47: ='Loan Book'!D50 -> 46 | C47: ='Loan Book'!E50 -> Walusiya Investment | D47: ='Loan Book'!F50 -> Debt | E47: ='Loan Book'!G50 -> 44844 | F47: ='Loan Book'!L50 -> 10000000 | G47: ='Loan Book'!M50 -> 10000000 | H47: ='Loan Book'!O50 -> 10000000 | I47: ='Loan Book'!R50 -> 9144189.6 | J47: 000104450000045 | K47: High | L47: =IFERROR(INDEX('E-Banker master'!$B$2:$B$186,MATCH($J47,'E-Banker master'!$A$2:$A$186,0)),"") -> Walusiya Investment | M47: =IFERROR(INDEX('E-Banker master'!$H$2:$H$186,MATCH($J47,'E-Banker master'!$A$2:$A$186,0)),"") -> 44841 | N47: =IFERROR(INDEX('E-Banker master'!$I$2:$I$186,MATCH($J47,'E-Banker master'!$A$2:$A$186,0)),"") -> 10000000 | O47: =IFERROR(INDEX('E-Banker master'!$N$2:$N$186,MATCH($J47,'E-Banker master'!$A$2:$A$186,0)),"") -> 10000000 | P47: =IFERROR(INDEX('E-Banker master'!$P$2:$P$186,MATCH($J47,'E-Banker master'!$A$2:$A$186,0)),"") -> 9371307 | Q47: =IFERROR(INDEX('E-Banker master'!$Q$2:$Q$186,MATCH($J47,'E-Banker master'!$A$2:$A$186,0)),"") -> 44844 | R47: =IFERROR(INDEX('E-Banker master'!$E$2:$E$186,MATCH($J47,'E-Banker master'!$A$2:$A$186,0)),"") -> H | S47: =IF($J47="","",IF(O47="","No take-on posting",IF(ABS(H47-O47)<1,"Yes",IF(ABS(H47/O47-1)<0.01,"Within 1%","No")))) -> Yes | T47: =IF($J47="","",IF(OR(P47="",P47=0),"No balance",IF(ABS(I47-P47)<1,"Yes",IF(ABS(I47/P47-1)<0.02,"Within 2%",IF(ABS(I47/P47-1)<0.05,"Within 5%","No"))))) -> Within 5% | U47: =IF($J47="","",IF(N47="","",IF(ABS(F47-N47)<1,"Yes",IF(ABS(G47-N47)<1,"Disbursed = sanction","No")))) -> Yes | V47: =IF(OR($J47="",Q47="",E47=""),"",ABS(E47-Q47)) -> 0 | W47: Yes
A48: 51 | B48: ='Loan Book'!D51 -> 47 | C48: ='Loan Book'!E51 -> G&T General Dealers | D48: ='Loan Book'!F51 -> Debt | E48: ='Loan Book'!G51 -> 44844 | F48: ='Loan Book'!L51 -> 12000000 | G48: ='Loan Book'!M51 -> 12000000 | H48: ='Loan Book'!O51 -> 12000000 | I48: ='Loan Book'!R51 -> 7041027.5 | J48: 000104450000046 | K48: High | L48: =IFERROR(INDEX('E-Banker master'!$B$2:$B$186,MATCH($J48,'E-Banker master'!$A$2:$A$186,0)),"") -> G&T General Dealers | M48: =IFERROR(INDEX('E-Banker master'!$H$2:$H$186,MATCH($J48,'E-Banker master'!$A$2:$A$186,0)),"") -> 44713 | N48: =IFERROR(INDEX('E-Banker master'!$I$2:$I$186,MATCH($J48,'E-Banker master'!$A$2:$A$186,0)),"") -> 12000000 | O48: =IFERROR(INDEX('E-Banker master'!$N$2:$N$186,MATCH($J48,'E-Banker master'!$A$2:$A$186,0)),"") -> 12000000 | P48: =IFERROR(INDEX('E-Banker master'!$P$2:$P$186,MATCH($J48,'E-Banker master'!$A$2:$A$186,0)),"") -> 7207696 | Q48: =IFERROR(INDEX('E-Banker master'!$Q$2:$Q$186,MATCH($J48,'E-Banker master'!$A$2:$A$186,0)),"") -> 44844 | R48: =IFERROR(INDEX('E-Banker master'!$E$2:$E$186,MATCH($J48,'E-Banker master'!$A$2:$A$186,0)),"") -> H | S48: =IF($J48="","",IF(O48="","No take-on posting",IF(ABS(H48-O48)<1,"Yes",IF(ABS(H48/O48-1)<0.01,"Within 1%","No")))) -> Yes | T48: =IF($J48="","",IF(OR(P48="",P48=0),"No balance",IF(ABS(I48-P48)<1,"Yes",IF(ABS(I48/P48-1)<0.02,"Within 2%",IF(ABS(I48/P48-1)<0.05,"Within 5%","No"))))) -> Within 5% | U48: =IF($J48="","",IF(N48="","",IF(ABS(F48-N48)<1,"Yes",IF(ABS(G48-N48)<1,"Disbursed = sanction","No")))) -> Yes | V48: =IF(OR($J48="",Q48="",E48=""),"",ABS(E48-Q48)) -> 0 | W48: Yes
A49: 52 | B49: ='Loan Book'!D52 -> 48 | C49: ='Loan Book'!E52 -> Rose Harris Investment | D49: ='Loan Book'!F52 -> Debt | E49: ='Loan Book'!G52 -> 44852 | F49: ='Loan Book'!L52 -> 24000000 | G49: ='Loan Book'!M52 -> 24000000 | H49: ='Loan Book'!O52 -> 24000000 | I49: ='Loan Book'!R52 -> 0 | J49: 000104450000047 | K49: High | L49: =IFERROR(INDEX('E-Banker master'!$B$2:$B$186,MATCH($J49,'E-Banker master'!$A$2:$A$186,0)),"") -> Rose Harris Investment | M49: =IFERROR(INDEX('E-Banker master'!$H$2:$H$186,MATCH($J49,'E-Banker master'!$A$2:$A$186,0)),"") -> 44847 | N49: =IFERROR(INDEX('E-Banker master'!$I$2:$I$186,MATCH($J49,'E-Banker master'!$A$2:$A$186,0)),"") -> 24000000 | O49: =IFERROR(INDEX('E-Banker master'!$N$2:$N$186,MATCH($J49,'E-Banker master'!$A$2:$A$186,0)),"") -> 0 | P49: =IFERROR(INDEX('E-Banker master'!$P$2:$P$186,MATCH($J49,'E-Banker master'!$A$2:$A$186,0)),"") -> 0 | Q49: =IFERROR(INDEX('E-Banker master'!$Q$2:$Q$186,MATCH($J49,'E-Banker master'!$A$2:$A$186,0)),"") -> 44852 | R49: =IFERROR(INDEX('E-Banker master'!$E$2:$E$186,MATCH($J49,'E-Banker master'!$A$2:$A$186,0)),"") -> C | S49: =IF($J49="","",IF(O49="","No take-on posting",IF(ABS(H49-O49)<1,"Yes",IF(ABS(H49/O49-1)<0.01,"Within 1%","No")))) -> #DIV/0! | T49: =IF($J49="","",IF(OR(P49="",P49=0),"No balance",IF(ABS(I49-P49)<1,"Yes",IF(ABS(I49/P49-1)<0.02,"Within 2%",IF(ABS(I49/P49-1)<0.05,"Within 5%","No"))))) -> No balance | U49: =IF($J49="","",IF(N49="","",IF(ABS(F49-N49)<1,"Yes",IF(ABS(G49-N49)<1,"Disbursed = sanction","No")))) -> Yes | V49: =IF(OR($J49="",Q49="",E49=""),"",ABS(E49-Q49)) -> 0 | W49: Yes
A50: 53 | B50: ='Loan Book'!D53 -> 49 | C50: ='Loan Book'!E53 -> Kaning'a General Dealer | D50: ='Loan Book'!F53 -> Debt | E50: ='Loan Book'!G53 -> 44861 | F50: ='Loan Book'!L53 -> 24000000 | G50: ='Loan Book'!M53 -> 24000000 | H50: ='Loan Book'!O53 -> 24000000 | I50: ='Loan Book'!R53 -> 0 | J50: 000104450000048 | K50: High | L50: =IFERROR(INDEX('E-Banker master'!$B$2:$B$186,MATCH($J50,'E-Banker master'!$A$2:$A$186,0)),"") -> KANING'A GENERAL DEALER | M50: =IFERROR(INDEX('E-Banker master'!$H$2:$H$186,MATCH($J50,'E-Banker master'!$A$2:$A$186,0)),"") -> 44860 | N50: =IFERROR(INDEX('E-Banker master'!$I$2:$I$186,MATCH($J50,'E-Banker master'!$A$2:$A$186,0)),"") -> 24000000 | O50: =IFERROR(INDEX('E-Banker master'!$N$2:$N$186,MATCH($J50,'E-Banker master'!$A$2:$A$186,0)),"") -> 24000000 | P50: =IFERROR(INDEX('E-Banker master'!$P$2:$P$186,MATCH($J50,'E-Banker master'!$A$2:$A$186,0)),"") -> 1685.92 | Q50: =IFERROR(INDEX('E-Banker master'!$Q$2:$Q$186,MATCH($J50,'E-Banker master'!$A$2:$A$186,0)),"") -> 44861 | R50: =IFERROR(INDEX('E-Banker master'!$E$2:$E$186,MATCH($J50,'E-Banker master'!$A$2:$A$186,0)),"") -> H | S50: =IF($J50="","",IF(O50="","No take-on posting",IF(ABS(H50-O50)<1,"Yes",IF(ABS(H50/O50-1)<0.01,"Within 1%","No")))) -> Yes | T50: =IF($J50="","",IF(OR(P50="",P50=0),"No balance",IF(ABS(I50-P50)<1,"Yes",IF(ABS(I50/P50-1)<0.02,"Within 2%",IF(ABS(I50/P50-1)<0.05,"Within 5%","No"))))) -> No | U50: =IF($J50="","",IF(N50="","",IF(ABS(F50-N50)<1,"Yes",IF(ABS(G50-N50)<1,"Disbursed = sanction","No")))) -> Yes | V50: =IF(OR($J50="",Q50="",E50=""),"",ABS(E50-Q50)) -> 0 | W50: Yes
A51: 54 | B51: ='Loan Book'!D54 -> 50 | C51: ='Loan Book'!E54 -> Uchi Conservation Limited | D51: ='Loan Book'!F54 -> Debt | E51: ='Loan Book'!G54 -> 44867 | F51: ='Loan Book'!L54 -> 10000000 | G51: ='Loan Book'!M54 -> 10000000 | H51: ='Loan Book'!O54 -> 10000000 | I51: ='Loan Book'!R54 -> 6698763.2 | J51: 000104450000049 | K51: High | L51: =IFERROR(INDEX('E-Banker master'!$B$2:$B$186,MATCH($J51,'E-Banker master'!$A$2:$A$186,0)),"") -> Uchi Conservation Limited | M51: =IFERROR(INDEX('E-Banker master'!$H$2:$H$186,MATCH($J51,'E-Banker master'!$A$2:$A$186,0)),"") -> 44866 | N51: =IFERROR(INDEX('E-Banker master'!$I$2:$I$186,MATCH($J51,'E-Banker master'!$A$2:$A$186,0)),"") -> 10000000 | O51: =IFERROR(INDEX('E-Banker master'!$N$2:$N$186,MATCH($J51,'E-Banker master'!$A$2:$A$186,0)),"") -> 10000000 | P51: =IFERROR(INDEX('E-Banker master'!$P$2:$P$186,MATCH($J51,'E-Banker master'!$A$2:$A$186,0)),"") -> 6882460.2 | Q51: =IFERROR(INDEX('E-Banker master'!$Q$2:$Q$186,MATCH($J51,'E-Banker master'!$A$2:$A$186,0)),"") -> 44867 | R51: =IFERROR(INDEX('E-Banker master'!$E$2:$E$186,MATCH($J51,'E-Banker master'!$A$2:$A$186,0)),"") -> D | S51: =IF($J51="","",IF(O51="","No take-on posting",IF(ABS(H51-O51)<1,"Yes",IF(ABS(H51/O51-1)<0.01,"Within 1%","No")))) -> Yes | T51: =IF($J51="","",IF(OR(P51="",P51=0),"No balance",IF(ABS(I51-P51)<1,"Yes",IF(ABS(I51/P51-1)<0.02,"Within 2%",IF(ABS(I51/P51-1)<0.05,"Within 5%","No"))))) -> Within 5% | U51: =IF($J51="","",IF(N51="","",IF(ABS(F51-N51)<1,"Yes",IF(ABS(G51-N51)<1,"Disbursed = sanction","No")))) -> Yes | V51: =IF(OR($J51="",Q51="",E51=""),"",ABS(E51-Q51)) -> 0 | W51: Yes
... A104: 107 | B104: ='Loan Book'!D107 -> 103 | C104: ='Loan Book'!E107 -> Agwenda Investment Limited | D104: ='Loan Book'!F107 -> Debt | E104: ='Loan Book'!G107 -> 45587 | F104: ='Loan Book'!L107 -> 50000000 | G104: ='Loan Book'!M107 -> 21295000 | H104: ='Loan Book'!O107 -> 21295000 | I104: ='Loan Book'!R107 -> 21490204 | J104: 000104430000064 | K104: High | L104: =IFERROR(INDEX('E-Banker master'!$B$2:$B$186,MATCH($J104,'E-Banker master'!$A$2:$A$186,0)),"") -> agwenda investments limited | M104: =IFERROR(INDEX('E-Banker master'!$H$2:$H$186,MATCH($J104,'E-Banker master'!$A$2:$A$186,0)),"") -> 45587 | N104: =IFERROR(INDEX('E-Banker master'!$I$2:$I$186,MATCH($J104,'E-Banker master'!$A$2:$A$186,0)),"") -> 50000000 | O104: =IFERROR(INDEX('E-Banker master'!$N$2:$N$186,MATCH($J104,'E-Banker master'!$A$2:$A$186,0)),"") -> 0 | P104: =IFERROR(INDEX('E-Banker master'!$P$2:$P$186,MATCH($J104,'E-Banker master'!$A$2:$A$186,0)),"") -> 21295000 | Q104: =IFERROR(INDEX('E-Banker master'!$Q$2:$Q$186,MATCH($J104,'E-Banker master'!$A$2:$A$186,0)),"") -> 45587 | R104: =IFERROR(INDEX('E-Banker master'!$E$2:$E$186,MATCH($J104,'E-Banker master'!$A$2:$A$186,0)),"") -> A | S104: =IF($J104="","",IF(O104="","No take-on posting",IF(ABS(H104-O104)<1,"Yes",IF(ABS(H104/O104-1)<0.01,"Within 1%","No")))) -> #DIV/0! | T104: =IF($J104="","",IF(OR(P104="",P104=0),"No balance",IF(ABS(I104-P104)<1,"Yes",IF(ABS(I104/P104-1)<0.02,"Within 2%",IF(ABS(I104/P104-1)<0.05,"Within 5%","No"))))) -> Within 2% | U104: =IF($J104="","",IF(N104="","",IF(ABS(F104-N104)<1,"Yes",IF(ABS(G104-N104)<1,"Disbursed = sanction","No")))) -> Yes | V104: =IF(OR($J104="",Q104="",E104=""),"",ABS(E104-Q104)) -> 0 | W104: Yes
A105: 111 | B105: ='Loan Book'!D111 -> 1 | C105: ='Loan Book'!E111 -> MMC Limited | D105: ='Loan Book'!F111 -> Equity | E105: ='Loan Book'!G111 -> 44918 | F105: ='Loan Book'!L111 -> 819476000 | G105: ='Loan Book'!M111 -> 819476000 | H105: ='Loan Book'!O111 -> 819476000 | I105: ='Loan Book'!R111 -> 819476000 | K105: Not matched | L105: =IFERROR(INDEX('E-Banker master'!$B$2:$B$186,MATCH($J105,'E-Banker master'!$A$2:$A$186,0)),"") | M105: =IFERROR(INDEX('E-Banker master'!$H$2:$H$186,MATCH($J105,'E-Banker master'!$A$2:$A$186,0)),"") | N105: =IFERROR(INDEX('E-Banker master'!$I$2:$I$186,MATCH($J105,'E-Banker master'!$A$2:$A$186,0)),"") | O105: =IFERROR(INDEX('E-Banker master'!$N$2:$N$186,MATCH($J105,'E-Banker master'!$A$2:$A$186,0)),"") | P105: =IFERROR(INDEX('E-Banker master'!$P$2:$P$186,MATCH($J105,'E-Banker master'!$A$2:$A$186,0)),"") | Q105: =IFERROR(INDEX('E-Banker master'!$Q$2:$Q$186,MATCH($J105,'E-Banker master'!$A$2:$A$186,0)),"") | R105: =IFERROR(INDEX('E-Banker master'!$E$2:$E$186,MATCH($J105,'E-Banker master'!$A$2:$A$186,0)),"") | S105: =IF($J105="","",IF(O105="","No take-on posting",IF(ABS(H105-O105)<1,"Yes",IF(ABS(H105/O105-1)<0.01,"Within 1%","No")))) | T105: =IF($J105="","",IF(OR(P105="",P105=0),"No balance",IF(ABS(I105-P105)<1,"Yes",IF(ABS(I105/P105-1)<0.02,"Within 2%",IF(ABS(I105/P105-1)<0.05,"Within 5%","No"))))) | U105: =IF($J105="","",IF(N105="","",IF(ABS(F105-N105)<1,"Yes",IF(ABS(G105-N105)<1,"Disbursed = sanction","No")))) | V105: =IF(OR($J105="",Q105="",E105=""),"",ABS(E105-Q105)) | W105: No
A106: 112 | B106: ='Loan Book'!D112 -> 2 | C106: ='Loan Book'!E112 -> Wi Jays Enterprises | D106: ='Loan Book'!F112 -> Equity | E106: ='Loan Book'!G112 -> 44918 | F106: ='Loan Book'!L112 -> 177939650 | G106: ='Loan Book'!M112 -> 177939650 | H106: ='Loan Book'!O112 -> 177939650 | I106: ='Loan Book'!R112 -> 210065735 | K106: Not matched | L106: =IFERROR(INDEX('E-Banker master'!$B$2:$B$186,MATCH($J106,'E-Banker master'!$A$2:$A$186,0)),"") | M106: =IFERROR(INDEX('E-Banker master'!$H$2:$H$186,MATCH($J106,'E-Banker master'!$A$2:$A$186,0)),"") | N106: =IFERROR(INDEX('E-Banker master'!$I$2:$I$186,MATCH($J106,'E-Banker master'!$A$2:$A$186,0)),"") | O106: =IFERROR(INDEX('E-Banker master'!$N$2:$N$186,MATCH($J106,'E-Banker master'!$A$2:$A$186,0)),"") | P106: =IFERROR(INDEX('E-Banker master'!$P$2:$P$186,MATCH($J106,'E-Banker master'!$A$2:$A$186,0)),"") | Q106: =IFERROR(INDEX('E-Banker master'!$Q$2:$Q$186,MATCH($J106,'E-Banker master'!$A$2:$A$186,0)),"") | R106: =IFERROR(INDEX('E-Banker master'!$E$2:$E$186,MATCH($J106,'E-Banker master'!$A$2:$A$186,0)),"") | S106: =IF($J106="","",IF(O106="","No take-on posting",IF(ABS(H106-O106)<1,"Yes",IF(ABS(H106/O106-1)<0.01,"Within 1%","No")))) | T106: =IF($J106="","",IF(OR(P106="",P106=0),"No balance",IF(ABS(I106-P106)<1,"Yes",IF(ABS(I106/P106-1)<0.02,"Within 2%",IF(ABS(I106/P106-1)<0.05,"Within 5%","No"))))) | U106: =IF($J106="","",IF(N106="","",IF(ABS(F106-N106)<1,"Yes",IF(ABS(G106-N106)<1,"Disbursed = sanction","No")))) | V106: =IF(OR($J106="",Q106="",E106=""),"",ABS(E106-Q106)) | W106: No
A107: 113 | B107: ='Loan Book'!D113 -> 3 | C107: ='Loan Book'!E113 -> Good Hope | D107: ='Loan Book'!F113 -> Equity | E107: ='Loan Book'!G113 -> 45016 | F107: ='Loan Book'!L113 -> 1500000000 | G107: ='Loan Book'!M113 -> 1500000000 | H107: ='Loan Book'!O113 -> 1500000000 | I107: ='Loan Book'!R113 -> 1375625000 | K107: Not matched | L107: =IFERROR(INDEX('E-Banker master'!$B$2:$B$186,MATCH($J107,'E-Banker master'!$A$2:$A$186,0)),"") | M107: =IFERROR(INDEX('E-Banker master'!$H$2:$H$186,MATCH($J107,'E-Banker master'!$A$2:$A$186,0)),"") | N107: =IFERROR(INDEX('E-Banker master'!$I$2:$I$186,MATCH($J107,'E-Banker master'!$A$2:$A$186,0)),"") | O107: =IFERROR(INDEX('E-Banker master'!$N$2:$N$186,MATCH($J107,'E-Banker master'!$A$2:$A$186,0)),"") | P107: =IFERROR(INDEX('E-Banker master'!$P$2:$P$186,MATCH($J107,'E-Banker master'!$A$2:$A$186,0)),"") | Q107: =IFERROR(INDEX('E-Banker master'!$Q$2:$Q$186,MATCH($J107,'E-Banker master'!$A$2:$A$186,0)),"") | R107: =IFERROR(INDEX('E-Banker master'!$E$2:$E$186,MATCH($J107,'E-Banker master'!$A$2:$A$186,0)),"") | S107: =IF($J107="","",IF(O107="","No take-on posting",IF(ABS(H107-O107)<1,"Yes",IF(ABS(H107/O107-1)<0.01,"Within 1%","No")))) | T107: =IF($J107="","",IF(OR(P107="",P107=0),"No balance",IF(ABS(I107-P107)<1,"Yes",IF(ABS(I107/P107-1)<0.02,"Within 2%",IF(ABS(I107/P107-1)<0.05,"Within 5%","No"))))) | U107: =IF($J107="","",IF(N107="","",IF(ABS(F107-N107)<1,"Yes",IF(ABS(G107-N107)<1,"Disbursed = sanction","No")))) | V107: =IF(OR($J107="",Q107="",E107=""),"",ABS(E107-Q107)) | W107: No
A108: 114 | B108: ='Loan Book'!D114 -> 4 | C108: ='Loan Book'!E114 -> NASCOMEX Limited | D108: ='Loan Book'!F114 -> Equity | E108: ='Loan Book'!G114 -> 45443 | F108: ='Loan Book'!L114 -> 2500000000 | G108: ='Loan Book'!M114 -> 2500000000 | H108: ='Loan Book'!O114 -> 2500000000 | I108: ='Loan Book'!R114 -> 2500000000 | J108: 000104470000004 | K108: High | L108: =IFERROR(INDEX('E-Banker master'!$B$2:$B$186,MATCH($J108,'E-Banker master'!$A$2:$A$186,0)),"") -> NASCOMEX Limited | M108: =IFERROR(INDEX('E-Banker master'!$H$2:$H$186,MATCH($J108,'E-Banker master'!$A$2:$A$186,0)),"") -> 45376 | N108: =IFERROR(INDEX('E-Banker master'!$I$2:$I$186,MATCH($J108,'E-Banker master'!$A$2:$A$186,0)),"") -> 2500000000 | O108: =IFERROR(INDEX('E-Banker master'!$N$2:$N$186,MATCH($J108,'E-Banker master'!$A$2:$A$186,0)),"") -> 0 | P108: =IFERROR(INDEX('E-Banker master'!$P$2:$P$186,MATCH($J108,'E-Banker master'!$A$2:$A$186,0)),"") -> 0 | Q108: =IFERROR(INDEX('E-Banker master'!$Q$2:$Q$186,MATCH($J108,'E-Banker master'!$A$2:$A$186,0)),"") -> 45376 | R108: =IFERROR(INDEX('E-Banker master'!$E$2:$E$186,MATCH($J108,'E-Banker master'!$A$2:$A$186,0)),"") -> A | S108: =IF($J108="","",IF(O108="","No take-on posting",IF(ABS(H108-O108)<1,"Yes",IF(ABS(H108/O108-1)<0.01,"Within 1%","No")))) -> #DIV/0! | T108: =IF($J108="","",IF(OR(P108="",P108=0),"No balance",IF(ABS(I108-P108)<1,"Yes",IF(ABS(I108/P108-1)<0.02,"Within 2%",IF(ABS(I108/P108-1)<0.05,"Within 5%","No"))))) -> No balance | U108: =IF($J108="","",IF(N108="","",IF(ABS(F108-N108)<1,"Yes",IF(ABS(G108-N108)<1,"Disbursed = sanction","No")))) -> Yes | V108: =IF(OR($J108="",Q108="",E108=""),"",ABS(E108-Q108)) -> 67 | W108: Yes
A109: 115 | B109: ='Loan Book'!D115 -> 5 | C109: ='Loan Book'!E115 -> Natures Gift | D109: ='Loan Book'!F115 -> Equity | E109: ='Loan Book'!G115 -> 45446 | F109: ='Loan Book'!L115 -> 500000000 | G109: ='Loan Book'!M115 -> 500000000 | H109: ='Loan Book'!O115 -> 500000000 | I109: ='Loan Book'!R115 -> 500000000 | J109: 000104430000057 | K109: High | L109: =IFERROR(INDEX('E-Banker master'!$B$2:$B$186,MATCH($J109,'E-Banker master'!$A$2:$A$186,0)),"") -> NATURES GIFT LIMITED | M109: =IFERROR(INDEX('E-Banker master'!$H$2:$H$186,MATCH($J109,'E-Banker master'!$A$2:$A$186,0)),"") -> 45446 | N109: =IFERROR(INDEX('E-Banker master'!$I$2:$I$186,MATCH($J109,'E-Banker master'!$A$2:$A$186,0)),"") -> 500000000 | O109: =IFERROR(INDEX('E-Banker master'!$N$2:$N$186,MATCH($J109,'E-Banker master'!$A$2:$A$186,0)),"") -> 0 | P109: =IFERROR(INDEX('E-Banker master'!$P$2:$P$186,MATCH($J109,'E-Banker master'!$A$2:$A$186,0)),"") -> 0 | Q109: =IFERROR(INDEX('E-Banker master'!$Q$2:$Q$186,MATCH($J109,'E-Banker master'!$A$2:$A$186,0)),"") -> 45446 | R109: =IFERROR(INDEX('E-Banker master'!$E$2:$E$186,MATCH($J109,'E-Banker master'!$A$2:$A$186,0)),"") -> C | S109: =IF($J109="","",IF(O109="","No take-on posting",IF(ABS(H109-O109)<1,"Yes",IF(ABS(H109/O109-1)<0.01,"Within 1%","No")))) -> #DIV/0! | T109: =IF($J109="","",IF(OR(P109="",P109=0),"No balance",IF(ABS(I109-P109)<1,"Yes",IF(ABS(I109/P109-1)<0.02,"Within 2%",IF(ABS(I109/P109-1)<0.05,"Within 5%","No"))))) -> No balance | U109: =IF($J109="","",IF(N109="","",IF(ABS(F109-N109)<1,"Yes",IF(ABS(G109-N109)<1,"Disbursed = sanction","No")))) -> Yes | V109: =IF(OR($J109="",Q109="",E109=""),"",ABS(E109-Q109)) -> 0 | W109: Yes
A110: 116 | B110: ='Loan Book'!D116 -> 6 | C110: ='Loan Book'!E116 -> Small Farm Cities Africa Ltd | D110: ='Loan Book'!F116 -> Equity | E110: ='Loan Book'!G116 -> 45488 | F110: ='Loan Book'!L116 -> 250000000 | G110: ='Loan Book'!M116 -> 250000000 | H110: ='Loan Book'!O116 -> 250000000 | I110: ='Loan Book'!R116 -> 250000000 | J110: 000104430000060 | K110: High | L110: =IFERROR(INDEX('E-Banker master'!$B$2:$B$186,MATCH($J110,'E-Banker master'!$A$2:$A$186,0)),"") -> SMALL FARM CITIES AFRICA LIMITED | M110: =IFERROR(INDEX('E-Banker master'!$H$2:$H$186,MATCH($J110,'E-Banker master'!$A$2:$A$186,0)),"") -> 45474 | N110: =IFERROR(INDEX('E-Banker master'!$I$2:$I$186,MATCH($J110,'E-Banker master'!$A$2:$A$186,0)),"") -> 250000000 | O110: =IFERROR(INDEX('E-Banker master'!$N$2:$N$186,MATCH($J110,'E-Banker master'!$A$2:$A$186,0)),"") -> 0 | P110: =IFERROR(INDEX('E-Banker master'!$P$2:$P$186,MATCH($J110,'E-Banker master'!$A$2:$A$186,0)),"") -> 0 | Q110: =IFERROR(INDEX('E-Banker master'!$Q$2:$Q$186,MATCH($J110,'E-Banker master'!$A$2:$A$186,0)),"") -> 45474 | R110: =IFERROR(INDEX('E-Banker master'!$E$2:$E$186,MATCH($J110,'E-Banker master'!$A$2:$A$186,0)),"") -> C | S110: =IF($J110="","",IF(O110="","No take-on posting",IF(ABS(H110-O110)<1,"Yes",IF(ABS(H110/O110-1)<0.01,"Within 1%","No")))) -> #DIV/0! | T110: =IF($J110="","",IF(OR(P110="",P110=0),"No balance",IF(ABS(I110-P110)<1,"Yes",IF(ABS(I110/P110-1)<0.02,"Within 2%",IF(ABS(I110/P110-1)<0.05,"Within 5%","No"))))) -> No balance | U110: =IF($J110="","",IF(N110="","",IF(ABS(F110-N110)<1,"Yes",IF(ABS(G110-N110)<1,"Disbursed = sanction","No")))) -> Yes | V110: =IF(OR($J110="",Q110="",E110=""),"",ABS(E110-Q110)) -> 14 | W110: Yes
A112: Columns A to I are formulas into the 'Loan Book' sheet; L to R are lookups into 'E-Banker master' by the account in J; S to V are tests computed here; J, K and W are typed values from our matching (see Instructions). Yellow columns are for Tamanda.

Sheet Not matched
A1: Loan Book # | B1: Facility name | C1: Type | D1: Value date | E1: Approved | F1: Nearest candidates | G1: Tamanda: account number or 'no account' | H1: Comment
A2: 38 | B2: Favoured Farms | C2: Debt | D2: 2022-07-13 | E2: 10000000 | F2: 000104450000050 Greendom Farming (score 0.64); 000104450000038 Tac-Maz Investment (score 0.60); 000104450000015 Zaithwa Farms (score 0.58)
A3: 1 | B3: MMC Limited | C3: Equity | D3: 2022-12-23 | E3: 819476000 | F3: 000104450000085 MMC Limited (score 0.45); 000104450000034 MMM Investments (score 0.23); 000104420000005 MUSECO (score 0.16)
A4: 2 | B4: Wi Jays Enterprises | C4: Equity | D4: 2022-12-23 | E4: 177939650 | F4: 000104450000045 Walusiya Investment (score 0.19); 000104450000051 JAT Investments (score 0.19); 000106050000005 Wallie Farms (score 0.18)
A5: 3 | B5: Good Hope | C5: Equity | D5: 2023-03-31 | E5: 1500000000 | F5: 000106050000010 KWACHA Boutique HOTEL (score 0.27); 000104450000068 The Food Empire Limited (score 0.26); 000104420000043 The Food Empire Limited (score 0.21)

Sheet Accounts without a block
A1: E-Banker account | B1: E-Banker name | C1: Opening date | D1: Sanction | E1: Status | F1: Tamanda: which facility is this, or 'none' | G1: Comment
A2: 000104430000055 | B2: =IFERROR(INDEX('E-Banker master'!$B$2:$B$186,MATCH($A2,'E-Banker master'!$A$2:$A$186,0)),"") -> NASCOMEX LIMITED | C2: =IFERROR(INDEX('E-Banker master'!$H$2:$H$186,MATCH($A2,'E-Banker master'!$A$2:$A$186,0)),"") -> 45446 | D2: =IFERROR(INDEX('E-Banker master'!$I$2:$I$186,MATCH($A2,'E-Banker master'!$A$2:$A$186,0)),"") -> 1762000051 | E2: =IFERROR(INDEX('E-Banker master'!$E$2:$E$186,MATCH($A2,'E-Banker master'!$A$2:$A$186,0)),"") -> C
A3: 000104430000056 | B3: =IFERROR(INDEX('E-Banker master'!$B$2:$B$186,MATCH($A3,'E-Banker master'!$A$2:$A$186,0)),"") -> NATURES GIFT LIMITED | C3: =IFERROR(INDEX('E-Banker master'!$H$2:$H$186,MATCH($A3,'E-Banker master'!$A$2:$A$186,0)),"") -> 45446 | D3: =IFERROR(INDEX('E-Banker master'!$I$2:$I$186,MATCH($A3,'E-Banker master'!$A$2:$A$186,0)),"") -> 481899500 | E3: =IFERROR(INDEX('E-Banker master'!$E$2:$E$186,MATCH($A3,'E-Banker master'!$A$2:$A$186,0)),"") -> C
A4: 000104430000058 | B4: =IFERROR(INDEX('E-Banker master'!$B$2:$B$186,MATCH($A4,'E-Banker master'!$A$2:$A$186,0)),"") -> MCHINJI CIVIL SERVANTS SACCO | C4: =IFERROR(INDEX('E-Banker master'!$H$2:$H$186,MATCH($A4,'E-Banker master'!$A$2:$A$186,0)),"") -> 45448 | D4: =IFERROR(INDEX('E-Banker master'!$I$2:$I$186,MATCH($A4,'E-Banker master'!$A$2:$A$186,0)),"") -> 50000000 | E4: =IFERROR(INDEX('E-Banker master'!$E$2:$E$186,MATCH($A4,'E-Banker master'!$A$2:$A$186,0)),"") -> C
A5: 000104430000059 | B5: =IFERROR(INDEX('E-Banker master'!$B$2:$B$186,MATCH($A5,'E-Banker master'!$A$2:$A$186,0)),"") -> INFRACON LIMITED | C5: =IFERROR(INDEX('E-Banker master'!$H$2:$H$186,MATCH($A5,'E-Banker master'!$A$2:$A$186,0)),"") -> 45421 | D5: =IFERROR(INDEX('E-Banker master'!$I$2:$I$186,MATCH($A5,'E-Banker master'!$A$2:$A$186,0)),"") -> 265656500 | E5: =IFERROR(INDEX('E-Banker master'!$E$2:$E$186,MATCH($A5,'E-Banker master'!$A$2:$A$186,0)),"") -> C
A6: 000104440000004 | B6: =IFERROR(INDEX('E-Banker master'!$B$2:$B$186,MATCH($A6,'E-Banker master'!$A$2:$A$186,0)),"") -> A.A Mirza General Traders | C6: =IFERROR(INDEX('E-Banker master'!$H$2:$H$186,MATCH($A6,'E-Banker master'!$A$2:$A$186,0)),"") -> 45383 | D6: =IFERROR(INDEX('E-Banker master'!$I$2:$I$186,MATCH($A6,'E-Banker master'!$A$2:$A$186,0)),"") -> 0 | E6: =IFERROR(INDEX('E-Banker master'!$E$2:$E$186,MATCH($A6,'E-Banker master'!$A$2:$A$186,0)),"") -> C
A7: 000104460000058 | B7: =IFERROR(INDEX('E-Banker master'!$B$2:$B$186,MATCH($A7,'E-Banker master'!$A$2:$A$186,0)),"") -> Tapempha Medical Care Limited | C7: =IFERROR(INDEX('E-Banker master'!$H$2:$H$186,MATCH($A7,'E-Banker master'!$A$2:$A$186,0)),"") -> 44972 | D7: =IFERROR(INDEX('E-Banker master'!$I$2:$I$186,MATCH($A7,'E-Banker master'!$A$2:$A$186,0)),"") -> 53391150 | E7: =IFERROR(INDEX('E-Banker master'!$E$2:$E$186,MATCH($A7,'E-Banker master'!$A$2:$A$186,0)),"") -> C
A8: 000104460000100 | B8: =IFERROR(INDEX('E-Banker master'!$B$2:$B$186,MATCH($A8,'E-Banker master'!$A$2:$A$186,0)),"") -> MCHINJI CIVIL SERVANTS SACCO | C8: =IFERROR(INDEX('E-Banker master'!$H$2:$H$186,MATCH($A8,'E-Banker master'!$A$2:$A$186,0)),"") -> 45448 | D8: =IFERROR(INDEX('E-Banker master'!$I$2:$I$186,MATCH($A8,'E-Banker master'!$A$2:$A$186,0)),"") -> 50000000 | E8: =IFERROR(INDEX('E-Banker master'!$E$2:$E$186,MATCH($A8,'E-Banker master'!$A$2:$A$186,0)),"") -> C
A9: 000104460000101 | B9: =IFERROR(INDEX('E-Banker master'!$B$2:$B$186,MATCH($A9,'E-Banker master'!$A$2:$A$186,0)),"") -> Ifracon Limited | C9: =IFERROR(INDEX('E-Banker master'!$H$2:$H$186,MATCH($A9,'E-Banker master'!$A$2:$A$186,0)),"") -> 45425 | D9: =IFERROR(INDEX('E-Banker master'!$I$2:$I$186,MATCH($A9,'E-Banker master'!$A$2:$A$186,0)),"") -> 627746500 | E9: =IFERROR(INDEX('E-Banker master'!$E$2:$E$186,MATCH($A9,'E-Banker master'!$A$2:$A$186,0)),"") -> C

Sheet Upload summary
A1: E-Banker account | B1: Confidence | C1: Loan Book row | D1: Facility name | E1: Type | F1: Value date | G1: Maturity date | H1: Tenor (years) | I1: Moratorium (text) | J1: Rate 31 Oct 2024 % | K1: Approved | L1: Disbursed | M1: Not yet disbursed | N1: Principal 31 Oct 2024 | O1: Interest to date | P1: Repayments | Q1: Carrying amount 31 Oct 2024 | R1: Arrears principal | S1: Arrears interest | T1: Arrears total | U1: Segment | V1: Industry | W1: E-Banker name | X1: Scheme id | Y1: GL code | Z1: Status | AA1: Interest policy | AB1: Rate now % | AC1: Sanction | AD1: Sanction date | AE1: Expiry | AF1: P moratorium | AG1: I moratorium | AH1: Take-on posting 31 Jul 2024 | AI1: Opening interest 31 Jul 2024 | AJ1: Balance 31 Oct 2024 | AK1: Carrying amount less balance | AL1: Block # | AM1: Go to block | AN1: Tamanda confirmed (from Mapping) | AO1: Arrangement fee (MK) | AP1: Legal fees (MK) | AQ1: Other integral fees (MK) | AR1: Fee date (dd/mm/yyyy) | AS1: Deducted from disbursement? (Y/N) | AT1: Source (offer letter ref or receipt) | AU1: Total fees (MK)
A2: =Mapping!J2 -> 000104430000001 | B2: =Mapping!K2 -> High | C2: 5 | D2: ='Loan Book'!E5 -> Chikho Hotel Limited | E2: ='Loan Book'!F5 -> Debt | F2: ='Loan Book'!G5 -> 44470 | G2: ='Loan Book'!H5 -> 46934 | H2: ='Loan Book'!I5 -> 6.7506849 | I2: ='Loan Book'!J5 -> - | J2: =IF('Loan Book'!K5="","",IF('Loan Book'!K5<1,'Loan Book'!K5*100,'Loan Book'!K5)) -> 30.67 | K2: ='Loan Book'!L5 -> 6.208559e+08 | L2: ='Loan Book'!M5 -> 6.208559e+08 | M2: ='Loan Book'!N5 -> 0 | N2: ='Loan Book'!O5 -> 6.0793125e+08 | O2: ='Loan Book'!P5 -> 2.3912411e+08 | P2: ='Loan Book'!Q5 -> -8.4705535e+08 | Q2: ='Loan Book'!R5 -> 1.7285347e-05 | R2: ='Loan Book'!S5 -> 0 | ... T2: ='Loan Book'!U5 -> 0 | U2: ='Loan Book'!AC5 -> CORPORATE | V2: ='Loan Book'!AE5 -> HOSPITALITY | W2: =IFERROR(INDEX('E-Banker master'!$B$2:$B$186,MATCH($A2,'E-Banker master'!$A$2:$A$186,0)),"") -> CHIKHO HOTEL | X2: =IFERROR(INDEX('E-Banker master'!$C$2:$C$186,MATCH($A2,'E-Banker master'!$A$2:$A$186,0)),"") -> 86 | Y2: =IFERROR(INDEX('E-Banker master'!$D$2:$D$186,MATCH($A2,'E-Banker master'!$A$2:$A$186,0)),"") -> 1050102 | Z2: =IFERROR(INDEX('E-Banker master'!$E$2:$E$186,MATCH($A2,'E-Banker master'!$A$2:$A$186,0)),"") -> C | AA2: =IFERROR(INDEX('E-Banker master'!$F$2:$F$186,MATCH($A2,'E-Banker master'!$A$2:$A$186,0)),"") -> M | AB2: =IFERROR(INDEX('E-Banker master'!$G$2:$G$186,MATCH($A2,'E-Banker master'!$A$2:$A$186,0)),"") -> 30.8 | AC2: =IFERROR(INDEX('E-Banker master'!$I$2:$I$186,MATCH($A2,'E-Banker master'!$A$2:$A$186,0)),"") -> 6.208559e+08 | AD2: =IFERROR(INDEX('E-Banker master'!$J$2:$J$186,MATCH($A2,'E-Banker master'!$A$2:$A$186,0)),"") -> 44652 | AE2: =IFERROR(INDEX('E-Banker master'!$K$2:$K$186,MATCH($A2,'E-Banker master'!$A$2:$A$186,0)),"") -> 47026 | AF2: =IFERROR(INDEX('E-Banker master'!$L$2:$L$186,MATCH($A2,'E-Banker master'!$A$2:$A$186,0)),"") -> 0 | AG2: =IFERROR(INDEX('E-Banker master'!$M$2:$M$186,MATCH($A2,'E-Banker master'!$A$2:$A$186,0)),"") -> 0 | AH2: =IFERROR(INDEX('E-Banker master'!$N$2:$N$186,MATCH($A2,'E-Banker master'!$A$2:$A$186,0)),"") -> 0 | AI2: =IFERROR(INDEX('E-Banker master'!$O$2:$O$186,MATCH($A2,'E-Banker master'!$A$2:$A$186,0)),"") -> 0 | AJ2: =IFERROR(INDEX('E-Banker master'!$P$2:$P$186,MATCH($A2,'E-Banker master'!$A$2:$A$186,0)),"") -> 0 | AK2: =IF(OR(Q2="",AJ2=""),"",Q2-AJ2) -> 1.7285347e-05 | AL2: 1 | AM2: =HYPERLINK("#'Amortisation and Repayments'!C4","block 1") -> block 1 | AN2: =Mapping!X2 -> 0 | AO2: ='Loan Book'!AS5 -> 7950000 | AP2: ='Loan Book'!AT5 -> 9353400 | AR2: =AD2 -> 44652 | AS2: Y | AT2: Offer letter and Quickbooks | AU2: =IF(COUNT(AO2:AQ2)=0,"",SUM(AO2:AQ2)) -> 17303400
A3: =Mapping!J3 -> 000104430000002 | B3: =Mapping!K3 -> High | C3: 6 | D3: ='Loan Book'!E6 -> Edge View Academy Limited | E3: ='Loan Book'!F6 -> Debt | F3: ='Loan Book'!G6 -> 43935 | G3: ='Loan Book'!H6 -> 45747 | H3: ='Loan Book'!I6 -> 4.9643836 | I3: ='Loan Book'!J6 -> 12 (Cap only) | J3: =IF('Loan Book'!K6="","",IF('Loan Book'!K6<1,'Loan Book'!K6*100,'Loan Book'!K6)) -> 32.89 | K3: ='Loan Book'!L6 -> 300000000 | L3: ='Loan Book'!M6 -> 300000000 | M3: ='Loan Book'!N6 -> 0 | N3: ='Loan Book'!O6 -> 3.3139585e+08 | O3: ='Loan Book'!P6 -> 2.3394515e+08 | P3: ='Loan Book'!Q6 -> -192487000 | Q3: ='Loan Book'!R6 -> 3.7285399e+08 | R3: ='Loan Book'!S6 -> 3382934.8 | ... T3: ='Loan Book'!U6 -> 54605500 | U3: ='Loan Book'!AC6 -> 0 | V3: ='Loan Book'!AE6 -> 0 | W3: =IFERROR(INDEX('E-Banker master'!$B$2:$B$186,MATCH($A3,'E-Banker master'!$A$2:$A$186,0)),"") -> Edge View Academy Limited | X3: =IFERROR(INDEX('E-Banker master'!$C$2:$C$186,MATCH($A3,'E-Banker master'!$A$2:$A$186,0)),"") -> 86 | Y3: =IFERROR(INDEX('E-Banker master'!$D$2:$D$186,MATCH($A3,'E-Banker master'!$A$2:$A$186,0)),"") -> 1050102 | Z3: =IFERROR(INDEX('E-Banker master'!$E$2:$E$186,MATCH($A3,'E-Banker master'!$A$2:$A$186,0)),"") -> A | AA3: =IFERROR(INDEX('E-Banker master'!$F$2:$F$186,MATCH($A3,'E-Banker master'!$A$2:$A$186,0)),"") -> M | AB3: =IFERROR(INDEX('E-Banker master'!$G$2:$G$186,MATCH($A3,'E-Banker master'!$A$2:$A$186,0)),"") -> 31.09 | AC3: =IFERROR(INDEX('E-Banker master'!$I$2:$I$186,MATCH($A3,'E-Banker master'!$A$2:$A$186,0)),"") -> 300000000 | AD3: =IFERROR(INDEX('E-Banker master'!$J$2:$J$186,MATCH($A3,'E-Banker master'!$A$2:$A$186,0)),"") -> 43894 | AE3: =IFERROR(INDEX('E-Banker master'!$K$2:$K$186,MATCH($A3,'E-Banker master'!$A$2:$A$186,0)),"") -> 45720 | AF3: =IFERROR(INDEX('E-Banker master'!$L$2:$L$186,MATCH($A3,'E-Banker master'!$A$2:$A$186,0)),"") -> 12 | AG3: =IFERROR(INDEX('E-Banker master'!$M$2:$M$186,MATCH($A3,'E-Banker master'!$A$2:$A$186,0)),"") -> 0 | AH3: =IFERROR(INDEX('E-Banker master'!$N$2:$N$186,MATCH($A3,'E-Banker master'!$A$2:$A$186,0)),"") -> 3.3139585e+08 | AI3: =IFERROR(INDEX('E-Banker master'!$O$2:$O$186,MATCH($A3,'E-Banker master'!$A$2:$A$186,0)),"") -> 2.0747143e+08 | AJ3: =IFERROR(INDEX('E-Banker master'!$P$2:$P$186,MATCH($A3,'E-Banker master'!$A$2:$A$186,0)),"") -> 3.7864473e+08 | AK3: =IF(OR(Q3="",AJ3=""),"",Q3-AJ3) -> -5790740.8 | AL3: 2 | AM3: =HYPERLINK("#'Amortisation and Repayments'!C41","block 2") -> block 2 | AN3: =Mapping!X3 -> 0 | AO3: ='Loan Book'!AS6 -> 4500000 | AP3: ='Loan Book'!AT6 -> 8500000 | AR3: =AD3 -> 43894 | AS3: Y | AT3: Offer letter and Quickbooks | AU3: =IF(COUNT(AO3:AQ3)=0,"",SUM(AO3:AQ3)) -> 13000000
A4: =Mapping!J4 -> 000104420000003 | B4: =Mapping!K4 -> High | C4: 7 | D4: ='Loan Book'!E7 -> Micholess Creamery | E4: ='Loan Book'!F7 -> Debt | F4: ='Loan Book'!G7 -> 44040 | G4: ='Loan Book'!H7 -> 44773 | H4: ='Loan Book'!I7 -> 2.0082192 | I4: ='Loan Book'!J7 -> 6 (Cap+Int) | J4: =IF('Loan Book'!K7="","",IF('Loan Book'!K7<1,'Loan Book'!K7*100,'Loan Book'!K7)) -> 20.2 | K4: ='Loan Book'!L7 -> 20000000 | L4: ='Loan Book'!M7 -> 18240000 | M4: ='Loan Book'!N7 -> 1760000 | N4: ='Loan Book'!O7 -> 18240000 | O4: ='Loan Book'!P7 -> 1004624.7 | P4: ='Loan Book'!Q7 -> -9000000 | Q4: ='Loan Book'!R7 -> 0 | R4: ='Loan Book'!S7 -> 0 | ... T4: ='Loan Book'!U7 -> 0 | U4: ='Loan Book'!AC7 -> 0 | V4: ='Loan Book'!AE7 -> 0 | W4: =IFERROR(INDEX('E-Banker master'!$B$2:$B$186,MATCH($A4,'E-Banker master'!$A$2:$A$186,0)),"") -> Micholess Creamery | X4: =IFERROR(INDEX('E-Banker master'!$C$2:$C$186,MATCH($A4,'E-Banker master'!$A$2:$A$186,0)),"") -> 84 | Y4: =IFERROR(INDEX('E-Banker master'!$D$2:$D$186,MATCH($A4,'E-Banker master'!$A$2:$A$186,0)),"") -> 1050101 | Z4: =IFERROR(INDEX('E-Banker master'!$E$2:$E$186,MATCH($A4,'E-Banker master'!$A$2:$A$186,0)),"") -> A | AA4: =IFERROR(INDEX('E-Banker master'!$F$2:$F$186,MATCH($A4,'E-Banker master'!$A$2:$A$186,0)),"") -> M | AB4: =IFERROR(INDEX('E-Banker master'!$G$2:$G$186,MATCH($A4,'E-Banker master'!$A$2:$A$186,0)),"") -> 20.2 | AC4: =IFERROR(INDEX('E-Banker master'!$I$2:$I$186,MATCH($A4,'E-Banker master'!$A$2:$A$186,0)),"") -> 20000000 | AD4: =IFERROR(INDEX('E-Banker master'!$J$2:$J$186,MATCH($A4,'E-Banker master'!$A$2:$A$186,0)),"") -> 44040 | AE4: =IFERROR(INDEX('E-Banker master'!$K$2:$K$186,MATCH($A4,'E-Banker master'!$A$2:$A$186,0)),"") -> 44769 | AF4: =IFERROR(INDEX('E-Banker master'!$L$2:$L$186,MATCH($A4,'E-Banker master'!$A$2:$A$186,0)),"") -> 6 | AG4: =IFERROR(INDEX('E-Banker master'!$M$2:$M$186,MATCH($A4,'E-Banker master'!$A$2:$A$186,0)),"") -> 6 | AH4: =IFERROR(INDEX('E-Banker master'!$N$2:$N$186,MATCH($A4,'E-Banker master'!$A$2:$A$186,0)),"") -> 18240000 | AI4: =IFERROR(INDEX('E-Banker master'!$O$2:$O$186,MATCH($A4,'E-Banker master'!$A$2:$A$186,0)),"") -> 1004624.7 | AJ4: =IFERROR(INDEX('E-Banker master'!$P$2:$P$186,MATCH($A4,'E-Banker master'!$A$2:$A$186,0)),"") -> 0 | AK4: =IF(OR(Q4="",AJ4=""),"",Q4-AJ4) -> 0 | AL4: 3 | AM4: =HYPERLINK("#'Amortisation and Repayments'!C204","block 3") -> block 3 | AN4: =Mapping!X4 -> 0 | AO4: ='Loan Book'!AS7 -> 300000 | AP4: ='Loan Book'!AT7 -> 430000 | AR4: =AD4 -> 44040 | AS4: Y | AT4: Offer letter and Quickbooks | AU4: =IF(COUNT(AO4:AQ4)=0,"",SUM(AO4:AQ4)) -> 730000
A5: =Mapping!J5 -> 000104430000004 | B5: =Mapping!K5 -> High | C5: 8 | D5: ='Loan Book'!E8 -> COMSIV Limited | E5: ='Loan Book'!F8 -> Debt | F5: ='Loan Book'!G8 -> 44552 | G5: ='Loan Book'!H8 -> 45291 | H5: ='Loan Book'!I8 -> 2.0246575 | I5: ='Loan Book'!J8 -> - | J5: =IF('Loan Book'!K8="","",IF('Loan Book'!K8<1,'Loan Book'!K8*100,'Loan Book'!K8)) -> 30.7 | K5: ='Loan Book'!L8 -> 309523514 | L5: ='Loan Book'!M8 -> 309523514 | M5: ='Loan Book'!N8 -> 0 | N5: ='Loan Book'!O8 -> 309523514 | O5: ='Loan Book'!P8 -> 32916948 | P5: ='Loan Book'!Q8 -> -334121496 | Q5: ='Loan Book'!R8 -> 8318966.5 | R5: ='Loan Book'!S8 -> 0 | ... T5: ='Loan Book'!U8 -> 0 | U5: ='Loan Book'!AC8 -> 0 | V5: ='Loan Book'!AE8 -> 0 | W5: =IFERROR(INDEX('E-Banker master'!$B$2:$B$186,MATCH($A5,'E-Banker master'!$A$2:$A$186,0)),"") -> COMSIV Limited | X5: =IFERROR(INDEX('E-Banker master'!$C$2:$C$186,MATCH($A5,'E-Banker master'!$A$2:$A$186,0)),"") -> 86 | Y5: =IFERROR(INDEX('E-Banker master'!$D$2:$D$186,MATCH($A5,'E-Banker master'!$A$2:$A$186,0)),"") -> 1050102 | Z5: =IFERROR(INDEX('E-Banker master'!$E$2:$E$186,MATCH($A5,'E-Banker master'!$A$2:$A$186,0)),"") -> H | AA5: =IFERROR(INDEX('E-Banker master'!$F$2:$F$186,MATCH($A5,'E-Banker master'!$A$2:$A$186,0)),"") -> M | AB5: =IFERROR(INDEX('E-Banker master'!$G$2:$G$186,MATCH($A5,'E-Banker master'!$A$2:$A$186,0)),"") -> 33.3 | AC5: =IFERROR(INDEX('E-Banker master'!$I$2:$I$186,MATCH($A5,'E-Banker master'!$A$2:$A$186,0)),"") -> 309523514 | AD5: =IFERROR(INDEX('E-Banker master'!$J$2:$J$186,MATCH($A5,'E-Banker master'!$A$2:$A$186,0)),"") -> 44525 | AE5: =IFERROR(INDEX('E-Banker master'!$K$2:$K$186,MATCH($A5,'E-Banker master'!$A$2:$A$186,0)),"") -> 45255 | AF5: =IFERROR(INDEX('E-Banker master'!$L$2:$L$186,MATCH($A5,'E-Banker master'!$A$2:$A$186,0)),"") -> 0 | AG5: =IFERROR(INDEX('E-Banker master'!$M$2:$M$186,MATCH($A5,'E-Banker master'!$A$2:$A$186,0)),"") -> 0 | AH5: =IFERROR(INDEX('E-Banker master'!$N$2:$N$186,MATCH($A5,'E-Banker master'!$A$2:$A$186,0)),"") -> 309523514 | AI5: =IFERROR(INDEX('E-Banker master'!$O$2:$O$186,MATCH($A5,'E-Banker master'!$A$2:$A$186,0)),"") -> 32916948 | AJ5: =IFERROR(INDEX('E-Banker master'!$P$2:$P$186,MATCH($A5,'E-Banker master'!$A$2:$A$186,0)),"") -> 8318966.5 | AK5: =IF(OR(Q5="",AJ5=""),"",Q5-AJ5) -> -0.00080769323 | AL5: 4 | AM5: =HYPERLINK("#'Amortisation and Repayments'!C244","block 4") -> block 4 | AN5: =Mapping!X5 -> 0 | AO5: ='Loan Book'!AS8 -> 3863451.8 | AP5: ='Loan Book'!AT8 -> 0 | AR5: =AD5 -> 44525 | AS5: Y | AT5: Offer letter and Quickbooks | AU5: =IF(COUNT(AO5:AQ5)=0,"",SUM(AO5:AQ5)) -> 3863451.8
A6: =Mapping!J6 -> 000104420000005 | B6: =Mapping!K6 -> High | C6: 9 | D6: ='Loan Book'!E9 -> MUSECO | E6: ='Loan Book'!F9 -> Debt | F6: ='Loan Book'!G9 -> 44035 | G6: ='Loan Book'!H9 -> 45869 | H6: ='Loan Book'!I9 -> 5.0246575 | I6: ='Loan Book'!J9 -> 13 (Cap only) | J6: =IF('Loan Book'!K9="","",IF('Loan Book'!K9<1,'Loan Book'!K9*100,'Loan Book'!K9)) -> 32.15 | K6: ='Loan Book'!L9 -> 4.0509799e+08 | L6: ='Loan Book'!M9 -> 4.0509799e+08 | M6: ='Loan Book'!N9 -> 0 | N6: ='Loan Book'!O9 -> 4.0509799e+08 | O6: ='Loan Book'!P9 -> 2.5491021e+08 | P6: ='Loan Book'!Q9 -> -2.7525517e+08 | Q6: ='Loan Book'!R9 -> 3.8475303e+08 | R6: ='Loan Book'!S9 -> 1.0022376e+08 | ... T6: ='Loan Book'!U9 -> 1.5150562e+08 | U6: ='Loan Book'!AC9 -> 0 | V6: ='Loan Book'!AE9 -> 0 | W6: =IFERROR(INDEX('E-Banker master'!$B$2:$B$186,MATCH($A6,'E-Banker master'!$A$2:$A$186,0)),"") -> MUSECO | X6: =IFERROR(INDEX('E-Banker master'!$C$2:$C$186,MATCH($A6,'E-Banker master'!$A$2:$A$186,0)),"") -> 84 | Y6: =IFERROR(INDEX('E-Banker master'!$D$2:$D$186,MATCH($A6,'E-Banker master'!$A$2:$A$186,0)),"") -> 1050101 | Z6: =IFERROR(INDEX('E-Banker master'!$E$2:$E$186,MATCH($A6,'E-Banker master'!$A$2:$A$186,0)),"") -> D | AA6: =IFERROR(INDEX('E-Banker master'!$F$2:$F$186,MATCH($A6,'E-Banker master'!$A$2:$A$186,0)),"") -> P | AB6: =IFERROR(INDEX('E-Banker master'!$G$2:$G$186,MATCH($A6,'E-Banker master'!$A$2:$A$186,0)),"") -> 30.35 | AC6: =IFERROR(INDEX('E-Banker master'!$I$2:$I$186,MATCH($A6,'E-Banker master'!$A$2:$A$186,0)),"") -> 370000000 | AD6: =IFERROR(INDEX('E-Banker master'!$J$2:$J$186,MATCH($A6,'E-Banker master'!$A$2:$A$186,0)),"") -> 43964 | AE6: =IFERROR(INDEX('E-Banker master'!$K$2:$K$186,MATCH($A6,'E-Banker master'!$A$2:$A$186,0)),"") -> 46225 | AF6: =IFERROR(INDEX('E-Banker master'!$L$2:$L$186,MATCH($A6,'E-Banker master'!$A$2:$A$186,0)),"") -> 13 | AG6: =IFERROR(INDEX('E-Banker master'!$M$2:$M$186,MATCH($A6,'E-Banker master'!$A$2:$A$186,0)),"") -> 0 | AH6: =IFERROR(INDEX('E-Banker master'!$N$2:$N$186,MATCH($A6,'E-Banker master'!$A$2:$A$186,0)),"") -> 4.0509799e+08 | AI6: =IFERROR(INDEX('E-Banker master'!$O$2:$O$186,MATCH($A6,'E-Banker master'!$A$2:$A$186,0)),"") -> 2.3737816e+08 | AJ6: =IFERROR(INDEX('E-Banker master'!$P$2:$P$186,MATCH($A6,'E-Banker master'!$A$2:$A$186,0)),"") -> 3.9924351e+08 | AK6: =IF(OR(Q6="",AJ6=""),"",Q6-AJ6) -> -14490475 | AL6: 5 | AM6: =HYPERLINK("#'Amortisation and Repayments'!C282","block 5") -> block 5 | AN6: =Mapping!X6 -> 0 | AO6: ='Loan Book'!AS9 -> 5550000 | AP6: ='Loan Book'!AT9 -> 6110500 | AR6: =AD6 -> 43964 | AS6: Y | AT6: Offer letter and Quickbooks | AU6: =IF(COUNT(AO6:AQ6)=0,"",SUM(AO6:AQ6)) -> 11660500
A7: =Mapping!J7 -> 000104420000006 | B7: =Mapping!K7 -> High | C7: 10 | D7: ='Loan Book'!E10 -> Nsanama Women Cooperatives | E7: ='Loan Book'!F10 -> Debt | F7: ='Loan Book'!G10 -> 44076 | G7: ='Loan Book'!H10 -> 44804 | H7: ='Loan Book'!I10 -> 1.9945205 | I7: ='Loan Book'!J10 -> 6 (Cap only) | J7: =IF('Loan Book'!K10="","",IF('Loan Book'!K10<1,'Loan Book'!K10*100,'Loan Book'!K10)) -> 23.12 | K7: ='Loan Book'!L10 -> 17000000 | L7: ='Loan Book'!M10 -> 12055000 | M7: ='Loan Book'!N10 -> 4945000 | N7: ='Loan Book'!O10 -> 12055000 | O7: ='Loan Book'!P10 -> 2792906.9 | P7: ='Loan Book'!Q10 -> -2000000 | Q7: ='Loan Book'!R10 -> 12847907 | R7: ='Loan Book'!S10 -> 12055000 | ... T7: ='Loan Book'!U10 -> 13551874 | U7: ='Loan Book'!AC10 -> 0 | V7: ='Loan Book'!AE10 -> 0 | W7: =IFERROR(INDEX('E-Banker master'!$B$2:$B$186,MATCH($A7,'E-Banker master'!$A$2:$A$186,0)),"") -> Nsanama Women Cooperatives | X7: =IFERROR(INDEX('E-Banker master'!$C$2:$C$186,MATCH($A7,'E-Banker master'!$A$2:$A$186,0)),"") -> 84 | Y7: =IFERROR(INDEX('E-Banker master'!$D$2:$D$186,MATCH($A7,'E-Banker master'!$A$2:$A$186,0)),"") -> 1050101 | Z7: =IFERROR(INDEX('E-Banker master'!$E$2:$E$186,MATCH($A7,'E-Banker master'!$A$2:$A$186,0)),"") -> D | AA7: =IFERROR(INDEX('E-Banker master'!$F$2:$F$186,MATCH($A7,'E-Banker master'!$A$2:$A$186,0)),"") -> P | AB7: =IFERROR(INDEX('E-Banker master'!$G$2:$G$186,MATCH($A7,'E-Banker master'!$A$2:$A$186,0)),"") -> 31.82 | AC7: =IFERROR(INDEX('E-Banker master'!$I$2:$I$186,MATCH($A7,'E-Banker master'!$A$2:$A$186,0)),"") -> 17000000 | AD7: =IFERROR(INDEX('E-Banker master'!$J$2:$J$186,MATCH($A7,'E-Banker master'!$A$2:$A$186,0)),"") -> 44076 | AE7: =IFERROR(INDEX('E-Banker master'!$K$2:$K$186,MATCH($A7,'E-Banker master'!$A$2:$A$186,0)),"") -> 44805 | AF7: =IFERROR(INDEX('E-Banker master'!$L$2:$L$186,MATCH($A7,'E-Banker master'!$A$2:$A$186,0)),"") -> 6 | AG7: =IFERROR(INDEX('E-Banker master'!$M$2:$M$186,MATCH($A7,'E-Banker master'!$A$2:$A$186,0)),"") -> 0 | AH7: =IFERROR(INDEX('E-Banker master'!$N$2:$N$186,MATCH($A7,'E-Banker master'!$A$2:$A$186,0)),"") -> 12055000 | AI7: =IFERROR(INDEX('E-Banker master'!$O$2:$O$186,MATCH($A7,'E-Banker master'!$A$2:$A$186,0)),"") -> 2792906.9 | AJ7: =IFERROR(INDEX('E-Banker master'!$P$2:$P$186,MATCH($A7,'E-Banker master'!$A$2:$A$186,0)),"") -> 13568451 | AK7: =IF(OR(Q7="",AJ7=""),"",Q7-AJ7) -> -720544.24 | AL7: 6 | AM7: =HYPERLINK("#'Amortisation and Repayments'!C357","block 6") -> block 6 | AN7: =Mapping!X7 -> 0 | AO7: ='Loan Book'!AS10 -> 255000 | AP7: ='Loan Book'!AT10 -> 0 | AR7: =AD7 -> 44076 | AS7: Y | AT7: Offer letter and Quickbooks | AU7: =IF(COUNT(AO7:AQ7)=0,"",SUM(AO7:AQ7)) -> 255000
A8: =Mapping!J8 -> 000104420000007 | B8: =Mapping!K8 -> High | C8: 11 | D8: ='Loan Book'!E11 -> LENZIEMILL MILLING LIMITED | E8: ='Loan Book'!F11 -> Debt | F8: ='Loan Book'!G11 -> 44134 | G8: ='Loan Book'!H11 -> 45869 | H8: ='Loan Book'!I11 -> 4.7534247 | I8: ='Loan Book'!J11 -> 6 (Cap+Int) | J8: =IF('Loan Book'!K11="","",IF('Loan Book'!K11<1,'Loan Book'!K11*100,'Loan Book'!K11)) -> 29.4 | K8: ='Loan Book'!L11 -> 460000000 | L8: ='Loan Book'!M11 -> 297400000 | M8: ='Loan Book'!N11 -> 0 | N8: ='Loan Book'!O11 -> 297400000 | O8: ='Loan Book'!P11 -> 2.3305268e+08 | P8: ='Loan Book'!Q11 -> -3.6339288e+08 | Q8: ='Loan Book'!R11 -> 1.670598e+08 | R8: ='Loan Book'!S11 -> 4685207.4 | ... T8: ='Loan Book'!U11 -> 9031286.4 | U8: ='Loan Book'!AC11 -> 0 | V8: ='Loan Book'!AE11 -> 0 | W8: =IFERROR(INDEX('E-Banker master'!$B$2:$B$186,MATCH($A8,'E-Banker master'!$A$2:$A$186,0)),"") -> LENZIEMILL MILLING LIMITED | X8: =IFERROR(INDEX('E-Banker master'!$C$2:$C$186,MATCH($A8,'E-Banker master'!$A$2:$A$186,0)),"") -> 84 | Y8: =IFERROR(INDEX('E-Banker master'!$D$2:$D$186,MATCH($A8,'E-Banker master'!$A$2:$A$186,0)),"") -> 1050101 | Z8: =IFERROR(INDEX('E-Banker master'!$E$2:$E$186,MATCH($A8,'E-Banker master'!$A$2:$A$186,0)),"") -> H | AA8: =IFERROR(INDEX('E-Banker master'!$F$2:$F$186,MATCH($A8,'E-Banker master'!$A$2:$A$186,0)),"") -> P | AB8: =IFERROR(INDEX('E-Banker master'!$G$2:$G$186,MATCH($A8,'E-Banker master'!$A$2:$A$186,0)),"") -> 32 | AC8: =IFERROR(INDEX('E-Banker master'!$I$2:$I$186,MATCH($A8,'E-Banker master'!$A$2:$A$186,0)),"") -> 460000000 | AD8: =IFERROR(INDEX('E-Banker master'!$J$2:$J$186,MATCH($A8,'E-Banker master'!$A$2:$A$186,0)),"") -> 44075 | AE8: =IFERROR(INDEX('E-Banker master'!$K$2:$K$186,MATCH($A8,'E-Banker master'!$A$2:$A$186,0)),"") -> 45901 | AF8: =IFERROR(INDEX('E-Banker master'!$L$2:$L$186,MATCH($A8,'E-Banker master'!$A$2:$A$186,0)),"") -> 6 | AG8: =IFERROR(INDEX('E-Banker master'!$M$2:$M$186,MATCH($A8,'E-Banker master'!$A$2:$A$186,0)),"") -> 0 | AH8: =IFERROR(INDEX('E-Banker master'!$N$2:$N$186,MATCH($A8,'E-Banker master'!$A$2:$A$186,0)),"") -> 297400000 | AI8: =IFERROR(INDEX('E-Banker master'!$O$2:$O$186,MATCH($A8,'E-Banker master'!$A$2:$A$186,0)),"") -> 2.1965419e+08 | AJ8: =IFERROR(INDEX('E-Banker master'!$P$2:$P$186,MATCH($A8,'E-Banker master'!$A$2:$A$186,0)),"") -> 1.6797652e+08 | AK8: =IF(OR(Q8="",AJ8=""),"",Q8-AJ8) -> -916718.97 | AL8: 7 | AM8: =HYPERLINK("#'Amortisation and Repayments'!C399","block 7") -> block 7 | AN8: =Mapping!X8 -> 0 | AO8: ='Loan Book'!AS11 -> 6900000 | AP8: ='Loan Book'!AT11 -> 6216000 | AR8: =AD8 -> 44075 | AS8: Y | AT8: Offer letter and Quickbooks | AU8: =IF(COUNT(AO8:AQ8)=0,"",SUM(AO8:AQ8)) -> 13116000
A9: =Mapping!J9 -> 000104430000008 | B9: =Mapping!K9 -> High | C9: 12 | D9: ='Loan Book'!E12 -> Corran Farming Limited | E9: ='Loan Book'!F12 -> Debt | F9: ='Loan Book'!G12 -> 44187 | G9: ='Loan Book'!H12 -> 46022 | H9: ='Loan Book'!I12 -> 5.0273973 | I9: ='Loan Book'!J12 -> 6 (Cap only) | J9: =IF('Loan Book'!K12="","",IF('Loan Book'!K12<1,'Loan Book'!K12*100,'Loan Book'!K12)) -> 29.3 | K9: ='Loan Book'!L12 -> 395623962 | L9: ='Loan Book'!M12 -> 395623962 | M9: ='Loan Book'!N12 -> 0 | N9: ='Loan Book'!O12 -> 395623962 | O9: ='Loan Book'!P12 -> 1.5030844e+08 | P9: ='Loan Book'!Q12 -> -5.459324e+08 | Q9: ='Loan Book'!R12 -> 0.00069212914 | R9: ='Loan Book'!S12 -> 0 | ... T9: ='Loan Book'!U12 -> 0 | U9: ='Loan Book'!AC12 -> 0 | V9: ='Loan Book'!AE12 -> 0 | W9: =IFERROR(INDEX('E-Banker master'!$B$2:$B$186,MATCH($A9,'E-Banker master'!$A$2:$A$186,0)),"") -> Corran Farming Limited | X9: =IFERROR(INDEX('E-Banker master'!$C$2:$C$186,MATCH($A9,'E-Banker master'!$A$2:$A$186,0)),"") -> 86 | Y9: =IFERROR(INDEX('E-Banker master'!$D$2:$D$186,MATCH($A9,'E-Banker master'!$A$2:$A$186,0)),"") -> 1050102 | Z9: =IFERROR(INDEX('E-Banker master'!$E$2:$E$186,MATCH($A9,'E-Banker master'!$A$2:$A$186,0)),"") -> C | AA9: =IFERROR(INDEX('E-Banker master'!$F$2:$F$186,MATCH($A9,'E-Banker master'!$A$2:$A$186,0)),"") -> M | AB9: =IFERROR(INDEX('E-Banker master'!$G$2:$G$186,MATCH($A9,'E-Banker master'!$A$2:$A$186,0)),"") -> 32.1 | AC9: =IFERROR(INDEX('E-Banker master'!$I$2:$I$186,MATCH($A9,'E-Banker master'!$A$2:$A$186,0)),"") -> 395623962 | AD9: =IFERROR(INDEX('E-Banker master'!$J$2:$J$186,MATCH($A9,'E-Banker master'!$A$2:$A$186,0)),"") -> 44501 | AE9: =IFERROR(INDEX('E-Banker master'!$K$2:$K$186,MATCH($A9,'E-Banker master'!$A$2:$A$186,0)),"") -> 46012 | AF9: =IFERROR(INDEX('E-Banker master'!$L$2:$L$186,MATCH($A9,'E-Banker master'!$A$2:$A$186,0)),"") -> 6 | AG9: =IFERROR(INDEX('E-Banker master'!$M$2:$M$186,MATCH($A9,'E-Banker master'!$A$2:$A$186,0)),"") -> 0 | AH9: =IFERROR(INDEX('E-Banker master'!$N$2:$N$186,MATCH($A9,'E-Banker master'!$A$2:$A$186,0)),"") -> 0 | AI9: =IFERROR(INDEX('E-Banker master'!$O$2:$O$186,MATCH($A9,'E-Banker master'!$A$2:$A$186,0)),"") -> 0 | AJ9: =IFERROR(INDEX('E-Banker master'!$P$2:$P$186,MATCH($A9,'E-Banker master'!$A$2:$A$186,0)),"") -> 0 | AK9: =IF(OR(Q9="",AJ9=""),"",Q9-AJ9) -> 0.00069212914 | AL9: 8 | AM9: =HYPERLINK("#'Amortisation and Repayments'!C489","block 8") -> block 8 | AN9: =Mapping!X9 -> 0 | AO9: ='Loan Book'!AS12 -> 6400000 | AP9: ='Loan Book'!AT12 -> 10000000 | AR9: =AD9 -> 44501 | AS9: Y | AT9: Offer letter and Quickbooks | AU9: =IF(COUNT(AO9:AQ9)=0,"",SUM(AO9:AQ9)) -> 16400000
A10: =Mapping!J10 -> 000104420000009 | B10: =Mapping!K10 -> High | C10: 13 | D10: ='Loan Book'!E13 -> Mach Milk Limited | E10: ='Loan Book'!F13 -> Debt | F10: ='Loan Book'!G13 -> 44242 | G10: ='Loan Book'!H13 -> 45716 | H10: ='Loan Book'!I13 -> 4.0383562 | I10: ='Loan Book'!J13 -> 12 (Cap+Int) | J10: =IF('Loan Book'!K13="","",IF('Loan Book'!K13<1,'Loan Book'!K13*100,'Loan Book'!K13)) -> 31.3 | K10: ='Loan Book'!L13 -> 81075927 | L10: ='Loan Book'!M13 -> 81075927 | M10: ='Loan Book'!N13 -> 0 | N10: ='Loan Book'!O13 -> 81075927 | O10: ='Loan Book'!P13 -> 59885873 | P10: ='Loan Book'!Q13 -> -13800000 | Q10: ='Loan Book'!R13 -> 1.271618e+08 | R10: ='Loan Book'!S13 -> 56187334 | ... T10: ='Loan Book'!U13 -> 93808597 | U10: ='Loan Book'!AC13 -> 0 | V10: ='Loan Book'!AE13 -> 0 | W10: =IFERROR(INDEX('E-Banker master'!$B$2:$B$186,MATCH($A10,'E-Banker master'!$A$2:$A$186,0)),"") -> Mach Milk Limited | X10: =IFERROR(INDEX('E-Banker master'!$C$2:$C$186,MATCH($A10,'E-Banker master'!$A$2:$A$186,0)),"") -> 84 | Y10: =IFERROR(INDEX('E-Banker master'!$D$2:$D$186,MATCH($A10,'E-Banker master'!$A$2:$A$186,0)),"") -> 1050101 | Z10: =IFERROR(INDEX('E-Banker master'!$E$2:$E$186,MATCH($A10,'E-Banker master'!$A$2:$A$186,0)),"") -> D | AA10: =IFERROR(INDEX('E-Banker master'!$F$2:$F$186,MATCH($A10,'E-Banker master'!$A$2:$A$186,0)),"") -> P | AB10: =IFERROR(INDEX('E-Banker master'!$G$2:$G$186,MATCH($A10,'E-Banker master'!$A$2:$A$186,0)),"") -> 33.9 | AC10: =IFERROR(INDEX('E-Banker master'!$I$2:$I$186,MATCH($A10,'E-Banker master'!$A$2:$A$186,0)),"") -> 65023440 | AD10: =IFERROR(INDEX('E-Banker master'!$J$2:$J$186,MATCH($A10,'E-Banker master'!$A$2:$A$186,0)),"") -> 44117 | AE10: =IFERROR(INDEX('E-Banker master'!$K$2:$K$186,MATCH($A10,'E-Banker master'!$A$2:$A$186,0)),"") -> 45760 | AF10: =IFERROR(INDEX('E-Banker master'!$L$2:$L$186,MATCH($A10,'E-Banker master'!$A$2:$A$186,0)),"") -> 6 | AG10: =IFERROR(INDEX('E-Banker master'!$M$2:$M$186,MATCH($A10,'E-Banker master'!$A$2:$A$186,0)),"") -> 0 | AH10: =IFERROR(INDEX('E-Banker master'!$N$2:$N$186,MATCH($A10,'E-Banker master'!$A$2:$A$186,0)),"") -> 81075927 | AI10: =IFERROR(INDEX('E-Banker master'!$O$2:$O$186,MATCH($A10,'E-Banker master'!$A$2:$A$186,0)),"") -> 56575015 | AJ10: =IFERROR(INDEX('E-Banker master'!$P$2:$P$186,MATCH($A10,'E-Banker master'!$A$2:$A$186,0)),"") -> 1.3507055e+08 | AK10: =IF(OR(Q10="",AJ10=""),"",Q10-AJ10) -> -7908753.5 | AL10: 9 | AM10: =HYPERLINK("#'Amortisation and Repayments'!C553","block 9") -> block 9 | AN10: =Mapping!X10 -> 0 | AO10: ='Loan Book'!AS13 -> 960440 | AP10: ='Loan Book'!AT13 -> 1562500 | AR10: =AD10 -> 44117 | AS10: Y | AT10: Offer letter and Quickbooks | AU10: =IF(COUNT(AO10:AQ10)=0,"",SUM(AO10:AQ10)) -> 2522940
A11: =Mapping!J11 -> 000104420000010 | B11: =Mapping!K11 -> High | C11: 14 | D11: ='Loan Book'!E14 -> Nature's Gift Limited | E11: ='Loan Book'!F14 -> Debt | F11: ='Loan Book'!G14 -> 44307 | G11: ='Loan Book'!H14 -> 46295 | H11: ='Loan Book'!I14 -> 5.4465753 | I11: ='Loan Book'!J14 -> - | J11: =IF('Loan Book'!K14="","",IF('Loan Book'!K14<1,'Loan Book'!K14*100,'Loan Book'!K14)) -> 28.7 | K11: ='Loan Book'!L14 -> 80000000 | L11: ='Loan Book'!M14 -> 80000000 | M11: ='Loan Book'!N14 -> 0 | N11: ='Loan Book'!O14 -> 80000000 | O11: ='Loan Book'!P14 -> 49606669 | P11: ='Loan Book'!Q14 -> -79619446 | Q11: ='Loan Book'!R14 -> 49987223 | R11: ='Loan Book'!S14 -> 0 | ... T11: ='Loan Book'!U14 -> 0 | U11: ='Loan Book'!AC14 -> 0 | V11: ='Loan Book'!AE14 -> 0 | W11: =IFERROR(INDEX('E-Banker master'!$B$2:$B$186,MATCH($A11,'E-Banker master'!$A$2:$A$186,0)),"") -> Nature's Gift Limited | X11: =IFERROR(INDEX('E-Banker master'!$C$2:$C$186,MATCH($A11,'E-Banker master'!$A$2:$A$186,0)),"") -> 84 | Y11: =IFERROR(INDEX('E-Banker master'!$D$2:$D$186,MATCH($A11,'E-Banker master'!$A$2:$A$186,0)),"") -> 1050101 | Z11: =IFERROR(INDEX('E-Banker master'!$E$2:$E$186,MATCH($A11,'E-Banker master'!$A$2:$A$186,0)),"") -> A | AA11: =IFERROR(INDEX('E-Banker master'!$F$2:$F$186,MATCH($A11,'E-Banker master'!$A$2:$A$186,0)),"") -> M | AB11: =IFERROR(INDEX('E-Banker master'!$G$2:$G$186,MATCH($A11,'E-Banker master'!$A$2:$A$186,0)),"") -> 26.8 | AC11: =IFERROR(INDEX('E-Banker master'!$I$2:$I$186,MATCH($A11,'E-Banker master'!$A$2:$A$186,0)),"") -> 80000000 | AD11: =IFERROR(INDEX('E-Banker master'!$J$2:$J$186,MATCH($A11,'E-Banker master'!$A$2:$A$186,0)),"") -> 44307 | AE11: =IFERROR(INDEX('E-Banker master'!$K$2:$K$186,MATCH($A11,'E-Banker master'!$A$2:$A$186,0)),"") -> 46133 | AF11: =IFERROR(INDEX('E-Banker master'!$L$2:$L$186,MATCH($A11,'E-Banker master'!$A$2:$A$186,0)),"") -> 0 | AG11: =IFERROR(INDEX('E-Banker master'!$M$2:$M$186,MATCH($A11,'E-Banker master'!$A$2:$A$186,0)),"") -> 0 | AH11: =IFERROR(INDEX('E-Banker master'!$N$2:$N$186,MATCH($A11,'E-Banker master'!$A$2:$A$186,0)),"") -> 80000000 | AI11: =IFERROR(INDEX('E-Banker master'!$O$2:$O$186,MATCH($A11,'E-Banker master'!$A$2:$A$186,0)),"") -> 46627490 | AJ11: =IFERROR(INDEX('E-Banker master'!$P$2:$P$186,MATCH($A11,'E-Banker master'!$A$2:$A$186,0)),"") -> 50784762 | AK11: =IF(OR(Q11="",AJ11=""),"",Q11-AJ11) -> -797538.95 | AL11: 10 | AM11: =HYPERLINK("#'Amortisation and Repayments'!C616","block 10") -> block 10 | AN11: =Mapping!X11 -> 0 | AO11: ='Loan Book'!AS14 -> 1650000 | AP11: ='Loan Book'!AT14 -> 3650000 | AR11: =AD11 -> 44307 | AS11: Y | AT11: Offer letter and Quickbooks | AU11: =IF(COUNT(AO11:AQ11)=0,"",SUM(AO11:AQ11)) -> 5300000
A12: =Mapping!J12 -> 000104420000012 | B12: =Mapping!K12 -> High | C12: 15 | D12: ='Loan Book'!E15 -> Nature's Gift Limited | E12: ='Loan Book'!F15 -> Debt | F12: ='Loan Book'!G15 -> 44400 | G12: ='Loan Book'!H15 -> 46142 | H12: ='Loan Book'!I15 -> 4.7726027 | I12: ='Loan Book'!J15 -> 0 | J12: =IF('Loan Book'!K15="","",IF('Loan Book'!K15<1,'Loan Book'!K15*100,'Loan Book'!K15)) -> 28.7 | K12: ='Loan Book'!L15 -> 85000000 | L12: ='Loan Book'!M15 -> 85000000 | M12: ='Loan Book'!N15 -> 0 | N12: ='Loan Book'!O15 -> 85000000 | O12: ='Loan Book'!P15 -> 48641493 | P12: ='Loan Book'!Q15 -> -91262043 | Q12: ='Loan Book'!R15 -> 42379450 | R12: ='Loan Book'!S15 -> 0 | ... T12: ='Loan Book'!U15 -> 0 | U12: ='Loan Book'!AC15 -> 0 | V12: ='Loan Book'!AE15 -> 0 | W12: =IFERROR(INDEX('E-Banker master'!$B$2:$B$186,MATCH($A12,'E-Banker master'!$A$2:$A$186,0)),"") -> Nature's Gift Limited | X12: =IFERROR(INDEX('E-Banker master'!$C$2:$C$186,MATCH($A12,'E-Banker master'!$A$2:$A$186,0)),"") -> 84 | Y12: =IFERROR(INDEX('E-Banker master'!$D$2:$D$186,MATCH($A12,'E-Banker master'!$A$2:$A$186,0)),"") -> 1050101 | Z12: =IFERROR(INDEX('E-Banker master'!$E$2:$E$186,MATCH($A12,'E-Banker master'!$A$2:$A$186,0)),"") -> A | AA12: =IFERROR(INDEX('E-Banker master'!$F$2:$F$186,MATCH($A12,'E-Banker master'!$A$2:$A$186,0)),"") -> M | AB12: =IFERROR(INDEX('E-Banker master'!$G$2:$G$186,MATCH($A12,'E-Banker master'!$A$2:$A$186,0)),"") -> 26.5 | AC12: =IFERROR(INDEX('E-Banker master'!$I$2:$I$186,MATCH($A12,'E-Banker master'!$A$2:$A$186,0)),"") -> 85000000 | AD12: =IFERROR(INDEX('E-Banker master'!$J$2:$J$186,MATCH($A12,'E-Banker master'!$A$2:$A$186,0)),"") -> 44400 | AE12: =IFERROR(INDEX('E-Banker master'!$K$2:$K$186,MATCH($A12,'E-Banker master'!$A$2:$A$186,0)),"") -> 46226 | AF12: =IFERROR(INDEX('E-Banker master'!$L$2:$L$186,MATCH($A12,'E-Banker master'!$A$2:$A$186,0)),"") -> 0 | AG12: =IFERROR(INDEX('E-Banker master'!$M$2:$M$186,MATCH($A12,'E-Banker master'!$A$2:$A$186,0)),"") -> 0 | AH12: =IFERROR(INDEX('E-Banker master'!$N$2:$N$186,MATCH($A12,'E-Banker master'!$A$2:$A$186,0)),"") -> 85000000 | AI12: =IFERROR(INDEX('E-Banker master'!$O$2:$O$186,MATCH($A12,'E-Banker master'!$A$2:$A$186,0)),"") -> 45506489 | AJ12: =IFERROR(INDEX('E-Banker master'!$P$2:$P$186,MATCH($A12,'E-Banker master'!$A$2:$A$186,0)),"") -> 42742352 | AK12: =IF(OR(Q12="",AJ12=""),"",Q12-AJ12) -> -362902.07 | AL12: 12 | AM12: =HYPERLINK("#'Amortisation and Repayments'!C756","block 12") -> block 12 | AN12: =Mapping!X12 -> 0 | AO12: ='Loan Book'!AS15 -> 0 | AP12: ='Loan Book'!AT15 -> 0 | AR12: =AD12 -> 44400 | AU12: =IF(COUNT(AO12:AQ12)=0,"",SUM(AO12:AQ12)) -> 0
A13: =Mapping!J13 -> 000104420000011 | B13: =Mapping!K13 -> High | C13: 16 | D13: ='Loan Book'!E16 -> Kajikhomele Foundation Ltd | E13: ='Loan Book'!F16 -> Debt | F13: ='Loan Book'!G16 -> 44336 | G13: ='Loan Book'!H16 -> 45796 | H13: ='Loan Book'!I16 -> 4 | I13: ='Loan Book'!J16 -> 12 (Cap+Int) | J13: =IF('Loan Book'!K16="","",IF('Loan Book'!K16<1,'Loan Book'!K16*100,'Loan Book'!K16)) -> 29.7 | K13: ='Loan Book'!L16 -> 96552500 | L13: ='Loan Book'!M16 -> 96552500 | M13: ='Loan Book'!N16 -> 0 | N13: ='Loan Book'!O16 -> 96552500 | O13: ='Loan Book'!P16 -> 79960564 | P13: ='Loan Book'!Q16 -> -23143102 | Q13: ='Loan Book'!R16 -> 1.5336996e+08 | R13: ='Loan Book'!S16 -> 58731537 | ... T13: ='Loan Book'!U16 -> 86196004 | U13: ='Loan Book'!AC16 -> 0 | V13: ='Loan Book'!AE16 -> 0 | W13: =IFERROR(INDEX('E-Banker master'!$B$2:$B$186,MATCH($A13,'E-Banker master'!$A$2:$A$186,0)),"") -> Kajikhomele Foundation Ltd | X13: =IFERROR(INDEX('E-Banker master'!$C$2:$C$186,MATCH($A13,'E-Banker master'!$A$2:$A$186,0)),"") -> 84 | Y13: =IFERROR(INDEX('E-Banker master'!$D$2:$D$186,MATCH($A13,'E-Banker master'!$A$2:$A$186,0)),"") -> 1050101 | Z13: =IFERROR(INDEX('E-Banker master'!$E$2:$E$186,MATCH($A13,'E-Banker master'!$A$2:$A$186,0)),"") -> D | AA13: =IFERROR(INDEX('E-Banker master'!$F$2:$F$186,MATCH($A13,'E-Banker master'!$A$2:$A$186,0)),"") -> P | AB13: =IFERROR(INDEX('E-Banker master'!$G$2:$G$186,MATCH($A13,'E-Banker master'!$A$2:$A$186,0)),"") -> 32.3 | AC13: =IFERROR(INDEX('E-Banker master'!$I$2:$I$186,MATCH($A13,'E-Banker master'!$A$2:$A$186,0)),"") -> 96552500 | AD13: =IFERROR(INDEX('E-Banker master'!$J$2:$J$186,MATCH($A13,'E-Banker master'!$A$2:$A$186,0)),"") -> 44266 | AE13: =IFERROR(INDEX('E-Banker master'!$K$2:$K$186,MATCH($A13,'E-Banker master'!$A$2:$A$186,0)),"") -> 45727 | AF13: =IFERROR(INDEX('E-Banker master'!$L$2:$L$186,MATCH($A13,'E-Banker master'!$A$2:$A$186,0)),"") -> 12 | AG13: =IFERROR(INDEX('E-Banker master'!$M$2:$M$186,MATCH($A13,'E-Banker master'!$A$2:$A$186,0)),"") -> 12 | AH13: =IFERROR(INDEX('E-Banker master'!$N$2:$N$186,MATCH($A13,'E-Banker master'!$A$2:$A$186,0)),"") -> 96552500 | AI13: =IFERROR(INDEX('E-Banker master'!$O$2:$O$186,MATCH($A13,'E-Banker master'!$A$2:$A$186,0)),"") -> 75812662 | AJ13: =IFERROR(INDEX('E-Banker master'!$P$2:$P$186,MATCH($A13,'E-Banker master'!$A$2:$A$186,0)),"") -> 1.6208554e+08 | AK13: =IF(OR(Q13="",AJ13=""),"",Q13-AJ13) -> -8715581.5 | AL13: 11 | AM13: =HYPERLINK("#'Amortisation and Repayments'!C692","block 11") -> block 11 | AN13: =Mapping!X13 -> 0 | AO13: ='Loan Book'!AS16 -> 1448288 | AP13: ='Loan Book'!AT16 -> 2605500 | AR13: =AD13 -> 44266 | AS13: Y | AT13: Offer letter and Quickbooks | AU13: =IF(COUNT(AO13:AQ13)=0,"",SUM(AO13:AQ13)) -> 4053788
A14: =Mapping!J14 -> 000104450000012 | B14: =Mapping!K14 -> High | C14: 17 | D14: ='Loan Book'!E17 -> Maluso Cooperative Union (MCU) | E14: ='Loan Book'!F17 -> Debt | F14: ='Loan Book'!G17 -> 44553 | G14: ='Loan Book'!H17 -> 45291 | H14: ='Loan Book'!I17 -> 2.0219178 | I14: ='Loan Book'!J17 -> 3 (Cap+Int) | J14: =IF('Loan Book'!K17="","",IF('Loan Book'!K17<1,'Loan Book'!K17*100,'Loan Book'!K17)) -> 10 | K14: ='Loan Book'!L17 -> 11511500 | L14: ='Loan Book'!M17 -> 11511500 | M14: ='Loan Book'!N17 -> 0 | N14: ='Loan Book'!O17 -> 11511500 | O14: ='Loan Book'!P17 -> 1430309.6 | P14: ='Loan Book'!Q17 -> -900000 | Q14: ='Loan Book'!R17 -> 0 | R14: ='Loan Book'!S17 -> 0 | ... T14: ='Loan Book'!U17 -> 0 | U14: ='Loan Book'!AC17 -> 0 | V14: ='Loan Book'!AE17 -> 0 | W14: =IFERROR(INDEX('E-Banker master'!$B$2:$B$186,MATCH($A14,'E-Banker master'!$A$2:$A$186,0)),"") -> Maluso Cooperative Union | X14: =IFERROR(INDEX('E-Banker master'!$C$2:$C$186,MATCH($A14,'E-Banker master'!$A$2:$A$186,0)),"") -> 90 | Y14: =IFERROR(INDEX('E-Banker master'!$D$2:$D$186,MATCH($A14,'E-Banker master'!$A$2:$A$186,0)),"") -> 1050201 | Z14: =IFERROR(INDEX('E-Banker master'!$E$2:$E$186,MATCH($A14,'E-Banker master'!$A$2:$A$186,0)),"") -> A | AA14: =IFERROR(INDEX('E-Banker master'!$F$2:$F$186,MATCH($A14,'E-Banker master'!$A$2:$A$186,0)),"") -> S | AB14: =IFERROR(INDEX('E-Banker master'!$G$2:$G$186,MATCH($A14,'E-Banker master'!$A$2:$A$186,0)),"") -> 10 | AC14: =IFERROR(INDEX('E-Banker master'!$I$2:$I$186,MATCH($A14,'E-Banker master'!$A$2:$A$186,0)),"") -> 11511500 | AD14: =IFERROR(INDEX('E-Banker master'!$J$2:$J$186,MATCH($A14,'E-Banker master'!$A$2:$A$186,0)),"") -> 44553 | AE14: =IFERROR(INDEX('E-Banker master'!$K$2:$K$186,MATCH($A14,'E-Banker master'!$A$2:$A$186,0)),"") -> 45282 | AF14: =IFERROR(INDEX('E-Banker master'!$L$2:$L$186,MATCH($A14,'E-Banker master'!$A$2:$A$186,0)),"") -> 3 | AG14: =IFERROR(INDEX('E-Banker master'!$M$2:$M$186,MATCH($A14,'E-Banker master'!$A$2:$A$186,0)),"") -> 3 | AH14: =IFERROR(INDEX('E-Banker master'!$N$2:$N$186,MATCH($A14,'E-Banker master'!$A$2:$A$186,0)),"") -> 11511500 | AI14: =IFERROR(INDEX('E-Banker master'!$O$2:$O$186,MATCH($A14,'E-Banker master'!$A$2:$A$186,0)),"") -> 1430309.6 | AJ14: =IFERROR(INDEX('E-Banker master'!$P$2:$P$186,MATCH($A14,'E-Banker master'!$A$2:$A$186,0)),"") -> 0 | AK14: =IF(OR(Q14="",AJ14=""),"",Q14-AJ14) -> 0 | AL14: 18 | AM14: =HYPERLINK("#'Amortisation and Repayments'!C1044","block 18") -> block 18 | AN14: =Mapping!X14 -> 0 | AO14: ='Loan Book'!AS17 -> 115115 | AP14: ='Loan Book'!AT17 -> 272696.76 | AR14: =AD14 -> 44553 | AS14: Y | AT14: Offer letter and Quickbooks | AU14: =IF(COUNT(AO14:AQ14)=0,"",SUM(AO14:AQ14)) -> 387811.76
A15: =Mapping!J15 -> 000104450000013 | B15: =Mapping!K15 -> High | C15: 18 | D15: ='Loan Book'!E18 -> Ndagha Sustainable Food Ltd | E15: ='Loan Book'!F18 -> Debt | F15: ='Loan Book'!G18 -> 44554 | G15: ='Loan Book'!H18 -> 45291 | H15: ='Loan Book'!I18 -> 2.0191781 | I15: ='Loan Book'!J18 -> 0 | J15: =IF('Loan Book'!K18="","",IF('Loan Book'!K18<1,'Loan Book'!K18*100,'Loan Book'!K18)) -> 10 | K15: ='Loan Book'!L18 -> 10000000 | L15: ='Loan Book'!M18 -> 10000000 | M15: ='Loan Book'!N18 -> 0 | N15: ='Loan Book'!O18 -> 10000000 | O15: ='Loan Book'!P18 -> 1096700.1 | P15: ='Loan Book'!Q18 -> -11096700 | Q15: ='Loan Book'!R18 -> -0.000776859 | R15: ='Loan Book'!S18 -> 0 | ... T15: ='Loan Book'!U18 -> 0 | U15: ='Loan Book'!AC18 -> 0 | V15: ='Loan Book'!AE18 -> 0 | W15: =IFERROR(INDEX('E-Banker master'!$B$2:$B$186,MATCH($A15,'E-Banker master'!$A$2:$A$186,0)),"") -> Ndagha Sustainable Foods Limited | X15: =IFERROR(INDEX('E-Banker master'!$C$2:$C$186,MATCH($A15,'E-Banker master'!$A$2:$A$186,0)),"") -> 90 | Y15: =IFERROR(INDEX('E-Banker master'!$D$2:$D$186,MATCH($A15,'E-Banker master'!$A$2:$A$186,0)),"") -> 1050201 | Z15: =IFERROR(INDEX('E-Banker master'!$E$2:$E$186,MATCH($A15,'E-Banker master'!$A$2:$A$186,0)),"") -> C | AA15: =IFERROR(INDEX('E-Banker master'!$F$2:$F$186,MATCH($A15,'E-Banker master'!$A$2:$A$186,0)),"") -> S | AB15: =IFERROR(INDEX('E-Banker master'!$G$2:$G$186,MATCH($A15,'E-Banker master'!$A$2:$A$186,0)),"") -> 10 | AC15: =IFERROR(INDEX('E-Banker master'!$I$2:$I$186,MATCH($A15,'E-Banker master'!$A$2:$A$186,0)),"") -> 10000000 | AD15: =IFERROR(INDEX('E-Banker master'!$J$2:$J$186,MATCH($A15,'E-Banker master'!$A$2:$A$186,0)),"") -> 44554 | AE15: =IFERROR(INDEX('E-Banker master'!$K$2:$K$186,MATCH($A15,'E-Banker master'!$A$2:$A$186,0)),"") -> 45283 | AF15: =IFERROR(INDEX('E-Banker master'!$L$2:$L$186,MATCH($A15,'E-Banker master'!$A$2:$A$186,0)),"") -> 0 | AG15: =IFERROR(INDEX('E-Banker master'!$M$2:$M$186,MATCH($A15,'E-Banker master'!$A$2:$A$186,0)),"") -> 0 | AH15: =IFERROR(INDEX('E-Banker master'!$N$2:$N$186,MATCH($A15,'E-Banker master'!$A$2:$A$186,0)),"") -> 0 | AI15: =IFERROR(INDEX('E-Banker master'!$O$2:$O$186,MATCH($A15,'E-Banker master'!$A$2:$A$186,0)),"") -> 0 | AJ15: =IFERROR(INDEX('E-Banker master'!$P$2:$P$186,MATCH($A15,'E-Banker master'!$A$2:$A$186,0)),"") -> 0 | AK15: =IF(OR(Q15="",AJ15=""),"",Q15-AJ15) -> -0.000776859 | AL15: 13 | AM15: =HYPERLINK("#'Amortisation and Repayments'!C830","block 13") -> block 13 | AN15: =Mapping!X15 -> 0 | AO15: ='Loan Book'!AS18 -> 100000 | AP15: ='Loan Book'!AT18 -> 210000 | AR15: =AD15 -> 44554 | AS15: Y | AT15: Offer letter and Quickbooks | AU15: =IF(COUNT(AO15:AQ15)=0,"",SUM(AO15:AQ15)) -> 310000
A16: =Mapping!J16 -> 000104460000014 | B16: =Mapping!K16 -> High | C16: 19 | D16: ='Loan Book'!E19 -> Ecogen Ltd | E16: ='Loan Book'!F19 -> Debt | F16: ='Loan Book'!G19 -> 44551 | G16: ='Loan Book'!H19 -> 45291 | H16: ='Loan Book'!I19 -> 2.0273973 | I16: ='Loan Book'!J19 -> 6 (Cap+Int) | J16: =IF('Loan Book'!K19="","",IF('Loan Book'!K19<1,'Loan Book'!K19*100,'Loan Book'!K19)) -> 10 | K16: ='Loan Book'!L19 -> 20000000 | L16: ='Loan Book'!M19 -> 20000000 | M16: ='Loan Book'!N19 -> 0 | N16: ='Loan Book'!O19 -> 20000000 | O16: ='Loan Book'!P19 -> 2784623.4 | P16: ='Loan Book'!Q19 -> -22784623 | Q16: ='Loan Book'!R19 -> 0 | R16: ='Loan Book'!S19 -> 0 | ... T16: ='Loan Book'!U19 -> 0 | U16: ='Loan Book'!AC19 -> 0 | V16: ='Loan Book'!AE19 -> 0 | W16: =IFERROR(INDEX('E-Banker master'!$B$2:$B$186,MATCH($A16,'E-Banker master'!$A$2:$A$186,0)),"") -> Ecogen Limited | X16: =IFERROR(INDEX('E-Banker master'!$C$2:$C$186,MATCH($A16,'E-Banker master'!$A$2:$A$186,0)),"") -> 92 | Y16: =IFERROR(INDEX('E-Banker master'!$D$2:$D$186,MATCH($A16,'E-Banker master'!$A$2:$A$186,0)),"") -> 1050202 | Z16: =IFERROR(INDEX('E-Banker master'!$E$2:$E$186,MATCH($A16,'E-Banker master'!$A$2:$A$186,0)),"") -> C | AA16: =IFERROR(INDEX('E-Banker master'!$F$2:$F$186,MATCH($A16,'E-Banker master'!$A$2:$A$186,0)),"") -> S | AB16: =IFERROR(INDEX('E-Banker master'!$G$2:$G$186,MATCH($A16,'E-Banker master'!$A$2:$A$186,0)),"") -> 10 | AC16: =IFERROR(INDEX('E-Banker master'!$I$2:$I$186,MATCH($A16,'E-Banker master'!$A$2:$A$186,0)),"") -> 20000000 | AD16: =IFERROR(INDEX('E-Banker master'!$J$2:$J$186,MATCH($A16,'E-Banker master'!$A$2:$A$186,0)),"") -> 44561 | AE16: =IFERROR(INDEX('E-Banker master'!$K$2:$K$186,MATCH($A16,'E-Banker master'!$A$2:$A$186,0)),"") -> 45290 | AF16: =IFERROR(INDEX('E-Banker master'!$L$2:$L$186,MATCH($A16,'E-Banker master'!$A$2:$A$186,0)),"") -> 6 | AG16: =IFERROR(INDEX('E-Banker master'!$M$2:$M$186,MATCH($A16,'E-Banker master'!$A$2:$A$186,0)),"") -> 6 | AH16: =IFERROR(INDEX('E-Banker master'!$N$2:$N$186,MATCH($A16,'E-Banker master'!$A$2:$A$186,0)),"") -> 0 | AI16: =IFERROR(INDEX('E-Banker master'!$O$2:$O$186,MATCH($A16,'E-Banker master'!$A$2:$A$186,0)),"") -> 0 | AJ16: =IFERROR(INDEX('E-Banker master'!$P$2:$P$186,MATCH($A16,'E-Banker master'!$A$2:$A$186,0)),"") -> 0 | AK16: =IF(OR(Q16="",AJ16=""),"",Q16-AJ16) -> 0 | AL16: 14 | AM16: =HYPERLINK("#'Amortisation and Repayments'!C871","block 14") -> block 14 | AN16: =Mapping!X16 -> 0 | AO16: ='Loan Book'!AS19 -> 200000 | AP16: ='Loan Book'!AT19 -> 378320 | AR16: =AD16 -> 44561 | AS16: Y | AT16: Offer letter and Quickbooks | AU16: =IF(COUNT(AO16:AQ16)=0,"",SUM(AO16:AQ16)) -> 578320
A17: =Mapping!J17 -> 000104450000015 | B17: =Mapping!K17 -> High | C17: 20 | D17: ='Loan Book'!E20 -> Zaithwa Farms | E17: ='Loan Book'!F20 -> Debt | F17: ='Loan Book'!G20 -> 44551 | G17: ='Loan Book'!H20 -> 45275 | H17: ='Loan Book'!I20 -> 1.9835616 | I17: ='Loan Book'!J20 -> 0 | J17: =IF('Loan Book'!K20="","",IF('Loan Book'!K20<1,'Loan Book'!K20*100,'Loan Book'!K20)) -> 10 | K17: ='Loan Book'!L20 -> 10000000 | L17: ='Loan Book'!M20 -> 10000000 | M17: ='Loan Book'!N20 -> 0 | N17: ='Loan Book'!O20 -> 10000000 | O17: ='Loan Book'!P20 -> 1104919.3 | P17: ='Loan Book'!Q20 -> 0 | Q17: ='Loan Book'!R20 -> 11104919 | R17: ='Loan Book'!S20 -> 10000000 | ... T17: ='Loan Book'!U20 -> 11074782 | U17: ='Loan Book'!AC20 -> 0 | V17: ='Loan Book'!AE20 -> 0 | W17: =IFERROR(INDEX('E-Banker master'!$B$2:$B$186,MATCH($A17,'E-Banker master'!$A$2:$A$186,0)),"") -> Zaithwa Farms | X17: =IFERROR(INDEX('E-Banker master'!$C$2:$C$186,MATCH($A17,'E-Banker master'!$A$2:$A$186,0)),"") -> 90 | Y17: =IFERROR(INDEX('E-Banker master'!$D$2:$D$186,MATCH($A17,'E-Banker master'!$A$2:$A$186,0)),"") -> 1050201 | Z17: =IFERROR(INDEX('E-Banker master'!$E$2:$E$186,MATCH($A17,'E-Banker master'!$A$2:$A$186,0)),"") -> D | AA17: =IFERROR(INDEX('E-Banker master'!$F$2:$F$186,MATCH($A17,'E-Banker master'!$A$2:$A$186,0)),"") -> S | AB17: =IFERROR(INDEX('E-Banker master'!$G$2:$G$186,MATCH($A17,'E-Banker master'!$A$2:$A$186,0)),"") -> 10 | AC17: =IFERROR(INDEX('E-Banker master'!$I$2:$I$186,MATCH($A17,'E-Banker master'!$A$2:$A$186,0)),"") -> 10000000 | AD17: =IFERROR(INDEX('E-Banker master'!$J$2:$J$186,MATCH($A17,'E-Banker master'!$A$2:$A$186,0)),"") -> 44551 | AE17: =IFERROR(INDEX('E-Banker master'!$K$2:$K$186,MATCH($A17,'E-Banker master'!$A$2:$A$186,0)),"") -> 45280 | AF17: =IFERROR(INDEX('E-Banker master'!$L$2:$L$186,MATCH($A17,'E-Banker master'!$A$2:$A$186,0)),"") -> 0 | AG17: =IFERROR(INDEX('E-Banker master'!$M$2:$M$186,MATCH($A17,'E-Banker master'!$A$2:$A$186,0)),"") -> 0 | AH17: =IFERROR(INDEX('E-Banker master'!$N$2:$N$186,MATCH($A17,'E-Banker master'!$A$2:$A$186,0)),"") -> 10000000 | AI17: =IFERROR(INDEX('E-Banker master'!$O$2:$O$186,MATCH($A17,'E-Banker master'!$A$2:$A$186,0)),"") -> 1104919.3 | AJ17: =IFERROR(INDEX('E-Banker master'!$P$2:$P$186,MATCH($A17,'E-Banker master'!$A$2:$A$186,0)),"") -> 11387182 | AK17: =IF(OR(Q17="",AJ17=""),"",Q17-AJ17) -> -282262.83 | AL17: 15 | AM17: =HYPERLINK("#'Amortisation and Repayments'!C911","block 15") -> block 15 | AN17: =Mapping!X17 -> 0 | AO17: ='Loan Book'!AS20 -> 100000 | AP17: ='Loan Book'!AT20 -> 210000 | AR17: =AD17 -> 44551 | AS17: Y | AT17: Offer letter and Quickbooks | AU17: =IF(COUNT(AO17:AQ17)=0,"",SUM(AO17:AQ17)) -> 310000
A18: =Mapping!J18 -> 000104450000016 | B18: =Mapping!K18 -> High | C18: 21 | D18: ='Loan Book'!E21 -> Beualaland Food Processors | E18: ='Loan Book'!F21 -> Debt | F18: ='Loan Book'!G21 -> 44208 | G18: ='Loan Book'!H21 -> 45657 | H18: ='Loan Book'!I21 -> 3 | I18: ='Loan Book'!J21 -> 3 (Cap+Int) | J18: =IF('Loan Book'!K21="","",IF('Loan Book'!K21<1,'Loan Book'!K21*100,'Loan Book'!K21)) -> 10 | K18: ='Loan Book'!L21 -> 23616000 | L18: ='Loan Book'!M21 -> 23616000 | M18: ='Loan Book'!N21 -> 0 | N18: ='Loan Book'!O21 -> 23616000 | O18: ='Loan Book'!P21 -> 3183922 | P18: ='Loan Book'!Q21 -> -26799922 | Q18: ='Loan Book'!R21 -> 0.0048211105 | R18: ='Loan Book'!S21 -> 0 | ... T18: ='Loan Book'!U21 -> 0 | U18: ='Loan Book'!AC21 -> 0 | V18: ='Loan Book'!AE21 -> 0 | W18: =IFERROR(INDEX('E-Banker master'!$B$2:$B$186,MATCH($A18,'E-Banker master'!$A$2:$A$186,0)),"") -> Beaulaland Food Processors | X18: =IFERROR(INDEX('E-Banker master'!$C$2:$C$186,MATCH($A18,'E-Banker master'!$A$2:$A$186,0)),"") -> 90 | Y18: =IFERROR(INDEX('E-Banker master'!$D$2:$D$186,MATCH($A18,'E-Banker master'!$A$2:$A$186,0)),"") -> 1050201 | Z18: =IFERROR(INDEX('E-Banker master'!$E$2:$E$186,MATCH($A18,'E-Banker master'!$A$2:$A$186,0)),"") -> C | AA18: =IFERROR(INDEX('E-Banker master'!$F$2:$F$186,MATCH($A18,'E-Banker master'!$A$2:$A$186,0)),"") -> S | AB18: =IFERROR(INDEX('E-Banker master'!$G$2:$G$186,MATCH($A18,'E-Banker master'!$A$2:$A$186,0)),"") -> 10 | AC18: =IFERROR(INDEX('E-Banker master'!$I$2:$I$186,MATCH($A18,'E-Banker master'!$A$2:$A$186,0)),"") -> 23616000 | AD18: =IFERROR(INDEX('E-Banker master'!$J$2:$J$186,MATCH($A18,'E-Banker master'!$A$2:$A$186,0)),"") -> 44208 | AE18: =IFERROR(INDEX('E-Banker master'!$K$2:$K$186,MATCH($A18,'E-Banker master'!$A$2:$A$186,0)),"") -> 45302 | AF18: =IFERROR(INDEX('E-Banker master'!$L$2:$L$186,MATCH($A18,'E-Banker master'!$A$2:$A$186,0)),"") -> 3 | AG18: =IFERROR(INDEX('E-Banker master'!$M$2:$M$186,MATCH($A18,'E-Banker master'!$A$2:$A$186,0)),"") -> 3 | AH18: =IFERROR(INDEX('E-Banker master'!$N$2:$N$186,MATCH($A18,'E-Banker master'!$A$2:$A$186,0)),"") -> 0 | AI18: =IFERROR(INDEX('E-Banker master'!$O$2:$O$186,MATCH($A18,'E-Banker master'!$A$2:$A$186,0)),"") -> 0 | AJ18: =IFERROR(INDEX('E-Banker master'!$P$2:$P$186,MATCH($A18,'E-Banker master'!$A$2:$A$186,0)),"") -> 0 | AK18: =IF(OR(Q18="",AJ18=""),"",Q18-AJ18) -> 0.0048211105 | AL18: 16 | AM18: =HYPERLINK("#'Amortisation and Repayments'!C951","block 16") -> block 16 | AN18: =Mapping!X18 -> 0 | AO18: ='Loan Book'!AS21 -> 236160 | AP18: ='Loan Book'!AT21 -> 427856 | AR18: =AD18 -> 44208 | AS18: Y | AT18: Offer letter and Quickbooks | AU18: =IF(COUNT(AO18:AQ18)=0,"",SUM(AO18:AQ18)) -> 664016
A19: =Mapping!J19 -> 000104460000017 | B19: =Mapping!K19 -> High | C19: 22 | D19: ='Loan Book'!E22 -> Steel Base Furnitures | E19: ='Loan Book'!F22 -> Debt | F19: ='Loan Book'!G22 -> 44220 | G19: ='Loan Book'!H22 -> 45657 | H19: ='Loan Book'!I22 -> 2 | I19: ='Loan Book'!J22 -> 3 (Cap+Int) | J19: =IF('Loan Book'!K22="","",IF('Loan Book'!K22<1,'Loan Book'!K22*100,'Loan Book'!K22)) -> 10 | K19: ='Loan Book'!L22 -> 14677500 | L19: ='Loan Book'!M22 -> 14677500 | M19: ='Loan Book'!N22 -> 0 | N19: ='Loan Book'!O22 -> 14677500 | O19: ='Loan Book'!P22 -> 2537771.4 | P19: ='Loan Book'!Q22 -> -17215271 | Q19: ='Loan Book'!R22 -> 0 | R19: ='Loan Book'!S22 -> 0 | ... T19: ='Loan Book'!U22 -> 0 | U19: ='Loan Book'!AC22 -> 0 | V19: ='Loan Book'!AE22 -> 0 | W19: =IFERROR(INDEX('E-Banker master'!$B$2:$B$186,MATCH($A19,'E-Banker master'!$A$2:$A$186,0)),"") -> Steel Base Furnitures | X19: =IFERROR(INDEX('E-Banker master'!$C$2:$C$186,MATCH($A19,'E-Banker master'!$A$2:$A$186,0)),"") -> 92 | Y19: =IFERROR(INDEX('E-Banker master'!$D$2:$D$186,MATCH($A19,'E-Banker master'!$A$2:$A$186,0)),"") -> 1050202 | Z19: =IFERROR(INDEX('E-Banker master'!$E$2:$E$186,MATCH($A19,'E-Banker master'!$A$2:$A$186,0)),"") -> H | AA19: =IFERROR(INDEX('E-Banker master'!$F$2:$F$186,MATCH($A19,'E-Banker master'!$A$2:$A$186,0)),"") -> S | AB19: =IFERROR(INDEX('E-Banker master'!$G$2:$G$186,MATCH($A19,'E-Banker master'!$A$2:$A$186,0)),"") -> 10 | AC19: =IFERROR(INDEX('E-Banker master'!$I$2:$I$186,MATCH($A19,'E-Banker master'!$A$2:$A$186,0)),"") -> 14677500 | AD19: =IFERROR(INDEX('E-Banker master'!$J$2:$J$186,MATCH($A19,'E-Banker master'!$A$2:$A$186,0)),"") -> 44220 | AE19: =IFERROR(INDEX('E-Banker master'!$K$2:$K$186,MATCH($A19,'E-Banker master'!$A$2:$A$186,0)),"") -> 44949 | AF19: =IFERROR(INDEX('E-Banker master'!$L$2:$L$186,MATCH($A19,'E-Banker master'!$A$2:$A$186,0)),"") -> 3 | AG19: =IFERROR(INDEX('E-Banker master'!$M$2:$M$186,MATCH($A19,'E-Banker master'!$A$2:$A$186,0)),"") -> 3 | AH19: =IFERROR(INDEX('E-Banker master'!$N$2:$N$186,MATCH($A19,'E-Banker master'!$A$2:$A$186,0)),"") -> 14677500 | AI19: =IFERROR(INDEX('E-Banker master'!$O$2:$O$186,MATCH($A19,'E-Banker master'!$A$2:$A$186,0)),"") -> 2537771.4 | AJ19: =IFERROR(INDEX('E-Banker master'!$P$2:$P$186,MATCH($A19,'E-Banker master'!$A$2:$A$186,0)),"") -> 349021.15 | AK19: =IF(OR(Q19="",AJ19=""),"",Q19-AJ19) -> -349021.15 | AL19: 17 | AM19: =HYPERLINK("#'Amortisation and Repayments'!C1004","block 17") -> block 17 | AN19: =Mapping!X19 -> 0 | AO19: ='Loan Book'!AS22 -> 146775 | AP19: ='Loan Book'!AT22 -> 234840 | AR19: =AD19 -> 44220 | AS19: Y | AT19: Offer letter and Quickbooks | AU19: =IF(COUNT(AO19:AQ19)=0,"",SUM(AO19:AQ19)) -> 381615
A20: =Mapping!J20 -> 000104450000018 | B20: =Mapping!K20 -> High | C20: 23 | D20: ='Loan Book'!E23 -> Muddy Boots | E20: ='Loan Book'!F23 -> Debt | F20: ='Loan Book'!G23 -> 44595 | G20: ='Loan Book'!H23 -> 45322 | H20: ='Loan Book'!I23 -> 2 | I20: ='Loan Book'!J23 -> 0 | J20: =IF('Loan Book'!K23="","",IF('Loan Book'!K23<1,'Loan Book'!K23*100,'Loan Book'!K23)) -> 10 | K20: ='Loan Book'!L23 -> 13000000 | L20: ='Loan Book'!M23 -> 13000000 | M20: ='Loan Book'!N23 -> 0 | N20: ='Loan Book'!O23 -> 13000000 | O20: ='Loan Book'!P23 -> 1294527.2 | P20: ='Loan Book'!Q23 -> -14294527 | Q20: ='Loan Book'!R23 -> -0.0012255572 | R20: ='Loan Book'!S23 -> 0 | ... T20: ='Loan Book'!U23 -> 0 | U20: ='Loan Book'!AC23 -> 0 | V20: ='Loan Book'!AE23 -> 0 | W20: =IFERROR(INDEX('E-Banker master'!$B$2:$B$186,MATCH($A20,'E-Banker master'!$A$2:$A$186,0)),"") -> Muddy Boots | X20: =IFERROR(INDEX('E-Banker master'!$C$2:$C$186,MATCH($A20,'E-Banker master'!$A$2:$A$186,0)),"") -> 90 | Y20: =IFERROR(INDEX('E-Banker master'!$D$2:$D$186,MATCH($A20,'E-Banker master'!$A$2:$A$186,0)),"") -> 1050201 | Z20: =IFERROR(INDEX('E-Banker master'!$E$2:$E$186,MATCH($A20,'E-Banker master'!$A$2:$A$186,0)),"") -> C | AA20: =IFERROR(INDEX('E-Banker master'!$F$2:$F$186,MATCH($A20,'E-Banker master'!$A$2:$A$186,0)),"") -> S | AB20: =IFERROR(INDEX('E-Banker master'!$G$2:$G$186,MATCH($A20,'E-Banker master'!$A$2:$A$186,0)),"") -> 10 | AC20: =IFERROR(INDEX('E-Banker master'!$I$2:$I$186,MATCH($A20,'E-Banker master'!$A$2:$A$186,0)),"") -> 13000000 | AD20: =IFERROR(INDEX('E-Banker master'!$J$2:$J$186,MATCH($A20,'E-Banker master'!$A$2:$A$186,0)),"") -> 44230 | AE20: =IFERROR(INDEX('E-Banker master'!$K$2:$K$186,MATCH($A20,'E-Banker master'!$A$2:$A$186,0)),"") -> 44959 | AF20: =IFERROR(INDEX('E-Banker master'!$L$2:$L$186,MATCH($A20,'E-Banker master'!$A$2:$A$186,0)),"") -> 0 | AG20: =IFERROR(INDEX('E-Banker master'!$M$2:$M$186,MATCH($A20,'E-Banker master'!$A$2:$A$186,0)),"") -> 0 | AH20: =IFERROR(INDEX('E-Banker master'!$N$2:$N$186,MATCH($A20,'E-Banker master'!$A$2:$A$186,0)),"") -> 0 | AI20: =IFERROR(INDEX('E-Banker master'!$O$2:$O$186,MATCH($A20,'E-Banker master'!$A$2:$A$186,0)),"") -> 0 | AJ20: =IFERROR(INDEX('E-Banker master'!$P$2:$P$186,MATCH($A20,'E-Banker master'!$A$2:$A$186,0)),"") -> 0 | AK20: =IF(OR(Q20="",AJ20=""),"",Q20-AJ20) -> -0.0012255572 | AL20: 19 | AM20: =HYPERLINK("#'Amortisation and Repayments'!C1083","block 19") -> block 19 | AN20: =Mapping!X20 -> 0 | AO20: ='Loan Book'!AS23 -> 130000 | AP20: ='Loan Book'!AT23 -> 300570 | AR20: =AD20 -> 44230 | AS20: Y | AT20: Offer letter and Quickbooks | AU20: =IF(COUNT(AO20:AQ20)=0,"",SUM(AO20:AQ20)) -> 430570
A21: =Mapping!J21 -> 000104460000019 | B21: =Mapping!K21 -> High | C21: 24 | D21: ='Loan Book'!E24 -> Zanzi Entertainment Ltd | E21: ='Loan Book'!F24 -> Debt | F21: ='Loan Book'!G24 -> 44603 | G21: ='Loan Book'!H24 -> 45350 | H21: ='Loan Book'!I24 -> 2 | I21: ='Loan Book'!J24 -> 3 (Cap+Int) | J21: =IF('Loan Book'!K24="","",IF('Loan Book'!K24<1,'Loan Book'!K24*100,'Loan Book'!K24)) -> 10 | K21: ='Loan Book'!L24 -> 24000000 | L21: ='Loan Book'!M24 -> 24000000 | M21: ='Loan Book'!N24 -> 0 | N21: ='Loan Book'!O24 -> 24000000 | O21: ='Loan Book'!P24 -> 2249744.4 | P21: ='Loan Book'!Q24 -> -26249744 | Q21: ='Loan Book'!R24 -> 0.0048153996 | R21: ='Loan Book'!S24 -> 0 | ... T21: ='Loan Book'!U24 -> 0 | U21: ='Loan Book'!AC24 -> 0 | V21: ='Loan Book'!AE24 -> 0 | W21: =IFERROR(INDEX('E-Banker master'!$B$2:$B$186,MATCH($A21,'E-Banker master'!$A$2:$A$186,0)),"") -> Zanzi Entertainment Ltd | X21: =IFERROR(INDEX('E-Banker master'!$C$2:$C$186,MATCH($A21,'E-Banker master'!$A$2:$A$186,0)),"") -> 92 | Y21: =IFERROR(INDEX('E-Banker master'!$D$2:$D$186,MATCH($A21,'E-Banker master'!$A$2:$A$186,0)),"") -> 1050202 | Z21: =IFERROR(INDEX('E-Banker master'!$E$2:$E$186,MATCH($A21,'E-Banker master'!$A$2:$A$186,0)),"") -> C | AA21: =IFERROR(INDEX('E-Banker master'!$F$2:$F$186,MATCH($A21,'E-Banker master'!$A$2:$A$186,0)),"") -> S | AB21: =IFERROR(INDEX('E-Banker master'!$G$2:$G$186,MATCH($A21,'E-Banker master'!$A$2:$A$186,0)),"") -> 10 | AC21: =IFERROR(INDEX('E-Banker master'!$I$2:$I$186,MATCH($A21,'E-Banker master'!$A$2:$A$186,0)),"") -> 24000000 | AD21: =IFERROR(INDEX('E-Banker master'!$J$2:$J$186,MATCH($A21,'E-Banker master'!$A$2:$A$186,0)),"") -> 44603 | AE21: =IFERROR(INDEX('E-Banker master'!$K$2:$K$186,MATCH($A21,'E-Banker master'!$A$2:$A$186,0)),"") -> 45332 | AF21: =IFERROR(INDEX('E-Banker master'!$L$2:$L$186,MATCH($A21,'E-Banker master'!$A$2:$A$186,0)),"") -> 3 | AG21: =IFERROR(INDEX('E-Banker master'!$M$2:$M$186,MATCH($A21,'E-Banker master'!$A$2:$A$186,0)),"") -> 3 | AH21: =IFERROR(INDEX('E-Banker master'!$N$2:$N$186,MATCH($A21,'E-Banker master'!$A$2:$A$186,0)),"") -> 0 | AI21: =IFERROR(INDEX('E-Banker master'!$O$2:$O$186,MATCH($A21,'E-Banker master'!$A$2:$A$186,0)),"") -> 0 | AJ21: =IFERROR(INDEX('E-Banker master'!$P$2:$P$186,MATCH($A21,'E-Banker master'!$A$2:$A$186,0)),"") -> 0 | AK21: =IF(OR(Q21="",AJ21=""),"",Q21-AJ21) -> 0.0048153996 | AL21: 20 | AM21: =HYPERLINK("#'Amortisation and Repayments'!C1124","block 20") -> block 20 | AN21: =Mapping!X21 -> 0 | AO21: ='Loan Book'!AS24 -> 240000 | AP21: ='Loan Book'!AT24 -> 434000 | AR21: =AD21 -> 44603 | AS21: Y | AT21: Offer letter and Quickbooks | AU21: =IF(COUNT(AO21:AQ21)=0,"",SUM(AO21:AQ21)) -> 674000
A22: =Mapping!J22 -> 000104450000020 | B22: =Mapping!K22 -> High | C22: 25 | D22: ='Loan Book'!E25 -> Kayola Processors | E22: ='Loan Book'!F25 -> Debt | F22: ='Loan Book'!G25 -> 44609 | G22: ='Loan Book'!H25 -> 45350 | H22: ='Loan Book'!I25 -> 2 | I22: ='Loan Book'!J25 -> 3 (Cap+Int) | J22: =IF('Loan Book'!K25="","",IF('Loan Book'!K25<1,'Loan Book'!K25*100,'Loan Book'!K25)) -> 10 | K22: ='Loan Book'!L25 -> 20400000 | L22: ='Loan Book'!M25 -> 20400000 | M22: ='Loan Book'!N25 -> 0 | N22: ='Loan Book'!O25 -> 20400000 | O22: ='Loan Book'!P25 -> 3206277.3 | P22: ='Loan Book'!Q25 -> -16712707 | Q22: ='Loan Book'!R25 -> 6893570.4 | R22: ='Loan Book'!S25 -> 1158963.2 | ... T22: ='Loan Book'!U25 -> 2160329 | U22: ='Loan Book'!AC25 -> 0 | V22: ='Loan Book'!AE25 -> 0 | W22: =IFERROR(INDEX('E-Banker master'!$B$2:$B$186,MATCH($A22,'E-Banker master'!$A$2:$A$186,0)),"") -> Kayola Processors | X22: =IFERROR(INDEX('E-Banker master'!$C$2:$C$186,MATCH($A22,'E-Banker master'!$A$2:$A$186,0)),"") -> 90 | Y22: =IFERROR(INDEX('E-Banker master'!$D$2:$D$186,MATCH($A22,'E-Banker master'!$A$2:$A$186,0)),"") -> 1050201 | Z22: =IFERROR(INDEX('E-Banker master'!$E$2:$E$186,MATCH($A22,'E-Banker master'!$A$2:$A$186,0)),"") -> H | AA22: =IFERROR(INDEX('E-Banker master'!$F$2:$F$186,MATCH($A22,'E-Banker master'!$A$2:$A$186,0)),"") -> S | AB22: =IFERROR(INDEX('E-Banker master'!$G$2:$G$186,MATCH($A22,'E-Banker master'!$A$2:$A$186,0)),"") -> 10 | AC22: =IFERROR(INDEX('E-Banker master'!$I$2:$I$186,MATCH($A22,'E-Banker master'!$A$2:$A$186,0)),"") -> 12543063 | AD22: =IFERROR(INDEX('E-Banker master'!$J$2:$J$186,MATCH($A22,'E-Banker master'!$A$2:$A$186,0)),"") -> 45352 | AE22: =IFERROR(INDEX('E-Banker master'!$K$2:$K$186,MATCH($A22,'E-Banker master'!$A$2:$A$186,0)),"") -> 45716 | AF22: =IFERROR(INDEX('E-Banker master'!$L$2:$L$186,MATCH($A22,'E-Banker master'!$A$2:$A$186,0)),"") -> 3 | AG22: =IFERROR(INDEX('E-Banker master'!$M$2:$M$186,MATCH($A22,'E-Banker master'!$A$2:$A$186,0)),"") -> 3 | AH22: =IFERROR(INDEX('E-Banker master'!$N$2:$N$186,MATCH($A22,'E-Banker master'!$A$2:$A$186,0)),"") -> 12543065 | AI22: =IFERROR(INDEX('E-Banker master'!$O$2:$O$186,MATCH($A22,'E-Banker master'!$A$2:$A$186,0)),"") -> 470669.82 | AJ22: =IFERROR(INDEX('E-Banker master'!$P$2:$P$186,MATCH($A22,'E-Banker master'!$A$2:$A$186,0)),"") -> 6954076.2 | AK22: =IF(OR(Q22="",AJ22=""),"",Q22-AJ22) -> -60505.779 | AL22: 21 | AM22: =HYPERLINK("#'Amortisation and Repayments'!C1164","block 21") -> block 21 | AN22: =Mapping!X22 -> 0 | AO22: ='Loan Book'!AS25 -> 204000 | AP22: ='Loan Book'!AT25 -> 376000 | AR22: =AD22 -> 45352 | AS22: Y | AT22: Offer letter and Quickbooks | AU22: =IF(COUNT(AO22:AQ22)=0,"",SUM(AO22:AQ22)) -> 580000
A23: =Mapping!J23 -> 000104430000021 | B23: =Mapping!K23 -> High | C23: 26 | D23: ='Loan Book'!E26 -> Malawi Fertilizer Co | E23: ='Loan Book'!F26 -> Debt | F23: ='Loan Book'!G26 -> 44631 | G23: ='Loan Book'!H26 -> 46823 | H23: ='Loan Book'!I26 -> 6 | I23: ='Loan Book'!J26 -> 9(Cap+Int) | J23: =IF('Loan Book'!K26="","",IF('Loan Book'!K26<1,'Loan Book'!K26*100,'Loan Book'!K26)) -> 9.36 | K23: ='Loan Book'!L26 -> 8.8115395e+08 | L23: ='Loan Book'!M26 -> 5.5233818e+08 | M23: ='Loan Book'!N26 -> 0 | N23: ='Loan Book'!O26 -> 5.5233818e+08 | O23: ='Loan Book'!P26 -> 89551327 | P23: ='Loan Book'!Q26 -> -6.4188951e+08 | Q23: ='Loan Book'!R26 -> -0.0014064312 | R23: ='Loan Book'!S26 -> 0 | ... T23: ='Loan Book'!U26 -> 0 | U23: ='Loan Book'!AC26 -> 0 | V23: ='Loan Book'!AE26 -> 0 | W23: =IFERROR(INDEX('E-Banker master'!$B$2:$B$186,MATCH($A23,'E-Banker master'!$A$2:$A$186,0)),"") -> Malawi Fertilizer Company | X23: =IFERROR(INDEX('E-Banker master'!$C$2:$C$186,MATCH($A23,'E-Banker master'!$A$2:$A$186,0)),"") -> 86 | Y23: =IFERROR(INDEX('E-Banker master'!$D$2:$D$186,MATCH($A23,'E-Banker master'!$A$2:$A$186,0)),"") -> 1050102 | Z23: =IFERROR(INDEX('E-Banker master'!$E$2:$E$186,MATCH($A23,'E-Banker master'!$A$2:$A$186,0)),"") -> C | AA23: =IFERROR(INDEX('E-Banker master'!$F$2:$F$186,MATCH($A23,'E-Banker master'!$A$2:$A$186,0)),"") -> M | AB23: =IFERROR(INDEX('E-Banker master'!$G$2:$G$186,MATCH($A23,'E-Banker master'!$A$2:$A$186,0)),"") -> 9.46 | AC23: =IFERROR(INDEX('E-Banker master'!$I$2:$I$186,MATCH($A23,'E-Banker master'!$A$2:$A$186,0)),"") -> 8.8115395e+08 | AD23: =IFERROR(INDEX('E-Banker master'!$J$2:$J$186,MATCH($A23,'E-Banker master'!$A$2:$A$186,0)),"") -> 44631 | AE23: =IFERROR(INDEX('E-Banker master'!$K$2:$K$186,MATCH($A23,'E-Banker master'!$A$2:$A$186,0)),"") -> 46822 | AF23: =IFERROR(INDEX('E-Banker master'!$L$2:$L$186,MATCH($A23,'E-Banker master'!$A$2:$A$186,0)),"") -> 9 | AG23: =IFERROR(INDEX('E-Banker master'!$M$2:$M$186,MATCH($A23,'E-Banker master'!$A$2:$A$186,0)),"") -> 9 | AH23: =IFERROR(INDEX('E-Banker master'!$N$2:$N$186,MATCH($A23,'E-Banker master'!$A$2:$A$186,0)),"") -> 0 | AI23: =IFERROR(INDEX('E-Banker master'!$O$2:$O$186,MATCH($A23,'E-Banker master'!$A$2:$A$186,0)),"") -> 0 | AJ23: =IFERROR(INDEX('E-Banker master'!$P$2:$P$186,MATCH($A23,'E-Banker master'!$A$2:$A$186,0)),"") -> 0 | AK23: =IF(OR(Q23="",AJ23=""),"",Q23-AJ23) -> -0.0014064312 | AN23: =Mapping!X23 -> 0 | AO23: ='Loan Book'!AS26 -> 5171331.5 | AP23: ='Loan Book'!AT26 -> 11163704 | AR23: =AD23 -> 44631 | AS23: Y | AT23: Offer letter and Quickbooks | AU23: =IF(COUNT(AO23:AQ23)=0,"",SUM(AO23:AQ23)) -> 16335035
A24: =Mapping!J24 -> 000104450000022 | B24: =Mapping!K24 -> High | C24: 27 | D24: ='Loan Book'!E27 -> Mwachisosa Women Producers & Marketing Co | E24: ='Loan Book'!F27 -> Debt | F24: ='Loan Book'!G27 -> 44644 | G24: ='Loan Book'!H27 -> 45382 | H24: ='Loan Book'!I27 -> 2 | I24: ='Loan Book'!J27 -> 3 (Cap+Int) | J24: =IF('Loan Book'!K27="","",IF('Loan Book'!K27<1,'Loan Book'!K27*100,'Loan Book'!K27)) -> 10 | K24: ='Loan Book'!L27 -> 12500000 | L24: ='Loan Book'!M27 -> 12500000 | M24: ='Loan Book'!N27 -> 0 | N24: ='Loan Book'!O27 -> 12500000 | O24: ='Loan Book'!P27 -> 2385285.8 | P24: ='Loan Book'!Q27 -> -4880000 | Q24: ='Loan Book'!R27 -> 10005286 | R24: ='Loan Book'!S27 -> 4699943.1 | ... T24: ='Loan Book'!U27 -> 5345395 | U24: ='Loan Book'!AC27 -> 0 | V24: ='Loan Book'!AE27 -> 0 | W24: =IFERROR(INDEX('E-Banker master'!$B$2:$B$186,MATCH($A24,'E-Banker master'!$A$2:$A$186,0)),"") -> Mwachisosa Women Producers & Marketing Co | X24: =IFERROR(INDEX('E-Banker master'!$C$2:$C$186,MATCH($A24,'E-Banker master'!$A$2:$A$186,0)),"") -> 90 | Y24: =IFERROR(INDEX('E-Banker master'!$D$2:$D$186,MATCH($A24,'E-Banker master'!$A$2:$A$186,0)),"") -> 1050201 | Z24: =IFERROR(INDEX('E-Banker master'!$E$2:$E$186,MATCH($A24,'E-Banker master'!$A$2:$A$186,0)),"") -> H | AA24: =IFERROR(INDEX('E-Banker master'!$F$2:$F$186,MATCH($A24,'E-Banker master'!$A$2:$A$186,0)),"") -> S | AB24: =IFERROR(INDEX('E-Banker master'!$G$2:$G$186,MATCH($A24,'E-Banker master'!$A$2:$A$186,0)),"") -> 10 | AC24: =IFERROR(INDEX('E-Banker master'!$I$2:$I$186,MATCH($A24,'E-Banker master'!$A$2:$A$186,0)),"") -> 13270994 | AD24: =IFERROR(INDEX('E-Banker master'!$J$2:$J$186,MATCH($A24,'E-Banker master'!$A$2:$A$186,0)),"") -> 45230 | AE24: =IFERROR(INDEX('E-Banker master'!$K$2:$K$186,MATCH($A24,'E-Banker master'!$A$2:$A$186,0)),"") -> 45717 | AF24: =IFERROR(INDEX('E-Banker master'!$L$2:$L$186,MATCH($A24,'E-Banker master'!$A$2:$A$186,0)),"") -> 3 | AG24: =IFERROR(INDEX('E-Banker master'!$M$2:$M$186,MATCH($A24,'E-Banker master'!$A$2:$A$186,0)),"") -> 3 | AH24: =IFERROR(INDEX('E-Banker master'!$N$2:$N$186,MATCH($A24,'E-Banker master'!$A$2:$A$186,0)),"") -> 12500000 | AI24: =IFERROR(INDEX('E-Banker master'!$O$2:$O$186,MATCH($A24,'E-Banker master'!$A$2:$A$186,0)),"") -> 2243037.4 | AJ24: =IFERROR(INDEX('E-Banker master'!$P$2:$P$186,MATCH($A24,'E-Banker master'!$A$2:$A$186,0)),"") -> 10117946 | AK24: =IF(OR(Q24="",AJ24=""),"",Q24-AJ24) -> -112659.95 | AL24: 22 | AM24: =HYPERLINK("#'Amortisation and Repayments'!C1237","block 22") -> block 22 | AN24: =Mapping!X24 -> 0 | AO24: ='Loan Book'!AS27 -> 125000 | AP24: ='Loan Book'!AT27 -> 250000 | AR24: =AD24 -> 45230 | AS24: Y | AT24: Offer letter and Quickbooks | AU24: =IF(COUNT(AO24:AQ24)=0,"",SUM(AO24:AQ24)) -> 375000
A25: =Mapping!J25 -> 000104450000023 | B25: =Mapping!K25 -> High | C25: 28 | D25: ='Loan Book'!E28 -> Natures Gift | E25: ='Loan Book'!F28 -> Debt | F25: ='Loan Book'!G28 -> 44673 | G25: ='Loan Book'!H28 -> 45747 | H25: ='Loan Book'!I28 -> 3 | I25: ='Loan Book'!J28 -> 0 | J25: =IF('Loan Book'!K28="","",IF('Loan Book'!K28<1,'Loan Book'!K28*100,'Loan Book'!K28)) -> 10 | K25: ='Loan Book'!L28 -> 24600000 | L25: ='Loan Book'!M28 -> 24600000 | M25: ='Loan Book'!N28 -> 0 | N25: ='Loan Book'!O28 -> 24600000 | O25: ='Loan Book'!P28 -> 3900598.2 | P25: ='Loan Book'!Q28 -> -19111205 | Q25: ='Loan Book'!R28 -> 9389393.6 | R25: ='Loan Book'!S28 -> 0 | ... T25: ='Loan Book'!U28 -> 0 | U25: ='Loan Book'!AC28 -> 0 | V25: ='Loan Book'!AE28 -> 0 | W25: =IFERROR(INDEX('E-Banker master'!$B$2:$B$186,MATCH($A25,'E-Banker master'!$A$2:$A$186,0)),"") -> Nature's Gift Limited | X25: =IFERROR(INDEX('E-Banker master'!$C$2:$C$186,MATCH($A25,'E-Banker master'!$A$2:$A$186,0)),"") -> 90 | Y25: =IFERROR(INDEX('E-Banker master'!$D$2:$D$186,MATCH($A25,'E-Banker master'!$A$2:$A$186,0)),"") -> 1050201 | Z25: =IFERROR(INDEX('E-Banker master'!$E$2:$E$186,MATCH($A25,'E-Banker master'!$A$2:$A$186,0)),"") -> H | AA25: =IFERROR(INDEX('E-Banker master'!$F$2:$F$186,MATCH($A25,'E-Banker master'!$A$2:$A$186,0)),"") -> S | AB25: =IFERROR(INDEX('E-Banker master'!$G$2:$G$186,MATCH($A25,'E-Banker master'!$A$2:$A$186,0)),"") -> 10 | AC25: =IFERROR(INDEX('E-Banker master'!$I$2:$I$186,MATCH($A25,'E-Banker master'!$A$2:$A$186,0)),"") -> 24600000 | AD25: =IFERROR(INDEX('E-Banker master'!$J$2:$J$186,MATCH($A25,'E-Banker master'!$A$2:$A$186,0)),"") -> 44673 | AE25: =IFERROR(INDEX('E-Banker master'!$K$2:$K$186,MATCH($A25,'E-Banker master'!$A$2:$A$186,0)),"") -> 45768 | AF25: =IFERROR(INDEX('E-Banker master'!$L$2:$L$186,MATCH($A25,'E-Banker master'!$A$2:$A$186,0)),"") -> 0 | AG25: =IFERROR(INDEX('E-Banker master'!$M$2:$M$186,MATCH($A25,'E-Banker master'!$A$2:$A$186,0)),"") -> 0 | AH25: =IFERROR(INDEX('E-Banker master'!$N$2:$N$186,MATCH($A25,'E-Banker master'!$A$2:$A$186,0)),"") -> 24600000 | AI25: =IFERROR(INDEX('E-Banker master'!$O$2:$O$186,MATCH($A25,'E-Banker master'!$A$2:$A$186,0)),"") -> 3747686.5 | AJ25: =IFERROR(INDEX('E-Banker master'!$P$2:$P$186,MATCH($A25,'E-Banker master'!$A$2:$A$186,0)),"") -> 9471253 | AK25: =IF(OR(Q25="",AJ25=""),"",Q25-AJ25) -> -81859.463 | AN25: =Mapping!X25 -> 0 | AO25: ='Loan Book'!AS28 -> 369000 | AP25: ='Loan Book'!AT28 -> 443600 | AR25: =AD25 -> 44673 | AS25: Y | AT25: Offer letter and Quickbooks | AU25: =IF(COUNT(AO25:AQ25)=0,"",SUM(AO25:AQ25)) -> 812600
A26: =Mapping!J26 -> 000104460000024 | B26: =Mapping!K26 -> High | C26: 29 | D26: ='Loan Book'!E29 -> Allied Bricks and Blocks Limited | E26: ='Loan Book'!F29 -> Debt | F26: ='Loan Book'!G29 -> 44715 | G26: ='Loan Book'!H29 -> 45808 | H26: ='Loan Book'!I29 -> 2 | I26: ='Loan Book'!J29 -> 3 (Cap+Int) | J26: =IF('Loan Book'!K29="","",IF('Loan Book'!K29<1,'Loan Book'!K29*100,'Loan Book'!K29)) -> 10 | K26: ='Loan Book'!L29 -> 12000000 | L26: ='Loan Book'!M29 -> 12000000 | M26: ='Loan Book'!N29 -> 0 | N26: ='Loan Book'!O29 -> 12000000 | O26: ='Loan Book'!P29 -> 1688417.5 | P26: ='Loan Book'!Q29 -> -13688417 | Q26: ='Loan Book'!R29 -> -0.0033015981 | R26: ='Loan Book'!S29 -> 0 | ... T26: ='Loan Book'!U29 -> 0 | U26: ='Loan Book'!AC29 -> 0 | V26: ='Loan Book'!AE29 -> 0 | W26: =IFERROR(INDEX('E-Banker master'!$B$2:$B$186,MATCH($A26,'E-Banker master'!$A$2:$A$186,0)),"") -> Allied Bricks and Blocks Limited | X26: =IFERROR(INDEX('E-Banker master'!$C$2:$C$186,MATCH($A26,'E-Banker master'!$A$2:$A$186,0)),"") -> 92 | Y26: =IFERROR(INDEX('E-Banker master'!$D$2:$D$186,MATCH($A26,'E-Banker master'!$A$2:$A$186,0)),"") -> 1050202 | Z26: =IFERROR(INDEX('E-Banker master'!$E$2:$E$186,MATCH($A26,'E-Banker master'!$A$2:$A$186,0)),"") -> D | AA26: =IFERROR(INDEX('E-Banker master'!$F$2:$F$186,MATCH($A26,'E-Banker master'!$A$2:$A$186,0)),"") -> S | AB26: =IFERROR(INDEX('E-Banker master'!$G$2:$G$186,MATCH($A26,'E-Banker master'!$A$2:$A$186,0)),"") -> 10 | AC26: =IFERROR(INDEX('E-Banker master'!$I$2:$I$186,MATCH($A26,'E-Banker master'!$A$2:$A$186,0)),"") -> 12000000 | AD26: =IFERROR(INDEX('E-Banker master'!$J$2:$J$186,MATCH($A26,'E-Banker master'!$A$2:$A$186,0)),"") -> 44715 | AE26: =IFERROR(INDEX('E-Banker master'!$K$2:$K$186,MATCH($A26,'E-Banker master'!$A$2:$A$186,0)),"") -> 45445 | AF26: =IFERROR(INDEX('E-Banker master'!$L$2:$L$186,MATCH($A26,'E-Banker master'!$A$2:$A$186,0)),"") -> 3 | AG26: =IFERROR(INDEX('E-Banker master'!$M$2:$M$186,MATCH($A26,'E-Banker master'!$A$2:$A$186,0)),"") -> 3 | AH26: =IFERROR(INDEX('E-Banker master'!$N$2:$N$186,MATCH($A26,'E-Banker master'!$A$2:$A$186,0)),"") -> 12000000 | AI26: =IFERROR(INDEX('E-Banker master'!$O$2:$O$186,MATCH($A26,'E-Banker master'!$A$2:$A$186,0)),"") -> 1605046.9 | AJ26: =IFERROR(INDEX('E-Banker master'!$P$2:$P$186,MATCH($A26,'E-Banker master'!$A$2:$A$186,0)),"") -> -29678.33 | AK26: =IF(OR(Q26="",AJ26=""),"",Q26-AJ26) -> 29678.327 | AL26: 23 | AM26: =HYPERLINK("#'Amortisation and Repayments'!C1438","block 23") -> block 23 | AN26: =Mapping!X26 -> 0 | AO26: ='Loan Book'!AS29 -> 120000 | AP26: ='Loan Book'!AT29 -> 242000 | AR26: =AD26 -> 44715 | AS26: Y | AT26: Offer letter and Quickbooks | AU26: =IF(COUNT(AO26:AQ26)=0,"",SUM(AO26:AQ26)) -> 362000
A27: =Mapping!J27 -> 000104450000025 | B27: =Mapping!K27 -> High | C27: 30 | D27: ='Loan Book'!E30 -> Lapani Farms | E27: ='Loan Book'!F30 -> Debt | F27: ='Loan Book'!G30 -> 44715 | G27: ='Loan Book'!H30 -> 45443 | H27: ='Loan Book'!I30 -> 2 | I27: ='Loan Book'!J30 -> 3 (Cap+Int) | J27: =IF('Loan Book'!K30="","",IF('Loan Book'!K30<1,'Loan Book'!K30*100,'Loan Book'!K30)) -> 10 | K27: ='Loan Book'!L30 -> 10900000 | L27: ='Loan Book'!M30 -> 10900000 | M27: ='Loan Book'!N30 -> 0 | N27: ='Loan Book'!O30 -> 10900000 | O27: ='Loan Book'!P30 -> 1320716.8 | P27: ='Loan Book'!Q30 -> -12216000 | Q27: ='Loan Book'!R30 -> 0 | R27: ='Loan Book'!S30 -> 0 | ... T27: ='Loan Book'!U30 -> 0 | U27: ='Loan Book'!AC30 -> 0 | V27: ='Loan Book'!AE30 -> 0 | W27: =IFERROR(INDEX('E-Banker master'!$B$2:$B$186,MATCH($A27,'E-Banker master'!$A$2:$A$186,0)),"") -> Lapani Farms | X27: =IFERROR(INDEX('E-Banker master'!$C$2:$C$186,MATCH($A27,'E-Banker master'!$A$2:$A$186,0)),"") -> 90 | Y27: =IFERROR(INDEX('E-Banker master'!$D$2:$D$186,MATCH($A27,'E-Banker master'!$A$2:$A$186,0)),"") -> 1050201 | Z27: =IFERROR(INDEX('E-Banker master'!$E$2:$E$186,MATCH($A27,'E-Banker master'!$A$2:$A$186,0)),"") -> C | AA27: =IFERROR(INDEX('E-Banker master'!$F$2:$F$186,MATCH($A27,'E-Banker master'!$A$2:$A$186,0)),"") -> S | AB27: =IFERROR(INDEX('E-Banker master'!$G$2:$G$186,MATCH($A27,'E-Banker master'!$A$2:$A$186,0)),"") -> 10 | AC27: =IFERROR(INDEX('E-Banker master'!$I$2:$I$186,MATCH($A27,'E-Banker master'!$A$2:$A$186,0)),"") -> 10900000 | AD27: =IFERROR(INDEX('E-Banker master'!$J$2:$J$186,MATCH($A27,'E-Banker master'!$A$2:$A$186,0)),"") -> 44715 | AE27: =IFERROR(INDEX('E-Banker master'!$K$2:$K$186,MATCH($A27,'E-Banker master'!$A$2:$A$186,0)),"") -> 45445 | AF27: =IFERROR(INDEX('E-Banker master'!$L$2:$L$186,MATCH($A27,'E-Banker master'!$A$2:$A$186,0)),"") -> 3 | AG27: =IFERROR(INDEX('E-Banker master'!$M$2:$M$186,MATCH($A27,'E-Banker master'!$A$2:$A$186,0)),"") -> 3 | AH27: =IFERROR(INDEX('E-Banker master'!$N$2:$N$186,MATCH($A27,'E-Banker master'!$A$2:$A$186,0)),"") -> 0 | AI27: =IFERROR(INDEX('E-Banker master'!$O$2:$O$186,MATCH($A27,'E-Banker master'!$A$2:$A$186,0)),"") -> 0 | AJ27: =IFERROR(INDEX('E-Banker master'!$P$2:$P$186,MATCH($A27,'E-Banker master'!$A$2:$A$186,0)),"") -> 0 | AK27: =IF(OR(Q27="",AJ27=""),"",Q27-AJ27) -> 0 | AL27: 24 | AM27: =HYPERLINK("#'Amortisation and Repayments'!C1504","block 24") -> block 24 | AN27: =Mapping!X27 -> 0 | AO27: ='Loan Book'!AS30 -> 109000 | AP27: ='Loan Book'!AT30 -> 224400 | AR27: =AD27 -> 44715 | AS27: Y | AT27: Offer letter and Quickbooks | AU27: =IF(COUNT(AO27:AQ27)=0,"",SUM(AO27:AQ27)) -> 333400
A28: =Mapping!J28 -> 000104450000026 | B28: =Mapping!K28 -> High | C28: 31 | D28: ='Loan Book'!E31 -> Mawindo Enterprise | E28: ='Loan Book'!F31 -> Debt | F28: ='Loan Book'!G31 -> 44715 | G28: ='Loan Book'!H31 -> 45443 | H28: ='Loan Book'!I31 -> 2 | I28: ='Loan Book'!J31 -> 3 (Cap+Int) | J28: =IF('Loan Book'!K31="","",IF('Loan Book'!K31<1,'Loan Book'!K31*100,'Loan Book'!K31)) -> 10 | K28: ='Loan Book'!L31 -> 20000000 | L28: ='Loan Book'!M31 -> 20000000 | M28: ='Loan Book'!N31 -> 0 | N28: ='Loan Book'!O31 -> 20000000 | O28: ='Loan Book'!P31 -> 2396932.8 | P28: ='Loan Book'!Q31 -> -22423353 | Q28: ='Loan Book'!R31 -> 0 | R28: ='Loan Book'!S31 -> 0 | ... T28: ='Loan Book'!U31 -> 0 | U28: ='Loan Book'!AC31 -> 0 | V28: ='Loan Book'!AE31 -> 0 | W28: =IFERROR(INDEX('E-Banker master'!$B$2:$B$186,MATCH($A28,'E-Banker master'!$A$2:$A$186,0)),"") -> Mawindo Enterprise | X28: =IFERROR(INDEX('E-Banker master'!$C$2:$C$186,MATCH($A28,'E-Banker master'!$A$2:$A$186,0)),"") -> 90 | Y28: =IFERROR(INDEX('E-Banker master'!$D$2:$D$186,MATCH($A28,'E-Banker master'!$A$2:$A$186,0)),"") -> 1050201 | Z28: =IFERROR(INDEX('E-Banker master'!$E$2:$E$186,MATCH($A28,'E-Banker master'!$A$2:$A$186,0)),"") -> C | AA28: =IFERROR(INDEX('E-Banker master'!$F$2:$F$186,MATCH($A28,'E-Banker master'!$A$2:$A$186,0)),"") -> S | AB28: =IFERROR(INDEX('E-Banker master'!$G$2:$G$186,MATCH($A28,'E-Banker master'!$A$2:$A$186,0)),"") -> 10 | AC28: =IFERROR(INDEX('E-Banker master'!$I$2:$I$186,MATCH($A28,'E-Banker master'!$A$2:$A$186,0)),"") -> 20000000 | AD28: =IFERROR(INDEX('E-Banker master'!$J$2:$J$186,MATCH($A28,'E-Banker master'!$A$2:$A$186,0)),"") -> 44715 | AE28: =IFERROR(INDEX('E-Banker master'!$K$2:$K$186,MATCH($A28,'E-Banker master'!$A$2:$A$186,0)),"") -> 45445 | AF28: =IFERROR(INDEX('E-Banker master'!$L$2:$L$186,MATCH($A28,'E-Banker master'!$A$2:$A$186,0)),"") -> 3 | AG28: =IFERROR(INDEX('E-Banker master'!$M$2:$M$186,MATCH($A28,'E-Banker master'!$A$2:$A$186,0)),"") -> 3 | AH28: =IFERROR(INDEX('E-Banker master'!$N$2:$N$186,MATCH($A28,'E-Banker master'!$A$2:$A$186,0)),"") -> 0 | AI28: =IFERROR(INDEX('E-Banker master'!$O$2:$O$186,MATCH($A28,'E-Banker master'!$A$2:$A$186,0)),"") -> 0 | AJ28: =IFERROR(INDEX('E-Banker master'!$P$2:$P$186,MATCH($A28,'E-Banker master'!$A$2:$A$186,0)),"") -> 0 | AK28: =IF(OR(Q28="",AJ28=""),"",Q28-AJ28) -> 0 | AL28: 25 | AM28: =HYPERLINK("#'Amortisation and Repayments'!C1544","block 25") -> block 25 | AN28: =Mapping!X28 -> 0 | AO28: ='Loan Book'!AS31 -> 200000 | AP28: ='Loan Book'!AT31 -> 370000 | AR28: =AD28 -> 44715 | AS28: Y | AT28: Offer letter and Quickbooks | AU28: =IF(COUNT(AO28:AQ28)=0,"",SUM(AO28:AQ28)) -> 570000
A29: =Mapping!J29 -> 000104450000027 | B29: =Mapping!K29 -> High | C29: 32 | D29: ='Loan Book'!E32 -> L J Traders & Suppliers | E29: ='Loan Book'!F32 -> Debt | F29: ='Loan Book'!G32 -> 44715 | G29: ='Loan Book'!H32 -> 45443 | H29: ='Loan Book'!I32 -> 2 | I29: ='Loan Book'!J32 -> 3 (Cap+Int) | J29: =IF('Loan Book'!K32="","",IF('Loan Book'!K32<1,'Loan Book'!K32*100,'Loan Book'!K32)) -> 10 | K29: ='Loan Book'!L32 -> 10000000 | L29: ='Loan Book'!M32 -> 10000000 | M29: ='Loan Book'!N32 -> 0 | N29: ='Loan Book'!O32 -> 10000000 | O29: ='Loan Book'!P32 -> 1211666.8 | P29: ='Loan Book'!Q32 -> -11232000 | Q29: ='Loan Book'!R32 -> 0 | R29: ='Loan Book'!S32 -> 0 | ... T29: ='Loan Book'!U32 -> 0 | U29: ='Loan Book'!AC32 -> 0 | V29: ='Loan Book'!AE32 -> 0 | W29: =IFERROR(INDEX('E-Banker master'!$B$2:$B$186,MATCH($A29,'E-Banker master'!$A$2:$A$186,0)),"") -> L. J Traders & Suppliers | X29: =IFERROR(INDEX('E-Banker master'!$C$2:$C$186,MATCH($A29,'E-Banker master'!$A$2:$A$186,0)),"") -> 90 | Y29: =IFERROR(INDEX('E-Banker master'!$D$2:$D$186,MATCH($A29,'E-Banker master'!$A$2:$A$186,0)),"") -> 1050201 | Z29: =IFERROR(INDEX('E-Banker master'!$E$2:$E$186,MATCH($A29,'E-Banker master'!$A$2:$A$186,0)),"") -> C | AA29: =IFERROR(INDEX('E-Banker master'!$F$2:$F$186,MATCH($A29,'E-Banker master'!$A$2:$A$186,0)),"") -> S | AB29: =IFERROR(INDEX('E-Banker master'!$G$2:$G$186,MATCH($A29,'E-Banker master'!$A$2:$A$186,0)),"") -> 10 | AC29: =IFERROR(INDEX('E-Banker master'!$I$2:$I$186,MATCH($A29,'E-Banker master'!$A$2:$A$186,0)),"") -> 10000000 | AD29: =IFERROR(INDEX('E-Banker master'!$J$2:$J$186,MATCH($A29,'E-Banker master'!$A$2:$A$186,0)),"") -> 44715 | AE29: =IFERROR(INDEX('E-Banker master'!$K$2:$K$186,MATCH($A29,'E-Banker master'!$A$2:$A$186,0)),"") -> 45445 | AF29: =IFERROR(INDEX('E-Banker master'!$L$2:$L$186,MATCH($A29,'E-Banker master'!$A$2:$A$186,0)),"") -> 3 | AG29: =IFERROR(INDEX('E-Banker master'!$M$2:$M$186,MATCH($A29,'E-Banker master'!$A$2:$A$186,0)),"") -> 3 | AH29: =IFERROR(INDEX('E-Banker master'!$N$2:$N$186,MATCH($A29,'E-Banker master'!$A$2:$A$186,0)),"") -> 0 | AI29: =IFERROR(INDEX('E-Banker master'!$O$2:$O$186,MATCH($A29,'E-Banker master'!$A$2:$A$186,0)),"") -> 0 | AJ29: =IFERROR(INDEX('E-Banker master'!$P$2:$P$186,MATCH($A29,'E-Banker master'!$A$2:$A$186,0)),"") -> 0 | AK29: =IF(OR(Q29="",AJ29=""),"",Q29-AJ29) -> 0 | AL29: 26 | AM29: =HYPERLINK("#'Amortisation and Repayments'!C1584","block 26") -> block 26 | AN29: =Mapping!X29 -> 0 | AO29: ='Loan Book'!AS32 -> 100000 | AP29: ='Loan Book'!AT32 -> 212100 | AR29: =AD29 -> 44715 | AS29: Y | AT29: Offer letter and Quickbooks | AU29: =IF(COUNT(AO29:AQ29)=0,"",SUM(AO29:AQ29)) -> 312100
A30: =Mapping!J30 -> 000104450000028 | B30: =Mapping!K30 -> High | C30: 33 | D30: ='Loan Book'!E33 -> Chikwendeni General Dealers | E30: ='Loan Book'!F33 -> Debt | F30: ='Loan Book'!G33 -> 44715 | G30: ='Loan Book'!H33 -> 45443 | H30: ='Loan Book'!I33 -> 2 | I30: ='Loan Book'!J33 -> 3 (Cap+Int) | J30: =IF('Loan Book'!K33="","",IF('Loan Book'!K33<1,'Loan Book'!K33*100,'Loan Book'!K33)) -> 10 | K30: ='Loan Book'!L33 -> 24000000 | L30: ='Loan Book'!M33 -> 24000000 | M30: ='Loan Book'!N33 -> 0 | N30: ='Loan Book'!O33 -> 24000000 | O30: ='Loan Book'!P33 -> 2750896.9 | P30: ='Loan Book'!Q33 -> -26750897 | Q30: ='Loan Book'!R33 -> 0.00011336058 | R30: ='Loan Book'!S33 -> 0 | ... T30: ='Loan Book'!U33 -> 0 | U30: ='Loan Book'!AC33 -> 0 | V30: ='Loan Book'!AE33 -> 0 | W30: =IFERROR(INDEX('E-Banker master'!$B$2:$B$186,MATCH($A30,'E-Banker master'!$A$2:$A$186,0)),"") -> Chikwendeni General Dealers | X30: =IFERROR(INDEX('E-Banker master'!$C$2:$C$186,MATCH($A30,'E-Banker master'!$A$2:$A$186,0)),"") -> 90 | Y30: =IFERROR(INDEX('E-Banker master'!$D$2:$D$186,MATCH($A30,'E-Banker master'!$A$2:$A$186,0)),"") -> 1050201 | Z30: =IFERROR(INDEX('E-Banker master'!$E$2:$E$186,MATCH($A30,'E-Banker master'!$A$2:$A$186,0)),"") -> C | AA30: =IFERROR(INDEX('E-Banker master'!$F$2:$F$186,MATCH($A30,'E-Banker master'!$A$2:$A$186,0)),"") -> S | AB30: =IFERROR(INDEX('E-Banker master'!$G$2:$G$186,MATCH($A30,'E-Banker master'!$A$2:$A$186,0)),"") -> 10 | AC30: =IFERROR(INDEX('E-Banker master'!$I$2:$I$186,MATCH($A30,'E-Banker master'!$A$2:$A$186,0)),"") -> 24000000 | AD30: =IFERROR(INDEX('E-Banker master'!$J$2:$J$186,MATCH($A30,'E-Banker master'!$A$2:$A$186,0)),"") -> 44715 | AE30: =IFERROR(INDEX('E-Banker master'!$K$2:$K$186,MATCH($A30,'E-Banker master'!$A$2:$A$186,0)),"") -> 45445 | AF30: =IFERROR(INDEX('E-Banker master'!$L$2:$L$186,MATCH($A30,'E-Banker master'!$A$2:$A$186,0)),"") -> 3 | AG30: =IFERROR(INDEX('E-Banker master'!$M$2:$M$186,MATCH($A30,'E-Banker master'!$A$2:$A$186,0)),"") -> 3 | AH30: =IFERROR(INDEX('E-Banker master'!$N$2:$N$186,MATCH($A30,'E-Banker master'!$A$2:$A$186,0)),"") -> 0 | AI30: =IFERROR(INDEX('E-Banker master'!$O$2:$O$186,MATCH($A30,'E-Banker master'!$A$2:$A$186,0)),"") -> 0 | AJ30: =IFERROR(INDEX('E-Banker master'!$P$2:$P$186,MATCH($A30,'E-Banker master'!$A$2:$A$186,0)),"") -> 0 | AK30: =IF(OR(Q30="",AJ30=""),"",Q30-AJ30) -> 0.00011336058 | AL30: 27 | AM30: =HYPERLINK("#'Amortisation and Repayments'!C1624","block 27") -> block 27 | AN30: =Mapping!X30 -> 0 | AO30: ='Loan Book'!AS33 -> 240000 | AP30: ='Loan Book'!AT33 -> 434000 | AR30: =AD30 -> 44715 | AS30: Y | AT30: Offer letter and Quickbooks | AU30: =IF(COUNT(AO30:AQ30)=0,"",SUM(AO30:AQ30)) -> 674000
A31: =Mapping!J31 -> 000104460000029 | B31: =Mapping!K31 -> High | C31: 34 | D31: ='Loan Book'!E34 -> Agwenda Investment Ltd | E31: ='Loan Book'!F34 -> Debt | F31: ='Loan Book'!G34 -> 44726 | G31: ='Loan Book'!H34 -> 45443 | H31: ='Loan Book'!I34 -> 2 | I31: ='Loan Book'!J34 -> 3 (Cap+Int) | J31: =IF('Loan Book'!K34="","",IF('Loan Book'!K34<1,'Loan Book'!K34*100,'Loan Book'!K34)) -> 10 | K31: ='Loan Book'!L34 -> 24000000 | L31: ='Loan Book'!M34 -> 24000000 | M31: ='Loan Book'!N34 -> 0 | N31: ='Loan Book'!O34 -> 24000000 | O31: ='Loan Book'!P34 -> 2944391.6 | P31: ='Loan Book'!Q34 -> -26946038 | Q31: ='Loan Book'!R34 -> 0 | R31: ='Loan Book'!S34 -> 0 | ... T31: ='Loan Book'!U34 -> 0 | U31: ='Loan Book'!AC34 -> 0 | V31: ='Loan Book'!AE34 -> 0 | W31: =IFERROR(INDEX('E-Banker master'!$B$2:$B$186,MATCH($A31,'E-Banker master'!$A$2:$A$186,0)),"") -> Angwenda Investments Limited | X31: =IFERROR(INDEX('E-Banker master'!$C$2:$C$186,MATCH($A31,'E-Banker master'!$A$2:$A$186,0)),"") -> 92 | Y31: =IFERROR(INDEX('E-Banker master'!$D$2:$D$186,MATCH($A31,'E-Banker master'!$A$2:$A$186,0)),"") -> 1050202 | Z31: =IFERROR(INDEX('E-Banker master'!$E$2:$E$186,MATCH($A31,'E-Banker master'!$A$2:$A$186,0)),"") -> C | AA31: =IFERROR(INDEX('E-Banker master'!$F$2:$F$186,MATCH($A31,'E-Banker master'!$A$2:$A$186,0)),"") -> S | AB31: =IFERROR(INDEX('E-Banker master'!$G$2:$G$186,MATCH($A31,'E-Banker master'!$A$2:$A$186,0)),"") -> 10 | AC31: =IFERROR(INDEX('E-Banker master'!$I$2:$I$186,MATCH($A31,'E-Banker master'!$A$2:$A$186,0)),"") -> 24000000 | AD31: =IFERROR(INDEX('E-Banker master'!$J$2:$J$186,MATCH($A31,'E-Banker master'!$A$2:$A$186,0)),"") -> 44726 | AE31: =IFERROR(INDEX('E-Banker master'!$K$2:$K$186,MATCH($A31,'E-Banker master'!$A$2:$A$186,0)),"") -> 45456 | AF31: =IFERROR(INDEX('E-Banker master'!$L$2:$L$186,MATCH($A31,'E-Banker master'!$A$2:$A$186,0)),"") -> 3 | AG31: =IFERROR(INDEX('E-Banker master'!$M$2:$M$186,MATCH($A31,'E-Banker master'!$A$2:$A$186,0)),"") -> 3 | AH31: =IFERROR(INDEX('E-Banker master'!$N$2:$N$186,MATCH($A31,'E-Banker master'!$A$2:$A$186,0)),"") -> 0 | AI31: =IFERROR(INDEX('E-Banker master'!$O$2:$O$186,MATCH($A31,'E-Banker master'!$A$2:$A$186,0)),"") -> 0 | AJ31: =IFERROR(INDEX('E-Banker master'!$P$2:$P$186,MATCH($A31,'E-Banker master'!$A$2:$A$186,0)),"") -> 0 | AK31: =IF(OR(Q31="",AJ31=""),"",Q31-AJ31) -> 0 | AL31: 28 | AM31: =HYPERLINK("#'Amortisation and Repayments'!C1664","block 28") -> block 28 | AN31: =Mapping!X31 -> 0 | AO31: ='Loan Book'!AS34 -> 240000 | AP31: ='Loan Book'!AT34 -> 434000 | AR31: =AD31 -> 44726 | AS31: Y | AT31: Offer letter and Quickbooks | AU31: =IF(COUNT(AO31:AQ31)=0,"",SUM(AO31:AQ31)) -> 674000
A32: =Mapping!J32 -> 000104450000030 | B32: =Mapping!K32 -> High | C32: 35 | D32: ='Loan Book'!E35 -> Perisha Agro and packaging Enterprise | E32: ='Loan Book'!F35 -> Debt | F32: ='Loan Book'!G35 -> 44728 | G32: ='Loan Book'!H35 -> 45565 | H32: ='Loan Book'!I35 -> 2 | I32: ='Loan Book'!J35 -> 3 (Cap+Int) | J32: =IF('Loan Book'!K35="","",IF('Loan Book'!K35<1,'Loan Book'!K35*100,'Loan Book'!K35)) -> 10 | K32: ='Loan Book'!L35 -> 12000000 | L32: ='Loan Book'!M35 -> 12000000 | M32: ='Loan Book'!N35 -> 0 | N32: ='Loan Book'!O35 -> 12000000 | O32: ='Loan Book'!P35 -> 1865934.9 | P32: ='Loan Book'!Q35 -> -13868000 | Q32: ='Loan Book'!R35 -> 0 | R32: ='Loan Book'!S35 -> 0 | ... T32: ='Loan Book'!U35 -> 0 | U32: ='Loan Book'!AC35 -> 0 | V32: ='Loan Book'!AE35 -> 0 | W32: =IFERROR(INDEX('E-Banker master'!$B$2:$B$186,MATCH($A32,'E-Banker master'!$A$2:$A$186,0)),"") -> Perisha Agro and packaging Enterprise | X32: =IFERROR(INDEX('E-Banker master'!$C$2:$C$186,MATCH($A32,'E-Banker master'!$A$2:$A$186,0)),"") -> 90 | Y32: =IFERROR(INDEX('E-Banker master'!$D$2:$D$186,MATCH($A32,'E-Banker master'!$A$2:$A$186,0)),"") -> 1050201 | Z32: =IFERROR(INDEX('E-Banker master'!$E$2:$E$186,MATCH($A32,'E-Banker master'!$A$2:$A$186,0)),"") -> H | AA32: =IFERROR(INDEX('E-Banker master'!$F$2:$F$186,MATCH($A32,'E-Banker master'!$A$2:$A$186,0)),"") -> S | AB32: =IFERROR(INDEX('E-Banker master'!$G$2:$G$186,MATCH($A32,'E-Banker master'!$A$2:$A$186,0)),"") -> 10 | AC32: =IFERROR(INDEX('E-Banker master'!$I$2:$I$186,MATCH($A32,'E-Banker master'!$A$2:$A$186,0)),"") -> 12000000 | AD32: =IFERROR(INDEX('E-Banker master'!$J$2:$J$186,MATCH($A32,'E-Banker master'!$A$2:$A$186,0)),"") -> 44728 | AE32: =IFERROR(INDEX('E-Banker master'!$K$2:$K$186,MATCH($A32,'E-Banker master'!$A$2:$A$186,0)),"") -> 45565 | AF32: =IFERROR(INDEX('E-Banker master'!$L$2:$L$186,MATCH($A32,'E-Banker master'!$A$2:$A$186,0)),"") -> 3 | AG32: =IFERROR(INDEX('E-Banker master'!$M$2:$M$186,MATCH($A32,'E-Banker master'!$A$2:$A$186,0)),"") -> 3 | AH32: =IFERROR(INDEX('E-Banker master'!$N$2:$N$186,MATCH($A32,'E-Banker master'!$A$2:$A$186,0)),"") -> 12000000 | AI32: =IFERROR(INDEX('E-Banker master'!$O$2:$O$186,MATCH($A32,'E-Banker master'!$A$2:$A$186,0)),"") -> 1849609.4 | AJ32: =IFERROR(INDEX('E-Banker master'!$P$2:$P$186,MATCH($A32,'E-Banker master'!$A$2:$A$186,0)),"") -> 1358.4 | AK32: =IF(OR(Q32="",AJ32=""),"",Q32-AJ32) -> -1358.4 | AL32: 29 | AM32: =HYPERLINK("#'Amortisation and Repayments'!C1705","block 29") -> block 29 | AN32: =Mapping!X32 -> 0 | AO32: ='Loan Book'!AS35 -> 120000 | AP32: ='Loan Book'!AT35 -> 242000 | AR32: =AD32 -> 44728 | AS32: Y | AT32: Offer letter and Quickbooks | AU32: =IF(COUNT(AO32:AQ32)=0,"",SUM(AO32:AQ32)) -> 362000
A33: =Mapping!J33 -> 000104460000031 | B33: =Mapping!K33 -> High | C33: 36 | D33: ='Loan Book'!E36 -> Pamela Investments | E33: ='Loan Book'!F36 -> Debt | F33: ='Loan Book'!G36 -> 44728 | G33: ='Loan Book'!H36 -> 45443 | H33: ='Loan Book'!I36 -> 2 | I33: ='Loan Book'!J36 -> 3 (Cap+Int) | J33: =IF('Loan Book'!K36="","",IF('Loan Book'!K36<1,'Loan Book'!K36*100,'Loan Book'!K36)) -> 10 | K33: ='Loan Book'!L36 -> 10000000 | L33: ='Loan Book'!M36 -> 10000000 | M33: ='Loan Book'!N36 -> 0 | N33: ='Loan Book'!O36 -> 10000000 | O33: ='Loan Book'!P36 -> 874211.37 | P33: ='Loan Book'!Q36 -> -10874211 | Q33: ='Loan Book'!R36 -> -0.00018463284 | R33: ='Loan Book'!S36 -> 0 | ... T33: ='Loan Book'!U36 -> 0 | U33: ='Loan Book'!AC36 -> 0 | V33: ='Loan Book'!AE36 -> 0 | W33: =IFERROR(INDEX('E-Banker master'!$B$2:$B$186,MATCH($A33,'E-Banker master'!$A$2:$A$186,0)),"") -> Pamela Investments | X33: =IFERROR(INDEX('E-Banker master'!$C$2:$C$186,MATCH($A33,'E-Banker master'!$A$2:$A$186,0)),"") -> 92 | Y33: =IFERROR(INDEX('E-Banker master'!$D$2:$D$186,MATCH($A33,'E-Banker master'!$A$2:$A$186,0)),"") -> 1050202 | Z33: =IFERROR(INDEX('E-Banker master'!$E$2:$E$186,MATCH($A33,'E-Banker master'!$A$2:$A$186,0)),"") -> C | AA33: =IFERROR(INDEX('E-Banker master'!$F$2:$F$186,MATCH($A33,'E-Banker master'!$A$2:$A$186,0)),"") -> S | AB33: =IFERROR(INDEX('E-Banker master'!$G$2:$G$186,MATCH($A33,'E-Banker master'!$A$2:$A$186,0)),"") -> 10 | AC33: =IFERROR(INDEX('E-Banker master'!$I$2:$I$186,MATCH($A33,'E-Banker master'!$A$2:$A$186,0)),"") -> 10000000 | AD33: =IFERROR(INDEX('E-Banker master'!$J$2:$J$186,MATCH($A33,'E-Banker master'!$A$2:$A$186,0)),"") -> 44728 | AE33: =IFERROR(INDEX('E-Banker master'!$K$2:$K$186,MATCH($A33,'E-Banker master'!$A$2:$A$186,0)),"") -> 45458 | AF33: =IFERROR(INDEX('E-Banker master'!$L$2:$L$186,MATCH($A33,'E-Banker master'!$A$2:$A$186,0)),"") -> 3 | AG33: =IFERROR(INDEX('E-Banker master'!$M$2:$M$186,MATCH($A33,'E-Banker master'!$A$2:$A$186,0)),"") -> 3 | AH33: =IFERROR(INDEX('E-Banker master'!$N$2:$N$186,MATCH($A33,'E-Banker master'!$A$2:$A$186,0)),"") -> 0 | AI33: =IFERROR(INDEX('E-Banker master'!$O$2:$O$186,MATCH($A33,'E-Banker master'!$A$2:$A$186,0)),"") -> 0 | AJ33: =IFERROR(INDEX('E-Banker master'!$P$2:$P$186,MATCH($A33,'E-Banker master'!$A$2:$A$186,0)),"") -> 0 | AK33: =IF(OR(Q33="",AJ33=""),"",Q33-AJ33) -> -0.00018463284 | AL33: 30 | AM33: =HYPERLINK("#'Amortisation and Repayments'!C1749","block 30") -> block 30 | AN33: =Mapping!X33 -> 0 | AO33: ='Loan Book'!AS36 -> 100000 | AP33: ='Loan Book'!AT36 -> 210000 | AR33: =AD33 -> 44728 | AS33: Y | AT33: Offer letter and Quickbooks | AU33: =IF(COUNT(AO33:AQ33)=0,"",SUM(AO33:AQ33)) -> 310000
A34: =Mapping!J34 -> 000104420000032 | B34: =Mapping!K34 -> High | C34: 37 | D34: ='Loan Book'!E37 -> African Honey products Industries | E34: ='Loan Book'!F37 -> Debt | F34: ='Loan Book'!G37 -> 44740 | G34: ='Loan Book'!H37 -> 46568 | H34: ='Loan Book'!I37 -> 5 | I34: ='Loan Book'!J37 -> 9 (Cap only) | J34: =IF('Loan Book'!K37="","",IF('Loan Book'!K37<1,'Loan Book'!K37*100,'Loan Book'!K37)) -> 30.7 | K34: ='Loan Book'!L37 -> 104979420 | L34: ='Loan Book'!M37 -> 104979420 | M34: ='Loan Book'!N37 -> 0 | N34: ='Loan Book'!O37 -> 104979420 | O34: ='Loan Book'!P37 -> 69336574 | P34: ='Loan Book'!Q37 -> -67295487 | Q34: ='Loan Book'!R37 -> 1.0702051e+08 | R34: ='Loan Book'!S37 -> 8484612.3 | ... T34: ='Loan Book'!U37 -> 14232905 | U34: ='Loan Book'!AC37 -> 0 | V34: ='Loan Book'!AE37 -> 0 | W34: =IFERROR(INDEX('E-Banker master'!$B$2:$B$186,MATCH($A34,'E-Banker master'!$A$2:$A$186,0)),"") -> African Honey products Industries | X34: =IFERROR(INDEX('E-Banker master'!$C$2:$C$186,MATCH($A34,'E-Banker master'!$A$2:$A$186,0)),"") -> 84 | Y34: =IFERROR(INDEX('E-Banker master'!$D$2:$D$186,MATCH($A34,'E-Banker master'!$A$2:$A$186,0)),"") -> 1050101 | Z34: =IFERROR(INDEX('E-Banker master'!$E$2:$E$186,MATCH($A34,'E-Banker master'!$A$2:$A$186,0)),"") -> A | AA34: =IFERROR(INDEX('E-Banker master'!$F$2:$F$186,MATCH($A34,'E-Banker master'!$A$2:$A$186,0)),"") -> M | AB34: =IFERROR(INDEX('E-Banker master'!$G$2:$G$186,MATCH($A34,'E-Banker master'!$A$2:$A$186,0)),"") -> 29.2 | AC34: =IFERROR(INDEX('E-Banker master'!$I$2:$I$186,MATCH($A34,'E-Banker master'!$A$2:$A$186,0)),"") -> 104979420 | AD34: =IFERROR(INDEX('E-Banker master'!$J$2:$J$186,MATCH($A34,'E-Banker master'!$A$2:$A$186,0)),"") -> 44699 | AE34: =IFERROR(INDEX('E-Banker master'!$K$2:$K$186,MATCH($A34,'E-Banker master'!$A$2:$A$186,0)),"") -> 46525 | AF34: =IFERROR(INDEX('E-Banker master'!$L$2:$L$186,MATCH($A34,'E-Banker master'!$A$2:$A$186,0)),"") -> 0 | AG34: =IFERROR(INDEX('E-Banker master'!$M$2:$M$186,MATCH($A34,'E-Banker master'!$A$2:$A$186,0)),"") -> 0 | AH34: =IFERROR(INDEX('E-Banker master'!$N$2:$N$186,MATCH($A34,'E-Banker master'!$A$2:$A$186,0)),"") -> 104979420 | AI34: =IFERROR(INDEX('E-Banker master'!$O$2:$O$186,MATCH($A34,'E-Banker master'!$A$2:$A$186,0)),"") -> 61336126 | AJ34: =IFERROR(INDEX('E-Banker master'!$P$2:$P$186,MATCH($A34,'E-Banker master'!$A$2:$A$186,0)),"") -> 1.0831447e+08 | AK34: =IF(OR(Q34="",AJ34=""),"",Q34-AJ34) -> -1293958.5 | AL34: 31 | AM34: =HYPERLINK("#'Amortisation and Repayments'!C1790","block 31") -> block 31 | AN34: =Mapping!X34 -> 0 | AO34: ='Loan Book'!AS37 -> 1551420 | AP34: ='Loan Book'!AT37 -> 3557725 | AR34: =AD34 -> 44699 | AS34: Y | AT34: Offer letter and Quickbooks | AU34: =IF(COUNT(AO34:AQ34)=0,"",SUM(AO34:AQ34)) -> 5109145
A35: =Mapping!J35 -> 000104450000033 | B35: =Mapping!K35 -> High | C35: 38 | D35: ='Loan Book'!E38 -> Mtengo Wa Kumunda | E35: ='Loan Book'!F38 -> Debt | F35: ='Loan Book'!G38 -> 44747 | G35: ='Loan Book'!H38 -> 45504 | H35: ='Loan Book'!I38 -> 2 | I35: ='Loan Book'!J38 -> 3 (Cap+Int) | J35: =IF('Loan Book'!K38="","",IF('Loan Book'!K38<1,'Loan Book'!K38*100,'Loan Book'!K38)) -> 10 | K35: ='Loan Book'!L38 -> 12000000 | L35: ='Loan Book'!M38 -> 12000000 | M35: ='Loan Book'!N38 -> 0 | N35: ='Loan Book'!O38 -> 12000000 | O35: ='Loan Book'!P38 -> 1482649.5 | P35: ='Loan Book'!Q38 -> -13482733 | Q35: ='Loan Book'!R38 -> 0 | R35: ='Loan Book'!S38 -> 0 | ... T35: ='Loan Book'!U38 -> 0 | U35: ='Loan Book'!AC38 -> 0 | V35: ='Loan Book'!AE38 -> 0 | W35: =IFERROR(INDEX('E-Banker master'!$B$2:$B$186,MATCH($A35,'E-Banker master'!$A$2:$A$186,0)),"") -> Mtengo wa Kumunda | X35: =IFERROR(INDEX('E-Banker master'!$C$2:$C$186,MATCH($A35,'E-Banker master'!$A$2:$A$186,0)),"") -> 90 | Y35: =IFERROR(INDEX('E-Banker master'!$D$2:$D$186,MATCH($A35,'E-Banker master'!$A$2:$A$186,0)),"") -> 1050201 | Z35: =IFERROR(INDEX('E-Banker master'!$E$2:$E$186,MATCH($A35,'E-Banker master'!$A$2:$A$186,0)),"") -> D | AA35: =IFERROR(INDEX('E-Banker master'!$F$2:$F$186,MATCH($A35,'E-Banker master'!$A$2:$A$186,0)),"") -> S | AB35: =IFERROR(INDEX('E-Banker master'!$G$2:$G$186,MATCH($A35,'E-Banker master'!$A$2:$A$186,0)),"") -> 10 | AC35: =IFERROR(INDEX('E-Banker master'!$I$2:$I$186,MATCH($A35,'E-Banker master'!$A$2:$A$186,0)),"") -> 12000000 | AD35: =IFERROR(INDEX('E-Banker master'!$J$2:$J$186,MATCH($A35,'E-Banker master'!$A$2:$A$186,0)),"") -> 44747 | AE35: =IFERROR(INDEX('E-Banker master'!$K$2:$K$186,MATCH($A35,'E-Banker master'!$A$2:$A$186,0)),"") -> 45477 | AF35: =IFERROR(INDEX('E-Banker master'!$L$2:$L$186,MATCH($A35,'E-Banker master'!$A$2:$A$186,0)),"") -> 3 | AG35: =IFERROR(INDEX('E-Banker master'!$M$2:$M$186,MATCH($A35,'E-Banker master'!$A$2:$A$186,0)),"") -> 3 | AH35: =IFERROR(INDEX('E-Banker master'!$N$2:$N$186,MATCH($A35,'E-Banker master'!$A$2:$A$186,0)),"") -> 12000000 | AI35: =IFERROR(INDEX('E-Banker master'!$O$2:$O$186,MATCH($A35,'E-Banker master'!$A$2:$A$186,0)),"") -> 1482649.5 | AJ35: =IFERROR(INDEX('E-Banker master'!$P$2:$P$186,MATCH($A35,'E-Banker master'!$A$2:$A$186,0)),"") -> -83.07 | AK35: =IF(OR(Q35="",AJ35=""),"",Q35-AJ35) -> 83.07 | AN35: =Mapping!X35 -> 0 | AO35: ='Loan Book'!AS38 -> 120000 | AP35: ='Loan Book'!AT38 -> 244420 | AR35: =AD35 -> 44747 | AS35: Y | AT35: Offer letter and Quickbooks | AU35: =IF(COUNT(AO35:AQ35)=0,"",SUM(AO35:AQ35)) -> 364420
A36: =Mapping!J36 -> 000104450000034 | B36: =Mapping!K36 -> High | C36: 39 | D36: ='Loan Book'!E39 -> MMM Investments | E36: ='Loan Book'!F39 -> Debt | F36: ='Loan Book'!G39 -> 44749 | G36: ='Loan Book'!H39 -> 45138 | H36: ='Loan Book'!I39 -> 1 | I36: ='Loan Book'!J39 -> 3 (Cap+Int) | J36: =IF('Loan Book'!K39="","",IF('Loan Book'!K39<1,'Loan Book'!K39*100,'Loan Book'!K39)) -> 10 | K36: ='Loan Book'!L39 -> 10000000 | L36: ='Loan Book'!M39 -> 10000000 | M36: ='Loan Book'!N39 -> 0 | N36: ='Loan Book'!O39 -> 10000000 | O36: ='Loan Book'!P39 -> 781375.07 | P36: ='Loan Book'!Q39 -> -10519237 | Q36: ='Loan Book'!R39 -> 262137.72 | R36: ='Loan Book'!S39 -> 262137.72 | ... T36: ='Loan Book'!U39 -> 262137.72 | U36: ='Loan Book'!AC39 -> 0 | V36: ='Loan Book'!AE39 -> 0 | W36: =IFERROR(INDEX('E-Banker master'!$B$2:$B$186,MATCH($A36,'E-Banker master'!$A$2:$A$186,0)),"") -> MMM Investments | X36: =IFERROR(INDEX('E-Banker master'!$C$2:$C$186,MATCH($A36,'E-Banker master'!$A$2:$A$186,0)),"") -> 90 | Y36: =IFERROR(INDEX('E-Banker master'!$D$2:$D$186,MATCH($A36,'E-Banker master'!$A$2:$A$186,0)),"") -> 1050201 | Z36: =IFERROR(INDEX('E-Banker master'!$E$2:$E$186,MATCH($A36,'E-Banker master'!$A$2:$A$186,0)),"") -> H | AA36: =IFERROR(INDEX('E-Banker master'!$F$2:$F$186,MATCH($A36,'E-Banker master'!$A$2:$A$186,0)),"") -> S | AB36: =IFERROR(INDEX('E-Banker master'!$G$2:$G$186,MATCH($A36,'E-Banker master'!$A$2:$A$186,0)),"") -> 10 | AC36: =IFERROR(INDEX('E-Banker master'!$I$2:$I$186,MATCH($A36,'E-Banker master'!$A$2:$A$186,0)),"") -> 10000000 | AD36: =IFERROR(INDEX('E-Banker master'!$J$2:$J$186,MATCH($A36,'E-Banker master'!$A$2:$A$186,0)),"") -> 44749 | AE36: =IFERROR(INDEX('E-Banker master'!$K$2:$K$186,MATCH($A36,'E-Banker master'!$A$2:$A$186,0)),"") -> 45113 | AF36: =IFERROR(INDEX('E-Banker master'!$L$2:$L$186,MATCH($A36,'E-Banker master'!$A$2:$A$186,0)),"") -> 3 | AG36: =IFERROR(INDEX('E-Banker master'!$M$2:$M$186,MATCH($A36,'E-Banker master'!$A$2:$A$186,0)),"") -> 3 | AH36: =IFERROR(INDEX('E-Banker master'!$N$2:$N$186,MATCH($A36,'E-Banker master'!$A$2:$A$186,0)),"") -> 10000000 | AI36: =IFERROR(INDEX('E-Banker master'!$O$2:$O$186,MATCH($A36,'E-Banker master'!$A$2:$A$186,0)),"") -> 781375.07 | AJ36: =IFERROR(INDEX('E-Banker master'!$P$2:$P$186,MATCH($A36,'E-Banker master'!$A$2:$A$186,0)),"") -> 268800.7 | AK36: =IF(OR(Q36="",AJ36=""),"",Q36-AJ36) -> -6662.978 | AL36: 32 | AM36: =HYPERLINK("#'Amortisation and Repayments'!C1868","block 32") -> block 32 | AN36: =Mapping!X36 -> 0 | AO36: ='Loan Book'!AS39 -> 100000 | AP36: ='Loan Book'!AT39 -> 210000 | AR36: =AD36 -> 44749 | AS36: Y | AT36: Offer letter and Quickbooks | AU36: =IF(COUNT(AO36:AQ36)=0,"",SUM(AO36:AQ36)) -> 310000
A37: =Mapping!J37 -> 000104450000035 | B37: =Mapping!K37 -> High | C37: 40 | D37: ='Loan Book'!E40 -> Sekuru Enterprise | E37: ='Loan Book'!F40 -> Debt | F37: ='Loan Book'!G40 -> 44749 | G37: ='Loan Book'!H40 -> 45504 | H37: ='Loan Book'!I40 -> 2 | I37: ='Loan Book'!J40 -> 3 (Cap+Int) | J37: =IF('Loan Book'!K40="","",IF('Loan Book'!K40<1,'Loan Book'!K40*100,'Loan Book'!K40)) -> 10 | K37: ='Loan Book'!L40 -> 10000000 | L37: ='Loan Book'!M40 -> 10000000 | M37: ='Loan Book'!N40 -> 0 | N37: ='Loan Book'!O40 -> 10000000 | O37: ='Loan Book'!P40 -> 1279939.7 | P37: ='Loan Book'!Q40 -> -11280000 | Q37: ='Loan Book'!R40 -> 0 | R37: ='Loan Book'!S40 -> 0 | ... T37: ='Loan Book'!U40 -> 0 | U37: ='Loan Book'!AC40 -> 0 | V37: ='Loan Book'!AE40 -> 0 | W37: =IFERROR(INDEX('E-Banker master'!$B$2:$B$186,MATCH($A37,'E-Banker master'!$A$2:$A$186,0)),"") -> Sekuru Enterprise | X37: =IFERROR(INDEX('E-Banker master'!$C$2:$C$186,MATCH($A37,'E-Banker master'!$A$2:$A$186,0)),"") -> 90 | Y37: =IFERROR(INDEX('E-Banker master'!$D$2:$D$186,MATCH($A37,'E-Banker master'!$A$2:$A$186,0)),"") -> 1050201 | Z37: =IFERROR(INDEX('E-Banker master'!$E$2:$E$186,MATCH($A37,'E-Banker master'!$A$2:$A$186,0)),"") -> C | AA37: =IFERROR(INDEX('E-Banker master'!$F$2:$F$186,MATCH($A37,'E-Banker master'!$A$2:$A$186,0)),"") -> S | AB37: =IFERROR(INDEX('E-Banker master'!$G$2:$G$186,MATCH($A37,'E-Banker master'!$A$2:$A$186,0)),"") -> 10 | AC37: =IFERROR(INDEX('E-Banker master'!$I$2:$I$186,MATCH($A37,'E-Banker master'!$A$2:$A$186,0)),"") -> 10000000 | AD37: =IFERROR(INDEX('E-Banker master'!$J$2:$J$186,MATCH($A37,'E-Banker master'!$A$2:$A$186,0)),"") -> 44749 | AE37: =IFERROR(INDEX('E-Banker master'!$K$2:$K$186,MATCH($A37,'E-Banker master'!$A$2:$A$186,0)),"") -> 45479 | AF37: =IFERROR(INDEX('E-Banker master'!$L$2:$L$186,MATCH($A37,'E-Banker master'!$A$2:$A$186,0)),"") -> 3 | AG37: =IFERROR(INDEX('E-Banker master'!$M$2:$M$186,MATCH($A37,'E-Banker master'!$A$2:$A$186,0)),"") -> 3 | AH37: =IFERROR(INDEX('E-Banker master'!$N$2:$N$186,MATCH($A37,'E-Banker master'!$A$2:$A$186,0)),"") -> 0 | AI37: =IFERROR(INDEX('E-Banker master'!$O$2:$O$186,MATCH($A37,'E-Banker master'!$A$2:$A$186,0)),"") -> 0 | AJ37: =IFERROR(INDEX('E-Banker master'!$P$2:$P$186,MATCH($A37,'E-Banker master'!$A$2:$A$186,0)),"") -> 0 | AK37: =IF(OR(Q37="",AJ37=""),"",Q37-AJ37) -> 0 | AL37: 33 | AM37: =HYPERLINK("#'Amortisation and Repayments'!C1915","block 33") -> block 33 | AN37: =Mapping!X37 -> 0 | AO37: ='Loan Book'!AS40 -> 100000 | AP37: ='Loan Book'!AT40 -> 212100 | AR37: =AD37 -> 44749 | AS37: Y | AT37: Offer letter and Quickbooks | AU37: =IF(COUNT(AO37:AQ37)=0,"",SUM(AO37:AQ37)) -> 312100
A38: =Mapping!J38 -> 000104450000036 | B38: =Mapping!K38 -> High | C38: 41 | D38: ='Loan Book'!E41 -> Agribusiness Solutions Ltd | E38: ='Loan Book'!F41 -> Debt | F38: ='Loan Book'!G41 -> 44755 | G38: ='Loan Book'!H41 -> 45504 | H38: ='Loan Book'!I41 -> 2 | I38: ='Loan Book'!J41 -> 3 (Cap+Int) | J38: =IF('Loan Book'!K41="","",IF('Loan Book'!K41<1,'Loan Book'!K41*100,'Loan Book'!K41)) -> 10 | K38: ='Loan Book'!L41 -> 24000000 | L38: ='Loan Book'!M41 -> 24000000 | M38: ='Loan Book'!N41 -> 0 | N38: ='Loan Book'!O41 -> 24000000 | O38: ='Loan Book'!P41 -> 3064926.6 | P38: ='Loan Book'!Q41 -> -27072315 | Q38: ='Loan Book'!R41 -> 0 | R38: ='Loan Book'!S41 -> 0 | ... T38: ='Loan Book'!U41 -> 0 | U38: ='Loan Book'!AC41 -> 0 | V38: ='Loan Book'!AE41 -> 0 | W38: =IFERROR(INDEX('E-Banker master'!$B$2:$B$186,MATCH($A38,'E-Banker master'!$A$2:$A$186,0)),"") -> Agribusiness Solutions Limited | X38: =IFERROR(INDEX('E-Banker master'!$C$2:$C$186,MATCH($A38,'E-Banker master'!$A$2:$A$186,0)),"") -> 90 | Y38: =IFERROR(INDEX('E-Banker master'!$D$2:$D$186,MATCH($A38,'E-Banker master'!$A$2:$A$186,0)),"") -> 1050201 | Z38: =IFERROR(INDEX('E-Banker master'!$E$2:$E$186,MATCH($A38,'E-Banker master'!$A$2:$A$186,0)),"") -> C | AA38: =IFERROR(INDEX('E-Banker master'!$F$2:$F$186,MATCH($A38,'E-Banker master'!$A$2:$A$186,0)),"") -> S | AB38: =IFERROR(INDEX('E-Banker master'!$G$2:$G$186,MATCH($A38,'E-Banker master'!$A$2:$A$186,0)),"") -> 10 | AC38: =IFERROR(INDEX('E-Banker master'!$I$2:$I$186,MATCH($A38,'E-Banker master'!$A$2:$A$186,0)),"") -> 24000000 | AD38: =IFERROR(INDEX('E-Banker master'!$J$2:$J$186,MATCH($A38,'E-Banker master'!$A$2:$A$186,0)),"") -> 44755 | AE38: =IFERROR(INDEX('E-Banker master'!$K$2:$K$186,MATCH($A38,'E-Banker master'!$A$2:$A$186,0)),"") -> 45485 | AF38: =IFERROR(INDEX('E-Banker master'!$L$2:$L$186,MATCH($A38,'E-Banker master'!$A$2:$A$186,0)),"") -> 3 | AG38: =IFERROR(INDEX('E-Banker master'!$M$2:$M$186,MATCH($A38,'E-Banker master'!$A$2:$A$186,0)),"") -> 3 | AH38: =IFERROR(INDEX('E-Banker master'!$N$2:$N$186,MATCH($A38,'E-Banker master'!$A$2:$A$186,0)),"") -> 0 | AI38: =IFERROR(INDEX('E-Banker master'!$O$2:$O$186,MATCH($A38,'E-Banker master'!$A$2:$A$186,0)),"") -> 0 | AJ38: =IFERROR(INDEX('E-Banker master'!$P$2:$P$186,MATCH($A38,'E-Banker master'!$A$2:$A$186,0)),"") -> 0 | AK38: =IF(OR(Q38="",AJ38=""),"",Q38-AJ38) -> 0 | AL38: 55 | AM38: =HYPERLINK("#'Amortisation and Repayments'!C2982","block 55") -> block 55 | AN38: =Mapping!X38 -> 0 | AO38: ='Loan Book'!AS41 -> 240000 | AP38: ='Loan Book'!AT41 -> 438340 | AR38: =AD38 -> 44755 | AS38: Y | AT38: Offer letter and Quickbooks | AU38: =IF(COUNT(AO38:AQ38)=0,"",SUM(AO38:AQ38)) -> 678340
A39: =Mapping!J39 -> 0 | B39: =Mapping!K39 -> Not matched | C39: 42 | D39: ='Loan Book'!E42 -> Favoured Farms | E39: ='Loan Book'!F42 -> Debt | F39: ='Loan Book'!G42 -> 44755 | G39: ='Loan Book'!H42 -> 45504 | H39: ='Loan Book'!I42 -> 2 | I39: ='Loan Book'!J42 -> 3 (Cap+Int) | J39: =IF('Loan Book'!K42="","",IF('Loan Book'!K42<1,'Loan Book'!K42*100,'Loan Book'!K42)) -> 10 | K39: ='Loan Book'!L42 -> 10000000 | L39: ='Loan Book'!M42 -> 10000000 | M39: ='Loan Book'!N42 -> 0 | N39: ='Loan Book'!O42 -> 10000000 | O39: ='Loan Book'!P42 -> 1216843.9 | P39: ='Loan Book'!Q42 -> -11215200 | Q39: ='Loan Book'!R42 -> 0 | R39: ='Loan Book'!S42 -> 0 | ... T39: ='Loan Book'!U42 -> 0 | U39: ='Loan Book'!AC42 -> 0 | V39: ='Loan Book'!AE42 -> 0 | W39: =IFERROR(INDEX('E-Banker master'!$B$2:$B$186,MATCH($A39,'E-Banker master'!$A$2:$A$186,0)),"") | X39: =IFERROR(INDEX('E-Banker master'!$C$2:$C$186,MATCH($A39,'E-Banker master'!$A$2:$A$186,0)),"") | Y39: =IFERROR(INDEX('E-Banker master'!$D$2:$D$186,MATCH($A39,'E-Banker master'!$A$2:$A$186,0)),"") | Z39: =IFERROR(INDEX('E-Banker master'!$E$2:$E$186,MATCH($A39,'E-Banker master'!$A$2:$A$186,0)),"") | AA39: =IFERROR(INDEX('E-Banker master'!$F$2:$F$186,MATCH($A39,'E-Banker master'!$A$2:$A$186,0)),"") | AB39: =IFERROR(INDEX('E-Banker master'!$G$2:$G$186,MATCH($A39,'E-Banker master'!$A$2:$A$186,0)),"") | AC39: =IFERROR(INDEX('E-Banker master'!$I$2:$I$186,MATCH($A39,'E-Banker master'!$A$2:$A$186,0)),"") | AD39: =IFERROR(INDEX('E-Banker master'!$J$2:$J$186,MATCH($A39,'E-Banker master'!$A$2:$A$186,0)),"") | AE39: =IFERROR(INDEX('E-Banker master'!$K$2:$K$186,MATCH($A39,'E-Banker master'!$A$2:$A$186,0)),"") | AF39: =IFERROR(INDEX('E-Banker master'!$L$2:$L$186,MATCH($A39,'E-Banker master'!$A$2:$A$186,0)),"") | AG39: =IFERROR(INDEX('E-Banker master'!$M$2:$M$186,MATCH($A39,'E-Banker master'!$A$2:$A$186,0)),"") | AH39: =IFERROR(INDEX('E-Banker master'!$N$2:$N$186,MATCH($A39,'E-Banker master'!$A$2:$A$186,0)),"") | AI39: =IFERROR(INDEX('E-Banker master'!$O$2:$O$186,MATCH($A39,'E-Banker master'!$A$2:$A$186,0)),"") | AJ39: =IFERROR(INDEX('E-Banker master'!$P$2:$P$186,MATCH($A39,'E-Banker master'!$A$2:$A$186,0)),"") | AK39: =IF(OR(Q39="",AJ39=""),"",Q39-AJ39) | AL39: 35 | AM39: =HYPERLINK("#'Amortisation and Repayments'!C2002","block 35") -> block 35 | AN39: =Mapping!X39 -> 0 | AO39: ='Loan Book'!AS42 -> 100000 | AP39: ='Loan Book'!AT42 -> 212100 | AR39: =AD39 | AS39: Y | AT39: Offer letter and Quickbooks | AU39: =IF(COUNT(AO39:AQ39)=0,"",SUM(AO39:AQ39)) -> 312100
A40: =Mapping!J40 -> 000104450000038 | B40: =Mapping!K40 -> High | C40: 43 | D40: ='Loan Book'!E43 -> Tac-Maz Investment | E40: ='Loan Book'!F43 -> Debt | F40: ='Loan Book'!G43 -> 44755 | G40: ='Loan Book'!H43 -> 45504 | H40: ='Loan Book'!I43 -> 2 | I40: ='Loan Book'!J43 -> 3 (Cap+Int) | J40: =IF('Loan Book'!K43="","",IF('Loan Book'!K43<1,'Loan Book'!K43*100,'Loan Book'!K43)) -> 10 | K40: ='Loan Book'!L43 -> 10000000 | L40: ='Loan Book'!M43 -> 10000000 | M40: ='Loan Book'!N43 -> 0 | N40: ='Loan Book'!O43 -> 10000000 | O40: ='Loan Book'!P43 -> 1872113.4 | P40: ='Loan Book'!Q43 -> -6019000 | Q40: ='Loan Book'!R43 -> 5853113.4 | R40: ='Loan Book'!S43 -> 2608863.5 | ... T40: ='Loan Book'!U43 -> 3156194.7 | U40: ='Loan Book'!AC43 -> 0 | V40: ='Loan Book'!AE43 -> 0 | W40: =IFERROR(INDEX('E-Banker master'!$B$2:$B$186,MATCH($A40,'E-Banker master'!$A$2:$A$186,0)),"") -> Tac-Maz Investment | X40: =IFERROR(INDEX('E-Banker master'!$C$2:$C$186,MATCH($A40,'E-Banker master'!$A$2:$A$186,0)),"") -> 90 | Y40: =IFERROR(INDEX('E-Banker master'!$D$2:$D$186,MATCH($A40,'E-Banker master'!$A$2:$A$186,0)),"") -> 1050201 | Z40: =IFERROR(INDEX('E-Banker master'!$E$2:$E$186,MATCH($A40,'E-Banker master'!$A$2:$A$186,0)),"") -> H | AA40: =IFERROR(INDEX('E-Banker master'!$F$2:$F$186,MATCH($A40,'E-Banker master'!$A$2:$A$186,0)),"") -> S | AB40: =IFERROR(INDEX('E-Banker master'!$G$2:$G$186,MATCH($A40,'E-Banker master'!$A$2:$A$186,0)),"") -> 10 | AC40: =IFERROR(INDEX('E-Banker master'!$I$2:$I$186,MATCH($A40,'E-Banker master'!$A$2:$A$186,0)),"") -> 10000000 | AD40: =IFERROR(INDEX('E-Banker master'!$J$2:$J$186,MATCH($A40,'E-Banker master'!$A$2:$A$186,0)),"") -> 44755 | AE40: =IFERROR(INDEX('E-Banker master'!$K$2:$K$186,MATCH($A40,'E-Banker master'!$A$2:$A$186,0)),"") -> 45485 | AF40: =IFERROR(INDEX('E-Banker master'!$L$2:$L$186,MATCH($A40,'E-Banker master'!$A$2:$A$186,0)),"") -> 3 | AG40: =IFERROR(INDEX('E-Banker master'!$M$2:$M$186,MATCH($A40,'E-Banker master'!$A$2:$A$186,0)),"") -> 3 | AH40: =IFERROR(INDEX('E-Banker master'!$N$2:$N$186,MATCH($A40,'E-Banker master'!$A$2:$A$186,0)),"") -> 10000000 | AI40: =IFERROR(INDEX('E-Banker master'!$O$2:$O$186,MATCH($A40,'E-Banker master'!$A$2:$A$186,0)),"") -> 1771854.1 | AJ40: =IFERROR(INDEX('E-Banker master'!$P$2:$P$186,MATCH($A40,'E-Banker master'!$A$2:$A$186,0)),"") -> 5917617.5 | AK40: =IF(OR(Q40="",AJ40=""),"",Q40-AJ40) -> -64504.121 | AL40: 36 | AM40: =HYPERLINK("#'Amortisation and Repayments'!C2043","block 36") -> block 36 | AN40: =Mapping!X40 -> 0 | AO40: ='Loan Book'!AS43 -> 100000 | AP40: ='Loan Book'!AT43 -> 212100 | AR40: =AD40 -> 44755 | AS40: Y | AT40: Offer letter and Quickbooks | AU40: =IF(COUNT(AO40:AQ40)=0,"",SUM(AO40:AQ40)) -> 312100
A41: =Mapping!J41 -> 000104450000039 | B41: =Mapping!K41 -> High | C41: 44 | D41: ='Loan Book'!E44 -> G & S Home Mart & Agrodealer | E41: ='Loan Book'!F44 -> Debt | F41: ='Loan Book'!G44 -> 44755 | G41: ='Loan Book'!H44 -> 45504 | H41: ='Loan Book'!I44 -> 2 | I41: ='Loan Book'!J44 -> 3 (Cap+Int) | J41: =IF('Loan Book'!K44="","",IF('Loan Book'!K44<1,'Loan Book'!K44*100,'Loan Book'!K44)) -> 10 | K41: ='Loan Book'!L44 -> 10000000 | L41: ='Loan Book'!M44 -> 7000000 | M41: ='Loan Book'!N44 -> 3000000 | N41: ='Loan Book'!O44 -> 7000000 | O41: ='Loan Book'!P44 -> 893936.94 | P41: ='Loan Book'!Q44 -> -7895000 | Q41: ='Loan Book'!R44 -> 0 | R41: ='Loan Book'!S44 -> 0 | ... T41: ='Loan Book'!U44 -> 0 | U41: ='Loan Book'!AC44 -> 0 | V41: ='Loan Book'!AE44 -> 0 | W41: =IFERROR(INDEX('E-Banker master'!$B$2:$B$186,MATCH($A41,'E-Banker master'!$A$2:$A$186,0)),"") -> G&S HomeMart and Agrodealer | X41: =IFERROR(INDEX('E-Banker master'!$C$2:$C$186,MATCH($A41,'E-Banker master'!$A$2:$A$186,0)),"") -> 90 | Y41: =IFERROR(INDEX('E-Banker master'!$D$2:$D$186,MATCH($A41,'E-Banker master'!$A$2:$A$186,0)),"") -> 1050201 | Z41: =IFERROR(INDEX('E-Banker master'!$E$2:$E$186,MATCH($A41,'E-Banker master'!$A$2:$A$186,0)),"") -> C | AA41: =IFERROR(INDEX('E-Banker master'!$F$2:$F$186,MATCH($A41,'E-Banker master'!$A$2:$A$186,0)),"") -> S | AB41: =IFERROR(INDEX('E-Banker master'!$G$2:$G$186,MATCH($A41,'E-Banker master'!$A$2:$A$186,0)),"") -> 10 | AC41: =IFERROR(INDEX('E-Banker master'!$I$2:$I$186,MATCH($A41,'E-Banker master'!$A$2:$A$186,0)),"") -> 10000000 | AD41: =IFERROR(INDEX('E-Banker master'!$J$2:$J$186,MATCH($A41,'E-Banker master'!$A$2:$A$186,0)),"") -> 44755 | AE41: =IFERROR(INDEX('E-Banker master'!$K$2:$K$186,MATCH($A41,'E-Banker master'!$A$2:$A$186,0)),"") -> 45485 | AF41: =IFERROR(INDEX('E-Banker master'!$L$2:$L$186,MATCH($A41,'E-Banker master'!$A$2:$A$186,0)),"") -> 3 | AG41: =IFERROR(INDEX('E-Banker master'!$M$2:$M$186,MATCH($A41,'E-Banker master'!$A$2:$A$186,0)),"") -> 3 | AH41: =IFERROR(INDEX('E-Banker master'!$N$2:$N$186,MATCH($A41,'E-Banker master'!$A$2:$A$186,0)),"") -> 0 | AI41: =IFERROR(INDEX('E-Banker master'!$O$2:$O$186,MATCH($A41,'E-Banker master'!$A$2:$A$186,0)),"") -> 0 | AJ41: =IFERROR(INDEX('E-Banker master'!$P$2:$P$186,MATCH($A41,'E-Banker master'!$A$2:$A$186,0)),"") -> 0 | AK41: =IF(OR(Q41="",AJ41=""),"",Q41-AJ41) -> 0 | AL41: 37 | AM41: =HYPERLINK("#'Amortisation and Repayments'!C2091","block 37") -> block 37 | AN41: =Mapping!X41 -> 0 | AO41: ='Loan Book'!AS44 -> 70000 | AP41: ='Loan Book'!AT44 -> 163620 | AR41: =AD41 -> 44755 | AS41: Y | AT41: Offer letter and Quickbooks | AU41: =IF(COUNT(AO41:AQ41)=0,"",SUM(AO41:AQ41)) -> 233620
A42: =Mapping!J42 -> 000104420000040 | B42: =Mapping!K42 -> High | C42: 45 | D42: ='Loan Book'!E45 -> Ziweto Enterprise | E42: ='Loan Book'!F45 -> Debt | F42: ='Loan Book'!G45 -> 44761 | G42: ='Loan Book'!H45 -> 46234 | H42: ='Loan Book'!I45 -> 4 | I42: ='Loan Book'!J45 -> 12 (Cap only) | J42: =IF('Loan Book'!K45="","",IF('Loan Book'!K45<1,'Loan Book'!K45*100,'Loan Book'!K45)) -> 29.95 | K42: ='Loan Book'!L45 -> 152910000 | L42: ='Loan Book'!M45 -> 152910000 | M42: ='Loan Book'!N45 -> 0 | N42: ='Loan Book'!O45 -> 152910000 | O42: ='Loan Book'!P45 -> 44727786 | P42: ='Loan Book'!Q45 -> -1.9763779e+08 | Q42: ='Loan Book'!R45 -> 0.00139907 | R42: ='Loan Book'!S45 -> 0 | ... T42: ='Loan Book'!U45 -> 0 | U42: ='Loan Book'!AC45 -> 0 | V42: ='Loan Book'!AE45 -> 0 | W42: =IFERROR(INDEX('E-Banker master'!$B$2:$B$186,MATCH($A42,'E-Banker master'!$A$2:$A$186,0)),"") -> Ziweto Enterprise | X42: =IFERROR(INDEX('E-Banker master'!$C$2:$C$186,MATCH($A42,'E-Banker master'!$A$2:$A$186,0)),"") -> 84 | Y42: =IFERROR(INDEX('E-Banker master'!$D$2:$D$186,MATCH($A42,'E-Banker master'!$A$2:$A$186,0)),"") -> 1050101 | Z42: =IFERROR(INDEX('E-Banker master'!$E$2:$E$186,MATCH($A42,'E-Banker master'!$A$2:$A$186,0)),"") -> C | AA42: =IFERROR(INDEX('E-Banker master'!$F$2:$F$186,MATCH($A42,'E-Banker master'!$A$2:$A$186,0)),"") -> M | AB42: =IFERROR(INDEX('E-Banker master'!$G$2:$G$186,MATCH($A42,'E-Banker master'!$A$2:$A$186,0)),"") -> 30.95 | AC42: =IFERROR(INDEX('E-Banker master'!$I$2:$I$186,MATCH($A42,'E-Banker master'!$A$2:$A$186,0)),"") -> 152910000 | AD42: =IFERROR(INDEX('E-Banker master'!$J$2:$J$186,MATCH($A42,'E-Banker master'!$A$2:$A$186,0)),"") -> 44761 | AE42: =IFERROR(INDEX('E-Banker master'!$K$2:$K$186,MATCH($A42,'E-Banker master'!$A$2:$A$186,0)),"") -> 46221 | AF42: =IFERROR(INDEX('E-Banker master'!$L$2:$L$186,MATCH($A42,'E-Banker master'!$A$2:$A$186,0)),"") -> 12 | AG42: =IFERROR(INDEX('E-Banker master'!$M$2:$M$186,MATCH($A42,'E-Banker master'!$A$2:$A$186,0)),"") -> 0 | AH42: =IFERROR(INDEX('E-Banker master'!$N$2:$N$186,MATCH($A42,'E-Banker master'!$A$2:$A$186,0)),"") -> 0 | AI42: =IFERROR(INDEX('E-Banker master'!$O$2:$O$186,MATCH($A42,'E-Banker master'!$A$2:$A$186,0)),"") -> 0 | AJ42: =IFERROR(INDEX('E-Banker master'!$P$2:$P$186,MATCH($A42,'E-Banker master'!$A$2:$A$186,0)),"") -> 0 | AK42: =IF(OR(Q42="",AJ42=""),"",Q42-AJ42) -> 0.00139907 | AL42: 38 | AM42: =HYPERLINK("#'Amortisation and Repayments'!C2133","block 38") -> block 38 | AN42: =Mapping!X42 -> 0 | AO42: ='Loan Book'!AS45 -> 2370000 | AP42: ='Loan Book'!AT45 -> 1540000 | AR42: =AD42 -> 44761 | AS42: Y | AT42: Offer letter and Quickbooks | AU42: =IF(COUNT(AO42:AQ42)=0,"",SUM(AO42:AQ42)) -> 3910000
A43: =Mapping!J43 -> 000104450000041 | B43: =Mapping!K43 -> High | C43: 46 | D43: ='Loan Book'!E46 -> Kadava Investment Limited | E43: ='Loan Book'!F46 -> Debt | F43: ='Loan Book'!G46 -> 44775 | G43: ='Loan Book'!H46 -> 45535 | H43: ='Loan Book'!I46 -> 2 | I43: ='Loan Book'!J46 -> 3 (Cap+Int) | J43: =IF('Loan Book'!K46="","",IF('Loan Book'!K46<1,'Loan Book'!K46*100,'Loan Book'!K46)) -> 10 | K43: ='Loan Book'!L46 -> 12000000 | L43: ='Loan Book'!M46 -> 12000000 | M43: ='Loan Book'!N46 -> 0 | N43: ='Loan Book'!O46 -> 12000000 | O43: ='Loan Book'!P46 -> 1548865.3 | P43: ='Loan Book'!Q46 -> -9441000 | Q43: ='Loan Book'!R46 -> 4107865.3 | R43: ='Loan Book'!S46 -> 3760659.9 | ... T43: ='Loan Book'!U46 -> 4107865.3 | U43: ='Loan Book'!AC46 -> 0 | V43: ='Loan Book'!AE46 -> 0 | W43: =IFERROR(INDEX('E-Banker master'!$B$2:$B$186,MATCH($A43,'E-Banker master'!$A$2:$A$186,0)),"") -> Kadava Investment Limited | X43: =IFERROR(INDEX('E-Banker master'!$C$2:$C$186,MATCH($A43,'E-Banker master'!$A$2:$A$186,0)),"") -> 90 | Y43: =IFERROR(INDEX('E-Banker master'!$D$2:$D$186,MATCH($A43,'E-Banker master'!$A$2:$A$186,0)),"") -> 1050201 | Z43: =IFERROR(INDEX('E-Banker master'!$E$2:$E$186,MATCH($A43,'E-Banker master'!$A$2:$A$186,0)),"") -> H | AA43: =IFERROR(INDEX('E-Banker master'!$F$2:$F$186,MATCH($A43,'E-Banker master'!$A$2:$A$186,0)),"") -> S | AB43: =IFERROR(INDEX('E-Banker master'!$G$2:$G$186,MATCH($A43,'E-Banker master'!$A$2:$A$186,0)),"") -> 10 | AC43: =IFERROR(INDEX('E-Banker master'!$I$2:$I$186,MATCH($A43,'E-Banker master'!$A$2:$A$186,0)),"") -> 12000000 | AD43: =IFERROR(INDEX('E-Banker master'!$J$2:$J$186,MATCH($A43,'E-Banker master'!$A$2:$A$186,0)),"") -> 44775 | AE43: =IFERROR(INDEX('E-Banker master'!$K$2:$K$186,MATCH($A43,'E-Banker master'!$A$2:$A$186,0)),"") -> 45505 | AF43: =IFERROR(INDEX('E-Banker master'!$L$2:$L$186,MATCH($A43,'E-Banker master'!$A$2:$A$186,0)),"") -> 0 | AG43: =IFERROR(INDEX('E-Banker master'!$M$2:$M$186,MATCH($A43,'E-Banker master'!$A$2:$A$186,0)),"") -> 0 | AH43: =IFERROR(INDEX('E-Banker master'!$N$2:$N$186,MATCH($A43,'E-Banker master'!$A$2:$A$186,0)),"") -> 12000000 | AI43: =IFERROR(INDEX('E-Banker master'!$O$2:$O$186,MATCH($A43,'E-Banker master'!$A$2:$A$186,0)),"") -> 1543533.2 | AJ43: =IFERROR(INDEX('E-Banker master'!$P$2:$P$186,MATCH($A43,'E-Banker master'!$A$2:$A$186,0)),"") -> 4496798.7 | AK43: =IF(OR(Q43="",AJ43=""),"",Q43-AJ43) -> -388933.37 | AN43: =Mapping!X43 -> 0 | AO43: ='Loan Book'!AS46 -> 120000 | AP43: ='Loan Book'!AT46 -> 244420 | AR43: =AD43 -> 44775 | AS43: Y | AT43: Offer letter and Quickbooks | AU43: =IF(COUNT(AO43:AQ43)=0,"",SUM(AO43:AQ43)) -> 364420
A44: =Mapping!J44 -> 000104450000042 | B44: =Mapping!K44 -> High | C44: 47 | D44: ='Loan Book'!E47 -> Zikometso Smallholder Farmers Association | E44: ='Loan Book'!F47 -> Debt | F44: ='Loan Book'!G47 -> 44775 | G44: ='Loan Book'!H47 -> 45535 | H44: ='Loan Book'!I47 -> 2 | I44: ='Loan Book'!J47 -> 3 (Cap+Int) | J44: =IF('Loan Book'!K47="","",IF('Loan Book'!K47<1,'Loan Book'!K47*100,'Loan Book'!K47)) -> 10 | K44: ='Loan Book'!L47 -> 24000000 | L44: ='Loan Book'!M47 -> 11423340 | M44: ='Loan Book'!N47 -> 12576660 | N44: ='Loan Book'!O47 -> 11423340 | O44: ='Loan Book'!P47 -> 1494531.5 | P44: ='Loan Book'!Q47 -> -12917874 | Q44: ='Loan Book'!R47 -> -0.0032923882 | R44: ='Loan Book'!S47 -> 0 | ... T44: ='Loan Book'!U47 -> 0 | U44: ='Loan Book'!AC47 -> 0 | V44: ='Loan Book'!AE47 -> 0 | W44: =IFERROR(INDEX('E-Banker master'!$B$2:$B$186,MATCH($A44,'E-Banker master'!$A$2:$A$186,0)),"") -> Zikometso Smallholder Farmers Association | X44: =IFERROR(INDEX('E-Banker master'!$C$2:$C$186,MATCH($A44,'E-Banker master'!$A$2:$A$186,0)),"") -> 90 | Y44: =IFERROR(INDEX('E-Banker master'!$D$2:$D$186,MATCH($A44,'E-Banker master'!$A$2:$A$186,0)),"") -> 1050201 | Z44: =IFERROR(INDEX('E-Banker master'!$E$2:$E$186,MATCH($A44,'E-Banker master'!$A$2:$A$186,0)),"") -> H | AA44: =IFERROR(INDEX('E-Banker master'!$F$2:$F$186,MATCH($A44,'E-Banker master'!$A$2:$A$186,0)),"") -> S | AB44: =IFERROR(INDEX('E-Banker master'!$G$2:$G$186,MATCH($A44,'E-Banker master'!$A$2:$A$186,0)),"") -> 10 | AC44: =IFERROR(INDEX('E-Banker master'!$I$2:$I$186,MATCH($A44,'E-Banker master'!$A$2:$A$186,0)),"") -> 24000000 | AD44: =IFERROR(INDEX('E-Banker master'!$J$2:$J$186,MATCH($A44,'E-Banker master'!$A$2:$A$186,0)),"") -> 44775 | AE44: =IFERROR(INDEX('E-Banker master'!$K$2:$K$186,MATCH($A44,'E-Banker master'!$A$2:$A$186,0)),"") -> 45505 | AF44: =IFERROR(INDEX('E-Banker master'!$L$2:$L$186,MATCH($A44,'E-Banker master'!$A$2:$A$186,0)),"") -> 3 | AG44: =IFERROR(INDEX('E-Banker master'!$M$2:$M$186,MATCH($A44,'E-Banker master'!$A$2:$A$186,0)),"") -> 3 | AH44: =IFERROR(INDEX('E-Banker master'!$N$2:$N$186,MATCH($A44,'E-Banker master'!$A$2:$A$186,0)),"") -> 11423340 | AI44: =IFERROR(INDEX('E-Banker master'!$O$2:$O$186,MATCH($A44,'E-Banker master'!$A$2:$A$186,0)),"") -> 1489447.8 | AJ44: =IFERROR(INDEX('E-Banker master'!$P$2:$P$186,MATCH($A44,'E-Banker master'!$A$2:$A$186,0)),"") -> 8338.12 | AK44: =IF(OR(Q44="",AJ44=""),"",Q44-AJ44) -> -8338.1233 | AL44: 41 | AM44: =HYPERLINK("#'Amortisation and Repayments'!C2279","block 41") -> block 41 | AN44: =Mapping!X44 -> 0 | AO44: ='Loan Book'!AS47 -> 240000 | AP44: ='Loan Book'!AT47 -> 438340 | AR44: =AD44 -> 44775 | AS44: Y | AT44: Offer letter and Quickbooks | AU44: =IF(COUNT(AO44:AQ44)=0,"",SUM(AO44:AQ44)) -> 678340
A45: =Mapping!J45 -> 000104420000043 | B45: =Mapping!K45 -> High | C45: 48 | D45: ='Loan Book'!E48 -> The Food Empire Limited | E45: ='Loan Book'!F48 -> Debt | F45: ='Loan Book'!G48 -> 44785 | G45: ='Loan Book'!H48 -> 46265 | H45: ='Loan Book'!I48 -> 4 | I45: ='Loan Book'!J48 -> 6 ( Cap only) | J45: =IF('Loan Book'!K48="","",IF('Loan Book'!K48<1,'Loan Book'!K48*100,'Loan Book'!K48)) -> 31.1 | K45: ='Loan Book'!L48 -> 154724500 | L45: ='Loan Book'!M48 -> 154724500 | M45: ='Loan Book'!N48 -> 0 | N45: ='Loan Book'!O48 -> 154724500 | O45: ='Loan Book'!P48 -> 89061033 | P45: ='Loan Book'!Q48 -> -1.4291087e+08 | Q45: ='Loan Book'!R48 -> 1.0087466e+08 | R45: ='Loan Book'!S48 -> 0 | ... T45: ='Loan Book'!U48 -> 0 | U45: ='Loan Book'!AC48 -> 0 | V45: ='Loan Book'!AE48 -> 0 | W45: =IFERROR(INDEX('E-Banker master'!$B$2:$B$186,MATCH($A45,'E-Banker master'!$A$2:$A$186,0)),"") -> The Food Empire Limited | X45: =IFERROR(INDEX('E-Banker master'!$C$2:$C$186,MATCH($A45,'E-Banker master'!$A$2:$A$186,0)),"") -> 84 | Y45: =IFERROR(INDEX('E-Banker master'!$D$2:$D$186,MATCH($A45,'E-Banker master'!$A$2:$A$186,0)),"") -> 1050101 | Z45: =IFERROR(INDEX('E-Banker master'!$E$2:$E$186,MATCH($A45,'E-Banker master'!$A$2:$A$186,0)),"") -> F | AA45: =IFERROR(INDEX('E-Banker master'!$F$2:$F$186,MATCH($A45,'E-Banker master'!$A$2:$A$186,0)),"") -> P | AB45: =IFERROR(INDEX('E-Banker master'!$G$2:$G$186,MATCH($A45,'E-Banker master'!$A$2:$A$186,0)),"") -> 0 | AC45: =IFERROR(INDEX('E-Banker master'!$I$2:$I$186,MATCH($A45,'E-Banker master'!$A$2:$A$186,0)),"") -> 154724500 | AD45: =IFERROR(INDEX('E-Banker master'!$J$2:$J$186,MATCH($A45,'E-Banker master'!$A$2:$A$186,0)),"") -> 44746 | AE45: =IFERROR(INDEX('E-Banker master'!$K$2:$K$186,MATCH($A45,'E-Banker master'!$A$2:$A$186,0)),"") -> 46207 | AF45: =IFERROR(INDEX('E-Banker master'!$L$2:$L$186,MATCH($A45,'E-Banker master'!$A$2:$A$186,0)),"") -> 0 | AG45: =IFERROR(INDEX('E-Banker master'!$M$2:$M$186,MATCH($A45,'E-Banker master'!$A$2:$A$186,0)),"") -> 0 | AH45: =IFERROR(INDEX('E-Banker master'!$N$2:$N$186,MATCH($A45,'E-Banker master'!$A$2:$A$186,0)),"") -> 154724500 | AI45: =IFERROR(INDEX('E-Banker master'!$O$2:$O$186,MATCH($A45,'E-Banker master'!$A$2:$A$186,0)),"") -> 79996060 | AJ45: =IFERROR(INDEX('E-Banker master'!$P$2:$P$186,MATCH($A45,'E-Banker master'!$A$2:$A$186,0)),"") -> 1.0142784e+08 | AK45: =IF(OR(Q45="",AJ45=""),"",Q45-AJ45) -> -553176.55 | AL45: 42 | AM45: =HYPERLINK("#'Amortisation and Repayments'!C2318","block 42") -> block 42 | AN45: =Mapping!X45 -> 0 | AO45: ='Loan Book'!AS48 -> 2250000 | AP45: ='Loan Book'!AT48 -> 2474500 | AR45: =AD45 -> 44746 | AS45: Y | AT45: Offer letter and Quickbooks | AU45: =IF(COUNT(AO45:AQ45)=0,"",SUM(AO45:AQ45)) -> 4724500
A46: =Mapping!J46 -> 000104420000044 | B46: =Mapping!K46 -> High | C46: 49 | D46: ='Loan Book'!E49 -> Global Seeds Ltd | E46: ='Loan Book'!F49 -> Debt | F46: ='Loan Book'!G49 -> 44803 | G46: ='Loan Book'!H49 -> 45900 | H46: ='Loan Book'!I49 -> 3 | I46: ='Loan Book'!J49 -> 0 | J46: =IF('Loan Book'!K49="","",IF('Loan Book'!K49<1,'Loan Book'!K49*100,'Loan Book'!K49)) -> 29.8 | K46: ='Loan Book'!L49 -> 103225546 | L46: ='Loan Book'!M49 -> 103225546 | M46: ='Loan Book'!N49 -> 0 | N46: ='Loan Book'!O49 -> 103225546 | O46: ='Loan Book'!P49 -> 38887896 | P46: ='Loan Book'!Q49 -> -1.4211344e+08 | Q46: ='Loan Book'!R49 -> 0.0030568242 | R46: ='Loan Book'!S49 -> 0 | ... T46: ='Loan Book'!U49 -> 0 | U46: ='Loan Book'!AC49 -> 0 | V46: ='Loan Book'!AE49 -> 0 | W46: =IFERROR(INDEX('E-Banker master'!$B$2:$B$186,MATCH($A46,'E-Banker master'!$A$2:$A$186,0)),"") -> Global Seeds Limited FInES | X46: =IFERROR(INDEX('E-Banker master'!$C$2:$C$186,MATCH($A46,'E-Banker master'!$A$2:$A$186,0)),"") -> 84 | Y46: =IFERROR(INDEX('E-Banker master'!$D$2:$D$186,MATCH($A46,'E-Banker master'!$A$2:$A$186,0)),"") -> 1050101 | Z46: =IFERROR(INDEX('E-Banker master'!$E$2:$E$186,MATCH($A46,'E-Banker master'!$A$2:$A$186,0)),"") -> C | AA46: =IFERROR(INDEX('E-Banker master'!$F$2:$F$186,MATCH($A46,'E-Banker master'!$A$2:$A$186,0)),"") -> M | AB46: =IFERROR(INDEX('E-Banker master'!$G$2:$G$186,MATCH($A46,'E-Banker master'!$A$2:$A$186,0)),"") -> 33.7 | AC46: =IFERROR(INDEX('E-Banker master'!$I$2:$I$186,MATCH($A46,'E-Banker master'!$A$2:$A$186,0)),"") -> 103225546 | AD46: =IFERROR(INDEX('E-Banker master'!$J$2:$J$186,MATCH($A46,'E-Banker master'!$A$2:$A$186,0)),"") -> 44803 | AE46: =IFERROR(INDEX('E-Banker master'!$K$2:$K$186,MATCH($A46,'E-Banker master'!$A$2:$A$186,0)),"") -> 45898 | AF46: =IFERROR(INDEX('E-Banker master'!$L$2:$L$186,MATCH($A46,'E-Banker master'!$A$2:$A$186,0)),"") -> 0 | AG46: =IFERROR(INDEX('E-Banker master'!$M$2:$M$186,MATCH($A46,'E-Banker master'!$A$2:$A$186,0)),"") -> 0 | AH46: =IFERROR(INDEX('E-Banker master'!$N$2:$N$186,MATCH($A46,'E-Banker master'!$A$2:$A$186,0)),"") -> 0 | AI46: =IFERROR(INDEX('E-Banker master'!$O$2:$O$186,MATCH($A46,'E-Banker master'!$A$2:$A$186,0)),"") -> 0 | AJ46: =IFERROR(INDEX('E-Banker master'!$P$2:$P$186,MATCH($A46,'E-Banker master'!$A$2:$A$186,0)),"") -> 0 | AK46: =IF(OR(Q46="",AJ46=""),"",Q46-AJ46) -> 0.0030568242 | AL46: 43 | AM46: =HYPERLINK("#'Amortisation and Repayments'!C2384","block 43") -> block 43 | AN46: =Mapping!X46 -> 0 | AO46: ='Loan Book'!AS49 -> 1524750 | AP46: ='Loan Book'!AT49 -> 1700796 | AR46: =AD46 -> 44803 | AS46: Y | AT46: Offer letter and Quickbooks | AU46: =IF(COUNT(AO46:AQ46)=0,"",SUM(AO46:AQ46)) -> 3225546
A47: =Mapping!J47 -> 000104450000045 | B47: =Mapping!K47 -> High | C47: 50 | D47: ='Loan Book'!E50 -> Walusiya Investment | E47: ='Loan Book'!F50 -> Debt | F47: ='Loan Book'!G50 -> 44844 | G47: ='Loan Book'!H50 -> 45575 | H47: ='Loan Book'!I50 -> 2 | I47: ='Loan Book'!J50 -> 3 (Cap+Int) | J47: =IF('Loan Book'!K50="","",IF('Loan Book'!K50<1,'Loan Book'!K50*100,'Loan Book'!K50)) -> 10 | K47: ='Loan Book'!L50 -> 10000000 | L47: ='Loan Book'!M50 -> 10000000 | M47: ='Loan Book'!N50 -> 0 | N47: ='Loan Book'!O50 -> 10000000 | O47: ='Loan Book'!P50 -> 1284189.6 | P47: ='Loan Book'!Q50 -> -2140000 | Q47: ='Loan Book'!R50 -> 9144189.6 | R47: ='Loan Book'!S50 -> 8947194.2 | ... T47: ='Loan Book'!U50 -> 9144189.6 | U47: ='Loan Book'!AC50 -> 0 | V47: ='Loan Book'!AE50 -> 0 | W47: =IFERROR(INDEX('E-Banker master'!$B$2:$B$186,MATCH($A47,'E-Banker master'!$A$2:$A$186,0)),"") -> Walusiya Investment | X47: =IFERROR(INDEX('E-Banker master'!$C$2:$C$186,MATCH($A47,'E-Banker master'!$A$2:$A$186,0)),"") -> 90 | Y47: =IFERROR(INDEX('E-Banker master'!$D$2:$D$186,MATCH($A47,'E-Banker master'!$A$2:$A$186,0)),"") -> 1050201 | Z47: =IFERROR(INDEX('E-Banker master'!$E$2:$E$186,MATCH($A47,'E-Banker master'!$A$2:$A$186,0)),"") -> H | AA47: =IFERROR(INDEX('E-Banker master'!$F$2:$F$186,MATCH($A47,'E-Banker master'!$A$2:$A$186,0)),"") -> S | AB47: =IFERROR(INDEX('E-Banker master'!$G$2:$G$186,MATCH($A47,'E-Banker master'!$A$2:$A$186,0)),"") -> 10 | AC47: =IFERROR(INDEX('E-Banker master'!$I$2:$I$186,MATCH($A47,'E-Banker master'!$A$2:$A$186,0)),"") -> 10000000 | AD47: =IFERROR(INDEX('E-Banker master'!$J$2:$J$186,MATCH($A47,'E-Banker master'!$A$2:$A$186,0)),"") -> 44844 | AE47: =IFERROR(INDEX('E-Banker master'!$K$2:$K$186,MATCH($A47,'E-Banker master'!$A$2:$A$186,0)),"") -> 45574 | AF47: =IFERROR(INDEX('E-Banker master'!$L$2:$L$186,MATCH($A47,'E-Banker master'!$A$2:$A$186,0)),"") -> 3 | AG47: =IFERROR(INDEX('E-Banker master'!$M$2:$M$186,MATCH($A47,'E-Banker master'!$A$2:$A$186,0)),"") -> 3 | AH47: =IFERROR(INDEX('E-Banker master'!$N$2:$N$186,MATCH($A47,'E-Banker master'!$A$2:$A$186,0)),"") -> 10000000 | AI47: =IFERROR(INDEX('E-Banker master'!$O$2:$O$186,MATCH($A47,'E-Banker master'!$A$2:$A$186,0)),"") -> 1270903.7 | AJ47: =IFERROR(INDEX('E-Banker master'!$P$2:$P$186,MATCH($A47,'E-Banker master'!$A$2:$A$186,0)),"") -> 9371307 | AK47: =IF(OR(Q47="",AJ47=""),"",Q47-AJ47) -> -227117.43 | AL47: 44 | AM47: =HYPERLINK("#'Amortisation and Repayments'!C2437","block 44") -> block 44 | AN47: =Mapping!X47 -> 0 | AO47: ='Loan Book'!AS50 -> 100000 | AP47: ='Loan Book'!AT50 -> 212100 | AR47: =AD47 -> 44844 | AS47: Y | AT47: Offer letter and Quickbooks | AU47: =IF(COUNT(AO47:AQ47)=0,"",SUM(AO47:AQ47)) -> 312100
A48: =Mapping!J48 -> 000104450000046 | B48: =Mapping!K48 -> High | C48: 51 | D48: ='Loan Book'!E51 -> G&T General Dealers | E48: ='Loan Book'!F51 -> Debt | F48: ='Loan Book'!G51 -> 44844 | G48: ='Loan Book'!H51 -> 45575 | H48: ='Loan Book'!I51 -> 2 | I48: ='Loan Book'!J51 -> 3 (Cap+Int) | J48: =IF('Loan Book'!K51="","",IF('Loan Book'!K51<1,'Loan Book'!K51*100,'Loan Book'!K51)) -> 10 | K48: ='Loan Book'!L51 -> 12000000 | L48: ='Loan Book'!M51 -> 12000000 | M48: ='Loan Book'!N51 -> 0 | N48: ='Loan Book'!O51 -> 12000000 | O48: ='Loan Book'!P51 -> 1541027.5 | P48: ='Loan Book'!Q51 -> -6500000 | Q48: ='Loan Book'!R51 -> 7041027.5 | R48: ='Loan Book'!S51 -> 6162160.6 | ... T48: ='Loan Book'!U51 -> 7041027.5 | U48: ='Loan Book'!AC51 -> 0 | V48: ='Loan Book'!AE51 -> 0 | W48: =IFERROR(INDEX('E-Banker master'!$B$2:$B$186,MATCH($A48,'E-Banker master'!$A$2:$A$186,0)),"") -> G&T General Dealers | X48: =IFERROR(INDEX('E-Banker master'!$C$2:$C$186,MATCH($A48,'E-Banker master'!$A$2:$A$186,0)),"") -> 90 | Y48: =IFERROR(INDEX('E-Banker master'!$D$2:$D$186,MATCH($A48,'E-Banker master'!$A$2:$A$186,0)),"") -> 1050201 | Z48: =IFERROR(INDEX('E-Banker master'!$E$2:$E$186,MATCH($A48,'E-Banker master'!$A$2:$A$186,0)),"") -> H | AA48: =IFERROR(INDEX('E-Banker master'!$F$2:$F$186,MATCH($A48,'E-Banker master'!$A$2:$A$186,0)),"") -> S | AB48: =IFERROR(INDEX('E-Banker master'!$G$2:$G$186,MATCH($A48,'E-Banker master'!$A$2:$A$186,0)),"") -> 10 | AC48: =IFERROR(INDEX('E-Banker master'!$I$2:$I$186,MATCH($A48,'E-Banker master'!$A$2:$A$186,0)),"") -> 12000000 | AD48: =IFERROR(INDEX('E-Banker master'!$J$2:$J$186,MATCH($A48,'E-Banker master'!$A$2:$A$186,0)),"") -> 44844 | AE48: =IFERROR(INDEX('E-Banker master'!$K$2:$K$186,MATCH($A48,'E-Banker master'!$A$2:$A$186,0)),"") -> 45574 | AF48: =IFERROR(INDEX('E-Banker master'!$L$2:$L$186,MATCH($A48,'E-Banker master'!$A$2:$A$186,0)),"") -> 3 | AG48: =IFERROR(INDEX('E-Banker master'!$M$2:$M$186,MATCH($A48,'E-Banker master'!$A$2:$A$186,0)),"") -> 3 | AH48: =IFERROR(INDEX('E-Banker master'!$N$2:$N$186,MATCH($A48,'E-Banker master'!$A$2:$A$186,0)),"") -> 12000000 | AI48: =IFERROR(INDEX('E-Banker master'!$O$2:$O$186,MATCH($A48,'E-Banker master'!$A$2:$A$186,0)),"") -> 1509229.2 | AJ48: =IFERROR(INDEX('E-Banker master'!$P$2:$P$186,MATCH($A48,'E-Banker master'!$A$2:$A$186,0)),"") -> 7207696 | AK48: =IF(OR(Q48="",AJ48=""),"",Q48-AJ48) -> -166668.46 | AL48: 45 | AM48: =HYPERLINK("#'Amortisation and Repayments'!C2478","block 45") -> block 45 | AN48: =Mapping!X48 -> 0 | AO48: ='Loan Book'!AS51 -> 120000 | AP48: ='Loan Book'!AT51 -> 244420 | AR48: =AD48 -> 44844 | AS48: Y | AT48: Offer letter and Quickbooks | AU48: =IF(COUNT(AO48:AQ48)=0,"",SUM(AO48:AQ48)) -> 364420
A49: =Mapping!J49 -> 000104450000047 | B49: =Mapping!K49 -> High | C49: 52 | D49: ='Loan Book'!E52 -> Rose Harris Investment | E49: ='Loan Book'!F52 -> Debt | F49: ='Loan Book'!G52 -> 44852 | G49: ='Loan Book'!H52 -> 45583 | H49: ='Loan Book'!I52 -> 2 | I49: ='Loan Book'!J52 -> 3 (Cap+Int) | J49: =IF('Loan Book'!K52="","",IF('Loan Book'!K52<1,'Loan Book'!K52*100,'Loan Book'!K52)) -> 10 | K49: ='Loan Book'!L52 -> 24000000 | L49: ='Loan Book'!M52 -> 24000000 | M49: ='Loan Book'!N52 -> 0 | N49: ='Loan Book'!O52 -> 24000000 | O49: ='Loan Book'!P52 -> 2453483.6 | P49: ='Loan Book'!Q52 -> -26454000 | Q49: ='Loan Book'!R52 -> 0 | R49: ='Loan Book'!S52 -> 0 | ... T49: ='Loan Book'!U52 -> 0 | U49: ='Loan Book'!AC52 -> 0 | V49: ='Loan Book'!AE52 -> 0 | W49: =IFERROR(INDEX('E-Banker master'!$B$2:$B$186,MATCH($A49,'E-Banker master'!$A$2:$A$186,0)),"") -> Rose Harris Investment | X49: =IFERROR(INDEX('E-Banker master'!$C$2:$C$186,MATCH($A49,'E-Banker master'!$A$2:$A$186,0)),"") -> 90 | Y49: =IFERROR(INDEX('E-Banker master'!$D$2:$D$186,MATCH($A49,'E-Banker master'!$A$2:$A$186,0)),"") -> 1050201 | Z49: =IFERROR(INDEX('E-Banker master'!$E$2:$E$186,MATCH($A49,'E-Banker master'!$A$2:$A$186,0)),"") -> C | AA49: =IFERROR(INDEX('E-Banker master'!$F$2:$F$186,MATCH($A49,'E-Banker master'!$A$2:$A$186,0)),"") -> S | AB49: =IFERROR(INDEX('E-Banker master'!$G$2:$G$186,MATCH($A49,'E-Banker master'!$A$2:$A$186,0)),"") -> 10 | AC49: =IFERROR(INDEX('E-Banker master'!$I$2:$I$186,MATCH($A49,'E-Banker master'!$A$2:$A$186,0)),"") -> 24000000 | AD49: =IFERROR(INDEX('E-Banker master'!$J$2:$J$186,MATCH($A49,'E-Banker master'!$A$2:$A$186,0)),"") -> 44852 | AE49: =IFERROR(INDEX('E-Banker master'!$K$2:$K$186,MATCH($A49,'E-Banker master'!$A$2:$A$186,0)),"") -> 45582 | AF49: =IFERROR(INDEX('E-Banker master'!$L$2:$L$186,MATCH($A49,'E-Banker master'!$A$2:$A$186,0)),"") -> 3 | AG49: =IFERROR(INDEX('E-Banker master'!$M$2:$M$186,MATCH($A49,'E-Banker master'!$A$2:$A$186,0)),"") -> 3 | AH49: =IFERROR(INDEX('E-Banker master'!$N$2:$N$186,MATCH($A49,'E-Banker master'!$A$2:$A$186,0)),"") -> 0 | AI49: =IFERROR(INDEX('E-Banker master'!$O$2:$O$186,MATCH($A49,'E-Banker master'!$A$2:$A$186,0)),"") -> 0 | AJ49: =IFERROR(INDEX('E-Banker master'!$P$2:$P$186,MATCH($A49,'E-Banker master'!$A$2:$A$186,0)),"") -> 0 | AK49: =IF(OR(Q49="",AJ49=""),"",Q49-AJ49) -> 0 | AL49: 46 | AM49: =HYPERLINK("#'Amortisation and Repayments'!C2519","block 46") -> block 46 | AN49: =Mapping!X49 -> 0 | AO49: ='Loan Book'!AS52 -> 240000 | AP49: ='Loan Book'!AT52 -> 438340 | AR49: =AD49 -> 44852 | AS49: Y | AT49: Offer letter and Quickbooks | AU49: =IF(COUNT(AO49:AQ49)=0,"",SUM(AO49:AQ49)) -> 678340
A50: =Mapping!J50 -> 000104450000048 | B50: =Mapping!K50 -> High | C50: 53 | D50: ='Loan Book'!E53 -> Kaning'a General Dealer | E50: ='Loan Book'!F53 -> Debt | F50: ='Loan Book'!G53 -> 44861 | G50: ='Loan Book'!H53 -> 45592 | H50: ='Loan Book'!I53 -> 2 | I50: ='Loan Book'!J53 -> 3 (Cap+Int) | J50: =IF('Loan Book'!K53="","",IF('Loan Book'!K53<1,'Loan Book'!K53*100,'Loan Book'!K53)) -> 10 | K50: ='Loan Book'!L53 -> 24000000 | L50: ='Loan Book'!M53 -> 24000000 | M50: ='Loan Book'!N53 -> 0 | N50: ='Loan Book'!O53 -> 24000000 | O50: ='Loan Book'!P53 -> 2959020.5 | P50: ='Loan Book'!Q53 -> -26989000 | Q50: ='Loan Book'!R53 -> 0 | R50: ='Loan Book'!S53 -> 0 | ... T50: ='Loan Book'!U53 -> 0 | U50: ='Loan Book'!AC53 -> 0 | V50: ='Loan Book'!AE53 -> 0 | W50: =IFERROR(INDEX('E-Banker master'!$B$2:$B$186,MATCH($A50,'E-Banker master'!$A$2:$A$186,0)),"") -> KANING'A GENERAL DEALER | X50: =IFERROR(INDEX('E-Banker master'!$C$2:$C$186,MATCH($A50,'E-Banker master'!$A$2:$A$186,0)),"") -> 90 | Y50: =IFERROR(INDEX('E-Banker master'!$D$2:$D$186,MATCH($A50,'E-Banker master'!$A$2:$A$186,0)),"") -> 1050201 | Z50: =IFERROR(INDEX('E-Banker master'!$E$2:$E$186,MATCH($A50,'E-Banker master'!$A$2:$A$186,0)),"") -> H | AA50: =IFERROR(INDEX('E-Banker master'!$F$2:$F$186,MATCH($A50,'E-Banker master'!$A$2:$A$186,0)),"") -> S | AB50: =IFERROR(INDEX('E-Banker master'!$G$2:$G$186,MATCH($A50,'E-Banker master'!$A$2:$A$186,0)),"") -> 10 | AC50: =IFERROR(INDEX('E-Banker master'!$I$2:$I$186,MATCH($A50,'E-Banker master'!$A$2:$A$186,0)),"") -> 24000000 | AD50: =IFERROR(INDEX('E-Banker master'!$J$2:$J$186,MATCH($A50,'E-Banker master'!$A$2:$A$186,0)),"") -> 44861 | AE50: =IFERROR(INDEX('E-Banker master'!$K$2:$K$186,MATCH($A50,'E-Banker master'!$A$2:$A$186,0)),"") -> 45591 | AF50: =IFERROR(INDEX('E-Banker master'!$L$2:$L$186,MATCH($A50,'E-Banker master'!$A$2:$A$186,0)),"") -> 3 | AG50: =IFERROR(INDEX('E-Banker master'!$M$2:$M$186,MATCH($A50,'E-Banker master'!$A$2:$A$186,0)),"") -> 3 | AH50: =IFERROR(INDEX('E-Banker master'!$N$2:$N$186,MATCH($A50,'E-Banker master'!$A$2:$A$186,0)),"") -> 24000000 | AI50: =IFERROR(INDEX('E-Banker master'!$O$2:$O$186,MATCH($A50,'E-Banker master'!$A$2:$A$186,0)),"") -> 2895712.9 | AJ50: =IFERROR(INDEX('E-Banker master'!$P$2:$P$186,MATCH($A50,'E-Banker master'!$A$2:$A$186,0)),"") -> 1685.92 | AK50: =IF(OR(Q50="",AJ50=""),"",Q50-AJ50) -> -1685.92 | AL50: 47 | AM50: =HYPERLINK("#'Amortisation and Repayments'!C2561","block 47") -> block 47 | AN50: =Mapping!X50 -> 0 | AO50: ='Loan Book'!AS53 -> 240000 | AP50: ='Loan Book'!AT53 -> 438340 | AR50: =AD50 -> 44861 | AS50: Y | AT50: Offer letter and Quickbooks | AU50: =IF(COUNT(AO50:AQ50)=0,"",SUM(AO50:AQ50)) -> 678340
A51: =Mapping!J51 -> 000104450000049 | B51: =Mapping!K51 -> High | C51: 54 | D51: ='Loan Book'!E54 -> Uchi Conservation Limited | E51: ='Loan Book'!F54 -> Debt | F51: ='Loan Book'!G54 -> 44867 | G51: ='Loan Book'!H54 -> 45598 | H51: ='Loan Book'!I54 -> 2 | I51: ='Loan Book'!J54 -> 6 (Cap+Int) | J51: =IF('Loan Book'!K54="","",IF('Loan Book'!K54<1,'Loan Book'!K54*100,'Loan Book'!K54)) -> 10 | K51: ='Loan Book'!L54 -> 10000000 | L51: ='Loan Book'!M54 -> 10000000 | M51: ='Loan Book'!N54 -> 0 | N51: ='Loan Book'!O54 -> 10000000 | O51: ='Loan Book'!P54 -> 1303763.2 | P51: ='Loan Book'!Q54 -> -4605000 | Q51: ='Loan Book'!R54 -> 6698763.2 | R51: ='Loan Book'!S54 -> 6074397.6 | ... T51: ='Loan Book'!U54 -> 6164727.1 | U51: ='Loan Book'!AC54 -> 0 | V51: ='Loan Book'!AE54 -> 0 | W51: =IFERROR(INDEX('E-Banker master'!$B$2:$B$186,MATCH($A51,'E-Banker master'!$A$2:$A$186,0)),"") -> Uchi Conservation Limited | X51: =IFERROR(INDEX('E-Banker master'!$C$2:$C$186,MATCH($A51,'E-Banker master'!$A$2:$A$186,0)),"") -> 90 | Y51: =IFERROR(INDEX('E-Banker master'!$D$2:$D$186,MATCH($A51,'E-Banker master'!$A$2:$A$186,0)),"") -> 1050201 | Z51: =IFERROR(INDEX('E-Banker master'!$E$2:$E$186,MATCH($A51,'E-Banker master'!$A$2:$A$186,0)),"") -> D | AA51: =IFERROR(INDEX('E-Banker master'!$F$2:$F$186,MATCH($A51,'E-Banker master'!$A$2:$A$186,0)),"") -> S | AB51: =IFERROR(INDEX('E-Banker master'!$G$2:$G$186,MATCH($A51,'E-Banker master'!$A$2:$A$186,0)),"") -> 10 | AC51: =IFERROR(INDEX('E-Banker master'!$I$2:$I$186,MATCH($A51,'E-Banker master'!$A$2:$A$186,0)),"") -> 10000000 | AD51: =IFERROR(INDEX('E-Banker master'!$J$2:$J$186,MATCH($A51,'E-Banker master'!$A$2:$A$186,0)),"") -> 44867 | AE51: =IFERROR(INDEX('E-Banker master'!$K$2:$K$186,MATCH($A51,'E-Banker master'!$A$2:$A$186,0)),"") -> 45597 | AF51: =IFERROR(INDEX('E-Banker master'!$L$2:$L$186,MATCH($A51,'E-Banker master'!$A$2:$A$186,0)),"") -> 6 | AG51: =IFERROR(INDEX('E-Banker master'!$M$2:$M$186,MATCH($A51,'E-Banker master'!$A$2:$A$186,0)),"") -> 6 | AH51: =IFERROR(INDEX('E-Banker master'!$N$2:$N$186,MATCH($A51,'E-Banker master'!$A$2:$A$186,0)),"") -> 10000000 | AI51: =IFERROR(INDEX('E-Banker master'!$O$2:$O$186,MATCH($A51,'E-Banker master'!$A$2:$A$186,0)),"") -> 1264076.7 | AJ51: =IFERROR(INDEX('E-Banker master'!$P$2:$P$186,MATCH($A51,'E-Banker master'!$A$2:$A$186,0)),"") -> 6882460.2 | AK51: =IF(OR(Q51="",AJ51=""),"",Q51-AJ51) -> -183697.04 | AL51: 48 | AM51: =HYPERLINK("#'Amortisation and Repayments'!C2605","block 48") -> block 48 | AN51: =Mapping!X51 -> 0 | AO51: ='Loan Book'!AS54 -> 100000 | AP51: ='Loan Book'!AT54 -> 212100 | AR51: =AD51 -> 44867 | AS51: Y | AT51: Offer letter and Quickbooks | AU51: =IF(COUNT(AO51:AQ51)=0,"",SUM(AO51:AQ51)) -> 312100
