Workbook
Name \: #REF!
Name \0: #REF!
Name \a: #REF!
Name \B: #REF!
Name \B_49_65_: #REF!
Name \BS: #REF!
Name \C: #REF!
Name \C_66_73_: #REF!
Name \d: #REF!
Name \D_SUMMARY_: #REF!
Name \E: #REF!
Name \I: #REF!
Name \M: #REF!
Name \P: #REF!
Name \R: #REF!
Name _______________________F375205: [1]Accounts!#REF!
Name ______________________F375205: [1]Accounts!#REF!
Name _____________________F375205: [1]Accounts!#REF!
Name ____________________F375205: [1]Accounts!#REF!
Name ___________________F375205: [1]Accounts!#REF!
Name __________________F375205: [1]Accounts!#REF!
Name _________________F375205: [2]Accounts!#REF!
Name ________________F375205: [2]Accounts!#REF!
Name _______________F375205: [2]Accounts!#REF!
Name ______________F375205: [3]Accounts!#REF!
Name _____________F375205: [3]Accounts!#REF!
Name _____________vat2: #REF!
Name ____________F375205: [1]Accounts!#REF!
Name ____________vat2: #REF!
Name ___________F375205: [1]Accounts!#REF!
Name ___________vat2: #REF!
Name __________F375205: [1]Accounts!#REF!
Name __________vat2: #REF!
Name _________F375205: [1]Accounts!#REF!
Name _________vat2: #REF!
Name ________F375205: [4]Accounts!#REF!
Name ________vat2: #REF!
Name _______DAT1: '[5]Auditors Assoc'!$A$4:$A$438
Name _______DAT10: '[5]Auditors Assoc'!#REF!
Name _______DAT11: '[5]Auditors Assoc'!#REF!
Name _______DAT12: '[5]Auditors Assoc'!#REF!
Name _______DAT13: '[5]Auditors Assoc'!#REF!
Name _______DAT14: '[5]Auditors Assoc'!#REF!
Name _______DAT15: '[5]Auditors Assoc'!#REF!
Name _______DAT16: '[5]Auditors Assoc'!#REF!
Name _______DAT17: '[5]Auditors Assoc'!$F$4:$F$438
Name _______DAT2: '[5]Auditors Assoc'!$B$4:$B$438
Name _______DAT3: '[5]Auditors Assoc'!#REF!
Name _______DAT4: '[5]Auditors Assoc'!#REF!
Name _______DAT5: '[5]Auditors Assoc'!$C$4:$C$438
Name _______DAT6: '[5]Auditors Assoc'!$D$4:$D$438
Name _______DAT7: '[5]Auditors Assoc'!#REF!
Name _______DAT8: '[5]Auditors Assoc'!#REF!
Name _______DAT9: '[5]Auditors Assoc'!$E$4:$E$438
Name _______F375205: [6]Accounts!#REF!
Name _______vat2: #REF!
Name ______DAT1: '[5]Auditors Assoc'!$A$4:$A$438
Name ______DAT10: '[5]Auditors Assoc'!#REF!
Name ______DAT11: '[5]Auditors Assoc'!#REF!
Name ______DAT12: '[5]Auditors Assoc'!#REF!

Sheet FINAL AFS TB as of 19th Mar 26
C1: Initial submitted to Auditors | D1: Final tie to AFS | E1: Journals Adjustments
C2: 45992 | D2: 45992 | E2: 45992
B3: ='TB December 2025 '!V3 -> 1001 · CDH Inv Bank 0050401042201 | C3: ='Initial TB Submitted to Auditor'!C3 -> 68950246 | D3: 68950246 | E3: =D3-C3 -> 0
B4: ='TB December 2025 '!V4 -> 1002 · CDH Inv Bank PIA 0050401044100 | C4: ='Initial TB Submitted to Auditor'!C4 -> -3276701.7 | D4: -3276701.7 | E4: =D4-C4 -> 0
B5: ='TB December 2025 '!V5 -> 1003 · FDI Project-Payments | C5: ='Initial TB Submitted to Auditor'!C5 -> 0 | D5: 0 | E5: =D5-C5 -> 0
B6: ='TB December 2025 '!V6 -> 1005 · FDI Project payment-USD | C6: ='Initial TB Submitted to Auditor'!C6 -> -4.67 | D6: -4.67 | E6: =D6-C6 -> 0
B7: ='TB December 2025 '!V7 -> 1006 · Petty cash | C7: ='Initial TB Submitted to Auditor'!C7 -> -71515.78 | D7: -71515.78 | E7: =D7-C7 -> 0
B8: ='TB December 2025 '!V8 -> 1012 · Money Market:1008 · Alliance Capital | C8: ='Initial TB Submitted to Auditor'!C8 -> 0 | D8: 0 | E8: =D8-C8 -> 0
B9: ='TB December 2025 '!V9 -> 1012 · Money Market:1009 · CDHIB Fixed Deposit | C9: ='Initial TB Submitted to Auditor'!C9 -> -1.8777713e+09 | D9: -1.8777713e+09 | E9: =D9-C9 -> 0
B10: ='TB December 2025 '!V10 -> 1012 · Money Market:1010 · CDHIB Call Account | C10: ='Initial TB Submitted to Auditor'!C10 -> -33611611 | D10: -33611611 | E10: =D10-C10 -> 0
B11: ='TB December 2025 '!V11 -> 1012 · Money Market:1011 · FDH Discount House | C11: ='Initial TB Submitted to Auditor'!C11 -> -2.6970178e+09 | D11: -2.6970178e+09 | E11: =D11-C11 -> 0
B12: ='TB December 2025 '!V12 -> 1012 · Money Market:1013 · MyBucks | C12: ='Initial TB Submitted to Auditor'!C12 -> 0 | D12: 0 | E12: =D12-C12 -> 0
B13: ='TB December 2025 '!V13 -> 1012 · Money Market:1014 · Continental Asset Management | C13: ='Initial TB Submitted to Auditor'!C13 -> -1.599258e+09 | D13: -1.599258e+09 | E13: =D13-C13 -> 0
B14: ='TB December 2025 '!V14 -> 1012 · Money Market:1015 · NICO-INV1 | C14: ='Initial TB Submitted to Auditor'!C14 -> 0 | D14: 0 | E14: =D14-C14 -> 0
... B42: ='TB December 2025 '!V42 -> 1048 · CDHIB MAIIC AGRA (MK) | C42: ='Initial TB Submitted to Auditor'!C42 -> -36188936 | D42: -36188936 | E42: =D42-C42 -> 0
B43: ='TB December 2025 '!V43 -> 1030 · Partial Credit Guarantee Fund | C43: ='Initial TB Submitted to Auditor'!C43 -> -71808009 | D43: 0 | E43: =D43-C43 -> 71808009 | F43: Reversal of paid agcom fees
B44: ='TB December 2025 '!V44 -> 1039 · Accrued Coupon Settlements | C44: ='Initial TB Submitted to Auditor'!C44 -> -5.3820299e+08 | D44: -5.3820299e+08 | E44: =D44-C44 -> 0
B45: ='TB December 2025 '!V45 -> 1040 · Accrued Interest Income- MM | C45: ='Initial TB Submitted to Auditor'!C45 -> -6.2353678e+08 | D45: -6.38507e+08 | E45: =D45-C45 -> -14970225 | F45: MM Interest adjusment
B46: ='TB December 2025 '!V46 -> 1041 · Accrued Interest income- TNote | C46: ='Initial TB Submitted to Auditor'!C46 -> 0 | D46: 0 | E46: =D46-C46 -> 0
B47: ='TB December 2025 '!V47 -> 1042 · Accrued Interest Income- T/Bill | C47: ='Initial TB Submitted to Auditor'!C47 -> 0 | D47: 0 | E47: =D47-C47 -> 0
B48: ='TB December 2025 '!V48 -> 1049 · Term Loan - USD | C48: ='Initial TB Submitted to Auditor'!C48 -> 0 | D48: 0 | E48: =D48-C48 -> 0
B49: ='TB December 2025 '!V49 -> 1050 · Term Loans | C49: ='Initial TB Submitted to Auditor'!C49 -> -1.4702425e+10 | D49: -1.4702425e+10 | E49: =D49-C49 -> 0
B50: ='TB December 2025 '!V50 -> 1053 · Accounts Receivables | C50: ='Initial TB Submitted to Auditor'!C50 -> -2.6638798e+08 | D50: -9.4894188e+08 | E50: =D50-C50 -> -6.825539e+08 | F50: MAIIC Interest Receivable net of Impairment
B51: ='TB December 2025 '!V51 -> 1054 · Mega Farms-Fertilizers-Loan | C51: ='Initial TB Submitted to Auditor'!C51 -> -3.3189976e+10 | D51: -3.3189976e+10 | E51: =D51-C51 -> 0
B52: ='TB December 2025 '!V52 -> 1055 · Mega Farms-Seed Loans | C52: ='Initial TB Submitted to Auditor'!C52 -> -7.5941669e+09 | D52: -7.5941669e+09 | E52: =D52-C52 -> 0
B53: ='TB December 2025 '!V53 -> 1056 · Mega Farms-Working Capital Loan | C53: ='Initial TB Submitted to Auditor'!C53 -> -6.6623228e+08 | D53: -6.6623228e+08 | E53: =D53-C53 -> 0
B54: ='TB December 2025 '!V54 -> 1057 · Mega Farms-Equipment Loan | C54: ='Initial TB Submitted to Auditor'!C54 -> -1.803483e+09 | D54: -1.803483e+09 | E54: =D54-C54 -> 0
B55: ='TB December 2025 '!V55 -> 1058 · Mega Farms-Irrigation Loan | C55: ='Initial TB Submitted to Auditor'!C55 -> -1.9758676e+09 | D55: -1.9758676e+09 | E55: =D55-C55 -> 0
B56: ='TB December 2025 '!V56 -> 1059 · Mega Farm Loans Interest-Capex | C56: ='Initial TB Submitted to Auditor'!C56 -> -2.1151775e+08 | D56: 2269530.6 | E56: =D56-C56 -> 2.1378728e+08 | F56: Transfer of MAIIC Interest to Receivables
B57: ='TB December 2025 '!V57 -> 1060 · Mega Farm Loans Interest-Fertil | C57: ='Initial TB Submitted to Auditor'!C57 -> -5.153939e+09 | D57: -3.1419031e+09 | E57: =D57-C57 -> 2.0120359e+09 | F57: Transfer of MAIIC Interest to Receivables
B58: ='TB December 2025 '!V58 -> 1061 · Mega Farm Loans Interest-OPEX | C58: ='Initial TB Submitted to Auditor'!C58 -> -4.3648824e+08 | D58: -3.9382455e+08 | E58: =D58-C58 -> 42663694 | F58: Transfer of MAIIC Interest to Receivables
B59: ='TB December 2025 '!V59 -> 1062 · Mega Farm Loans Interest-Seed | C59: ='Initial TB Submitted to Auditor'!C59 -> -1.2029564e+09 | D59: -7.905338e+08 | E59: =D59-C59 -> 4.1242264e+08 | F59: Transfer of MAIIC Interest to Receivables
B60: ='TB December 2025 '!V60 -> 1063 · Mega Farm - Pesticides Loan | C60: ='Initial TB Submitted to Auditor'!C60 -> -1.9370391e+09 | D60: -1.9370391e+09 | E60: =D60-C60 -> 0
B61: ='TB December 2025 '!V61 -> 1066 · ECL Megafarm Loans | C61: ='Initial TB Submitted to Auditor'!C61 -> -4.3218781e+10 | D61: -4.0944381e+10 | E61: =D61-C61 -> 2.2744004e+09 | F61: ECL Adjustment
B62: ='TB December 2025 '!V62 -> 1067 · Mega Farm Loans Interest-Pestic | C62: ='Initial TB Submitted to Auditor'!C62 -> -3.0853077e+08 | D62: -2.0172964e+08 | E62: =D62-C62 -> 1.0680113e+08 | F62: Transfer of MAIIC Interest to Receivables
B63: ='TB December 2025 '!V63 -> 1051 · Employee loan and advances | C63: ='Initial TB Submitted to Auditor'!C63 -> -3.5151237e+08 | D63: -3.5151237e+08 | E63: =D63-C63 -> 0
B64: ='TB December 2025 '!V64 -> 1052 · Prepaid expenses | C64: ='Initial TB Submitted to Auditor'!C64 -> -58392454 | D64: -58392454 | E64: =D64-C64 -> 0
B65: ='TB December 2025 '!V65 -> 1070. Mega Farms Receivable- ADMARC | C65: ='Initial TB Submitted to Auditor'!C65 -> -3.1017893e+09 | D65: -2.0844024e+09 | E65: =D65-C65 -> 1.0173869e+09 | F65: Fair Value Adjustment on Maize
B66: ='TB December 2025 '!V66 -> 1071. Mega Farms Receivable- NFRA | C66: ='Initial TB Submitted to Auditor'!C66 -> -70177833 | D66: -45345677 | E66: =D66-C66 -> 24832156 | F66: Fair Value Adjustment on Maize
B67: ='TB December 2025 '!V67 -> 1074 . Mega Farm Receivable ACE Agriculture Limited | C67: ='Initial TB Submitted to Auditor'!C67 -> -4.2913496e+08 | D67: -2.8837869e+08 | E67: =D67-C67 -> 1.4075627e+08 | F67: Fair Value Adjustment on Maize
B68: ='TB December 2025 '!V68 -> 1100 · Cash Collateral | C68: ='Initial TB Submitted to Auditor'!C68 -> 7000000 | D68: 7000000 | E68: =D68-C68 -> 0
B69: ='TB December 2025 '!V69 -> 1210 · Cash passport card | C69: ='Initial TB Submitted to Auditor'!C69 -> 0 | D69: 0 | E69: =D69-C69 -> 0
B70: ='TB December 2025 '!V70 -> 1310 · Prepaid Insurance | C70: ='Initial TB Submitted to Auditor'!C70 -> -81652611 | D70: -81652611 | E70: =D70-C70 -> 0
B71: ='TB December 2025 '!V71 -> 1320 · Interest Suspense | C71: ='Initial TB Submitted to Auditor'!C71 -> 21865867 | D71: 0 | E71: =D71-C71 -> -21865867 | F71: Reversal of Interest in Suspense
B72: ='TB December 2025 '!V72 -> 1321 · Capital Raising Prepayment | C72: ='Initial TB Submitted to Auditor'!C72 -> 0 | D72: 0 | E72: =D72-C72 -> 0
B73: ='TB December 2025 '!V73 -> 1877 · Prepaid Loan Repayments Account | C73: ='Initial TB Submitted to Auditor'!C73 -> 0 | D73: 0 | E73: =D73-C73 -> 0
B74: ='TB December 2025 '!V74 -> 1500 · Furniture and Fixtures | C74: ='Initial TB Submitted to Auditor'!C74 -> -460175 | D74: -460175 | E74: =D74-C74 -> 0
B75: ='TB December 2025 '!V75 -> 1500 · Furniture and Fixtures:1501 · Cost | C75: ='Initial TB Submitted to Auditor'!C75 -> -1.1332595e+08 | D75: -1.1332595e+08 | E75: =D75-C75 -> 0
B76: ='TB December 2025 '!V76 -> 1500 · Furniture and Fixtures:1502 · Depreciation | C76: ='Initial TB Submitted to Auditor'!C76 -> 94359370 | D76: 94359370 | E76: =D76-C76 -> 0
B77: ='TB December 2025 '!V77 -> 1510 · Computer Equipment:1511 · Cost | C77: ='Initial TB Submitted to Auditor'!C77 -> -2.0782183e+08 | D77: -2.0782183e+08 | E77: =D77-C77 -> 0
B78: ='TB December 2025 '!V78 -> 1510 · Computer Equipment:1512 · Depreciation | C78: ='Initial TB Submitted to Auditor'!C78 -> 1.1016554e+08 | D78: 1.1016554e+08 | E78: =D78-C78 -> 0
B79: ='TB December 2025 '!V79 -> 1520 · Office Equipment:1521 · Cost | C79: ='Initial TB Submitted to Auditor'!C79 -> -53624127 | D79: -53624127 | E79: =D79-C79 -> 0
B80: ='TB December 2025 '!V80 -> 1520 · Office Equipment:1522 · Depreciation | C80: ='Initial TB Submitted to Auditor'!C80 -> 28875489 | D80: 28875489 | E80: =D80-C80 -> 0
B81: ='TB December 2025 '!V81 -> 1530 · Motor Vehicles:1531 · Cost | C81: ='Initial TB Submitted to Auditor'!C81 -> -8.018451e+08 | D81: -8.018451e+08 | E81: =D81-C81 -> 0
B82: ='TB December 2025 '!V82 -> 1530 · Motor Vehicles:1532 · Depreciation | C82: ='Initial TB Submitted to Auditor'!C82 -> 3.2174819e+08 | D82: 3.2174819e+08 | E82: =D82-C82 -> 0
B83: ='TB December 2025 '!V83 -> 1545 · Software | C83: ='Initial TB Submitted to Auditor'!C83 -> 0 | D83: 0 | E83: =D83-C83 -> 0
B84: ='TB December 2025 '!V84 -> 1545 · Software:1546 · Cost | C84: ='Initial TB Submitted to Auditor'!C84 -> -1.8970459e+09 | D84: -2.2019879e+09 | E84: =D84-C84 -> -3.0494203e+08 | F84: Core Operating System invoice
B85: ='TB December 2025 '!V85 -> 1545 · Software:1547 · Depreciation | C85: ='Initial TB Submitted to Auditor'!C85 -> 2.9260368e+08 | D85: 3.3834499e+08 | E85: =D85-C85 -> 45741305 | F85: Additional amortisation
B86: ='TB December 2025 '!V86 -> 1595 · Right of Use:1596 · Cost | C86: ='Initial TB Submitted to Auditor'!C86 -> 0 | D86: 0 | E86: =D86-C86 -> 0
B87: ='TB December 2025 '!V87 -> 1595 · Right of Use:1597 · Amortisation/ Depreciation | C87: ='Initial TB Submitted to Auditor'!C87 -> 0 | D87: 0 | E87: =D87-C87 -> 0
B88: ='TB December 2025 '!V88 -> 1548 · Amortization | C88: ='Initial TB Submitted to Auditor'!C88 -> 0 | D88: 0 | E88: =D88-C88 -> 0
B89: ='TB December 2025 '!V89 -> 1549 · WIP | C89: ='Initial TB Submitted to Auditor'!C89 -> 1.4857679e+08 | D89: 1.4857679e+08 | E89: =D89-C89 -> 0
B90: ='TB December 2025 '!V90 -> 1871 · Undrawn Commitment-MAIIC | C90: ='Initial TB Submitted to Auditor'!C90 -> -1.4404147e+09 | D90: -1.4404147e+09 | E90: =D90-C90 -> 0
B91: ='TB December 2025 '!V91 -> 1872 · Undrawn Commitments-FInES | C91: ='Initial TB Submitted to Auditor'!C91 -> 2.8041628e+08 | D91: 2.8041628e+08 | E91: =D91-C91 -> 0
B92: ='TB December 2025 '!V92 -> 1873 · Guarantees MAIIC | C92: ='Initial TB Submitted to Auditor'!C92 -> -40847815 | D92: -40847815 | E92: =D92-C92 -> 0
B93: ='TB December 2025 '!V93 -> 1874 · Guarantees -FInES | C93: ='Initial TB Submitted to Auditor'!C93 -> -1338483000 | D93: -1338483000 | E93: =D93-C93 -> 0
B94: ='TB December 2025 '!V94 -> 1875 · Guarantees -AGCOM | C94: ='Initial TB Submitted to Auditor'!C94 -> -170064000 | D94: -170064000 | E94: =D94-C94 -> 0
B95: ='TB December 2025 '!V95 -> 1876 · ECL Write Offs | C95: ='Initial TB Submitted to Auditor'!C95 -> 1.6042212e+08 | D95: 1.6042212e+08 | E95: =D95-C95 -> 0
B96: ='TB December 2025 '!V96 -> 2000 · Accounts Payable | C96: ='Initial TB Submitted to Auditor'!C96 -> 22012167 | D96: 22012167 | E96: =D96-C96 -> 0
B97: ='TB December 2025 '!V97 -> 2001 · Accounts Payable - USD | C97: ='Initial TB Submitted to Auditor'!C97 -> 0 | D97: 0 | E97: =D97-C97 -> 0
... B103: ='TB December 2025 '!V103 -> 2040 · T-Bill Provision | C103: ='Initial TB Submitted to Auditor'!C103 -> 0 | D103: 0 | E103: =D103-C103 -> 0
B104: ='TB December 2025 '!V104 -> 2041 · ECL Preference Shares | C104: ='Initial TB Submitted to Auditor'!C104 -> 1.1755523e+08 | D104: 1.4076907e+08 | E104: =D104-C104 -> 23213844 | F104: ECL Adjustment
B105: ='TB December 2025 '!V105 -> 2042 · ECL Staff Loans | C105: ='Initial TB Submitted to Auditor'!C105 -> 3893096.5 | D105: 17745222 | E105: =D105-C105 -> 13852125 | F105: ECL Adjustment
B106: ='TB December 2025 '!V106 -> 2043 · ECL WHT Receivables | C106: ='Initial TB Submitted to Auditor'!C106 -> 573386.67 | D106: 573386.67 | E106: =D106-C106 -> 0
B107: ='TB December 2025 '!V107 -> 2051 · Accruals and Provisions | C107: ='Initial TB Submitted to Auditor'!C107 -> 2.0617429e+08 | D107: 1.6521329e+08 | E107: =D107-C107 -> -40961000 | F107: reversal of excess accruals
B108: ='TB December 2025 '!V108 -> 2052 · Malawi Revenue Authority- Other | C108: ='Initial TB Submitted to Auditor'!C108 -> -1.9796796e+09 | D108: -2.0081406e+09 | E108: =D108-C108 -> -28461031 | F108: tax adjustment on interest income
B109: ='TB December 2025 '!V109 -> 2053 · Lease Liability | C109: ='Initial TB Submitted to Auditor'!C109 -> 0 | D109: 0 | E109: =D109-C109 -> 0
B110: ='TB December 2025 '!V110 -> 2055 · Expected Credit Losses | C110: ='Initial TB Submitted to Auditor'!C110 -> 4.8848044e+08 | D110: 4.757385e+08 | E110: =D110-C110 -> -12741948 | F110: ECL Adjustment
B111: ='TB December 2025 '!V111 -> 2056 · ECL-Money Market Investments | C111: ='Initial TB Submitted to Auditor'!C111 -> 5487533.5 | D111: 50506455 | E111: =D111-C111 -> 45018921 | F111: ECL Adjustment
B112: ='TB December 2025 '!V112 -> 2057 · ECL Treasury Investments | C112: ='Initial TB Submitted to Auditor'!C112 -> 0 | D112: 0 | E112: =D112-C112 -> 0
B113: ='TB December 2025 '!V113 -> 2058 · Salaries Control Account | C113: ='Initial TB Submitted to Auditor'!C113 -> 0.01 | D113: 0.01 | E113: =D113-C113 -> 0
B114: ='TB December 2025 '!V114 -> 2059 · Mega farm Loans ECL | C114: ='Initial TB Submitted to Auditor'!C114 -> 4.3218781e+10 | D114: 3.9761406e+10 | E114: =D114-C114 -> -3.4573757e+09 | F114: Mega Farm ECL Movements plus Fair Value Loss on Maize
B115: ='TB December 2025 '!V115 -> 2063 · Undrawn Commitments MAIIC | C115: ='Initial TB Submitted to Auditor'!C115 -> 1.4404147e+09 | D115: 1.4404147e+09 | E115: =D115-C115 -> 0
B116: ='TB December 2025 '!V116 -> 2064 · Undrawn Commitments FInES | C116: ='Initial TB Submitted to Auditor'!C116 -> -2.8041628e+08 | D116: -2.8041628e+08 | E116: =D116-C116 -> 0
B117: ='TB December 2025 '!V117 -> 2065 · Guarantees- MAIIC | C117: ='Initial TB Submitted to Auditor'!C117 -> 40847815 | D117: 40847815 | E117: =D117-C117 -> 0
B118: ='TB December 2025 '!V118 -> 2068 · Guarantees FInES | C118: ='Initial TB Submitted to Auditor'!C118 -> 1338483000 | D118: 1338483000 | E118: =D118-C118 -> 0
B119: ='TB December 2025 '!V119 -> 2069 · Guarantees-AGCOM | C119: ='Initial TB Submitted to Auditor'!C119 -> 170064000 | D119: 170064000 | E119: =D119-C119 -> 0
B120: ='TB December 2025 '!V120 -> 2071 · Mega Farm Loans Interest | C120: ='Initial TB Submitted to Auditor'!C120 -> 6.4206557e+09 | D120: 6.4206557e+09 | E120: =D120-C120 -> 0
B121: ='TB December 2025 '!V121 -> 2072 · Mega Farm waiting Funding | C121: ='Initial TB Submitted to Auditor'!C121 -> 2.9580247e+10 | D121: 2.9580247e+10 | E121: =D121-C121 -> 0
B122: ='TB December 2025 '!V122 -> 2553 · Malawi Revenue Authority-VAT | C122: ='Initial TB Submitted to Auditor'!C122 -> 0 | D122: 0 | E122: =D122-C122 -> 0
B123: ='TB December 2025 '!V123 -> 2554 · MRA Liabilities | C123: ='Initial TB Submitted to Auditor'!C123 -> 39061781 | D123: 39061781 | E123: =D123-C123 -> 0
B124: ='TB December 2025 '!V124 -> 2060 · FInES Liability | C124: ='Initial TB Submitted to Auditor'!C124 -> 2.0602763e+10 | D124: 2.0912791e+10 | E124: =D124-C124 -> 3.1002778e+08 | F124: Core Operating System invoice
B125: ='TB December 2025 '!V125 -> 2061 · AGCOM Liability- USD | C125: ='Initial TB Submitted to Auditor'!C125 -> 1.9534268e+09 | D125: 1.9169308e+09 | E125: =D125-C125 -> -36495984 | F125: Reversal of overbooked money market interest income
B126: ='TB December 2025 '!V126 -> 2062 · Deferred Income | C126: ='Initial TB Submitted to Auditor'!C126 -> 0 | D126: 0 | E126: =D126-C126 -> 0
B127: ='TB December 2025 '!V127 -> 2070 · Mega Farms- Liability | C127: ='Initial TB Submitted to Auditor'!C127 -> 2.0914267e+10 | D127: 2.0914267e+10 | E127: =D127-C127 -> 0
B128: ='TB December 2025 '!V128 -> 3000 · Share Capital Account:3001 · Malawi Government | C128: ='Initial TB Submitted to Auditor'!C128 -> 11300000000 | D128: 11300000000 | E128: =D128-C128 -> 0
B129: ='TB December 2025 '!V129 -> 3000 · Share Capital Account:3002 · CDH Investment Bank | C129: ='Initial TB Submitted to Auditor'!C129 -> 5.522241e+08 | D129: 5.522241e+08 | E129: =D129-C129 -> 0
B130: ='TB December 2025 '!V130 -> 3000 · Share Capital Account:3003 · Investment Alliance | C130: ='Initial TB Submitted to Auditor'!C130 -> 94989242 | D130: 94989242 | E130: =D130-C130 -> 0
B131: ='TB December 2025 '!V131 -> 3010 · Capital contribution:3011 · CDH Investment Bank Limited | C131: ='Initial TB Submitted to Auditor'!C131 -> 0 | D131: 0 | E131: =D131-C131 -> 0
B132: ='TB December 2025 '!V132 -> 3010 · Capital contribution:3012 · Malawi Government | C132: ='Initial TB Submitted to Auditor'!C132 -> 0 | D132: 0 | E132: =D132-C132 -> 0
...

Sheet Initial TB Submitted to Auditor
C2: 45992
B3: ='TB December 2025 '!V3 -> 1001 · CDH Inv Bank 0050401042201 | C3: ='TB December 2025 '!W3 -> 68950246
B4: ='TB December 2025 '!V4 -> 1002 · CDH Inv Bank PIA 0050401044100 | C4: ='TB December 2025 '!W4 -> -3276701.7
B5: ='TB December 2025 '!V5 -> 1003 · FDI Project-Payments | C5: ='TB December 2025 '!W5 -> 0
B6: ='TB December 2025 '!V6 -> 1005 · FDI Project payment-USD | C6: ='TB December 2025 '!W6 -> -4.67
B7: ='TB December 2025 '!V7 -> 1006 · Petty cash | C7: ='TB December 2025 '!W7 -> -71515.78
B8: ='TB December 2025 '!V8 -> 1012 · Money Market:1008 · Alliance Capital | C8: ='TB December 2025 '!W8 -> 0
B9: ='TB December 2025 '!V9 -> 1012 · Money Market:1009 · CDHIB Fixed Deposit | C9: ='TB December 2025 '!W9 -> -1.8777713e+09
B10: ='TB December 2025 '!V10 -> 1012 · Money Market:1010 · CDHIB Call Account | C10: ='TB December 2025 '!W10 -> -33611611
B11: ='TB December 2025 '!V11 -> 1012 · Money Market:1011 · FDH Discount House | C11: ='TB December 2025 '!W11 -> -2.6970178e+09
B12: ='TB December 2025 '!V12 -> 1012 · Money Market:1013 · MyBucks | C12: ='TB December 2025 '!W12 -> 0
B13: ='TB December 2025 '!V13 -> 1012 · Money Market:1014 · Continental Asset Management | C13: ='TB December 2025 '!W13 -> -1.599258e+09
B14: ='TB December 2025 '!V14 -> 1012 · Money Market:1015 · NICO-INV1 | C14: ='TB December 2025 '!W14 -> 0
... B211: ='TB December 2025 '!V211 -> 6860 · Utilities | C211: ='TB December 2025 '!W211 -> -14188694
B213: Totals | C213: =SUM(C3:C212) -> 1.3561919e-05

Sheet TB December 2025   
C1: December 31, 25 | N1: E-BANKER EXTRACTS ENTRIES
F2: Journals Dec 2025 | G2: JN No. | H2: Final | J2: QB Short Code | K2: QuickBooks GL Code and Description | N2: Dr | O2: Cr | Q2: Cr | R2: Dr | S2: Nett | W2: 45992
B3: 1001 · CDH Inv Bank 0050401042201 | C3: =S3 -> -68950246 | H3: =E3-C3+F3 -> 68950246 | J3: =LEFT(K3,4) -> 1001 | K3: =B3 -> 1001 · CDH Inv Bank 0050401042201 | N3: =SUMIF('Final E-Banker TB Dec 2025'!$A$3:$A$192,J3,'Final E-Banker TB Dec 2025'!$G$3:$G$192) -> 0 | O3: =SUMIF('Final E-Banker TB Dec 2025'!$A$3:$A$192,'TB December 2025 '!J3,'Final E-Banker TB Dec 2025'!$H$3:$H$192) -> 68950246 | Q3: =-O3 -> -68950246 | R3: =N3 -> 0 | S3: =Q3+R3 -> -68950246 | V3: =B3 -> 1001 · CDH Inv Bank 0050401042201 | W3: =H3 -> 68950246
B4: 1002 · CDH Inv Bank PIA 0050401044100 | C4: =S4 -> 3276701.7 | H4: =E4-C4+F4 -> -3276701.7 | J4: =LEFT(K4,4) -> 1002 | K4: =B4 -> 1002 · CDH Inv Bank PIA 0050401044100 | N4: =SUMIF('Final E-Banker TB Dec 2025'!$A$3:$A$192,J4,'Final E-Banker TB Dec 2025'!$G$3:$G$192) -> 3276701.7 | O4: =SUMIF('Final E-Banker TB Dec 2025'!$A$3:$A$192,'TB December 2025 '!J4,'Final E-Banker TB Dec 2025'!$H$3:$H$192) -> 0 | Q4: =-O4 -> 0 | R4: =N4 -> 3276701.7 | S4: =Q4+R4 -> 3276701.7 | V4: =B4 -> 1002 · CDH Inv Bank PIA 0050401044100 | W4: =H4 -> -3276701.7
B5: 1003 · FDI Project-Payments | C5: =S5 -> 0 | H5: =E5-C5+F5 -> 0 | J5: =LEFT(K5,4) -> 1003 | K5: =B5 -> 1003 · FDI Project-Payments | N5: =SUMIF('Final E-Banker TB Dec 2025'!$A$3:$A$192,J5,'Final E-Banker TB Dec 2025'!$G$3:$G$192) -> 0 | O5: =SUMIF('Final E-Banker TB Dec 2025'!$A$3:$A$192,'TB December 2025 '!J5,'Final E-Banker TB Dec 2025'!$H$3:$H$192) -> 0 | Q5: =-O5 -> 0 | R5: =N5 -> 0 | S5: =Q5+R5 -> 0 | V5: =B5 -> 1003 · FDI Project-Payments | W5: =H5 -> 0
B6: 1005 · FDI Project payment-USD | C6: =S6 -> 4.67 | H6: =E6-C6+F6 -> -4.67 | J6: =LEFT(K6,4) -> 1005 | K6: =B6 -> 1005 · FDI Project payment-USD | N6: =SUMIF('Final E-Banker TB Dec 2025'!$A$3:$A$192,J6,'Final E-Banker TB Dec 2025'!$G$3:$G$192) -> 4.67 | O6: =SUMIF('Final E-Banker TB Dec 2025'!$A$3:$A$192,'TB December 2025 '!J6,'Final E-Banker TB Dec 2025'!$H$3:$H$192) -> 0 | Q6: =-O6 -> 0 | R6: =N6 -> 4.67 | S6: =Q6+R6 -> 4.67 | V6: =B6 -> 1005 · FDI Project payment-USD | W6: =H6 -> -4.67
B7: 1006 · Petty cash | C7: =S7 -> 71515.78 | H7: =E7-C7+F7 -> -71515.78 | J7: =LEFT(K7,4) -> 1006 | K7: =B7 -> 1006 · Petty cash | N7: =SUMIF('Final E-Banker TB Dec 2025'!$A$3:$A$192,J7,'Final E-Banker TB Dec 2025'!$G$3:$G$192) -> 71515.78 | O7: =SUMIF('Final E-Banker TB Dec 2025'!$A$3:$A$192,'TB December 2025 '!J7,'Final E-Banker TB Dec 2025'!$H$3:$H$192) -> 0 | Q7: =-O7 -> 0 | R7: =N7 -> 71515.78 | S7: =Q7+R7 -> 71515.78 | V7: =B7 -> 1006 · Petty cash | W7: =H7 -> -71515.78
B8: 1012 · Money Market:1008 · Alliance Capital | C8: =S8 -> 0 | H8: =E8-C8+F8 -> 0 | J8: =LEFT(K8,4) -> 1012 | K8: =B8 -> 1012 · Money Market:1008 · Alliance Capital | N8: =SUMIF('Final E-Banker TB Dec 2025'!$A$3:$A$192,J8,'Final E-Banker TB Dec 2025'!$G$3:$G$192) -> 0 | O8: =SUMIF('Final E-Banker TB Dec 2025'!$A$3:$A$192,'TB December 2025 '!J8,'Final E-Banker TB Dec 2025'!$H$3:$H$192) -> 0 | Q8: =-O8 -> 0 | R8: =N8 -> 0 | S8: =Q8+R8 -> 0 | V8: =B8 -> 1012 · Money Market:1008 · Alliance Capital | W8: =H8 -> 0
B9: 1012 · Money Market:1009 · CDHIB Fixed Deposit | C9: =S9 -> 1.8777713e+09 | H9: =E9-C9+F9 -> -1.8777713e+09 | J9: =LEFT(K9,4) -> 1012 | K9: =B9 -> 1012 · Money Market:1009 · CDHIB Fixed Deposit | N9: ='Final E-Banker TB Dec 2025'!G13 -> 1.8777713e+09 | O9: =SUMIF('Final E-Banker TB Dec 2025'!$A$3:$A$192,'TB December 2025 '!J9,'Final E-Banker TB Dec 2025'!$H$3:$H$192) -> 0 | Q9: =-O9 -> 0 | R9: =N9 -> 1.8777713e+09 | S9: =Q9+R9 -> 1.8777713e+09 | V9: =B9 -> 1012 · Money Market:1009 · CDHIB Fixed Deposit | W9: =H9 -> -1.8777713e+09
B10: 1012 · Money Market:1010 · CDHIB Call Account | C10: =S10 -> 33611611 | H10: =E10-C10+F10 -> -33611611 | J10: =LEFT(K10,4) -> 1012 | K10: =B10 -> 1012 · Money Market:1010 · CDHIB Call Account | N10: ='Final E-Banker TB Dec 2025'!G9 -> 33611611 | O10: =SUMIF('Final E-Banker TB Dec 2025'!$A$3:$A$192,'TB December 2025 '!J10,'Final E-Banker TB Dec 2025'!$H$3:$H$192) -> 0 | Q10: =-O10 -> 0 | R10: =N10 -> 33611611 | S10: =Q10+R10 -> 33611611 | V10: =B10 -> 1012 · Money Market:1010 · CDHIB Call Account | W10: =H10 -> -33611611
B11: 1012 · Money Market:1011 · FDH Discount House | C11: =S11 -> 2.6970178e+09 | H11: =E11-C11+F11 -> -2.6970178e+09 | J11: =LEFT(K11,4) -> 1012 | K11: =B11 -> 1012 · Money Market:1011 · FDH Discount House | N11: ='Final E-Banker TB Dec 2025'!G10 -> 2.6970178e+09 | O11: =SUMIF('Final E-Banker TB Dec 2025'!$A$3:$A$192,'TB December 2025 '!J11,'Final E-Banker TB Dec 2025'!$H$3:$H$192) -> 0 | Q11: =-O11 -> 0 | R11: =N11 -> 2.6970178e+09 | S11: =Q11+R11 -> 2.6970178e+09 | V11: =B11 -> 1012 · Money Market:1011 · FDH Discount House | W11: =H11 -> -2.6970178e+09
B12: 1012 · Money Market:1013 · MyBucks | C12: =S12 -> 0 | H12: =E12-C12+F12 -> 0 | J12: =LEFT(K12,4) -> 1012 | K12: =B12 -> 1012 · Money Market:1013 · MyBucks | N12: =SUMIF('Final E-Banker TB Dec 2025'!$A$3:$A$192,J12,'Final E-Banker TB Dec 2025'!$G$3:$G$192) -> 0 | O12: =SUMIF('Final E-Banker TB Dec 2025'!$A$3:$A$192,'TB December 2025 '!J12,'Final E-Banker TB Dec 2025'!$H$3:$H$192) -> 0 | Q12: =-O12 -> 0 | R12: =N12 -> 0 | S12: =Q12+R12 -> 0 | V12: =B12 -> 1012 · Money Market:1013 · MyBucks | W12: =H12 -> 0
B13: 1012 · Money Market:1014 · Continental Asset Management | C13: =S13 -> 1.599258e+09 | H13: =E13-C13+F13 -> -1.599258e+09 | J13: 1014 | K13: =B13 -> 1012 · Money Market:1014 · Continental Asset Management | N13: =SUMIF('Final E-Banker TB Dec 2025'!$A$3:$A$192,J13,'Final E-Banker TB Dec 2025'!$G$3:$G$192) -> 1.599258e+09 | O13: =SUMIF('Final E-Banker TB Dec 2025'!$A$3:$A$192,'TB December 2025 '!J13,'Final E-Banker TB Dec 2025'!$H$3:$H$192) -> 0 | Q13: =-O13 -> 0 | R13: =N13 -> 1.599258e+09 | S13: =Q13+R13 -> 1.599258e+09 | V13: =B13 -> 1012 · Money Market:1014 · Continental Asset Management | W13: =H13 -> -1.599258e+09
B14: 1012 · Money Market:1015 · NICO-INV1 | C14: =S14 -> 0 | H14: =E14-C14+F14 -> 0 | J14: =LEFT(K14,4) -> 1012 | K14: =B14 -> 1012 · Money Market:1015 · NICO-INV1 | N14: =SUMIF('Final E-Banker TB Dec 2025'!$A$3:$A$192,J14,'Final E-Banker TB Dec 2025'!$G$3:$G$192) -> 0 | O14: =SUMIF('Final E-Banker TB Dec 2025'!$A$3:$A$192,'TB December 2025 '!J14,'Final E-Banker TB Dec 2025'!$H$3:$H$192) -> 0 | Q14: =-O14 -> 0 | R14: =N14 -> 0 | S14: =Q14+R14 -> 0 | V14: =B14 -> 1012 · Money Market:1015 · NICO-INV1 | W14: =H14 -> 0
B15: 1012 · Money Market:1016 · Treasury Note | C15: =S15 -> 0 | H15: =E15-C15+F15 -> 0 | J15: =LEFT(K15,4) -> 1012 | K15: =B15 -> 1012 · Money Market:1016 · Treasury Note | N15: =SUMIF('Final E-Banker TB Dec 2025'!$A$3:$A$192,J15,'Final E-Banker TB Dec 2025'!$G$3:$G$192) -> 0 | O15: =SUMIF('Final E-Banker TB Dec 2025'!$A$3:$A$192,'TB December 2025 '!J15,'Final E-Banker TB Dec 2025'!$H$3:$H$192) -> 0 | Q15: =-O15 -> 0 | R15: =N15 -> 0 | S15: =Q15+R15 -> 0 | V15: =B15 -> 1012 · Money Market:1016 · Treasury Note | W15: =H15 -> 0
B16: 1012 · Money Market:1020 · FINCA | C16: =S16 -> 0 | H16: =E16-C16+F16 -> 0 | J16: =LEFT(K16,4) -> 1012 | K16: =B16 -> 1012 · Money Market:1020 · FINCA | N16: =SUMIF('Final E-Banker TB Dec 2025'!$A$3:$A$192,J16,'Final E-Banker TB Dec 2025'!$G$3:$G$192) -> 0 | O16: =SUMIF('Final E-Banker TB Dec 2025'!$A$3:$A$192,'TB December 2025 '!J16,'Final E-Banker TB Dec 2025'!$H$3:$H$192) -> 0 | Q16: =-O16 -> 0 | R16: =N16 -> 0 | S16: =Q16+R16 -> 0 | V16: =B16 -> 1012 · Money Market:1020 · FINCA | W16: =H16 -> 0
B17: 1012 · Money Market:1025 · CDHIB Fixed Deposit (USD) | C17: =S17 -> 2.9358364e+08 | H17: =E17-C17+F17 -> -2.9358364e+08 | J17: 1025 | K17: =B17 -> 1012 · Money Market:1025 · CDHIB Fixed Deposit (USD) | N17: =SUMIF('Final E-Banker TB Dec 2025'!$A$3:$A$192,J17,'Final E-Banker TB Dec 2025'!$G$3:$G$192) -> 2.9358364e+08 | O17: =SUMIF('Final E-Banker TB Dec 2025'!$A$3:$A$192,'TB December 2025 '!J17,'Final E-Banker TB Dec 2025'!$H$3:$H$192) -> 0 | Q17: =-O17 -> 0 | R17: =N17 -> 2.9358364e+08 | S17: =Q17+R17 -> 2.9358364e+08 | V17: =B17 -> 1012 · Money Market:1025 · CDHIB Fixed Deposit (USD) | W17: =H17 -> -2.9358364e+08
B18: 1012 · Money Market:1026 · NICO-INV 2 | C18: =S18 -> 0 | H18: =E18-C18+F18 -> 0 | J18: =LEFT(K18,4) -> 1012 | K18: =B18 -> 1012 · Money Market:1026 · NICO-INV 2 | N18: =SUMIF('Final E-Banker TB Dec 2025'!$A$3:$A$192,J18,'Final E-Banker TB Dec 2025'!$G$3:$G$192) -> 0 | O18: =SUMIF('Final E-Banker TB Dec 2025'!$A$3:$A$192,'TB December 2025 '!J18,'Final E-Banker TB Dec 2025'!$H$3:$H$192) -> 0 | Q18: =-O18 -> 0 | R18: =N18 -> 0 | S18: =Q18+R18 -> 0 | V18: =B18 -> 1012 · Money Market:1026 · NICO-INV 2 | W18: =H18 -> 0
B19: 1012 · Money Market:1027 · CDHIB Call Account FInES | C19: =S19 -> 36229353 | H19: =E19-C19+F19 -> -36229353 | J19: 1027 | K19: =B19 -> 1012 · Money Market:1027 · CDHIB Call Account FInES | N19: =SUMIF('Final E-Banker TB Dec 2025'!$A$3:$A$192,J19,'Final E-Banker TB Dec 2025'!$G$3:$G$192) -> 36229353 | O19: =SUMIF('Final E-Banker TB Dec 2025'!$A$3:$A$192,'TB December 2025 '!J19,'Final E-Banker TB Dec 2025'!$H$3:$H$192) -> 0 | Q19: =-O19 -> 0 | R19: =N19 -> 36229353 | S19: =Q19+R19 -> 36229353 | V19: =B19 -> 1012 · Money Market:1027 · CDHIB Call Account FInES | W19: =H19 -> -36229353
B20: 1012 · Money Market:1028 · Old Mutual Investment Group Ltd | C20: =S20 -> 0.18 | H20: =E20-C20+F20 -> -0.18 | J20: 1028 | K20: =B20 -> 1012 · Money Market:1028 · Old Mutual Investment Group Ltd | N20: =SUMIF('Final E-Banker TB Dec 2025'!$A$3:$A$192,J20,'Final E-Banker TB Dec 2025'!$G$3:$G$192) -> 0.18 | O20: =SUMIF('Final E-Banker TB Dec 2025'!$A$3:$A$192,'TB December 2025 '!J20,'Final E-Banker TB Dec 2025'!$H$3:$H$192) -> 0 | Q20: =-O20 -> 0 | R20: =N20 -> 0.18 | S20: =Q20+R20 -> 0.18 | V20: =B20 -> 1012 · Money Market:1028 · Old Mutual Investment Group Ltd | W20: =H20 -> -0.18
B21: 1012 · Money Market:1031 · CDHIB Fixed Deposit (USD) 2 | C21: =S21 -> 3.6123281e+08 | H21: =E21-C21+F21 -> -3.6123281e+08 | J21: 1031 | K21: =B21 -> 1012 · Money Market:1031 · CDHIB Fixed Deposit (USD) 2 | N21: =SUMIF('Final E-Banker TB Dec 2025'!$A$3:$A$192,J21,'Final E-Banker TB Dec 2025'!$G$3:$G$192) -> 3.6123281e+08 | O21: =SUMIF('Final E-Banker TB Dec 2025'!$A$3:$A$192,'TB December 2025 '!J21,'Final E-Banker TB Dec 2025'!$H$3:$H$192) -> 0 | Q21: =-O21 -> 0 | R21: =N21 -> 3.6123281e+08 | S21: =Q21+R21 -> 3.6123281e+08 | V21: =B21 -> 1012 · Money Market:1031 · CDHIB Fixed Deposit (USD) 2 | W21: =H21 -> -3.6123281e+08
B22: 1012 · Money Market:1032 · CDHIB Fixed Deposit (USD) 3 | C22: =S22 -> 44302226 | H22: =E22-C22+F22 -> -44302226 | J22: 1032 | K22: =B22 -> 1012 · Money Market:1032 · CDHIB Fixed Deposit (USD) 3 | N22: =SUMIF('Final E-Banker TB Dec 2025'!$A$3:$A$192,J22,'Final E-Banker TB Dec 2025'!$G$3:$G$192) -> 44302226 | O22: =SUMIF('Final E-Banker TB Dec 2025'!$A$3:$A$192,'TB December 2025 '!J22,'Final E-Banker TB Dec 2025'!$H$3:$H$192) -> 0 | Q22: =-O22 -> 0 | R22: =N22 -> 44302226 | S22: =Q22+R22 -> 44302226 | V22: =B22 -> 1012 · Money Market:1032 · CDHIB Fixed Deposit (USD) 3 | W22: =H22 -> -44302226
B23: 1012 · Money Market:1033 · NBS Bank- Mega Farms 1 | C23: =S23 -> 0 | H23: =E23-C23+F23 -> 0 | J23: =LEFT(K23,4) -> 1012 | K23: =B23 -> 1012 · Money Market:1033 · NBS Bank- Mega Farms 1 | N23: =SUMIF('Final E-Banker TB Dec 2025'!$A$3:$A$192,J23,'Final E-Banker TB Dec 2025'!$G$3:$G$192) -> 0 | O23: =SUMIF('Final E-Banker TB Dec 2025'!$A$3:$A$192,'TB December 2025 '!J23,'Final E-Banker TB Dec 2025'!$H$3:$H$192) -> 0 | Q23: =-O23 -> 0 | R23: =N23 -> 0 | S23: =Q23+R23 -> 0 | V23: =B23 -> 1012 · Money Market:1033 · NBS Bank- Mega Farms 1 | W23: =H23 -> 0
B24: 1012 · Money Market:1034 · NBS Bank Mega Farms 2 | C24: =S24 -> 0 | H24: =E24-C24+F24 -> 0 | J24: =LEFT(K24,4) -> 1012 | K24: =B24 -> 1012 · Money Market:1034 · NBS Bank Mega Farms 2 | N24: =SUMIF('Final E-Banker TB Dec 2025'!$A$3:$A$192,J24,'Final E-Banker TB Dec 2025'!$G$3:$G$192) -> 0 | O24: =SUMIF('Final E-Banker TB Dec 2025'!$A$3:$A$192,'TB December 2025 '!J24,'Final E-Banker TB Dec 2025'!$H$3:$H$192) -> 0 | Q24: =-O24 -> 0 | R24: =N24 -> 0 | S24: =Q24+R24 -> 0 | V24: =B24 -> 1012 · Money Market:1034 · NBS Bank Mega Farms 2 | W24: =H24 -> 0
B25: 1012 · Money Market:1035 · Continental Asset Management 2 | C25: =S25 -> 6.4545771e+09 | H25: =E25-C25+F25 -> -6.4545771e+09 | J25: 1035 | K25: =B25 -> 1012 · Money Market:1035 · Continental Asset Management 2 | N25: =SUMIF('Final E-Banker TB Dec 2025'!$A$3:$A$192,J25,'Final E-Banker TB Dec 2025'!$G$3:$G$192) -> 6.4545771e+09 | O25: =SUMIF('Final E-Banker TB Dec 2025'!$A$3:$A$192,'TB December 2025 '!J25,'Final E-Banker TB Dec 2025'!$H$3:$H$192) -> 0 | Q25: =-O25 -> 0 | R25: =N25 -> 6.4545771e+09 | S25: =Q25+R25 -> 6.4545771e+09 | V25: =B25 -> 1012 · Money Market:1035 · Continental Asset Management 2 | W25: =H25 -> -6.4545771e+09
B26: 1012 · Money Market:1037 · CDHIB Call Account AGCOM | C26: =S26 -> 29851626 | H26: =E26-C26+F26 -> -29851626 | J26: 1037 | K26: =B26 -> 1012 · Money Market:1037 · CDHIB Call Account AGCOM | N26: =SUMIF('Final E-Banker TB Dec 2025'!$A$3:$A$192,J26,'Final E-Banker TB Dec 2025'!$G$3:$G$192) -> 29851626 | O26: =SUMIF('Final E-Banker TB Dec 2025'!$A$3:$A$192,'TB December 2025 '!J26,'Final E-Banker TB Dec 2025'!$H$3:$H$192) -> 0 | Q26: =-O26 -> 0 | R26: =N26 -> 29851626 | S26: =Q26+R26 -> 29851626 | V26: =B26 -> 1012 · Money Market:1037 · CDHIB Call Account AGCOM | W26: =H26 -> -29851626
B27: 1012 · Money Market:1038 · CDHIB Fixed Deposit AGCOM | C27: =S27 -> 1808285074 | H27: =E27-C27+F27 -> -1808285074 | J27: 1038 | K27: =B27 -> 1012 · Money Market:1038 · CDHIB Fixed Deposit AGCOM | N27: =SUMIF('Final E-Banker TB Dec 2025'!$A$3:$A$192,J27,'Final E-Banker TB Dec 2025'!$G$3:$G$192) -> 1808285074 | O27: =SUMIF('Final E-Banker TB Dec 2025'!$A$3:$A$192,'TB December 2025 '!J27,'Final E-Banker TB Dec 2025'!$H$3:$H$192) -> 0 | Q27: =-O27 -> 0 | R27: =N27 -> 1808285074 | S27: =Q27+R27 -> 1808285074 | V27: =B27 -> 1012 · Money Market:1038 · CDHIB Fixed Deposit AGCOM | W27: =H27 -> -1808285074
B28: 1012 · Money Market:1043 · NBS Money Market | C28: =S28 -> 0 | H28: =E28-C28+F28 -> 0 | J28: =LEFT(K28,4) -> 1012 | K28: =B28 -> 1012 · Money Market:1043 · NBS Money Market | N28: =SUMIF('Final E-Banker TB Dec 2025'!$A$3:$A$192,J28,'Final E-Banker TB Dec 2025'!$G$3:$G$192) -> 0 | O28: =SUMIF('Final E-Banker TB Dec 2025'!$A$3:$A$192,'TB December 2025 '!J28,'Final E-Banker TB Dec 2025'!$H$3:$H$192) -> 0 | Q28: =-O28 -> 0 | R28: =N28 -> 0 | S28: =Q28+R28 -> 0 | V28: =B28 -> 1012 · Money Market:1043 · NBS Money Market | W28: =H28 -> 0
B29: 1012 · Money Market:1044 · FDH Discount House 2 | C29: =S29 -> 2.0169857e+09 | H29: =E29-C29+F29 -> -2.0169857e+09 | J29: 1044 | K29: =B29 -> 1012 · Money Market:1044 · FDH Discount House 2 | N29: =SUMIF('Final E-Banker TB Dec 2025'!$A$3:$A$192,J29,'Final E-Banker TB Dec 2025'!$G$3:$G$192) -> 2.0169857e+09 | O29: =SUMIF('Final E-Banker TB Dec 2025'!$A$3:$A$192,'TB December 2025 '!J29,'Final E-Banker TB Dec 2025'!$H$3:$H$192) -> 0 | Q29: =-O29 -> 0 | R29: =N29 -> 2.0169857e+09 | S29: =Q29+R29 -> 2.0169857e+09 | V29: =B29 -> 1012 · Money Market:1044 · FDH Discount House 2 | W29: =H29 -> -2.0169857e+09
B30: 1012 · Money Market:1045 · FDH Discount House 3 | C30: =S30 -> 0 | H30: =E30-C30+F30 -> 0 | J30: =LEFT(K30,4) -> 1012 | K30: =B30 -> 1012 · Money Market:1045 · FDH Discount House 3 | N30: =SUMIF('Final E-Banker TB Dec 2025'!$A$3:$A$192,J30,'Final E-Banker TB Dec 2025'!$G$3:$G$192) -> 0 | O30: =SUMIF('Final E-Banker TB Dec 2025'!$A$3:$A$192,'TB December 2025 '!J30,'Final E-Banker TB Dec 2025'!$H$3:$H$192) -> 0 | Q30: =-O30 -> 0 | R30: =N30 -> 0 | S30: =Q30+R30 -> 0 | V30: =B30 -> 1012 · Money Market:1045 · FDH Discount House 3 | W30: =H30 -> 0
B31: 1012 · Money Market:1047 · NICO Asset Managers | C31: =S31 -> 3.8223606e+09 | H31: =E31-C31+F31 -> -3.8223606e+09 | J31: 1047 | K31: =B31 -> 1012 · Money Market:1047 · NICO Asset Managers | N31: =SUMIF('Final E-Banker TB Dec 2025'!$A$3:$A$192,J31,'Final E-Banker TB Dec 2025'!$G$3:$G$192) -> 3.8223606e+09 | O31: =SUMIF('Final E-Banker TB Dec 2025'!$A$3:$A$192,'TB December 2025 '!J31,'Final E-Banker TB Dec 2025'!$H$3:$H$192) -> 0 | Q31: =-O31 -> 0 | R31: =N31 -> 3.8223606e+09 | S31: =Q31+R31 -> 3.8223606e+09 | V31: =B31 -> 1012 · Money Market:1047 · NICO Asset Managers | W31: =H31 -> -3.8223606e+09
B32: 1017 · NBS Cash collection | C32: =S32 -> 3.3951404e+08 | H32: =E32-C32+F32 -> -3.3951404e+08 | J32: =LEFT(K32,4) -> 1017 | K32: =B32 -> 1017 · NBS Cash collection | N32: =SUMIF('Final E-Banker TB Dec 2025'!$A$3:$A$192,J32,'Final E-Banker TB Dec 2025'!$G$3:$G$192) -> 3.3951404e+08 | O32: =SUMIF('Final E-Banker TB Dec 2025'!$A$3:$A$192,'TB December 2025 '!J32,'Final E-Banker TB Dec 2025'!$H$3:$H$192) -> 0 | Q32: =-O32 -> 0 | R32: =N32 -> 3.3951404e+08 | S32: =Q32+R32 -> 3.3951404e+08 | V32: =B32 -> 1017 · NBS Cash collection | W32: =H32 -> -3.3951404e+08
B33: 1018 · NBS Current A/C 21011223 | C33: =S33 -> 1.93082e+08 | H33: =E33-C33+F33 -> -1.93082e+08 | J33: =LEFT(K33,4) -> 1018 | K33: =B33 -> 1018 · NBS Current A/C 21011223 | N33: =SUMIF('Final E-Banker TB Dec 2025'!$A$3:$A$192,J33,'Final E-Banker TB Dec 2025'!$G$3:$G$192) -> 1.93082e+08 | O33: =SUMIF('Final E-Banker TB Dec 2025'!$A$3:$A$192,'TB December 2025 '!J33,'Final E-Banker TB Dec 2025'!$H$3:$H$192) -> 0 | Q33: =-O33 -> 0 | R33: =N33 -> 1.93082e+08 | S33: =Q33+R33 -> 1.93082e+08 | V33: =B33 -> 1018 · NBS Current A/C 21011223 | W33: =H33 -> -1.93082e+08
B34: 1019 · NBS USD A/C 21011436 | C34: =S34 -> 1846377.7 | H34: =E34-C34+F34 -> -1846377.7 | J34: =LEFT(K34,4) -> 1019 | K34: =B34 -> 1019 · NBS USD A/C 21011436 | N34: =SUMIF('Final E-Banker TB Dec 2025'!$A$3:$A$192,J34,'Final E-Banker TB Dec 2025'!$G$3:$G$192) -> 1846377.7 | O34: =SUMIF('Final E-Banker TB Dec 2025'!$A$3:$A$192,'TB December 2025 '!J34,'Final E-Banker TB Dec 2025'!$H$3:$H$192) -> 0 | Q34: =-O34 -> 0 | R34: =N34 -> 1846377.7 | S34: =Q34+R34 -> 1846377.7 | V34: =B34 -> 1019 · NBS USD A/C 21011436 | W34: =H34 -> -1846377.7
B35: 1021 · NBS Money Market | C35: =S35 -> 1.5152771e+09 | H35: =E35-C35+F35 -> -1.5152771e+09 | J35: =LEFT(K35,4) -> 1021 | K35: =B35 -> 1021 · NBS Money Market | N35: =SUMIF('Final E-Banker TB Dec 2025'!$A$3:$A$192,J35,'Final E-Banker TB Dec 2025'!$G$3:$G$192) -> 1.5152771e+09 | O35: =SUMIF('Final E-Banker TB Dec 2025'!$A$3:$A$192,'TB December 2025 '!J35,'Final E-Banker TB Dec 2025'!$H$3:$H$192) -> 0 | Q35: =-O35 -> 0 | R35: =N35 -> 1.5152771e+09 | S35: =Q35+R35 -> 1.5152771e+09 | V35: =B35 -> 1021 · NBS Money Market | W35: =H35 -> -1.5152771e+09
B36: 1022 · AGRA- FCDA | C36: =S36 -> 2.7874847e+08 | H36: =E36-C36+F36 -> -2.7874847e+08 | J36: =LEFT(K36,4) -> 1022 | K36: =B36 -> 1022 · AGRA- FCDA | N36: =SUMIF('Final E-Banker TB Dec 2025'!$A$3:$A$192,J36,'Final E-Banker TB Dec 2025'!$G$3:$G$192) -> 2.7874847e+08 | O36: =SUMIF('Final E-Banker TB Dec 2025'!$A$3:$A$192,'TB December 2025 '!J36,'Final E-Banker TB Dec 2025'!$H$3:$H$192) -> 0 | Q36: =-O36 -> 0 | R36: =N36 -> 2.7874847e+08 | S36: =Q36+R36 -> 2.7874847e+08 | V36: =B36 -> 1022 · AGRA- FCDA | W36: =H36 -> -2.7874847e+08
B37: 1023 · MICF- Mbora FCDA | C37: =S37 -> 5.46 | H37: =E37-C37+F37 -> -5.46 | J37: =LEFT(K37,4) -> 1023 | K37: =B37 -> 1023 · MICF- Mbora FCDA | N37: =SUMIF('Final E-Banker TB Dec 2025'!$A$3:$A$192,J37,'Final E-Banker TB Dec 2025'!$G$3:$G$192) -> 5.46 | O37: =SUMIF('Final E-Banker TB Dec 2025'!$A$3:$A$192,'TB December 2025 '!J37,'Final E-Banker TB Dec 2025'!$H$3:$H$192) -> 0 | Q37: =-O37 -> 0 | R37: =N37 -> 5.46 | S37: =Q37+R37 -> 5.46 | V37: =B37 -> 1023 · MICF- Mbora FCDA | W37: =H37 -> -5.46
B38: 1024 · RBM - Treasury Bills | C38: =S38 -> 0 | H38: =E38-C38+F38 -> 0 | J38: =LEFT(K38,4) -> 1024 | K38: =B38 -> 1024 · RBM - Treasury Bills | N38: =SUMIF('Final E-Banker TB Dec 2025'!$A$3:$A$192,J38,'Final E-Banker TB Dec 2025'!$G$3:$G$192) -> 0 | O38: =SUMIF('Final E-Banker TB Dec 2025'!$A$3:$A$192,'TB December 2025 '!J38,'Final E-Banker TB Dec 2025'!$H$3:$H$192) -> 0 | Q38: =-O38 -> 0 | R38: =N38 -> 0 | S38: =Q38+R38 -> 0 | V38: =B38 -> 1024 · RBM - Treasury Bills | W38: =H38 -> 0
B39: 1029 · NBS Money Market Acc 2 | C39: =S39 -> 8.0886178e+08 | H39: =E39-C39+F39 -> -8.0886178e+08 | J39: =LEFT(K39,4) -> 1029 | K39: =B39 -> 1029 · NBS Money Market Acc 2 | N39: =SUMIF('Final E-Banker TB Dec 2025'!$A$3:$A$192,J39,'Final E-Banker TB Dec 2025'!$G$3:$G$192) -> 8.0886178e+08 | O39: =SUMIF('Final E-Banker TB Dec 2025'!$A$3:$A$192,'TB December 2025 '!J39,'Final E-Banker TB Dec 2025'!$H$3:$H$192) -> 0 | Q39: =-O39 -> 0 | R39: =N39 -> 8.0886178e+08 | S39: =Q39+R39 -> 8.0886178e+08 | V39: =B39 -> 1029 · NBS Money Market Acc 2 | W39: =H39 -> -8.0886178e+08
B40: 1036 · NBS Bank Mega Farms | C40: =S40 -> 0 | H40: =E40-C40+F40 -> 0 | J40: =LEFT(K40,4) -> 1036 | K40: =B40 -> 1036 · NBS Bank Mega Farms | N40: =SUMIF('Final E-Banker TB Dec 2025'!$A$3:$A$192,J40,'Final E-Banker TB Dec 2025'!$G$3:$G$192) -> 0 | O40: =SUMIF('Final E-Banker TB Dec 2025'!$A$3:$A$192,'TB December 2025 '!J40,'Final E-Banker TB Dec 2025'!$H$3:$H$192) -> 0 | Q40: =-O40 -> 0 | R40: =N40 -> 0 | S40: =Q40+R40 -> 0 | V40: =B40 -> 1036 · NBS Bank Mega Farms | W40: =H40 -> 0
B41: 1046 · First Capital Bank | C41: =S41 -> 28486995 | H41: =E41-C41+F41 -> -28486995 | J41: =LEFT(K41,4) -> 1046 | K41: =B41 -> 1046 · First Capital Bank | N41: =SUMIF('Final E-Banker TB Dec 2025'!$A$3:$A$192,J41,'Final E-Banker TB Dec 2025'!$G$3:$G$192) -> 28486995 | O41: =SUMIF('Final E-Banker TB Dec 2025'!$A$3:$A$192,'TB December 2025 '!J41,'Final E-Banker TB Dec 2025'!$H$3:$H$192) -> 0 | Q41: =-O41 -> 0 | R41: =N41 -> 28486995 | S41: =Q41+R41 -> 28486995 | V41: =B41 -> 1046 · First Capital Bank | W41: =H41 -> -28486995
B42: 1048 · CDHIB MAIIC AGRA (MK) | C42: =S42 -> 36188936 | H42: =E42-C42+F42 -> -36188936 | J42: =LEFT(K42,4) -> 1048 | K42: =B42 -> 1048 · CDHIB MAIIC AGRA (MK) | N42: =SUMIF('Final E-Banker TB Dec 2025'!$A$3:$A$192,J42,'Final E-Banker TB Dec 2025'!$G$3:$G$192) -> 36188936 | O42: =SUMIF('Final E-Banker TB Dec 2025'!$A$3:$A$192,'TB December 2025 '!J42,'Final E-Banker TB Dec 2025'!$H$3:$H$192) -> 0 | Q42: =-O42 -> 0 | R42: =N42 -> 36188936 | S42: =Q42+R42 -> 36188936 | V42: =B42 -> 1048 · CDHIB MAIIC AGRA (MK) | W42: =H42 -> -36188936
B43: 1030 · Partial Credit Guarantee Fund | C43: =S43 -> 71808009 | H43: =E43-C43+F43 -> -71808009 | J43: =LEFT(K43,4) -> 1030 | K43: =B43 -> 1030 · Partial Credit Guarantee Fund | N43: =SUMIF('Final E-Banker TB Dec 2025'!$A$3:$A$192,J43,'Final E-Banker TB Dec 2025'!$G$3:$G$192) -> 71808009 | O43: =SUMIF('Final E-Banker TB Dec 2025'!$A$3:$A$192,'TB December 2025 '!J43,'Final E-Banker TB Dec 2025'!$H$3:$H$192) -> 0 | Q43: =-O43 -> 0 | R43: =N43 -> 71808009 | S43: =Q43+R43 -> 71808009 | V43: =B43 -> 1030 · Partial Credit Guarantee Fund | W43: =H43 -> -71808009
... B48: 1049 · Term Loan - USD | C48: =S48 -> 0 | H48: =E48-C48+F48 -> 0 | J48: =LEFT(K48,4) -> 1049 | K48: =B48 -> 1049 · Term Loan - USD | N48: =SUMIF('Final E-Banker TB Dec 2025'!$A$3:$A$192,J48,'Final E-Banker TB Dec 2025'!$G$3:$G$192) -> 0 | O48: =SUMIF('Final E-Banker TB Dec 2025'!$A$3:$A$192,'TB December 2025 '!J48,'Final E-Banker TB Dec 2025'!$H$3:$H$192) -> 0 | Q48: =-O48 -> 0 | R48: =N48 -> 0 | S48: =Q48+R48 -> 0 | V48: =B48 -> 1049 · Term Loan - USD | W48: =H48 -> 0
B49: 1050 · Term Loans | C49: =S49 -> 1.4840561e+10 | F49: =-F100 -> 1.3813568e+08 | G49: Reversal of Museco Loan Balance | H49: =E49-C49+F49 -> -1.4702425e+10 | J49: =LEFT(K49,4) -> 1050 | K49: =B49 -> 1050 · Term Loans | N49: ='Final E-Banker TB Dec 2025'!G34+'Final E-Banker TB Dec 2025'!G35+'Final E-Banker TB Dec 2025'!G36+'Final E-Banker TB Dec 2025'!G37+'Final E-Banker TB Dec 2025'!G38 -> 1.4840613e+10 | O49: ='Final E-Banker TB Dec 2025'!H30 -> 52033.5 | Q49: =-O49 -> -52033.5 | R49: =N49 -> 1.4840613e+10 | S49: =Q49+R49 -> 1.4840561e+10 | V49: =B49 -> 1050 · Term Loans | W49: =H49 -> -1.4702425e+10
B50: 1053 · Accounts Receivables | C50: =S50 -> 2.6638798e+08 | H50: =E50-C50+F50 -> -2.6638798e+08 | J50: =LEFT(K50,4) -> 1053 | K50: =B50 -> 1053 · Accounts Receivables | N50: =SUMIF('Final E-Banker TB Dec 2025'!$A$3:$A$192,J50,'Final E-Banker TB Dec 2025'!$G$3:$G$192) -> 2.6638798e+08 | O50: =SUMIF('Final E-Banker TB Dec 2025'!$A$3:$A$192,'TB December 2025 '!J50,'Final E-Banker TB Dec 2025'!$H$3:$H$192) -> 0 | Q50: =-O50 -> 0 | R50: =N50 -> 2.6638798e+08 | S50: =Q50+R50 -> 2.6638798e+08 | V50: =B50 -> 1053 · Accounts Receivables | W50: =H50 -> -2.6638798e+08
B51: 1054 · Mega Farms-Fertilizers-Loan | C51: =S51 -> 3.3189976e+10 | H51: =E51-C51+F51 -> -3.3189976e+10 | J51: =LEFT(K51,4) -> 1054 | K51: =B51 -> 1054 · Mega Farms-Fertilizers-Loan | N51: ='Final E-Banker TB Dec 2025'!G39 -> 3.3189976e+10 | O51: =SUMIF('Final E-Banker TB Dec 2025'!$A$3:$A$192,'TB December 2025 '!J51,'Final E-Banker TB Dec 2025'!$H$3:$H$192) -> 0 | Q51: =-O51 -> 0 | R51: =N51 -> 3.3189976e+10 | S51: =Q51+R51 -> 3.3189976e+10 | V51: =B51 -> 1054 · Mega Farms-Fertilizers-Loan | W51: =H51 -> -3.3189976e+10
B52: 1055 · Mega Farms-Seed Loans | C52: =S52 -> 7.5941669e+09 | H52: =E52-C52+F52 -> -7.5941669e+09 | J52: =LEFT(K52,4) -> 1055 | K52: =B52 -> 1055 · Mega Farms-Seed Loans | N52: ='Final E-Banker TB Dec 2025'!G40 -> 7.5941669e+09 | O52: =SUMIF('Final E-Banker TB Dec 2025'!$A$3:$A$192,'TB December 2025 '!J52,'Final E-Banker TB Dec 2025'!$H$3:$H$192) -> 0 | Q52: =-O52 -> 0 | R52: =N52 -> 7.5941669e+09 | S52: =Q52+R52 -> 7.5941669e+09 | V52: =B52 -> 1055 · Mega Farms-Seed Loans | W52: =H52 -> -7.5941669e+09
B53: 1056 · Mega Farms-Working Capital Loan | C53: =S53 -> 6.6623228e+08 | H53: =E53-C53+F53 -> -6.6623228e+08 | J53: =LEFT(K53,4) -> 1056 | K53: =B53 -> 1056 · Mega Farms-Working Capital Loan | N53: ='Final E-Banker TB Dec 2025'!G41 -> 6.6623228e+08 | O53: =SUMIF('Final E-Banker TB Dec 2025'!$A$3:$A$192,'TB December 2025 '!J53,'Final E-Banker TB Dec 2025'!$H$3:$H$192) -> 0 | Q53: =-O53 -> 0 | R53: =N53 -> 6.6623228e+08 | S53: =Q53+R53 -> 6.6623228e+08 | V53: =B53 -> 1056 · Mega Farms-Working Capital Loan | W53: =H53 -> -6.6623228e+08
B54: 1057 · Mega Farms-Equipment Loan | C54: =S54 -> 1.803483e+09 | H54: =E54-C54+F54 -> -1.803483e+09 | J54: =LEFT(K54,4) -> 1057 | K54: =B54 -> 1057 · Mega Farms-Equipment Loan | N54: ='Final E-Banker TB Dec 2025'!G42 -> 1.803483e+09 | O54: =SUMIF('Final E-Banker TB Dec 2025'!$A$3:$A$192,'TB December 2025 '!J54,'Final E-Banker TB Dec 2025'!$H$3:$H$192) -> 0 | Q54: =-O54 -> 0 | R54: =N54 -> 1.803483e+09 | S54: =Q54+R54 -> 1.803483e+09 | V54: =B54 -> 1057 · Mega Farms-Equipment Loan | W54: =H54 -> -1.803483e+09
B55: 1058 · Mega Farms-Irrigation Loan | C55: =S55 -> 1.9758676e+09 | H55: =E55-C55+F55 -> -1.9758676e+09 | J55: =LEFT(K55,4) -> 1058 | K55: =B55 -> 1058 · Mega Farms-Irrigation Loan | N55: ='Final E-Banker TB Dec 2025'!G43 -> 1.9758676e+09 | O55: =SUMIF('Final E-Banker TB Dec 2025'!$A$3:$A$192,'TB December 2025 '!J55,'Final E-Banker TB Dec 2025'!$H$3:$H$192) -> 0 | Q55: =-O55 -> 0 | R55: =N55 -> 1.9758676e+09 | S55: =Q55+R55 -> 1.9758676e+09 | V55: =B55 -> 1058 · Mega Farms-Irrigation Loan | W55: =H55 -> -1.9758676e+09
B56: 1059 · Mega Farm Loans Interest-Capex | C56: =S56 -> 2.1151775e+08 | H56: =E56-C56+F56 -> -2.1151775e+08 | J56: =LEFT(K56,4) -> 1059 | K56: =B56 -> 1059 · Mega Farm Loans Interest-Capex | N56: ='Final E-Banker TB Dec 2025'!G87+'Final E-Banker TB Dec 2025'!G89 -> 2.1151775e+08 | O56: =SUMIF('Final E-Banker TB Dec 2025'!$A$3:$A$192,'TB December 2025 '!J56,'Final E-Banker TB Dec 2025'!$H$3:$H$192) -> 0 | Q56: =-O56 -> 0 | R56: =N56 -> 2.1151775e+08 | S56: =Q56+R56 -> 2.1151775e+08 | V56: =B56 -> 1059 · Mega Farm Loans Interest-Capex | W56: =H56 -> -2.1151775e+08
B57: 1060 · Mega Farm Loans Interest-Fertil | C57: =S57 -> 5.153939e+09 | H57: =E57-C57+F57 -> -5.153939e+09 | J57: =LEFT(K57,4) -> 1060 | K57: =B57 -> 1060 · Mega Farm Loans Interest-Fertil | N57: =SUMIF('Final E-Banker TB Dec 2025'!$A$3:$A$192,J57,'Final E-Banker TB Dec 2025'!$G$3:$G$192)+'Final E-Banker TB Dec 2025'!G83 -> 5.153939e+09 | O57: =SUMIF('Final E-Banker TB Dec 2025'!$A$3:$A$192,'TB December 2025 '!J57,'Final E-Banker TB Dec 2025'!$H$3:$H$192) -> 0 | Q57: =-O57 -> 0 | R57: =N57 -> 5.153939e+09 | S57: =Q57+R57 -> 5.153939e+09 | V57: =B57 -> 1060 · Mega Farm Loans Interest-Fertil | W57: =H57 -> -5.153939e+09
B58: 1061 · Mega Farm Loans Interest-OPEX | C58: =S58 -> 4.3648824e+08 | H58: =E58-C58+F58 -> -4.3648824e+08 | J58: =LEFT(K58,4) -> 1061 | K58: =B58 -> 1061 · Mega Farm Loans Interest-OPEX | N58: ='Final E-Banker TB Dec 2025'!G85+'Final E-Banker TB Dec 2025'!G86+'Final E-Banker TB Dec 2025'!G91+'Final E-Banker TB Dec 2025'!G93 -> 4.3648824e+08 | O58: =SUMIF('Final E-Banker TB Dec 2025'!$A$3:$A$192,'TB December 2025 '!J58,'Final E-Banker TB Dec 2025'!$H$3:$H$192) -> 0 | Q58: =-O58 -> 0 | R58: =N58 -> 4.3648824e+08 | S58: =Q58+R58 -> 4.3648824e+08 | V58: =B58 -> 1061 · Mega Farm Loans Interest-OPEX | W58: =H58 -> -4.3648824e+08
B59: 1062 · Mega Farm Loans Interest-Seed | C59: =S59 -> 1.2029564e+09 | H59: =E59-C59+F59 -> -1.2029564e+09 | J59: =LEFT(K59,4) -> 1062 | K59: =B59 -> 1062 · Mega Farm Loans Interest-Seed | N59: =SUMIF('Final E-Banker TB Dec 2025'!$A$3:$A$192,J59,'Final E-Banker TB Dec 2025'!$G$3:$G$192)+'Final E-Banker TB Dec 2025'!G84 -> 1.2029564e+09 | O59: =SUMIF('Final E-Banker TB Dec 2025'!$A$3:$A$192,'TB December 2025 '!J59,'Final E-Banker TB Dec 2025'!$H$3:$H$192) -> 0 | Q59: =-O59 -> 0 | R59: =N59 -> 1.2029564e+09 | S59: =Q59+R59 -> 1.2029564e+09 | V59: =B59 -> 1062 · Mega Farm Loans Interest-Seed | W59: =H59 -> -1.2029564e+09
B60: 1063 · Mega Farm - Pesticides Loan | C60: =S60 -> 1.9370391e+09 | H60: =E60-C60+F60 -> -1.9370391e+09 | J60: =LEFT(K60,4) -> 1063 | K60: =B60 -> 1063 · Mega Farm - Pesticides Loan | N60: ='Final E-Banker TB Dec 2025'!G44 -> 1.9370391e+09 | O60: =SUMIF('Final E-Banker TB Dec 2025'!$A$3:$A$192,'TB December 2025 '!J60,'Final E-Banker TB Dec 2025'!$H$3:$H$192) -> 0 | Q60: =-O60 -> 0 | R60: =N60 -> 1.9370391e+09 | S60: =Q60+R60 -> 1.9370391e+09 | V60: =B60 -> 1063 · Mega Farm - Pesticides Loan | W60: =H60 -> -1.9370391e+09
B61: 1066 · ECL Megafarm Loans | C61: =S61 -> 1.8927463e+09 | F61: =-F114-447850999.2 -> -4.1326035e+10 | G61: Additional Mega Farms ECL | H61: =E61-C61+F61 -> -4.3218781e+10 | J61: =LEFT(K61,4) -> 1066 | K61: =B61 -> 1066 · ECL Megafarm Loans | N61: =SUMIF('Final E-Banker TB Dec 2025'!$A$3:$A$192,J61,'Final E-Banker TB Dec 2025'!$G$3:$G$192) -> 1.8927463e+09 | O61: =SUMIF('Final E-Banker TB Dec 2025'!$A$3:$A$192,'TB December 2025 '!J61,'Final E-Banker TB Dec 2025'!$H$3:$H$192) -> 0 | Q61: =-O61 -> 0 | R61: =N61 -> 1.8927463e+09 | S61: =Q61+R61 -> 1.8927463e+09 | V61: =B61 -> 1066 · ECL Megafarm Loans | W61: =H61 -> -4.3218781e+10
B62: 1067 · Mega Farm Loans Interest-Pestic | C62: =S62 -> 3.0853077e+08 | H62: =E62-C62+F62 -> -3.0853077e+08 | J62: =LEFT(K62,4) -> 1067 | K62: =B62 -> 1067 · Mega Farm Loans Interest-Pestic | N62: ='Final E-Banker TB Dec 2025'!G94+'Final E-Banker TB Dec 2025'!G88 -> 3.0853077e+08 | O62: =SUMIF('Final E-Banker TB Dec 2025'!$A$3:$A$192,'TB December 2025 '!J62,'Final E-Banker TB Dec 2025'!$H$3:$H$192) -> 0 | Q62: =-O62 -> 0 | R62: =N62 -> 3.0853077e+08 | S62: =Q62+R62 -> 3.0853077e+08 | V62: =B62 -> 1067 · Mega Farm Loans Interest-Pestic | W62: =H62 -> -3.0853077e+08
B63: 1051 · Employee loan and advances | C63: =S63 -> 3.5151237e+08 | H63: =E63-C63+F63 -> -3.5151237e+08 | J63: =LEFT(K63,4) -> 1051 | K63: =B63 -> 1051 · Employee loan and advances | N63: =SUMIF('Final E-Banker TB Dec 2025'!$A$3:$A$192,J63,'Final E-Banker TB Dec 2025'!$G$3:$G$192) -> 3.5151237e+08 | O63: =SUMIF('Final E-Banker TB Dec 2025'!$A$3:$A$192,'TB December 2025 '!J63,'Final E-Banker TB Dec 2025'!$H$3:$H$192) -> 0 | Q63: =-O63 -> 0 | R63: =N63 -> 3.5151237e+08 | S63: =Q63+R63 -> 3.5151237e+08 | V63: =B63 -> 1051 · Employee loan and advances | W63: =H63 -> -3.5151237e+08
B64: 1052 · Prepaid expenses | C64: =S64 -> 58392454 | H64: =E64-C64+F64 -> -58392454 | J64: =LEFT(K64,4) -> 1052 | K64: =B64 -> 1052 · Prepaid expenses | N64: =SUMIF('Final E-Banker TB Dec 2025'!$A$3:$A$192,J64,'Final E-Banker TB Dec 2025'!$G$3:$G$192) -> 58392454 | O64: =SUMIF('Final E-Banker TB Dec 2025'!$A$3:$A$192,'TB December 2025 '!J64,'Final E-Banker TB Dec 2025'!$H$3:$H$192) -> 0 | Q64: =-O64 -> 0 | R64: =N64 -> 58392454 | S64: =Q64+R64 -> 58392454 | V64: =B64 -> 1052 · Prepaid expenses | W64: =H64 -> -58392454
B65: 1070. Mega Farms Receivable- ADMARC | C65: =S65 -> 3.1017893e+09 | H65: =E65-C65+F65 -> -3.1017893e+09 | J65: =LEFT(K65,4) -> 1070 | K65: =B65 -> 1070. Mega Farms Receivable- ADMARC | N65: =SUMIF('Final E-Banker TB Dec 2025'!$A$3:$A$192,J65,'Final E-Banker TB Dec 2025'!$G$3:$G$192) -> 3.1017893e+09 | O65: =SUMIF('Final E-Banker TB Dec 2025'!$A$3:$A$192,'TB December 2025 '!J65,'Final E-Banker TB Dec 2025'!$H$3:$H$192) -> 0 | Q65: =-O65 -> 0 | R65: =N65 -> 3.1017893e+09 | S65: =Q65+R65 -> 3.1017893e+09 | V65: =B65 -> 1070. Mega Farms Receivable- ADMARC | W65: =H65 -> -3.1017893e+09
B66: 1071. Mega Farms Receivable- NFRA | C66: =S66 -> 70177833 | H66: =E66-C66+F66 -> -70177833 | J66: =LEFT(K66,4) -> 1071 | K66: =B66 -> 1071. Mega Farms Receivable- NFRA | N66: =SUMIF('Final E-Banker TB Dec 2025'!$A$3:$A$192,J66,'Final E-Banker TB Dec 2025'!$G$3:$G$192) -> 70177833 | O66: =SUMIF('Final E-Banker TB Dec 2025'!$A$3:$A$192,'TB December 2025 '!J66,'Final E-Banker TB Dec 2025'!$H$3:$H$192) -> 0 | Q66: =-O66 -> 0 | R66: =N66 -> 70177833 | S66: =Q66+R66 -> 70177833 | V66: =B66 -> 1071. Mega Farms Receivable- NFRA | W66: =H66 -> -70177833
B67: 1074 . Mega Farm Receivable ACE Agriculture Limited | C67: =S67 -> 4.2913496e+08 | H67: =E67-C67+F67 -> -4.2913496e+08 | J67: =LEFT(K67,4) -> 1074 | K67: =B67 -> 1074 . Mega Farm Receivable ACE Agriculture Limited | N67: =SUMIF('Final E-Banker TB Dec 2025'!$A$3:$A$192,J67,'Final E-Banker TB Dec 2025'!$G$3:$G$192) -> 4.2913496e+08 | O67: =SUMIF('Final E-Banker TB Dec 2025'!$A$3:$A$192,'TB December 2025 '!J67,'Final E-Banker TB Dec 2025'!$H$3:$H$192) -> 0 | Q67: =-O67 -> 0 | R67: =N67 -> 4.2913496e+08 | S67: =Q67+R67 -> 4.2913496e+08 | V67: =B67 -> 1074 . Mega Farm Receivable ACE Agriculture Limited | W67: =H67 -> -4.2913496e+08
B68: 1100 · Cash Collateral | C68: =S68 -> -7000000 | H68: =E68-C68+F68 -> 7000000 | J68: =LEFT(K68,4) -> 1100 | K68: =B68 -> 1100 · Cash Collateral | N68: =SUMIF('Final E-Banker TB Dec 2025'!$A$3:$A$192,J68,'Final E-Banker TB Dec 2025'!$G$3:$G$192) -> 0 | O68: =SUMIF('Final E-Banker TB Dec 2025'!$A$3:$A$192,'TB December 2025 '!J68,'Final E-Banker TB Dec 2025'!$H$3:$H$192) -> 7000000 | Q68: =-O68 -> -7000000 | R68: =N68 -> 0 | S68: =Q68+R68 -> -7000000 | V68: =B68 -> 1100 · Cash Collateral | W68: =H68 -> 7000000
B69: 1210 · Cash passport card | C69: =S69 -> 2683823.6 | F69: =2683823.61 -> 2683823.6 | G69: Travel expenses | H69: =E69-C69+F69 -> 0 | J69: =LEFT(K69,4) -> 1210 | K69: =B69 -> 1210 · Cash passport card | N69: =SUMIF('Final E-Banker TB Dec 2025'!$A$3:$A$192,J69,'Final E-Banker TB Dec 2025'!$G$3:$G$192) -> 2683823.6 | O69: =SUMIF('Final E-Banker TB Dec 2025'!$A$3:$A$192,'TB December 2025 '!J69,'Final E-Banker TB Dec 2025'!$H$3:$H$192) -> 0 | Q69: =-O69 -> 0 | R69: =N69 -> 2683823.6 | S69: =Q69+R69 -> 2683823.6 | V69: =B69 -> 1210 · Cash passport card | W69: =H69 -> 0
B70: 1310 · Prepaid Insurance | C70: =S70 -> 81652611 | H70: =E70-C70+F70 -> -81652611 | J70: =LEFT(K70,4) -> 1310 | K70: =B70 -> 1310 · Prepaid Insurance | N70: =SUMIF('Final E-Banker TB Dec 2025'!$A$3:$A$192,J70,'Final E-Banker TB Dec 2025'!$G$3:$G$192) -> 81652611 | O70: =SUMIF('Final E-Banker TB Dec 2025'!$A$3:$A$192,'TB December 2025 '!J70,'Final E-Banker TB Dec 2025'!$H$3:$H$192) -> 0 | Q70: =-O70 -> 0 | R70: =N70 -> 81652611 | S70: =Q70+R70 -> 81652611 | V70: =B70 -> 1310 · Prepaid Insurance | W70: =H70 -> -81652611
B71: 1320 · Interest Suspense | C71: =S71 -> -21865867 | H71: =E71-C71+F71 -> 21865867 | J71: =LEFT(K71,4) -> 1320 | K71: =B71 -> 1320 · Interest Suspense | N71: =SUMIF('Final E-Banker TB Dec 2025'!$A$3:$A$192,J71,'Final E-Banker TB Dec 2025'!$G$3:$G$192) -> 0 | O71: =SUMIF('Final E-Banker TB Dec 2025'!$A$3:$A$192,'TB December 2025 '!J71,'Final E-Banker TB Dec 2025'!$H$3:$H$192) -> 21865867 | Q71: =-O71 -> -21865867 | R71: =N71 -> 0 | S71: =Q71+R71 -> -21865867 | V71: =B71 -> 1320 · Interest Suspense | W71: =H71 -> 21865867
B72: 1321 · Capital Raising Prepayment | C72: =S72 -> 0 | H72: =E72-C72+F72 -> 0 | J72: =LEFT(K72,4) -> 1321 | K72: =B72 -> 1321 · Capital Raising Prepayment | N72: =SUMIF('Final E-Banker TB Dec 2025'!$A$3:$A$192,J72,'Final E-Banker TB Dec 2025'!$G$3:$G$192) -> 0 | O72: =SUMIF('Final E-Banker TB Dec 2025'!$A$3:$A$192,'TB December 2025 '!J72,'Final E-Banker TB Dec 2025'!$H$3:$H$192) -> 0 | Q72: =-O72 -> 0 | R72: =N72 -> 0 | S72: =Q72+R72 -> 0 | V72: =B72 -> 1321 · Capital Raising Prepayment | W72: =H72 -> 0
B73: 1877 · Prepaid Loan Repayments Account | C73: =S73 -> 0 | H73: =E73-C73+F73 -> 0 | J73: =LEFT(K73,4) -> 1877 | K73: =B73 -> 1877 · Prepaid Loan Repayments Account | N73: =SUMIF('Final E-Banker TB Dec 2025'!$A$3:$A$192,J73,'Final E-Banker TB Dec 2025'!$G$3:$G$192) -> 0 | O73: =SUMIF('Final E-Banker TB Dec 2025'!$A$3:$A$192,'TB December 2025 '!J73,'Final E-Banker TB Dec 2025'!$H$3:$H$192) -> 0 | Q73: =-O73 -> 0 | R73: =N73 -> 0 | S73: =Q73+R73 -> 0 | V73: =B73 -> 1877 · Prepaid Loan Repayments Account | W73: =H73 -> 0
B74: 1500 · Furniture and Fixtures | C74: =S74 -> 460175 | H74: =E74-C74+F74 -> -460175 | J74: =LEFT(K74,4) -> 1500 | K74: =B74 -> 1500 · Furniture and Fixtures | N74: =SUMIF('Final E-Banker TB Dec 2025'!$A$3:$A$192,J74,'Final E-Banker TB Dec 2025'!$G$3:$G$192) -> 460175 | O74: =SUMIF('Final E-Banker TB Dec 2025'!$A$3:$A$192,'TB December 2025 '!J74,'Final E-Banker TB Dec 2025'!$H$3:$H$192) -> 0 | Q74: =-O74 -> 0 | R74: =N74 -> 460175 | S74: =Q74+R74 -> 460175 | V74: =B74 -> 1500 · Furniture and Fixtures | W74: =H74 -> -460175
B75: 1500 · Furniture and Fixtures:1501 · Cost | C75: =S75 -> 1.1332595e+08 | H75: =E75-C75+F75 -> -1.1332595e+08 | J75: =LEFT(K75,4) -> 1500 | K75: =B75 -> 1500 · Furniture and Fixtures:1501 · Cost | N75: ='Final E-Banker TB Dec 2025'!G54 -> 1.1332595e+08 | O75: =SUMIF('Final E-Banker TB Dec 2025'!$A$3:$A$192,'TB December 2025 '!J75,'Final E-Banker TB Dec 2025'!$H$3:$H$192) -> 0 | Q75: =-O75 -> 0 | R75: =N75 -> 1.1332595e+08 | S75: =Q75+R75 -> 1.1332595e+08 | V75: =B75 -> 1500 · Furniture and Fixtures:1501 · Cost | W75: =H75 -> -1.1332595e+08
B76: 1500 · Furniture and Fixtures:1502 · Depreciation | C76: =S76 -> -94359370 | H76: =E76-C76+F76 -> 94359370 | J76: =LEFT(K76,4) -> 1500 | K76: =B76 -> 1500 · Furniture and Fixtures:1502 · Depreciation | N76: 0 | O76: ='Final E-Banker TB Dec 2025'!H58 -> 94359370 | Q76: =-O76 -> -94359370 | R76: =N76 -> 0 | S76: =Q76+R76 -> -94359370 | V76: =B76 -> 1500 · Furniture and Fixtures:1502 · Depreciation | W76: =H76 -> 94359370
B77: 1510 · Computer Equipment:1511 · Cost | C77: =S77 -> 2.0782183e+08 | H77: =E77-C77+F77 -> -2.0782183e+08 | J77: =LEFT(K77,4) -> 1510 | K77: =B77 -> 1510 · Computer Equipment:1511 · Cost | N77: ='Final E-Banker TB Dec 2025'!G53 -> 2.0782183e+08 | O77: =SUMIF('Final E-Banker TB Dec 2025'!$A$3:$A$192,'TB December 2025 '!J77,'Final E-Banker TB Dec 2025'!$H$3:$H$192) -> 0 | Q77: =-O77 -> 0 | R77: =N77 -> 2.0782183e+08 | S77: =Q77+R77 -> 2.0782183e+08 | V77: =B77 -> 1510 · Computer Equipment:1511 · Cost | W77: =H77 -> -2.0782183e+08
B78: 1510 · Computer Equipment:1512 · Depreciation | C78: =S78 -> -1.1016554e+08 | H78: =E78-C78+F78 -> 1.1016554e+08 | J78: =LEFT(K78,4) -> 1510 | K78: =B78 -> 1510 · Computer Equipment:1512 · Depreciation | N78: =SUMIF('Final E-Banker TB Dec 2025'!$A$3:$A$192,J78,'Final E-Banker TB Dec 2025'!$G$3:$G$192) -> 0 | O78: ='Final E-Banker TB Dec 2025'!H57 -> 1.1016554e+08 | Q78: =-O78 -> -1.1016554e+08 | R78: =N78 -> 0 | S78: =Q78+R78 -> -1.1016554e+08 | V78: =B78 -> 1510 · Computer Equipment:1512 · Depreciation | W78: =H78 -> 1.1016554e+08
B79: 1520 · Office Equipment:1521 · Cost | C79: =S79 -> 53624127 | H79: =E79-C79+F79 -> -53624127 | J79: =LEFT(K79,4) -> 1520 | K79: =B79 -> 1520 · Office Equipment:1521 · Cost | N79: ='Final E-Banker TB Dec 2025'!G51 -> 53624127 | O79: =SUMIF('Final E-Banker TB Dec 2025'!$A$3:$A$192,'TB December 2025 '!J79,'Final E-Banker TB Dec 2025'!$H$3:$H$192) -> 0 | Q79: =-O79 -> 0 | R79: =N79 -> 53624127 | S79: =Q79+R79 -> 53624127 | V79: =B79 -> 1520 · Office Equipment:1521 · Cost | W79: =H79 -> -53624127
B80: 1520 · Office Equipment:1522 · Depreciation | C80: =S80 -> -28875489 | H80: =E80-C80+F80 -> 28875489 | J80: =LEFT(K80,4) -> 1520 | K80: =B80 -> 1520 · Office Equipment:1522 · Depreciation | N80: =SUMIF('Final E-Banker TB Dec 2025'!$A$3:$A$192,J80,'Final E-Banker TB Dec 2025'!$G$3:$G$192) -> 0 | O80: ='Final E-Banker TB Dec 2025'!H56 -> 28875489 | Q80: =-O80 -> -28875489 | R80: =N80 -> 0 | S80: =Q80+R80 -> -28875489 | V80: =B80 -> 1520 · Office Equipment:1522 · Depreciation | W80: =H80 -> 28875489
B81: 1530 · Motor Vehicles:1531 · Cost | C81: =S81 -> 8.018451e+08 | H81: =E81-C81+F81 -> -8.018451e+08 | J81: =LEFT(K81,4) -> 1530 | K81: =B81 -> 1530 · Motor Vehicles:1531 · Cost | N81: ='Final E-Banker TB Dec 2025'!G55 -> 8.018451e+08 | O81: =SUMIF('Final E-Banker TB Dec 2025'!$A$3:$A$192,'TB December 2025 '!J81,'Final E-Banker TB Dec 2025'!$H$3:$H$192) -> 0 | Q81: =-O81 -> 0 | R81: =N81 -> 8.018451e+08 | S81: =Q81+R81 -> 8.018451e+08 | V81: =B81 -> 1530 · Motor Vehicles:1531 · Cost | W81: =H81 -> -8.018451e+08
B82: 1530 · Motor Vehicles:1532 · Depreciation | C82: =S82 -> -3.2174819e+08 | H82: =E82-C82+F82 -> 3.2174819e+08 | J82: =LEFT(K82,4) -> 1530 | K82: =B82 -> 1530 · Motor Vehicles:1532 · Depreciation | N82: =SUMIF('Final E-Banker TB Dec 2025'!$A$3:$A$192,J82,'Final E-Banker TB Dec 2025'!$G$3:$G$192) -> 0 | O82: ='Final E-Banker TB Dec 2025'!H59 -> 3.2174819e+08 | Q82: =-O82 -> -3.2174819e+08 | R82: =N82 -> 0 | S82: =Q82+R82 -> -3.2174819e+08 | V82: =B82 -> 1530 · Motor Vehicles:1532 · Depreciation | W82: =H82 -> 3.2174819e+08
B83: 1545 · Software | C83: =S83 -> 0 | H83: =E83-C83+F83 -> 0 | J83: =LEFT(K83,4) -> 1545 | K83: =B83 -> 1545 · Software | N83: =SUMIF('Final E-Banker TB Dec 2025'!$A$3:$A$192,J83,'Final E-Banker TB Dec 2025'!$G$3:$G$192) -> 0 | O83: =SUMIF('Final E-Banker TB Dec 2025'!$A$3:$A$192,'TB December 2025 '!J83,'Final E-Banker TB Dec 2025'!$H$3:$H$192) -> 0 | Q83: =-O83 -> 0 | R83: =N83 -> 0 | S83: =Q83+R83 -> 0 | V83: =B83 -> 1545 · Software | W83: =H83 -> 0
B84: 1545 · Software:1546 · Cost | C84: =S84 -> 1.8970459e+09 | H84: =E84-C84+F84 -> -1.8970459e+09 | J84: =LEFT(K84,4) -> 1545 | K84: =B84 -> 1545 · Software:1546 · Cost | N84: ='Final E-Banker TB Dec 2025'!G60 -> 1.8970459e+09 | O84: =SUMIF('Final E-Banker TB Dec 2025'!$A$3:$A$192,'TB December 2025 '!J84,'Final E-Banker TB Dec 2025'!$H$3:$H$192) -> 0 | Q84: =-O84 -> 0 | R84: =N84 -> 1.8970459e+09 | S84: =Q84+R84 -> 1.8970459e+09 | V84: =B84 -> 1545 · Software:1546 · Cost | W84: =H84 -> -1.8970459e+09
B85: 1545 · Software:1547 · Depreciation | C85: =S85 -> -2.9260368e+08 | H85: =E85-C85+F85 -> 2.9260368e+08 | J85: =LEFT(K85,4) -> 1545 | K85: =B85 -> 1545 · Software:1547 · Depreciation | N85: =SUMIF('Final E-Banker TB Dec 2025'!$A$3:$A$192,J85,'Final E-Banker TB Dec 2025'!$G$3:$G$192) -> 0 | O85: ='Final E-Banker TB Dec 2025'!H61 -> 2.9260368e+08 | Q85: =-O85 -> -2.9260368e+08 | R85: =N85 -> 0 | S85: =Q85+R85 -> -2.9260368e+08 | V85: =B85 -> 1545 · Software:1547 · Depreciation | W85: =H85 -> 2.9260368e+08
B86: 1595 · Right of Use:1596 · Cost | C86: =S86 -> 0 | H86: =E86-C86+F86 -> 0 | J86: =LEFT(K86,4) -> 1595 | K86: =B86 -> 1595 · Right of Use:1596 · Cost | N86: =SUMIF('Final E-Banker TB Dec 2025'!$A$3:$A$192,J86,'Final E-Banker TB Dec 2025'!$G$3:$G$192) -> 0 | O86: =SUMIF('Final E-Banker TB Dec 2025'!$A$3:$A$192,'TB December 2025 '!J86,'Final E-Banker TB Dec 2025'!$H$3:$H$192) -> 0 | Q86: =-O86 -> 0 | R86: =N86 -> 0 | S86: =Q86+R86 -> 0 | V86: =B86 -> 1595 · Right of Use:1596 · Cost | W86: =H86 -> 0
B87: 1595 · Right of Use:1597 · Amortisation/ Depreciation | C87: =S87 -> 0 | H87: =E87-C87+F87 -> 0 | J87: =LEFT(K87,4) -> 1595 | K87: =B87 -> 1595 · Right of Use:1597 · Amortisation/ Depreciation | N87: =SUMIF('Final E-Banker TB Dec 2025'!$A$3:$A$192,J87,'Final E-Banker TB Dec 2025'!$G$3:$G$192) -> 0 | O87: =SUMIF('Final E-Banker TB Dec 2025'!$A$3:$A$192,'TB December 2025 '!J87,'Final E-Banker TB Dec 2025'!$H$3:$H$192) -> 0 | Q87: =-O87 -> 0 | R87: =N87 -> 0 | S87: =Q87+R87 -> 0 | V87: =B87 -> 1595 · Right of Use:1597 · Amortisation/ Depreciation | W87: =H87 -> 0
B88: 1548 · Amortization | C88: =S88 -> 0 | H88: =E88-C88+F88 -> 0 | J88: =LEFT(K88,4) -> 1548 | K88: =B88 -> 1548 · Amortization | N88: =SUMIF('Final E-Banker TB Dec 2025'!$A$3:$A$192,J88,'Final E-Banker TB Dec 2025'!$G$3:$G$192) -> 0 | O88: =SUMIF('Final E-Banker TB Dec 2025'!$A$3:$A$192,'TB December 2025 '!J88,'Final E-Banker TB Dec 2025'!$H$3:$H$192) -> 0 | Q88: =-O88 -> 0 | R88: =N88 -> 0 | S88: =Q88+R88 -> 0 | V88: =B88 -> 1548 · Amortization | W88: =H88 -> 0
B89: 1549 · WIP | C89: =S89 -> -1.4857679e+08 | F89: 0 | H89: =E89-C89+F89 -> 1.4857679e+08 | J89: =LEFT(K89,4) -> 1549 | K89: =B89 -> 1549 · WIP | N89: =SUMIF('Final E-Banker TB Dec 2025'!$A$3:$A$192,J89,'Final E-Banker TB Dec 2025'!$G$3:$G$192) -> 0 | O89: =SUMIF('Final E-Banker TB Dec 2025'!$A$3:$A$192,'TB December 2025 '!J89,'Final E-Banker TB Dec 2025'!$H$3:$H$192) -> 1.4857679e+08 | Q89: =-O89 -> -1.4857679e+08 | R89: =N89 -> 0 | S89: =Q89+R89 -> -1.4857679e+08 | V89: =B89 -> 1549 · WIP | W89: =H89 -> 1.4857679e+08
B90: 1871 · Undrawn Commitment-MAIIC | C90: =S90 -> 2.9191638e+09 | F90: 1478749196 | G90: Undrawn commitments | H90: =E90-C90+F90 -> -1.4404147e+09 | J90: =LEFT(K90,4) -> 1871 | K90: =B90 -> 1871 · Undrawn Commitment-MAIIC | N90: =SUMIF('Final E-Banker TB Dec 2025'!$A$3:$A$192,J90,'Final E-Banker TB Dec 2025'!$G$3:$G$192) -> 2.9191638e+09 | O90: =SUMIF('Final E-Banker TB Dec 2025'!$A$3:$A$192,'TB December 2025 '!J90,'Final E-Banker TB Dec 2025'!$H$3:$H$192) -> 0 | Q90: =-O90 -> 0 | R90: =N90 -> 2.9191638e+09 | S90: =Q90+R90 -> 2.9191638e+09 | V90: =B90 -> 1871 · Undrawn Commitment-MAIIC | W90: =H90 -> -1.4404147e+09
B91: 1872 · Undrawn Commitments-FInES | C91: =S91 -> 39568984 | F91: 3.1998526e+08 | G91: Undrawn commitments | H91: =E91-C91+F91 -> 2.8041628e+08 | J91: =LEFT(K91,4) -> 1872 | K91: =B91 -> 1872 · Undrawn Commitments-FInES | N91: =SUMIF('Final E-Banker TB Dec 2025'!$A$3:$A$192,J91,'Final E-Banker TB Dec 2025'!$G$3:$G$192) -> 39568984 | O91: =SUMIF('Final E-Banker TB Dec 2025'!$A$3:$A$192,'TB December 2025 '!J91,'Final E-Banker TB Dec 2025'!$H$3:$H$192) -> 0 | Q91: =-O91 -> 0 | R91: =N91 -> 39568984 | S91: =Q91+R91 -> 39568984 | V91: =B91 -> 1872 · Undrawn Commitments-FInES | W91: =H91 -> 2.8041628e+08
B92: 1873 · Guarantees MAIIC | C92: =S92 -> 40847815 | H92: =E92-C92+F92 -> -40847815 | J92: =LEFT(K92,4) -> 1873 | K92: =B92 -> 1873 · Guarantees MAIIC | N92: =SUMIF('Final E-Banker TB Dec 2025'!$A$3:$A$192,J92,'Final E-Banker TB Dec 2025'!$G$3:$G$192) -> 40847815 | O92: =SUMIF('Final E-Banker TB Dec 2025'!$A$3:$A$192,'TB December 2025 '!J92,'Final E-Banker TB Dec 2025'!$H$3:$H$192) -> 0 | Q92: =-O92 -> 0 | R92: =N92 -> 40847815 | S92: =Q92+R92 -> 40847815 | V92: =B92 -> 1873 · Guarantees MAIIC | W92: =H92 -> -40847815
B93: 1874 · Guarantees -FInES | C93: =S93 -> 1338483000 | H93: =E93-C93+F93 -> -1338483000 | J93: =LEFT(K93,4) -> 1874 | K93: =B93 -> 1874 · Guarantees -FInES | N93: =SUMIF('Final E-Banker TB Dec 2025'!$A$3:$A$192,J93,'Final E-Banker TB Dec 2025'!$G$3:$G$192) -> 1338483000 | O93: =SUMIF('Final E-Banker TB Dec 2025'!$A$3:$A$192,'TB December 2025 '!J93,'Final E-Banker TB Dec 2025'!$H$3:$H$192) -> 0 | Q93: =-O93 -> 0 | R93: =N93 -> 1338483000 | S93: =Q93+R93 -> 1338483000 | V93: =B93 -> 1874 · Guarantees -FInES | W93: =H93 -> -1338483000
B94: 1875 · Guarantees -AGCOM | C94: =S94 -> 170064000 | H94: =E94-C94+F94 -> -170064000 | J94: =LEFT(K94,4) -> 1875 | K94: =B94 -> 1875 · Guarantees -AGCOM | N94: =SUMIF('Final E-Banker TB Dec 2025'!$A$3:$A$192,J94,'Final E-Banker TB Dec 2025'!$G$3:$G$192) -> 170064000 | O94: =SUMIF('Final E-Banker TB Dec 2025'!$A$3:$A$192,'TB December 2025 '!J94,'Final E-Banker TB Dec 2025'!$H$3:$H$192) -> 0 | Q94: =-O94 -> 0 | R94: =N94 -> 170064000 | S94: =Q94+R94 -> 170064000 | V94: =B94 -> 1875 · Guarantees -AGCOM | W94: =H94 -> -170064000
B95: 1876 · ECL Write Offs | C95: =S95 -> -22286434 | F95: =-F100 -> 1.3813568e+08 | G95: MUSECO Write Off | H95: =E95-C95+F95 -> 1.6042212e+08 | J95: =LEFT(K95,4) -> 1876 | K95: =B95 -> 1876 · ECL Write Offs | N95: =SUMIF('Final E-Banker TB Dec 2025'!$A$3:$A$192,J95,'Final E-Banker TB Dec 2025'!$G$3:$G$192) -> 0 | O95: =SUMIF('Final E-Banker TB Dec 2025'!$A$3:$A$192,'TB December 2025 '!J95,'Final E-Banker TB Dec 2025'!$H$3:$H$192) -> 22286434 | Q95: =-O95 -> -22286434 | R95: =N95 -> 0 | S95: =Q95+R95 -> -22286434 | V95: =B95 -> 1876 · ECL Write Offs | W95: =H95 -> 1.6042212e+08
B96: 2000 · Accounts Payable | C96: =S96 -> -22012167 | H96: =E96-C96+F96 -> 22012167 | J96: =LEFT(K96,4) -> 2000 | K96: =B96 -> 2000 · Accounts Payable | N96: =SUMIF('Final E-Banker TB Dec 2025'!$A$3:$A$192,J96,'Final E-Banker TB Dec 2025'!$G$3:$G$192) -> 0 | O96: =SUMIF('Final E-Banker TB Dec 2025'!$A$3:$A$192,'TB December 2025 '!J96,'Final E-Banker TB Dec 2025'!$H$3:$H$192) -> 22012167 | Q96: =-O96 -> -22012167 | R96: =N96 -> 0 | S96: =Q96+R96 -> -22012167 | V96: =B96 -> 2000 · Accounts Payable | W96: =H96 -> 22012167
B97: 2001 · Accounts Payable - USD | C97: =S97 -> 0 | H97: =E97-C97+F97 -> 0 | J97: =LEFT(K97,4) -> 2001 | K97: =B97 -> 2001 · Accounts Payable - USD | N97: =SUMIF('Final E-Banker TB Dec 2025'!$A$3:$A$192,J97,'Final E-Banker TB Dec 2025'!$G$3:$G$192) -> 0 | O97: =SUMIF('Final E-Banker TB Dec 2025'!$A$3:$A$192,'TB December 2025 '!J97,'Final E-Banker TB Dec 2025'!$H$3:$H$192) -> 0 | Q97: =-O97 -> 0 | R97: =N97 -> 0 | S97: =Q97+R97 -> 0 | V97: =B97 -> 2001 · Accounts Payable - USD | W97: =H97 -> 0
B98: 2002 · Accounts Payable - ZAR | C98: =S98 -> -0.03 | H98: =E98-C98+F98 -> 0.03 | J98: =LEFT(K98,4) -> 2002 | K98: =B98 -> 2002 · Accounts Payable - ZAR | N98: =SUMIF('Final E-Banker TB Dec 2025'!$A$3:$A$192,J98,'Final E-Banker TB Dec 2025'!$G$3:$G$192) -> 0 | O98: =SUMIF('Final E-Banker TB Dec 2025'!$A$3:$A$192,'TB December 2025 '!J98,'Final E-Banker TB Dec 2025'!$H$3:$H$192) -> 0.03 | Q98: =-O98 -> -0.03 | R98: =N98 -> 0 | S98: =Q98+R98 -> -0.03 | V98: =B98 -> 2002 · Accounts Payable - ZAR | W98: =H98 -> 0.03
B99: 2003 · Capital Raising WIP Payables | C99: =S99 -> 0 | H99: =E99-C99+F99 -> 0 | J99: =LEFT(K99,4) -> 2003 | K99: =B99 -> 2003 · Capital Raising WIP Payables | N99: =SUMIF('Final E-Banker TB Dec 2025'!$A$3:$A$192,J99,'Final E-Banker TB Dec 2025'!$G$3:$G$192) -> 0 | O99: =SUMIF('Final E-Banker TB Dec 2025'!$A$3:$A$192,'TB December 2025 '!J99,'Final E-Banker TB Dec 2025'!$H$3:$H$192) -> 0 | Q99: =-O99 -> 0 | R99: =N99 -> 0 | S99: =Q99+R99 -> 0 | V99: =B99 -> 2003 · Capital Raising WIP Payables | W99: =H99 -> 0
B100: 1064 · Term Loans Write Offs | C100: =S100 -> 22286434 | F100: =-138135680.8 -> -1.3813568e+08 | G100: MUSECO Write Off | H100: =E100-C100+F100 -> -1.6042212e+08 | J100: =LEFT(K100,4) -> 1064 | K100: =B100 -> 1064 · Term Loans Write Offs | N100: =SUMIF('Final E-Banker TB Dec 2025'!$A$3:$A$192,J100,'Final E-Banker TB Dec 2025'!$G$3:$G$192) -> 22286434 | O100: =SUMIF('Final E-Banker TB Dec 2025'!$A$3:$A$192,'TB December 2025 '!J100,'Final E-Banker TB Dec 2025'!$H$3:$H$192) -> 0 | Q100: =-O100 -> 0 | R100: =N100 -> 22286434 | S100: =Q100+R100 -> 22286434 | V100: =B100 -> 1064 · Term Loans Write Offs | W100: =H100 -> -1.6042212e+08
B101: 2010 · Loan draw down account | C101: =S101 -> 0 | H101: =E101-C101+F101 -> 0 | J101: =LEFT(K101,4) -> 2010 | K101: =B101 -> 2010 · Loan draw down account | N101: =SUMIF('Final E-Banker TB Dec 2025'!$A$3:$A$192,J101,'Final E-Banker TB Dec 2025'!$G$3:$G$192) -> 0 | O101: =SUMIF('Final E-Banker TB Dec 2025'!$A$3:$A$192,'TB December 2025 '!J101,'Final E-Banker TB Dec 2025'!$H$3:$H$192) -> 0 | Q101: =-O101 -> 0 | R101: =N101 -> 0 | S101: =Q101+R101 -> 0 | V101: =B101 -> 2010 · Loan draw down account | W101: =H101 -> 0
B102: 2030 · Insurance Buffer | C102: =S102 -> -26181588 | H102: =E102-C102+F102 -> 26181588 | J102: =LEFT(K102,4) -> 2030 | K102: =B102 -> 2030 · Insurance Buffer | N102: =SUMIF('Final E-Banker TB Dec 2025'!$A$3:$A$192,J102,'Final E-Banker TB Dec 2025'!$G$3:$G$192) -> 0 | O102: =SUMIF('Final E-Banker TB Dec 2025'!$A$3:$A$192,'TB December 2025 '!J102,'Final E-Banker TB Dec 2025'!$H$3:$H$192) -> 26181588 | Q102: =-O102 -> -26181588 | R102: =N102 -> 0 | S102: =Q102+R102 -> -26181588 | V102: =B102 -> 2030 · Insurance Buffer | W102: =H102 -> 26181588
B103: 2040 · T-Bill Provision | C103: =S103 -> 0 | H103: =E103-C103+F103 -> 0 | J103: =LEFT(K103,4) -> 2040 | K103: =B103 -> 2040 · T-Bill Provision | N103: =SUMIF('Final E-Banker TB Dec 2025'!$A$3:$A$192,J103,'Final E-Banker TB Dec 2025'!$G$3:$G$192) -> 0 | O103: =SUMIF('Final E-Banker TB Dec 2025'!$A$3:$A$192,'TB December 2025 '!J103,'Final E-Banker TB Dec 2025'!$H$3:$H$192) -> 0 | Q103: =-O103 -> 0 | R103: =N103 -> 0 | S103: =Q103+R103 -> 0 | V103: =B103 -> 2040 · T-Bill Provision | W103: =H103 -> 0
B104: 2041 · ECL Preference Shares | C104: =S104 -> -1.3481953e+08 | F104: =61896238.64-79160536.02 -> -17264297 | G104: ECL Adjustment | H104: =E104-C104+F104 -> 1.1755523e+08 | J104: =LEFT(K104,4) -> 2041 | K104: =B104 -> 2041 · ECL Preference Shares | N104: =SUMIF('Final E-Banker TB Dec 2025'!$A$3:$A$192,J104,'Final E-Banker TB Dec 2025'!$G$3:$G$192) -> 0 | O104: =SUMIF('Final E-Banker TB Dec 2025'!$A$3:$A$192,'TB December 2025 '!J104,'Final E-Banker TB Dec 2025'!$H$3:$H$192) -> 1.3481953e+08 | Q104: =-O104 -> -1.3481953e+08 | R104: =N104 -> 0 | S104: =Q104+R104 -> -1.3481953e+08 | V104: =B104 -> 2041 · ECL Preference Shares | W104: =H104 -> 1.1755523e+08
...

Sheet Final E-Banker TB Dec 2025
B2: GL Title | C2: Debit | D2: Credit | G2: Dr | H2: Cr
A3: =LEFT(B3,4) -> 1017 | B3: 1017...NBS Cash Collection | C3: 3.3951404e+08 | D3: 0.00 | G3: =C3*1 -> 3.3951404e+08 | H3: =D3*1 -> 0
A4: =LEFT(B4,4) -> 1018 | B4: 1018...NBS Current A/C 21011223 | C4: 1.93082e+08 | D4: 0.00 | G4: =C4*1 -> 1.93082e+08 | H4: =D4*1 -> 0
A5: =LEFT(B5,4) -> 1046 | B5: 1046...First Capital Bank | C5: 28486995 | D5: 0.00 | G5: =C5*1 -> 28486995 | H5: =D5*1 -> 0
A6: =LEFT(B6,4) -> 1001 | B6: 1001...CDH Inv Bank 0050401042201 | C6: 0.00 | D6: 68950246 | G6: =C6*1 -> 0 | H6: =D6*1 -> 68950246
A7: =LEFT(B7,4) -> 1048 | B7: 1048...CDH MAIIC AGRA (MK) | C7: 36188936 | D7: 0.00 | G7: =C7*1 -> 36188936 | H7: =D7*1 -> 0
A8: =LEFT(B8,4) -> 1022 | B8: 1022...AGRA- FCDA | C8: 2.7874847e+08 | D8: 0.00 | G8: =C8*1 -> 2.7874847e+08 | H8: =D8*1 -> 0
A9: =LEFT(B9,4) -> 1010 | B9: 1010...Money Market CDHIB Call Account | C9: 33611611 | D9: 0.00 | G9: =C9*1 -> 33611611 | H9: =D9*1 -> 0
A10: =LEFT(B10,4) -> 1011 | B10: 1011...Money Market FDH Discount House | C10: 2.6970178e+09 | D10: 0.00 | G10: =C10*1 -> 2.6970178e+09 | H10: =D10*1 -> 0
A11: =LEFT(B11,4) -> 1002 | B11: 1002...CDH Inv Bank PIA 0050401044100 | C11: 3276701.7 | D11: 0.00 | G11: =C11*1 -> 3276701.7 | H11: =D11*1 -> 0
A12: =LEFT(B12,4) -> 1005 | B12: 1005...FDI Project Payment-USD | C12: 4.67 | D12: 0.00 | G12: =C12*1 -> 4.67 | H12: =D12*1 -> 0
A13: =LEFT(B13,4) -> 1009 | B13: 1009...Money Market CDHIB Fixed Deposit | C13: 1.8777713e+09 | D13: 0.00 | G13: =C13*1 -> 1.8777713e+09 | H13: =D13*1 -> 0
A14: =LEFT(B14,4) -> 1014 | B14: 1014...Money Market Continental Asset Management | C14: 1.599258e+09 | D14: 0.00 | G14: =C14*1 -> 1.599258e+09 | H14: =D14*1 -> 0
A15: =LEFT(B15,4) -> 1019 | B15: 1019...NBS USD A/C 21011436 | C15: 1846377.7 | D15: 0.00 | G15: =C15*1 -> 1846377.7 | H15: =D15*1 -> 0
A16: =LEFT(B16,4) -> 1021 | B16: 1021...NBS Money Market | C16: 1.5152771e+09 | D16: 0.00 | G16: =C16*1 -> 1.5152771e+09 | H16: =D16*1 -> 0
A17: =LEFT(B17,4) -> 1023 | B17: 1023...MICF- Mbora FCDA - USD | C17: 5.46 | D17: 0.00 | G17: =C17*1 -> 5.46 | H17: =D17*1 -> 0
A18: =LEFT(B18,4) -> 1025 | B18: 1025...Money Market CDHIB Fixed Deposit (USD) | C18: 2.9358364e+08 | D18: 0.00 | G18: =C18*1 -> 2.9358364e+08 | H18: =D18*1 -> 0
A19: =LEFT(B19,4) -> 1027 | B19: 1027...Money Market CDHIB Call Account Fines | C19: 36229353 | D19: 0.00 | G19: =C19*1 -> 36229353 | H19: =D19*1 -> 0
A20: =LEFT(B20,4) -> 1031 | B20: 1031...Money Market CDHIB Fixed Deposit (USD) 2 | C20: 3.6123281e+08 | D20: 0.00 | G20: =C20*1 -> 3.6123281e+08 | H20: =D20*1 -> 0
A21: =LEFT(B21,4) -> 1032 | B21: 1032...Money Market CDHIB Fixed Deposit (USD) 3 | C21: 44302226 | D21: 0.00 | G21: =C21*1 -> 44302226 | H21: =D21*1 -> 0
A22: =LEFT(B22,4) -> 1029 | B22: 1029...NBS Money Market Acc 2 | C22: 8.0886178e+08 | D22: 0.00 | G22: =C22*1 -> 8.0886178e+08 | H22: =D22*1 -> 0
A23: =LEFT(B23,4) -> 1028 | B23: 1028...Money Market Old Mutual Investment Group Ltd | C23: 0.18 | D23: 0.00 | G23: =C23*1 -> 0.18 | H23: =D23*1 -> 0
A24: =LEFT(B24,4) -> 1035 | B24: 1035...Money Market Continental Asset Management 2 | C24: 6.4545771e+09 | D24: 0.00 | G24: =C24*1 -> 6.4545771e+09 | H24: =D24*1 -> 0
A25: =LEFT(B25,4) -> 1037 | B25: 1037...CDHIB Call Account AGCOM | C25: 29851626 | D25: 0.00 | G25: =C25*1 -> 29851626 | H25: =D25*1 -> 0
A26: =LEFT(B26,4) -> 1038 | B26: 1038...CDHIB Fixed Deposit AGCOM | C26: 1808285074 | D26: 0.00 | G26: =C26*1 -> 1808285074 | H26: =D26*1 -> 0
A27: =LEFT(B27,4) -> 1044 | B27: 1044...FDH Discount House 2 | C27: 2.0169857e+09 | D27: 0.00 | G27: =C27*1 -> 2.0169857e+09 | H27: =D27*1 -> 0
A28: =LEFT(B28,4) -> 1047 | B28: 1047...NICO Asset Managers | C28: 3.8223606e+09 | D28: 0.00 | G28: =C28*1 -> 3.8223606e+09 | H28: =D28*1 -> 0
A29: =LEFT(B29,4) -> 1006 | B29: 1006...Petty Cash | C29: 71515.78 | D29: 0.00 | G29: =C29*1 -> 71515.78 | H29: =D29*1 -> 0
A30: =LEFT(B30,4) -> 1050 | B30: 1050...Term Loans | C30: 0.00 | D30: 52033.5 | G30: =C30*1 -> 0 | H30: =D30*1 -> 52033.5
A31: =LEFT(B31,4) -> 1871 | B31: 1871...Undrawn Commitment-MAIIC | C31: 2.9191638e+09 | D31: 0.00 | G31: =C31*1 -> 2.9191638e+09 | H31: =D31*1 -> 0
A32: =LEFT(B32,4) -> 1872 | B32: 1872...Undrawn Commitments-Fines | C32: 39568984 | D32: 0.00 | G32: =C32*1 -> 39568984 | H32: =D32*1 -> 0
A33: =LEFT(B33,4) -> 2063 | B33: 2063...Undrawn Commitments MAIIC | C33: 0.00 | D33: 2.9191638e+09 | G33: =C33*1 -> 0 | H33: =D33*1 -> 2.9191638e+09
A34: =LEFT(B34,4) -> 1050 | B34: 1050101...MAIIC Agricultural Loans | C34: 1.3687378e+09 | D34: 0.00 | G34: =C34*1 -> 1.3687378e+09 | H34: =D34*1 -> 0
A35: =LEFT(B35,4) -> 1050 | B35: 1050102...MAIIC Industrial Loans | C35: 6.4340451e+09 | D35: 0.00 | G35: =C35*1 -> 6.4340451e+09 | H35: =D35*1 -> 0
A36: =LEFT(B36,4) -> 1050 | B36: 1050401...MAIIC Term Loan | C36: 1.8271481e+09 | D36: 0.00 | G36: =C36*1 -> 1.8271481e+09 | H36: =D36*1 -> 0
A37: =LEFT(B37,4) -> 1050 | B37: 1050201...FInES Agricultural Loans | C37: 1.4023931e+09 | D37: 0.00 | G37: =C37*1 -> 1.4023931e+09 | H37: =D37*1 -> 0
A38: =LEFT(B38,4) -> 1050 | B38: 1050202...FInES Industrial Loans | C38: 3.8082887e+09 | D38: 0.00 | G38: =C38*1 -> 3.8082887e+09 | H38: =D38*1 -> 0
A39: =LEFT(B39,7) -> 1050301 | B39: 1050301...Mega Farm Fertilizer Loans | C39: 3.3189976e+10 | D39: 0.00 | G39: =C39*1 -> 3.3189976e+10 | H39: =D39*1 -> 0
A40: =LEFT(B40,7) -> 1050302 | B40: 1050302...Mega Farm Seed Loans | C40: 7.5941669e+09 | D40: 0.00 | G40: =C40*1 -> 7.5941669e+09 | H40: =D40*1 -> 0
A41: =LEFT(B41,7) -> 1050303 | B41: 1050303...Mega Farm Working Capital Loans | C41: 6.6623228e+08 | D41: 0.00 | G41: =C41*1 -> 6.6623228e+08 | H41: =D41*1 -> 0
A42: =LEFT(B42,7) -> 1050304 | B42: 1050304...Mega Farm Equipment Loans | C42: 1.803483e+09 | D42: 0.00 | G42: =C42*1 -> 1.803483e+09 | H42: =D42*1 -> 0
A43: =LEFT(B43,7) -> 1050305 | B43: 1050305...Mega Farms Irrigation | C43: 1.9758676e+09 | D43: 0.00 | G43: =C43*1 -> 1.9758676e+09 | H43: =D43*1 -> 0
A44: =LEFT(B44,7) -> 1050307 | B44: 1050307...Mega Farm-Pesticides Loans | C44: 1.9370391e+09 | D44: 0.00 | G44: =C44*1 -> 1.9370391e+09 | H44: =D44*1 -> 0
A45: =LEFT(B45,4) -> 1051 | B45: 1051...Employee Loan And Advances | C45: 3.5151237e+08 | D45: 0.00 | G45: =C45*1 -> 3.5151237e+08 | H45: =D45*1 -> 0
A46: =LEFT(B46,4) -> 2056 | B46: 2056...ECL-Money Market Investments | C46: 0.00 | D46: 11611179 | G46: =C46*1 -> 0 | H46: =D46*1 -> 11611179
A47: =LEFT(B47,4) -> 2055 | B47: 2055...ECL Loans and Advances | C47: 0.00 | D47: 5.6787009e+08 | G47: =C47*1 -> 0 | H47: =D47*1 -> 5.6787009e+08
A48: =LEFT(B48,4) -> 2041 | B48: 2041...ECL Preference Shares | C48: 0.00 | D48: 1.3481953e+08 | G48: =C48*1 -> 0 | H48: =D48*1 -> 1.3481953e+08
A49: =LEFT(B49,4) -> 2042 | B49: 2042...ECL Staff Loans | C49: 0.00 | D49: 3893096.5 | G49: =C49*1 -> 0 | H49: =D49*1 -> 3893096.5
A50: =LEFT(B50,4) -> 2043 | B50: 2043...ECL Preference Shares | C50: 0.00 | D50: 573386.67 | G50: =C50*1 -> 0 | H50: =D50*1 -> 573386.67
A51: =LEFT(B51,4) -> 1521 | B51: 1521...Office Equipment Cost | C51: 53624127 | D51: 0.00 | G51: =C51*1 -> 53624127 | H51: =D51*1 -> 0
A52: =LEFT(B52,4) -> 1500 | B52: 1500...Furniture And Fixtures | C52: 460175 | D52: 0.00 | G52: =C52*1 -> 460175 | H52: =D52*1 -> 0
A53: =LEFT(B53,4) -> 1511 | B53: 1511...Computer Equipment Cost | C53: 2.0782183e+08 | D53: 0.00 | G53: =C53*1 -> 2.0782183e+08 | H53: =D53*1 -> 0
A54: =LEFT(B54,4) -> 1501 | B54: 1501...Furniture And Fixtures Cost | C54: 1.1332595e+08 | D54: 0.00 | G54: =C54*1 -> 1.1332595e+08 | H54: =D54*1 -> 0
A55: =LEFT(B55,4) -> 1531 | B55: 1531...Motor Vehicles Cost | C55: 8.018451e+08 | D55: 0.00 | G55: =C55*1 -> 8.018451e+08 | H55: =D55*1 -> 0
A56: =LEFT(B56,4) -> 1522 | B56: 1522...Office Equipment Depreciation | C56: 0.00 | D56: 28875489 | G56: =C56*1 -> 0 | H56: =D56*1 -> 28875489
A57: =LEFT(B57,4) -> 1512 | B57: 1512...Computer Equipment Depreciation | C57: 0.00 | D57: 1.1016554e+08 | G57: =C57*1 -> 0 | H57: =D57*1 -> 1.1016554e+08
A58: =LEFT(B58,4) -> 1502 | B58: 1502...Furniture And Fixtures Depreciation | C58: 0.00 | D58: 94359370 | G58: =C58*1 -> 0 | H58: =D58*1 -> 94359370
A59: =LEFT(B59,4) -> 1532 | B59: 1532...Motor Vehicles Depreciation | C59: 0.00 | D59: 3.2174819e+08 | G59: =C59*1 -> 0 | H59: =D59*1 -> 3.2174819e+08
A60: =LEFT(B60,4) -> 1546 | B60: 1546...Software Cost | C60: 1.8970459e+09 | D60: 0.00 | G60: =C60*1 -> 1.8970459e+09 | H60: =D60*1 -> 0
A61: =LEFT(B61,4) -> 1547 | B61: 1547...Software Depreciation | C61: 0.00 | D61: 2.9260368e+08 | G61: =C61*1 -> 0 | H61: =D61*1 -> 2.9260368e+08
A62: =LEFT(B62,4) -> 3065 | B62: 3065...NASCOMEX Limited | C62: 2064285713 | D62: 0.00 | G62: =C62*1 -> 2064285713 | H62: =D62*1 -> 0
A63: =LEFT(B63,4) -> 3061 | B63: 3061...MMC Limited | C63: 1.82929e+08 | D63: 0.00 | G63: =C63*1 -> 1.82929e+08 | H63: =D63*1 -> 0
A64: =LEFT(B64,4) -> 3062 | B64: 3062...Wijays Enterprise | C64: 210065735 | D64: 0.00 | G64: =C64*1 -> 210065735 | H64: =D64*1 -> 0
A65: =LEFT(B65,4) -> 3063 | B65: 3063...Good Hope Private Clinic Limite | C65: 1125625000 | D65: 0.00 | G65: =C65*1 -> 1125625000 | H65: =D65*1 -> 0
A66: =LEFT(B66,4) -> 3067 | B66: 3067...NATURES GIFT LIMITED | C66: 400000000 | D66: 0.00 | G66: =C66*1 -> 400000000 | H66: =D66*1 -> 0
A67: =LEFT(B67,4) -> 3068 | B67: 3068...Small Farm Cities Africa Ltd | C67: 200000000 | D67: 0.00 | G67: =C67*1 -> 200000000 | H67: =D67*1 -> 0
A68: =LEFT(B68,4) -> 3069 | B68: 3069...Kwalingana Investment Limited | C68: 400000000 | D68: 0.00 | G68: =C68*1 -> 400000000 | H68: =D68*1 -> 0
A69: =LEFT(B69,4) -> 3071 | B69: 3071...Napoleon Dzombe T/A Santhe Busi | C69: 2100000000 | D69: 0.00 | G69: =C69*1 -> 2100000000 | H69: =D69*1 -> 0
A70: =LEFT(B70,4) -> 1030 | B70: 1030...Partial Credit Guarantee Fund | C70: 71808009 | D70: 0.00 | G70: =C70*1 -> 71808009 | H70: =D70*1 -> 0
A71: =LEFT(B71,4) -> 1052 | B71: 1052...Prepaid Expenses | C71: 58392454 | D71: 0.00 | G71: =C71*1 -> 58392454 | H71: =D71*1 -> 0
A72: =LEFT(B72,4) -> 1310 | B72: 1310...Prepaid Insurance | C72: 81652611 | D72: 0.00 | G72: =C72*1 -> 81652611 | H72: =D72*1 -> 0
A73: =LEFT(B73,4) -> 1210 | B73: 1210...Cash Passport | C73: 2683823.6 | D73: 0.00 | G73: =C73*1 -> 2683823.6 | H73: =D73*1 -> 0
A74: =LEFT(B74,4) -> 2052 | B74: 2052...Malawi Revenue Authority- Other | C74: 1.9937796e+09 | D74: 0.00 | G74: =C74*1 -> 1.9937796e+09 | H74: =D74*1 -> 0
A75: =LEFT(B75,4) -> 1549 | B75: 1549...WIP | C75: 0.00 | D75: 1.4857679e+08 | G75: =C75*1 -> 0 | H75: =D75*1 -> 1.4857679e+08
A76: =LEFT(B76,4) -> 1053 | B76: 1053...Accounts Receivables | C76: 2.6638798e+08 | D76: 0.00 | G76: =C76*1 -> 2.6638798e+08 | H76: =D76*1 -> 0
A77: =LEFT(B77,4) -> 1074 | B77: 1074...Mega Farm Receivable ACE Agriculture Limited | C77: 4.2913496e+08 | D77: 0.00 | G77: =C77*1 -> 4.2913496e+08 | H77: =D77*1 -> 0
A78: =LEFT(B78,4) -> 1039 | B78: 1039...Accrued Coupon Settlements TOTAL | C78: 5.3820299e+08 | D78: 0.00 | G78: =C78*1 -> 5.3820299e+08 | H78: =D78*1 -> 0
A79: =LEFT(B79,4) -> 1040 | B79: 1040...Accrued Interest Income | C79: 6.2353678e+08 | D79: 0.00 | G79: =C79*1 -> 6.2353678e+08 | H79: =D79*1 -> 0
A80: =LEFT(B80,4) -> 1320 | B80: 1320...Interest Suspense | C80: 0.00 | D80: 21865867 | G80: =C80*1 -> 0 | H80: =D80*1 -> 21865867
A81: =LEFT(B81,4) -> 1070 | B81: 1070...Mega Farms Receivable -ADMARC | C81: 3.1017893e+09 | D81: 0.00 | G81: =C81*1 -> 3.1017893e+09 | H81: =D81*1 -> 0
A82: =LEFT(B82,4) -> 1071 | B82: 1071...Mega Farms Receivable -NFRA | C82: 70177833 | D82: 0.00 | G82: =C82*1 -> 70177833 | H82: =D82*1 -> 0
A83: =LEFT(B83,6) -> 105031 | B83: 105031...Interest Receivable Mega Farm Fertilizer Loans | C83: 1.6797721e+09 | D83: 0.00 | G83: =C83*1 -> 1.6797721e+09 | H83: =D83*1 -> 0
A84: =LEFT(B84,6) -> 105032 | B84: 105032...Interest Receivable On Mega Farm Seed Loans | C84: 3.8982781e+08 | D84: 0.00 | G84: =C84*1 -> 3.8982781e+08 | H84: =D84*1 -> 0
A85: =LEFT(B85,6) -> 105033 | B85: 105033...Interest Receivable On Mega Farm Working Capital Loans | C85: 64723278 | D85: 0.00 | G85: =C85*1 -> 64723278 | H85: =D85*1 -> 0
A86: =LEFT(B86,6) -> 105034 | B86: 105034...Interest Receivable On Mega Farm OPEX | C86: 51266429 | D86: 0.00 | G86: =C86*1 -> 51266429 | H86: =D86*1 -> 0
A87: =LEFT(B87,6) -> 105035 | B87: 105035...Interest Receivable On Mega Farm Irrigation | C87: 1.3166534e+08 | D87: 0.00 | G87: =C87*1 -> 1.3166534e+08 | H87: =D87*1 -> 0
A88: =LEFT(B88,6) -> 105037 | B88: 105037...Interest Receivable On Mega Farm Pesticides Loans | C88: 1.0164954e+08 | D88: 0.00 | G88: =C88*1 -> 1.0164954e+08 | H88: =D88*1 -> 0
A89: =LEFT(B89,4) -> 1059 | B89: 1059...Interest Receivable- Mega Farm Irrigation (Govt) | C89: 79852409 | D89: 0.00 | G89: =C89*1 -> 79852409 | H89: =D89*1 -> 0
A90: =LEFT(B90,4) -> 1060 | B90: 1060...Interest Receivable- Mega Farm Fertilizer (Govt) | C90: 3.4741669e+09 | D90: 0.00 | G90: =C90*1 -> 3.4741669e+09 | H90: =D90*1 -> 0
A91: =LEFT(B91,4) -> 1061 | B91: 1061...Interest Receivable- Mega Farm Working Capital (Govt) | C91: 1.8854414e+08 | D91: 0.00 | G91: =C91*1 -> 1.8854414e+08 | H91: =D91*1 -> 0
A92: =LEFT(B92,4) -> 1062 | B92: 1062...Interest Receivable- Mega Farm Seed (Govt) | C92: 8.1312863e+08 | D92: 0.00 | G92: =C92*1 -> 8.1312863e+08 | H92: =D92*1 -> 0
A93: =LEFT(B93,4) -> 1063 | B93: 1063...Interest Receivable- Mega Farm Equipment (Govt) | C93: 1.319544e+08 | D93: 0.00 | G93: =C93*1 -> 1.319544e+08 | H93: =D93*1 -> 0
A94: =LEFT(B94,4) -> 1065 | B94: 1065...Interest Receivable- Mega Farm Pesticides Loans (Govt) | C94: 2.0688123e+08 | D94: 0.00 | G94: =C94*1 -> 2.0688123e+08 | H94: =D94*1 -> 0
A95: =LEFT(B95,4) -> 1064 | B95: 1064...Term Loans Write Offs | C95: 22286434 | D95: 0.00 | G95: =C95*1 -> 22286434 | H95: =D95*1 -> 0
A96: =LEFT(B96,4) -> 1066 | B96: 1066...ECL Megafarm Loans | C96: 1.8927463e+09 | D96: 0.00 | G96: =C96*1 -> 1.8927463e+09 | H96: =D96*1 -> 0
A97: =LEFT(B97,4) -> 1873 | B97: 1873...Guarantees MAIIC | C97: 40847815 | D97: 0.00 | G97: =C97*1 -> 40847815 | H97: =D97*1 -> 0
A98: =LEFT(B98,4) -> 1874 | B98: 1874...Guarantees -Fines | C98: 1338483000 | D98: 0.00 | G98: =C98*1 -> 1338483000 | H98: =D98*1 -> 0
A99: =LEFT(B99,4) -> 1875 | B99: 1875...Guarantees -AGCOM | C99: 170064000 | D99: 0.00 | G99: =C99*1 -> 170064000 | H99: =D99*1 -> 0
A100: =LEFT(B100,4) -> 3200 | B100: 3200...Retained Earnings | C100: 0.00 | D100: 1.0085046e+10 | G100: =C100*1 -> 0 | H100: =D100*1 -> 1.0085046e+10
A101: =LEFT(B101,4) -> 3003 | B101: 3003...Investment Alliance | C101: 0.00 | D101: 94989242 | G101: =C101*1 -> 0 | H101: =D101*1 -> 94989242
...
