Workbook

Sheet Contents
A1: IFRS 9 - impairment - compliance audit
A2: Contents (the standard's own order of sections). Click a section to open its row on the Audit sheet.
A4: Status definitions | C4: Sections
A5: Done | B5: Implemented in the system and visible in an approved output; the test in column 11 fails if the behaviour changes. | C5: =COUNTIF(Audit!$D:$D,"Done")
A6: Partially done | B6: The mechanics are in place, but a parameter, an input or a piece of evidence still differs from the requirement. | C6: =COUNTIF(Audit!$D:$D,"Partially done")
A7: Outstanding | B7: Required for MAIIC and not built. | C7: =COUNTIF(Audit!$D:$D,"Outstanding")
A8: Not applicable, documented | B8: Does not apply to MAIIC by a recorded decision or fact (reason and reference given); revisit if the facts change. | C8: =COUNTIF(Audit!$D:$D,"Not applicable, documented")
A9: Evidence needed from MAIIC | B9: The system is ready; MAIIC must supply a document, minute or dataset before the row can be closed. | C9: =COUNTIF(Audit!$D:$D,"Evidence needed from MAIIC")
A10: Sections audited | C10: =COUNTA(Audit!$A$5:$A$22)-4
A11: Baselines passing | C11: =COUNTIF(Baselines!$E:$E,"PASS")&" of "&COUNTA(Baselines!$A$5:$A$500)
A13: Ref | B13: Section | C13: Status | D13: Open in Audit
A14: 5.5 RECOGNITION OF EXPECTED CREDIT LOSSES
A15: 5.5.1 | B15: A loss allowance for expected credit losses | C15: =Audit!D6 | D15: Audit row 6
A16: 5.5.3 | B16: Lifetime ECL on a significant increase in credit risk | C16: =Audit!D7 | D16: Audit row 7
A17: 5.5.5 | B17: 12-month ECL where credit risk has not increased significantly | C17: =Audit!D8 | D17: Audit row 8
A18: 5.5.9 to 5.5.11 | B18: Determining a significant increase in credit risk; the 30-days-past-due rebuttable presumption | C18: =Audit!D9 | D18: Audit row 9
A19: B5.5.37 | B19: Definition of default; the 90-days-past-due rebuttable presumption | C19: =Audit!D10 | D19: Audit row 10
A20: 5.5 MEASUREMENT
A21: 5.5.17 | B21: Measurement of expected credit losses | C21: =Audit!D12 | D21: Audit row 12
A22: B5.5.41 to B5.5.43 | B22: Probability-weighted outcomes | C22: =Audit!D13 | D22: Audit row 13
A23: B5.5.49 to B5.5.54 | B23: Reasonable and supportable information; forward-looking information | C23: =Audit!D14 | D23: Audit row 14
A24: B5.5.52 (transmission) | B24: How forward-looking information reaches the PD | C24: =Audit!D15 | D24: Audit row 15
A25: B5.5.1 to B5.5.6, B5.5.28 to B5.5.30 | B25: Collective assessment and segmentation | C25: =Audit!D16 | D25: Audit row 16
A26: B5.5.55 | B26: Loss given default and collateral | C26: =Audit!D17 | D26: Audit row 17
A27: 5.5.17(b), B5.5.44 | B27: Time value of money | C27: =Audit!D18 | D27: Audit row 18
A28: 5.5 WRITE-OFF AND PRESENTATION
A29: 5.4.4, B5.4.9 | B29: Write-off | C29: =Audit!D20 | D29: Audit row 20
A30: THE MEGA FARM PROGRAMME
A31: 16 | B31: The Mega Farm loans in the allowance | C31: =Audit!D22 | D31: Audit row 22
A33: Findings that need a decision or a fix: see the 'Findings' sheet
A34: The acceptance ties read from the system: see the 'Baselines' sheet
A35: Source: IFRS 9 Financial Instruments as issued by the IASB, section 5.5 and B5.5.1 to B5.5.55; 5.4.4 and B5.4.9 (write-off). The Reserve Bank of Malawi Financial Services (Credit Risk Management for Development Finance Institutions) Directive 2018 (docs/regulatory). Specification: docs/MAIIC_EIR_Engine_Specification_v4_2026-10-07.md sections 3.6, 13, 14, 15, 16.

Sheet Audit
A1: IFRS 9 Financial Instruments - impairment (5.5 and B5.5): staging, significant increase in credit risk, 12-month and lifetime expected credit losses, forward-looking information, write-off - compliance audit
A2: Malawi Agricultural and Industrial Investment Company (MAIIC) - IFRS 9 EIR and ECL system - build of 14 October 2026 (branch eir_revenue_recognition, commit abe140d) against specification v4. As of 14 October 2026: the code at commit abe140d and the fresh bootstrap maiic_ifrs9_results2 of 13 October 2026 (made before commit 216aee2, so its discounting and Mega Farm figures predate those changes), read with SELECTs only; the Governance Centre's staging and forward-looking settings; the PHPUnit suite as written (not run for this audit). Main book at September 2026 on that bootstrap: 134 loans, gross 23.19bn, ECL 11.57bn undiscounted, 7.12bn discounted on the 62 loans the time-phased engine resolved (72 unresolved). Reviewer: Dr Thomson Kumwenda (CFO), then Deloitte. Status definitions: see 'Contents'.
A3: Back to Contents
A4: Reference | B4: Section name | C4: What it requires | D4: Status | E4: What the engine does (evidence checked) | F4: General comment | G4: Compliance comment | H4: Where to see it (screen; report or export) | I4: Reviewer sign-off (initials / date) | J4: Governance setting | K4: Test that proves it
A5: 5.5 RECOGNITION OF EXPECTED CREDIT LOSSES
A6: 5.5.1 | B6: A loss allowance for expected credit losses | C6: Recognise a loss allowance for expected credit losses on a financial asset measured at amortised cost. | D6: Done | E6: ifrs9:segment-ecl computes the allowance per loan as EAD x PD x LGD on the post-FLI PD for every portfolio of a month and fails closed, naming the loans, when a stage, PD or LGD is missing or a portfolio mixes Mega Farm with MAIIC's own loans; the bootstrap and the month-end (fli:month-end) run it for every period. On the fresh bootstrap the main book carries an allowance in every month (11.57bn undiscounted at September 2026). | F6: Fresh bootstrap maiic_ifrs9_results2 (13 October 2026, before commit 216aee2). Until 14 October 2026 the row said the PD engine must run for a figure. | G6: Compliant; the figures are system figures under the bootstrap label, not MAIIC-approved (finding F1). | H6: ECL Processing, ECL Calculation: /expected-credit-loss/list | K6: Tests\Feature\Ecl\EclGoldenNumberTest::it_computes_golden_ecl_per_stage_for_prefli_collection_lgd; Tests\Feature\Ecl\TimePhasedEclServiceTest
A7: 5.5.3 | B7: Lifetime ECL on a significant increase in credit risk | C7: At each reporting date, measure the loss allowance at lifetime ECL if the credit risk has increased significantly since initial recognition. | D7: Done | E7: StagingService stages every period: Stage 2 from 31 days past due in every class, the SICR flag from the qualitative groups; the ECL takes the lifetime PD for Stage 2, compounding beyond the 12-month PD. Since 216aee2 the days past due read E-Banker's instalment chart in force at each month-end. | F7: Spec v4 section 3.6, decision D31. | G7: Compliant. | H7: Settings, Staging basis: /setting?tab=staging; IFRS 9 Model Setup, Staging & SICR Rules: /sicr-groups; ECL Processing, ECL Calculation: /expected-credit-loss/list | J7: dpd_basis | K7: Tests\Feature\Ecl\TimePhasedEclServiceTest::test_a_stage_two_lifetime_compounds_beyond_the_twelve_month_pd; Tests\Feature\Eir\StagingServiceTest::test_the_trigger_reads_the_chart_in_force_at_the_month_end_not_a_later_one
A8: 5.5.5 | B8: 12-month ECL where credit risk has not increased significantly | C8: Measure the loss allowance at 12-month ECL where the credit risk has not increased significantly since initial recognition. | D8: Done | E8: Stage 1 loans take the 12-month PD window; the staging writes the stage every period. | G8: Compliant. | H8: ECL Processing, ECL Calculation: /expected-credit-loss/list | K8: Tests\Feature\Ecl\TimePhasedEclServiceTest::test_stage_one_builds_a_twelve_month_marginal_pd_curve_and_discounts_each_shortfall
A9: 5.5.9 to 5.5.11 | B9: Determining a significant increase in credit risk; the 30-days-past-due rebuttable presumption | C9: Assess the change in the risk of default since initial recognition using reasonable and supportable information; there is a rebuttable presumption that credit risk has increased significantly when payments are more than 30 days past due. | D9: Done | E9: Stage 2 from 31 days past due in every facility class, counted from the oldest overdue instalment, with the bucket ageing beside it. The rebuttal is recorded on the threshold rows (staging_thresholds.rebuttal_basis); the LONG_TERM row proposing Stage 2 at 91 days for medium- and long-term facilities only is seeded future-dated (2099) and inactive pending CFO sign-off. The threshold rows are seeded and read-only on screen (a change is a release, not a setting). The staging_rebuttal catalogue setting is shown on Settings but read by no engine. | F9: The O13 rebuttal paper of 8 October 2026. | G9: Compliant; the presumption is applied and the rebuttal awaits the CFO. | H9: Settings, Staging basis: /setting?tab=staging; IFRS 9 Model Setup, Staging & SICR Rules: /sicr-groups; Governance: Governance Centre /eir-governance | J9: dpd_basis; staging_rebuttal (shown, not read) | K9: Tests\Feature\Eir\StagingThresholdSeederTest::test_the_long_term_stage_2_rebuttal_is_inactive_until_signed; Tests\Feature\Eir\StagingServiceTest
A10: B5.5.37 | B10: Definition of default; the 90-days-past-due rebuttable presumption | C10: Apply a definition of default consistent with internal credit risk management; default occurs no later than 90 days past due unless reasonable and supportable information supports a more lagging criterion. | D10: Done | E10: Stage 3 from 91 days for a facility of 12 months or less and for the Mega Farm class, and from 181 days for a medium- or long-term facility, as the RBM directive classifies them; the four-consecutive-missed-instalments trigger lifts a loan to Stage 3 beside the day count, reading the chart in force and net cash (216aee2). The more lagging criterion rests on the directive, cited on each threshold row. | F10: Spec v4 section 3.6 compares the policy (90 days), the November 2025 model (181) and the directive (181/91). | G10: Compliant; the rebuttal is documented on the threshold rows. | H10: Settings, Staging basis: /setting?tab=staging; IFRS 9 Model Setup, Staging & SICR Rules: /sicr-groups | J10: dpd_basis; stage3_missed_instalments | K10: Tests\Feature\Eir\StagingServiceTest::test_the_directive_thresholds_by_tenor_class_and_the_bucket_fallback; Tests\Feature\Eir\StagingThresholdSeederTest::test_medium_and_long_term_facilities_are_stage_3_at_181_days_with_the_rebuttal_cited
A11: 5.5 MEASUREMENT
A12: 5.5.17 | B12: Measurement of expected credit losses | C12: ECL is an unbiased, probability-weighted amount determined by evaluating a range of possible outcomes, the time value of money, and reasonable and supportable information about past events, current conditions and forecasts. | D12: Partially done | E12: The PD and LGD by segment, the forward-looking route once per scenario and the weighted ECL run for every period; discounting at the EIR is the month-end default since 216aee2. What is missing: no fit is approved by a MAIIC reviewer, so the route holds the PD (overlay at zero); the governed scenario set is approved only under the bootstrap label; the legacy synthetic scenario assumptions are still seeded APPROVED (EclScenarioAssumptionSeeder); and the reports read the undiscounted ecl_value (5.5.17(b) row). | F12: Fresh bootstrap maiic_ifrs9_results2 (13 October 2026, before commit 216aee2). Until 14 October 2026 the row said the PD engine had not run on the clean install. | G12: Partially done: the mechanics are in place; an approved fit and set, and the discounted figure in the reports, are awaited. | H12: ECL Processing, ECL Calculation: /expected-credit-loss/list; Forward-Looking Information, Scenario Sets: /scenario-sets | J12: scenario_weighting_method; fli_adjustment_route | K12: Tests\Feature\FLI\FliRouteServiceTest::test_the_ecl_on_the_post_fli_pd_is_the_weighted_ecl_across_scenarios; Tests\Feature\Ecl\TimePhasedEclServiceTest::test_scenario_weights_combine_into_one_allowance
A13: B5.5.41 to B5.5.43 | B13: Probability-weighted outcomes | C13: The estimate reflects the possibility that a credit loss occurs and the possibility that none occurs; a range of scenarios, at least two, weighted by their probabilities. | D13: Done | E13: The governed scenario set: three or more scenarios, weights summing to 100, the base at least 40 percent and no weight above 60, every scenario but the base a shock on the base path; the first set (Base 50, Upside 15, Downside 25, Severe 10) is seeded as a proposal for the CFO. On the fresh bootstrap one set (September 2026) is APPROVED under the bootstrap label. | F13: Fresh bootstrap maiic_ifrs9_results2 (13 October 2026, before commit 216aee2). | G13: Compliant. | H13: Forward-Looking Information, Scenario Sets: /scenario-sets | J13: scenario_minimum_count; scenario_weight_bounds; scenario_calibration_note | K13: Tests\Feature\Scenario\ScenarioSetServiceTest::test_a_set_that_breaks_a_rule_is_refused_with_the_reason
A14: B5.5.49 to B5.5.54 | B14: Reasonable and supportable information; forward-looking information | C14: Use information reasonably available without undue cost or effort, including forecasts of future economic conditions; a statistical relationship used must be supportable. | D14: Done | E14: Malawi macro series with their provenance (13 variables, 261 data points on the fresh bootstrap; none yet carries a release date, so revisions replace the earlier value); the correlation finder sweeps every driver against every credit-loss proxy over the lag grid under the guardrail (expected sign, R2 cutoff, p-value, minimum observations) and declines a failing fit with the reason. On the fresh bootstrap: 209 fits, 32 applied by the guardrail, 177 declined, none approved. | F14: Fresh bootstrap maiic_ifrs9_results2 (13 October 2026, before commit 216aee2). Until 14 October 2026 the row said 39 applied and 170 declined, from the 8 October install. | G14: Compliant; an applied fit is a proposal under maker-checker. | H14: Forward-Looking Information: Overview /fli; Correlation Finder /fli-correlation; Regression /fli-adjustments; transmission methods /fli/transmission-methods; Macro Statistics: /macro-statistics | J14: fli_expected_sign_test; fli_r2_cutoff; fli_min_observations; fli_alpha; macro_source_precedence | K14: Tests\Feature\FLI\FliBridgeServiceTest; Tests\Feature\Macro\MacroImportPrecedenceTest
A15: B5.5.52 (transmission) | B15: How forward-looking information reaches the PD | C15: The method of adjusting the PD for the forecast must be documented and supportable. | D15: Done | E15: Governed transmission methods, each with a card (what it does, the formula, its preconditions checked live against the data, a worked example on one loan); a method whose preconditions are not met cannot be selected; the scalar is seeded because the history cannot yet support the richer methods. | F15: Spec v4 section 14.7. | G15: Compliant. | H15: Forward-Looking Information: Overview /fli; Correlation Finder /fli-correlation; Regression /fli-adjustments; transmission methods /fli/transmission-methods; Governance: Governance Centre /eir-governance | J15: fli_transmission_method; fli_asset_correlation | K15: Tests\Feature\FLI\TransmissionMethodCatalogueTest
A16: B5.5.1 to B5.5.6, B5.5.28 to B5.5.30 | B16: Collective assessment and segmentation | C16: Where information is not available at the instrument level, assess on a collective basis grouped by shared credit-risk characteristics. | D16: Done | E16: PdSegmentationService and LgdSegmentationService measure the PD and LGD per portfolio on the governed basis, a thin segment taking its parent's or the pooled figure under the governed rule, with the lineage on each loan; the Mega Farm programme is its own segment, kept out of MAIIC's PD, LGD and ECL, and a portfolio mixing the two is refused (216aee2). Both run for every period in the bootstrap and the month-end. | F16: Until 14 October 2026 this row was Partially done and said the transition matrices were not in the bootstrap chain. | G16: Compliant. | H16: IFRS 9 Model Setup, PD Model and LGD Model; Reports: PD by portfolio /ifrs9-reports/sector-ecl | J16: pd_segmentation_basis; pd_segment_min_observations; pd_segment_thin_rule; lgd_segment_min_cohort | K16: Tests\Feature\Pd\PdSegmentationTest::test_each_portfolio_gets_its_own_pd_or_its_parents_with_the_lineage_recorded; Tests\Feature\Ecl\MegaFarmProgrammeSeparationTest::test_the_programme_portfolio_is_kept_out_of_the_maiic_scope_and_a_blended_book_is_refused
A17: B5.5.55 | B17: Loss given default and collateral | C17: The cash shortfalls reflect the cash flows expected from collateral and other credit enhancements that are integral to the contractual terms. | D17: Partially done | E17: The LGD is the Stage 3 cohort workout per portfolio (cure, recovery discounted, write-off as loss; a written-off loan left at nil is no longer a cure since 216aee2). Collateral does not enter it: the engine reads no collateral, and on the fresh bootstrap collateral_registers and collateral_allocations are empty although the E-Banker security register (P2_11, 185 rows) is landed. | F17: Until 14 October 2026 this row was referenced B5.5.33 to B5.5.35 and marked Evidence needed; the collateral link is also Dupleix's to build. | G17: Partially done: Credit supplies the collateral and valuations; Dupleix brings collateral into the LGD. | H17: IFRS 9 Model Setup, LGD Model; Collateral Management, Collateral Register: /collateral/register; Reports: LGD and collateral /ifrs9-reports/lgd-collateral | J17: lgd_segment_min_cohort | K17: Tests\Feature\Pd\PdAndLgdEngineTest::test_a_loan_closed_at_nil_is_not_a_cure_and_a_nil_start_balance_is_no_member
A18: 5.5.17(b), B5.5.44 | B18: Time value of money | C18: Discount the expected credit losses at the EIR determined at initial recognition (or an approximation). | D18: Partially done | E18: EclDiscountRateService takes the loan's locked EIR; an unlocked or missing EIR is unresolved, never defaulted, and a floating loan's rate is labelled a proxy; a Stage 3 loss at the reporting date needs no rate. Since 216aee2 the month-end and the bootstrap run discounted by default: ecl_value keeps the engine's measure and ecl_value_discounted holds the discounted allowance, shown on the ECL screen. But the IFRS 9 note, the ECL reconciliation, the RBM Return and the other reports still read ecl_value, so the figure they carry is undiscounted. On the fresh bootstrap at September 2026, 62 main-book loans are discounted (7.12bn) and 72 are unresolved. | F18: Fresh bootstrap maiic_ifrs9_results2 (13 October 2026, before commit 216aee2). Until 14 October 2026 the row said 'the contractual rate where none is locked', which the code never did. | G18: Partially done: the discounted allowance is computed; the reports must carry it. | H18: ECL Processing, ECL Calculation: /expected-credit-loss/list | K18: Tests\Feature\Ecl\EclDiscountRateServiceTest::test_an_unlocked_or_missing_eir_is_unresolved_never_defaulted; Tests\Feature\Ecl\EclGoldenNumberTest::discounted_mode_keeps_undiscounted_ecl_and_names_unresolved_contracts
A19: 5.5 WRITE-OFF AND PRESENTATION
A20: 5.4.4, B5.4.9 | B20: Write-off | C20: Write off the gross carrying amount when there is no reasonable expectation of recovery. | D20: Evidence needed from MAIIC | E20: WriteOffClassifier (220a5a6) identifies ledger write-offs (type 300; a batch debiting GL 1064; ACCOUNT CLOSURE on a status-H account) for the loan-book build, the contract inputs and the EIR cash; the PD cohort counts a write-off as a default (216aee2); the register records a write-off not on the loan account under two-person approval. On the fresh bootstrap: 22 ledger write-offs of 60,778,466.86; the register is empty. | F20: Fresh bootstrap maiic_ifrs9_results2 (13 October 2026, before commit 216aee2). Until 14 October 2026 the row said no write-off had been posted since the take-on. | G20: Evidence needed: MAIIC's write-off policy and Finance's confirmation of status H. | H20: EIR Data, Write-offs: /eir-write-offs | K20: Tests\Feature\Eir\WriteOffTest::test_a_closure_credit_in_a_batch_that_debits_the_write_off_gl_is_a_write_off; Tests\Feature\Pd\PdSegmentationTest::test_a_nil_start_balance_is_no_observation_and_a_write_off_in_the_window_is_a_default
A21: THE MEGA FARM PROGRAMME
A22: 16 | B22: The Mega Farm loans in the allowance | C22: Loans extended under the Government's Mega Farm programme (losses to the fund; MAIIC's 5 percent share) must be in the ECL on a documented basis. | D22: Evidence needed from MAIIC | E22: The programme's monthly books (MF_01 and MF_03) are landed: on the fresh bootstrap 3,692 loans on six of the programme's seven GLs (1050301 to 1050305 and 1050307) with 56.18bn gross at September 2026, 3,559 of them over 90 days past due. Since 216aee2 the programme is segmented as its own portfolio, kept out of MAIIC's PD, LGD and ECL, and provided by megafarm:ecl from its own LGD cohort under the governed PD method; MAIIC's share is read from the mega_farms_scope text (it falls back to 1.0 when the text names no share). Not built: the interest split, the maize receivable and the fund liability of spec 16.4 and 16.5 (they wait on D30). | F22: Fresh bootstrap maiic_ifrs9_results2 (13 October 2026, before commit 216aee2). Until 14 October 2026 the row said 3,490 loans (K54.85bn) from a November 2025 book. | G22: Evidence needed: the CFO's confirmation of D30; how the K39.76bn provision of 2025 was arrived at. | H22: ECL Processing, Mega Farm Programme: /megafarm; Governance: Governance Centre /eir-governance | J22: mega_farms_scope; megafarm_pd_method; megafarm_scalar_ceiling | K22: Tests\Feature\Ecl\MegaFarmProgrammeSeparationTest::test_the_programme_lgd_is_its_own_cohort_and_a_missing_cohort_declines

Sheet Findings
A1: Findings - items that need a decision or a fix before this standard can be signed off
A2: Back to Contents
A4: No. | B4: Reference | C4: Finding | D4: What was found | E4: Impact | F4: Recommended action | G4: Owner | H4: Status
A5: F1 | B5: 5.5.1, 5.5.17 | C5: The PD, LGD and ECL are the bootstrap's, not MAIIC's | D5: The PD and LGD engines run under the bootstrap label; no MAIIC reviewer has approved a segment run, a fit or the scenario set. On the fresh bootstrap the main-book ECL at September 2026 is 11.57bn undiscounted (7.12bn discounted on 62 loans, 72 unresolved). (Until 14 October 2026 this finding quoted 8.33bn, which the Contract Schedule 1 workbook gave as 8.94bn; neither is current.) | E5: The ECL is a system figure awaiting review. | F5: A reviewer approves the segment runs, a fit and the set; the month is re-run discounted and signed. | G5: Dr Thom / the reviewer | H5: Open
A6: F2 | B6: B5.5.49 | C6: No fit is approved by a MAIIC reviewer | D6: On the fresh bootstrap the guardrail applied 32 of 209 fits and declined 177; none is approved for the route. | E6: The forward-looking adjustment is the overlay at zero until then. | F6: A reviewer approves a fit on the Regression (FLI adjustments) screen; a second person reviews. | G6: Dr Thom / the reviewer | H6: Open
A7: F3 | B7: 16 | C7: The Mega Farm provision basis is undocumented | D7: The 2025 statements carry K39.76bn against K48.7bn Stage 3. On the fresh bootstrap (staging before 216aee2) the December 2025 programme book of 3,692 loans (54.50bn) is 3,219 loans Stage 1 (47.25bn) and 471 Stage 3 (7.25bn). | E7: The ECL golden number at 31 December 2025 cannot be set. | F7: The CFO confirms D30 and the provisioning method; the next bootstrap on 216aee2 restages the programme on the chart in force. | G7: Dr Thom / Dupleix | H7: Open
A8: F4 | B8: 5.5.17(b) | C8: The reports carry the undiscounted allowance | D8: The discounted allowance is held in ecl_value_discounted; the IFRS 9 note, ECL reconciliation, RBM Return and other reports read ecl_value. | E8: The disclosed allowance is undiscounted. | F8: Point the note and the reports at the booked (discounted) allowance, with the undiscounted measure as a reconciling line. | G8: Dupleix | H8: Open
A9: F5 | B9: B5.5.55 | C9: Collateral is not in the LGD | D9: The LGD engine reads no collateral; the collateral register is empty on the fresh bootstrap. | E9: The cash flows from collateral are not reflected in the shortfall. | F9: Credit supplies the collateral and valuations; Dupleix adds the collateral recovery to the LGD. | G9: Credit / Dupleix | H9: Open

Sheet Baselines
A1: Baselines - the acceptance ties of specification section 9, read from the system at generation
A2: Back to Contents
A3: Generated 2026-10-14 08:30:38 from maiic_ifrs9_results2. The PASS/FAIL in column E is a formula on columns B and C, so it recomputes if a figure is typed over.
A4: Tie | B4: Expected | C4: System figure at generation | D4: Tolerance | E4: Result | F4: Note
A5: Interest posted Jan 2025 to Jul 2026 (ledger, types 303 and 120) | B5: 5.2939882e+09 | C5: 5.2939882e+09 | D5: 1 | E5: =IF(ABS(B5-C5)<=D5,"PASS","FAIL")
A6: Derived carrying amount against the stored report, in-scope loan GLs (over 2 cents) | B6: 0 differences | C6: 0 of 2495 account-months | D6: 0.01 | E6: =IF(B6=C6,"PASS","FAIL")
A7: Mega Farm: account-months whose MF_03 ledger differs from the Loan Book Report (reported, not a test) | B7: reported | C7: 77540 account-months | D7: 0.01 | E7: =IF(B7=C7,"PASS","FAIL")
A8: Year-end interest batch contra on 4215 | B8: 32956676 | C8: 32956676 | D8: 1 | E8: =IF(ABS(B8-C8)<=D8,"PASS","FAIL")
A9: Year-end interest batch contra on 4216 | B9: -21733263 | C9: -21733263 | D9: 0.01 | E9: =IF(ABS(B9-C9)<=D9,"PASS","FAIL")
A10: Loan book 1050101 at 31 Dec 2025 against the trial balance | B10: 1.3687378e+09 | C10: 1.3687378e+09 | D10: 1 | E10: =IF(ABS(B10-C10)<=D10,"PASS","FAIL")
A11: Loan book 1050102 at 31 Dec 2025 against the trial balance | B11: 6.4340451e+09 | C11: 6.4340451e+09 | D11: 1 | E11: =IF(ABS(B11-C11)<=D11,"PASS","FAIL")
A12: Loan book 1050201 at 31 Dec 2025 against the trial balance (accepted exception, spec 3.5: -400,000.00) | B12: 1.4023931e+09 | C12: 1.4019931e+09 | D12: 1 | E12: =IF(ABS(B12-C12)<=D12,"PASS","FAIL")
A13: Loan book 1050202 at 31 Dec 2025 against the trial balance (accepted exception, spec 3.5: 1,000,000.00) | B13: 3.8082887e+09 | C13: 3.8092887e+09 | D13: 1 | E13: =IF(ABS(B13-C13)<=D13,"PASS","FAIL")
A14: Loan book 1050401 at 31 Dec 2025 against the trial balance | B14: 1.8271481e+09 | C14: 1.8271481e+09 | D14: 1 | E14: =IF(ABS(B14-C14)<=D14,"PASS","FAIL")
